Workbook
Name 收支类别: 资金账户!$K$3:$W$3

Sheet 档案
A1: 表号 | B1: 资金户名 | C1: 公司名称 | E1: 首行 | F1: 行数 | G1: 余额
A2: 1 | B2: 华夏银行汉正街支行186346 | C2: 武汉开明 | E2: =IF(F2=0,MATCH(单日流水!$G$2,INDIRECT("'"&A2&"'!A:A"),1),MATCH(单日流水!$G$2,INDIRECT("'"&A2&"'!A:A"),0)-1) -> 1 | F2: =COUNTIF(INDIRECT("'"&A2&"'!A:A"),单日流水!$G$2) -> 0 | G2: {=INDEX(INDIRECT("'"&A2&"'!f:f"),E2,1)} -> 0
A3: 2 | B3: 浦发银行光谷支行004954 | C3: 武汉开明 | E3: =IF(F3=0,MATCH(单日流水!$G$2,INDIRECT("'"&A3&"'!A:A"),1),MATCH(单日流水!$G$2,INDIRECT("'"&A3&"'!A:A"),0)-1) -> #N/A | F3: =COUNTIF(INDIRECT("'"&A3&"'!A:A"),单日流水!$G$2) -> 0 | G3: {=INDEX(INDIRECT("'"&A3&"'!f:f"),E3,1)} -> #N/A
A4: 3 | B4: 汉口梅苑支行149501 | C4: 武汉开明 | E4: =IF(F4=0,MATCH(单日流水!$G$2,INDIRECT("'"&A4&"'!A:A"),1),MATCH(单日流水!$G$2,INDIRECT("'"&A4&"'!A:A"),0)-1) -> 1 | F4: =COUNTIF(INDIRECT("'"&A4&"'!A:A"),单日流水!$G$2) -> 0 | G4: {=INDEX(INDIRECT("'"&A4&"'!f:f"),E4,1)} -> 0
A5: 4 | B5: 光大洪山支行97500 | C5: 武汉开明 | E5: =IF(F5=0,MATCH(单日流水!$G$2,INDIRECT("'"&A5&"'!A:A"),1),MATCH(单日流水!$G$2,INDIRECT("'"&A5&"'!A:A"),0)-1) -> 1 | F5: =COUNTIF(INDIRECT("'"&A5&"'!A:A"),单日流水!$G$2) -> 0 | G5: {=INDEX(INDIRECT("'"&A5&"'!f:f"),E5,1)} -> 0
A6: 5 | B6: 建设豪威银行500746（扣ETC) | C6: 武汉开明 | E6: =IF(F6=0,MATCH(单日流水!$G$2,INDIRECT("'"&A6&"'!A:A"),1),MATCH(单日流水!$G$2,INDIRECT("'"&A6&"'!A:A"),0)-1) -> 1 | F6: =COUNTIF(INDIRECT("'"&A6&"'!A:A"),单日流水!$G$2) -> 0 | G6: {=INDEX(INDIRECT("'"&A6&"'!f:f"),E6,1)} -> 0
A7: 6 | B7: 交通银行洪山支行4632877 | C7: 武汉开明 | E7: =IF(F7=0,MATCH(单日流水!$G$2,INDIRECT("'"&A7&"'!A:A"),1),MATCH(单日流水!$G$2,INDIRECT("'"&A7&"'!A:A"),0)-1) -> 1 | F7: =COUNTIF(INDIRECT("'"&A7&"'!A:A"),单日流水!$G$2) -> 0 | G7: {=INDEX(INDIRECT("'"&A7&"'!f:f"),E7,1)} -> 0
A8: 7 | B8: 邮政储蓄凤凰支行096669 | C8: 武汉开明 | E8: =IF(F8=0,MATCH(单日流水!$G$2,INDIRECT("'"&A8&"'!A:A"),1),MATCH(单日流水!$G$2,INDIRECT("'"&A8&"'!A:A"),0)-1) -> 1 | F8: =COUNTIF(INDIRECT("'"&A8&"'!A:A"),单日流水!$G$2) -> 0 | G8: {=INDEX(INDIRECT("'"&A8&"'!f:f"),E8,1)} -> 0
A9: 8 | B9: 宁波银行余姚支行营业部825161 | C9: 武汉开明 | E9: =IF(F9=0,MATCH(单日流水!$G$2,INDIRECT("'"&A9&"'!A:A"),1),MATCH(单日流水!$G$2,INDIRECT("'"&A9&"'!A:A"),0)-1) -> #N/A | F9: =COUNTIF(INDIRECT("'"&A9&"'!A:A"),单日流水!$G$2) -> 0 | G9: {=INDEX(INDIRECT("'"&A9&"'!f:f"),E9,1)} -> #N/A
A10: 9 | B10: 农商行豹澥支行310028 | C10: 武汉开明 | E10: =IF(F10=0,MATCH(单日流水!$G$2,INDIRECT("'"&A10&"'!A:A"),1),MATCH(单日流水!$G$2,INDIRECT("'"&A10&"'!A:A"),0)-1) -> 1 | F10: =COUNTIF(INDIRECT("'"&A10&"'!A:A"),单日流水!$G$2) -> 0 | G10: {=INDEX(INDIRECT("'"&A10&"'!f:f"),E10,1)} -> 0
A11: 10 | B11: 工行武汉瀚城支行004604 | C11: 武汉开明 | E11: =IF(F11=0,MATCH(单日流水!$G$2,INDIRECT("'"&A11&"'!A:A"),1),MATCH(单日流水!$G$2,INDIRECT("'"&A11&"'!A:A"),0)-1) -> 1 | F11: =COUNTIF(INDIRECT("'"&A11&"'!A:A"),单日流水!$G$2) -> 0 | G11: {=INDEX(INDIRECT("'"&A11&"'!f:f"),E11,1)} -> 0
A12: 11 | B12: 青海农商行农民工工资保证金954442 | C12: 武汉开明 | E12: =IF(F12=0,MATCH(单日流水!$G$2,INDIRECT("'"&A12&"'!A:A"),1),MATCH(单日流水!$G$2,INDIRECT("'"&A12&"'!A:A"),0)-1) -> #N/A | F12: =COUNTIF(INDIRECT("'"&A12&"'!A:A"),单日流水!$G$2) -> 0 | G12: {=INDEX(INDIRECT("'"&A12&"'!f:f"),E12,1)} -> #N/A
A13: 12 | B13: 中国银行鹦鹉大道支行 | C13: 武汉开明 | E13: =IF(F13=0,MATCH(单日流水!$G$2,INDIRECT("'"&A13&"'!A:A"),1),MATCH(单日流水!$G$2,INDIRECT("'"&A13&"'!A:A"),0)-1) -> #N/A | F13: =COUNTIF(INDIRECT("'"&A13&"'!A:A"),单日流水!$G$2) -> 0 | G13: {=INDEX(INDIRECT("'"&A13&"'!f:f"),E13,1)} -> #N/A
... A22: 21 | B22: 汉口银行光谷分行454891 | C22: 武汉彤烨 | E22: =IF(F22=0,MATCH(单日流水!$G$2,INDIRECT("'"&A22&"'!A:A"),1),MATCH(单日流水!$G$2,INDIRECT("'"&A22&"'!A:A"),0)-1) -> 1 | F22: =COUNTIF(INDIRECT("'"&A22&"'!A:A"),单日流水!$G$2) -> 0 | G22: {=INDEX(INDIRECT("'"&A22&"'!f:f"),E22,1)} -> 0
A23: 22 | C23: 武汉彤烨 | E23: =IF(F23=0,MATCH(单日流水!$G$2,INDIRECT("'"&A23&"'!A:A"),1),MATCH(单日流水!$G$2,INDIRECT("'"&A23&"'!A:A"),0)-1) -> 3 | F23: =COUNTIF(INDIRECT("'"&A23&"'!A:A"),单日流水!$G$2) -> 0 | G23: {=INDEX(INDIRECT("'"&A23&"'!f:f"),E23,1)} -> 0
A24: 23 | C24: 武汉彤烨 | E24: =IF(F24=0,MATCH(单日流水!$G$2,INDIRECT("'"&A24&"'!A:A"),1),MATCH(单日流水!$G$2,INDIRECT("'"&A24&"'!A:A"),0)-1) -> 3 | F24: =COUNTIF(INDIRECT("'"&A24&"'!A:A"),单日流水!$G$2) -> 0 | G24: {=INDEX(INDIRECT("'"&A24&"'!f:f"),E24,1)} -> 0
A25: 24 | C25: 武汉彤烨 | E25: =IF(F25=0,MATCH(单日流水!$G$2,INDIRECT("'"&A25&"'!A:A"),1),MATCH(单日流水!$G$2,INDIRECT("'"&A25&"'!A:A"),0)-1) -> 3 | F25: =COUNTIF(INDIRECT("'"&A25&"'!A:A"),单日流水!$G$2) -> 0 | G25: {=INDEX(INDIRECT("'"&A25&"'!f:f"),E25,1)} -> 0
A26: 25 | B26: 电子承兑汇票 | C26: 武汉彤烨 | E26: =IF(F26=0,MATCH(单日流水!$G$2,INDIRECT("'"&A26&"'!A:A"),1),MATCH(单日流水!$G$2,INDIRECT("'"&A26&"'!A:A"),0)-1) -> 1 | F26: =COUNTIF(INDIRECT("'"&A26&"'!A:A"),单日流水!$G$2) -> 0 | G26: {=INDEX(INDIRECT("'"&A26&"'!f:f"),E26,1)} -> 0
A27: 26 | B27: 库存现金 | C27: 武汉彤烨 | E27: =IF(F27=0,MATCH(单日流水!$G$2,INDIRECT("'"&A27&"'!A:A"),1),MATCH(单日流水!$G$2,INDIRECT("'"&A27&"'!A:A"),0)-1) -> 3 | F27: =COUNTIF(INDIRECT("'"&A27&"'!A:A"),单日流水!$G$2) -> 0 | G27: {=INDEX(INDIRECT("'"&A27&"'!f:f"),E27,1)} -> 0
A28: 27 | B28: 邮政凤凰路支行 | C28: 湖北开明 | E28: =IF(F28=0,MATCH(单日流水!$G$2,INDIRECT("'"&A28&"'!A:A"),1),MATCH(单日流水!$G$2,INDIRECT("'"&A28&"'!A:A"),0)-1) -> 1 | F28: =COUNTIF(INDIRECT("'"&A28&"'!A:A"),单日流水!$G$2) -> 0 | G28: {=INDEX(INDIRECT("'"&A28&"'!f:f"),E28,1)} -> 0
A29: 28 | B29: 农商行开发区支行604928 | C29: 湖北开明 | E29: =IF(F29=0,MATCH(单日流水!$G$2,INDIRECT("'"&A29&"'!A:A"),1),MATCH(单日流水!$G$2,INDIRECT("'"&A29&"'!A:A"),0)-1) -> 1 | F29: =COUNTIF(INDIRECT("'"&A29&"'!A:A"),单日流水!$G$2) -> 0 | G29: {=INDEX(INDIRECT("'"&A29&"'!f:f"),E29,1)} -> 0
A30: 29 | B30: 工行西山支行004096 | C30: 湖北开明 | E30: =IF(F30=0,MATCH(单日流水!$G$2,INDIRECT("'"&A30&"'!A:A"),1),MATCH(单日流水!$G$2,INDIRECT("'"&A30&"'!A:A"),0)-1) -> 1 | F30: =COUNTIF(INDIRECT("'"&A30&"'!A:A"),单日流水!$G$2) -> 0 | G30: {=INDEX(INDIRECT("'"&A30&"'!f:f"),E30,1)} -> 0
A31: 30 | B31: 工行虹桥支行54786 | C31: 湖北开明 | E31: =IF(F31=0,MATCH(单日流水!$G$2,INDIRECT("'"&A31&"'!A:A"),1),MATCH(单日流水!$G$2,INDIRECT("'"&A31&"'!A:A"),0)-1) -> 1 | F31: =COUNTIF(INDIRECT("'"&A31&"'!A:A"),单日流水!$G$2) -> 0 | G31: {=INDEX(INDIRECT("'"&A31&"'!f:f"),E31,1)} -> 0
A32: 31 | B32: 中国银行鄂州分行0592794 | C32: 湖北开明 | E32: =IF(F32=0,MATCH(单日流水!$G$2,INDIRECT("'"&A32&"'!A:A"),1),MATCH(单日流水!$G$2,INDIRECT("'"&A32&"'!A:A"),0)-1) -> 1 | F32: =COUNTIF(INDIRECT("'"&A32&"'!A:A"),单日流水!$G$2) -> 0 | G32: {=INDEX(INDIRECT("'"&A32&"'!f:f"),E32,1)} -> 0
A33: 32 | C33: 湖北开明 | E33: =IF(F33=0,MATCH(单日流水!$G$2,INDIRECT("'"&A33&"'!A:A"),1),MATCH(单日流水!$G$2,INDIRECT("'"&A33&"'!A:A"),0)-1) -> 3 | F33: =COUNTIF(INDIRECT("'"&A33&"'!A:A"),单日流水!$G$2) -> 0 | G33: {=INDEX(INDIRECT("'"&A33&"'!f:f"),E33,1)} -> 0
A34: 33 | C34: 湖北开明 | E34: =IF(F34=0,MATCH(单日流水!$G$2,INDIRECT("'"&A34&"'!A:A"),1),MATCH(单日流水!$G$2,INDIRECT("'"&A34&"'!A:A"),0)-1) -> 3 | F34: =COUNTIF(INDIRECT("'"&A34&"'!A:A"),单日流水!$G$2) -> 0 | G34: {=INDEX(INDIRECT("'"&A34&"'!f:f"),E34,1)} -> 0
A35: 34 | C35: 湖北开明 | E35: =IF(F35=0,MATCH(单日流水!$G$2,INDIRECT("'"&A35&"'!A:A"),1),MATCH(单日流水!$G$2,INDIRECT("'"&A35&"'!A:A"),0)-1) -> 3 | F35: =COUNTIF(INDIRECT("'"&A35&"'!A:A"),单日流水!$G$2) -> 0 | G35: {=INDEX(INDIRECT("'"&A35&"'!f:f"),E35,1)} -> 0
A36: 35 | C36: 湖北开明 | E36: =IF(F36=0,MATCH(单日流水!$G$2,INDIRECT("'"&A36&"'!A:A"),1),MATCH(单日流水!$G$2,INDIRECT("'"&A36&"'!A:A"),0)-1) -> 3 | F36: =COUNTIF(INDIRECT("'"&A36&"'!A:A"),单日流水!$G$2) -> 0 | G36: {=INDEX(INDIRECT("'"&A36&"'!f:f"),E36,1)} -> 0
A37: 36 | B37: 电子承兑汇票 | C37: 湖北开明 | E37: =IF(F37=0,MATCH(单日流水!$G$2,INDIRECT("'"&A37&"'!A:A"),1),MATCH(单日流水!$G$2,INDIRECT("'"&A37&"'!A:A"),0)-1) -> 1 | F37: =COUNTIF(INDIRECT("'"&A37&"'!A:A"),单日流水!$G$2) -> 0 | G37: {=INDEX(INDIRECT("'"&A37&"'!f:f"),E37,1)} -> 0
A38: 37 | B38: 库存现金 | C38: 湖北开明 | E38: =IF(F38=0,MATCH(单日流水!$G$2,INDIRECT("'"&A38&"'!A:A"),1),MATCH(单日流水!$G$2,INDIRECT("'"&A38&"'!A:A"),0)-1) -> 3 | F38: =COUNTIF(INDIRECT("'"&A38&"'!A:A"),单日流水!$G$2) -> 0 | G38: {=INDEX(INDIRECT("'"&A38&"'!f:f"),E38,1)} -> 0
A39: 38 | B39: 浦发银行光谷支行01894 | C39: 武汉信茂 | E39: =IF(F39=0,MATCH(单日流水!$G$2,INDIRECT("'"&A39&"'!A:A"),1),MATCH(单日流水!$G$2,INDIRECT("'"&A39&"'!A:A"),0)-1) -> 1 | F39: =COUNTIF(INDIRECT("'"&A39&"'!A:A"),单日流水!$G$2) -> 0 | G39: {=INDEX(INDIRECT("'"&A39&"'!f:f"),E39,1)} -> 0
A40: 39 | C40: 武汉信茂 | E40: =IF(F40=0,MATCH(单日流水!$G$2,INDIRECT("'"&A40&"'!A:A"),1),MATCH(单日流水!$G$2,INDIRECT("'"&A40&"'!A:A"),0)-1) -> 3 | F40: =COUNTIF(INDIRECT("'"&A40&"'!A:A"),单日流水!$G$2) -> 0 | G40: {=INDEX(INDIRECT("'"&A40&"'!f:f"),E40,1)} -> 0
A41: 40 | C41: 武汉信茂 | E41: =IF(F41=0,MATCH(单日流水!$G$2,INDIRECT("'"&A41&"'!A:A"),1),MATCH(单日流水!$G$2,INDIRECT("'"&A41&"'!A:A"),0)-1) -> 3 | F41: =COUNTIF(INDIRECT("'"&A41&"'!A:A"),单日流水!$G$2) -> 0 | G41: {=INDEX(INDIRECT("'"&A41&"'!f:f"),E41,1)} -> 0
A42: 41 | C42: 武汉信茂 | E42: =IF(F42=0,MATCH(单日流水!$G$2,INDIRECT("'"&A42&"'!A:A"),1),MATCH(单日流水!$G$2,INDIRECT("'"&A42&"'!A:A"),0)-1) -> 3 | F42: =COUNTIF(INDIRECT("'"&A42&"'!A:A"),单日流水!$G$2) -> 0 | G42: {=INDEX(INDIRECT("'"&A42&"'!f:f"),E42,1)} -> 0
A43: 42 | B43: 电子承兑汇票 | C43: 武汉信茂 | E43: =IF(F43=0,MATCH(单日流水!$G$2,INDIRECT("'"&A43&"'!A:A"),1),MATCH(单日流水!$G$2,INDIRECT("'"&A43&"'!A:A"),0)-1) -> 1 | F43: =COUNTIF(INDIRECT("'"&A43&"'!A:A"),单日流水!$G$2) -> 0 | G43: {=INDEX(INDIRECT("'"&A43&"'!f:f"),E43,1)} -> 0
A44: 43 | B44: 库存现金 | C44: 武汉信茂 | E44: =IF(F44=0,MATCH(单日流水!$G$2,INDIRECT("'"&A44&"'!A:A"),1),MATCH(单日流水!$G$2,INDIRECT("'"&A44&"'!A:A"),0)-1) -> 3 | F44: =COUNTIF(INDIRECT("'"&A44&"'!A:A"),单日流水!$G$2) -> 0 | G44: {=INDEX(INDIRECT("'"&A44&"'!f:f"),E44,1)} -> 0
A45: 44 | B45: 王先梅 邮储银行4262 | C45: 个体户 | E45: =IF(F45=0,MATCH(单日流水!$G$2,INDIRECT("'"&A45&"'!A:A"),1),MATCH(单日流水!$G$2,INDIRECT("'"&A45&"'!A:A"),0)-1) -> 1 | F45: =COUNTIF(INDIRECT("'"&A45&"'!A:A"),单日流水!$G$2) -> 0 | G45: {=INDEX(INDIRECT("'"&A45&"'!f:f"),E45,1)} -> 0
A46: 45 | B46: 林家祥 邮储银行7677 | C46: 个体户 | E46: =IF(F46=0,MATCH(单日流水!$G$2,INDIRECT("'"&A46&"'!A:A"),1),MATCH(单日流水!$G$2,INDIRECT("'"&A46&"'!A:A"),0)-1) -> 1 | F46: =COUNTIF(INDIRECT("'"&A46&"'!A:A"),单日流水!$G$2) -> 0 | G46: {=INDEX(INDIRECT("'"&A46&"'!f:f"),E46,1)} -> 0
A47: 46 | B47: 湖北岚丹农民工发放账户01679 | C47: 湖北岚丹 | E47: =IF(F47=0,MATCH(单日流水!$G$2,INDIRECT("'"&A47&"'!A:A"),1),MATCH(单日流水!$G$2,INDIRECT("'"&A47&"'!A:A"),0)-1) -> 1 | F47: =COUNTIF(INDIRECT("'"&A47&"'!A:A"),单日流水!$G$2) -> 0 | G47: {=INDEX(INDIRECT("'"&A47&"'!f:f"),E47,1)} -> 0
A48: 47 | B48: 岚丹电子承兑汇票 | C48: 湖北岚丹 | E48: =IF(F48=0,MATCH(单日流水!$G$2,INDIRECT("'"&A48&"'!A:A"),1),MATCH(单日流水!$G$2,INDIRECT("'"&A48&"'!A:A"),0)-1) -> 1 | F48: =COUNTIF(INDIRECT("'"&A48&"'!A:A"),单日流水!$G$2) -> 0 | G48: {=INDEX(INDIRECT("'"&A48&"'!f:f"),E48,1)} -> 0
A49: 48 | B49: 湖北岚丹农民工账户53528 | C49: 湖北岚丹 | E49: =IF(F49=0,MATCH(单日流水!$G$2,INDIRECT("'"&A49&"'!A:A"),1),MATCH(单日流水!$G$2,INDIRECT("'"&A49&"'!A:A"),0)-1) -> 1 | F49: =COUNTIF(INDIRECT("'"&A49&"'!A:A"),单日流水!$G$2) -> 0 | G49: {=INDEX(INDIRECT("'"&A49&"'!f:f"),E49,1)} -> 0
A50: 50 | B50: 库存现金 | C50: 个体户 | E50: =IF(F50=0,MATCH(单日流水!$G$2,INDIRECT("'"&A50&"'!A:A"),1),MATCH(单日流水!$G$2,INDIRECT("'"&A50&"'!A:A"),0)-1) -> 1 | F50: =COUNTIF(INDIRECT("'"&A50&"'!A:A"),单日流水!$G$2) -> 0 | G50: {=INDEX(INDIRECT("'"&A50&"'!f:f"),E50,1)} -> 0
A51: 51 | B51: 工会工行西山支行029092 | E51: =IF(F51=0,MATCH(单日流水!$G$2,INDIRECT("'"&A51&"'!A:A"),1),MATCH(单日流水!$G$2,INDIRECT("'"&A51&"'!A:A"),0)-1) -> 1 | F51: =COUNTIF(INDIRECT("'"&A51&"'!A:A"),单日流水!$G$2) -> 0 | G51: {=INDEX(INDIRECT("'"&A51&"'!f:f"),E51,1)} -> 0
A52: 52 | E52: =IF(F52=0,MATCH(单日流水!$G$2,INDIRECT("'"&A52&"'!A:A"),1),MATCH(单日流水!$G$2,INDIRECT("'"&A52&"'!A:A"),0)-1) -> 3 | F52: =COUNTIF(INDIRECT("'"&A52&"'!A:A"),单日流水!$G$2) -> 0 | G52: {=INDEX(INDIRECT("'"&A52&"'!f:f"),E52,1)} -> 0
A53: 53 | B53: 岚丹中信银行武汉东湖支行068761 | E53: =IF(F53=0,MATCH(单日流水!$G$2,INDIRECT("'"&A53&"'!A:A"),1),MATCH(单日流水!$G$2,INDIRECT("'"&A53&"'!A:A"),0)-1) -> 1 | F53: =COUNTIF(INDIRECT("'"&A53&"'!A:A"),单日流水!$G$2) -> 0 | G53: {=INDEX(INDIRECT("'"&A53&"'!f:f"),E53,1)} -> 0

Sheet 资金账户
F1: 资金账户明细表
E2: 报告日期： | F2: 45980 | J2: 单位：元
A3: 首行 | B3: 行数 | D3: 项目 | F3: 资金户名 | G3: 昨日余额 | H3: 收款小计 | I3: 付款小计 | J3: 本日余额 | K3: 营业回款 | L3: 投标保证金回款 | M3: 借款到账 | N3: 其他收款 | O3: 他行转入或存现 | P3: 付货款 | Q3: 付投标保证金 | R3: 付日常费用 | S3: 还借款及利息 | T3: 其他付款 | U3: 转出他行或提现 | V3: 项目成本 | W3: 外协成本
A4: =IF(B4=0,MATCH($F$2,INDIRECT("'"&C4&"'!A:A"),1),MATCH($F$2,INDIRECT("'"&C4&"'!A:A"),0)) -> 158 | B4: =COUNTIF(INDIRECT("'"&C4&"'!A:A"),$F$2) -> 2 | C4: 1 | D4: 武汉开明 | E4: 银行存款 | F4: =VLOOKUP(C4,档案!A:B,2,FALSE) -> 华夏银行汉正街支行186346 | G4: =IF(B4=0,INDEX(INDIRECT("'"&$C4&"'!$F:$F"),$A4,1),INDEX(INDIRECT("'"&$C4&"'!$F:$F"),$A4-1,1)) -> 20039.02 | H4: =SUM(K4:O4) -> 0 | I4: =SUM(P4:W4) -> 3.5 | J4: =G4+H4-I4 -> 20035.52 | K4: =SUMIFS(INDIRECT("'"&$C4&"'!$D:$D"),INDIRECT("'"&$C4&"'!$C:$C"),K$3,INDIRECT("'"&$C4&"'!$A:$A"),$F$2) -> 0 | L4: =SUMIFS(INDIRECT("'"&$C4&"'!$D:$D"),INDIRECT("'"&$C4&"'!$C:$C"),L$3,INDIRECT("'"&$C4&"'!$A:$A"),$F$2) -> 0 | M4: =SUMIFS(INDIRECT("'"&$C4&"'!$D:$D"),INDIRECT("'"&$C4&"'!$C:$C"),M$3,INDIRECT("'"&$C4&"'!$A:$A"),$F$2) -> 0 | N4: =SUMIFS(INDIRECT("'"&$C4&"'!$D:$D"),INDIRECT("'"&$C4&"'!$C:$C"),N$3,INDIRECT("'"&$C4&"'!$A:$A"),$F$2) -> 0 | O4: =SUMIFS(INDIRECT("'"&$C4&"'!$D:$D"),INDIRECT("'"&$C4&"'!$C:$C"),O$3,INDIRECT("'"&$C4&"'!$A:$A"),$F$2) -> 0 | P4: =SUMIFS(INDIRECT("'"&$C4&"'!$e:$e"),INDIRECT("'"&$C4&"'!$C:$C"),P$3,INDIRECT("'"&$C4&"'!$A:$A"),$F$2) -> 0 | Q4: =SUMIFS(INDIRECT("'"&$C4&"'!$e:$e"),INDIRECT("'"&$C4&"'!$C:$C"),Q$3,INDIRECT("'"&$C4&"'!$A:$A"),$F$2) -> 0 | R4: =SUMIFS(INDIRECT("'"&$C4&"'!$e:$e"),INDIRECT("'"&$C4&"'!$C:$C"),R$3,INDIRECT("'"&$C4&"'!$A:$A"),$F$2) -> 1.5 | S4: =SUMIFS(INDIRECT("'"&$C4&"'!$e:$e"),INDIRECT("'"&$C4&"'!$C:$C"),S$3,INDIRECT("'"&$C4&"'!$A:$A"),$F$2) -> 0 | T4: =SUMIFS(INDIRECT("'"&$C4&"'!$e:$e"),INDIRECT("'"&$C4&"'!$C:$C"),T$3,INDIRECT("'"&$C4&"'!$A:$A"),$F$2) -> 0 | U4: =SUMIFS(INDIRECT("'"&$C4&"'!$e:$e"),INDIRECT("'"&$C4&"'!$C:$C"),U$3,INDIRECT("'"&$C4&"'!$A:$A"),$F$2) -> 2 | V4: =SUMIFS(INDIRECT("'"&$C4&"'!$e:$e"),INDIRECT("'"&$C4&"'!$C:$C"),V$3,INDIRECT("'"&$C4&"'!$A:$A"),$F$2) -> 0 | W4: =SUMIFS(INDIRECT("'"&$C4&"'!$e:$e"),INDIRECT("'"&$C4&"'!$C:$C"),W$3,INDIRECT("'"&$C4&"'!$A:$A"),$F$2) -> 0
A5: =IF(B5=0,MATCH($F$2,INDIRECT("'"&C5&"'!A:A"),1),MATCH($F$2,INDIRECT("'"&C5&"'!A:A"),0)) -> 741 | B5: =COUNTIF(INDIRECT("'"&C5&"'!A:A"),$F$2) -> 1 | C5: 2 | F5: =VLOOKUP(C5,档案!A:B,2,FALSE) -> 浦发银行光谷支行004954 | G5: =IF(B5=0,INDEX(INDIRECT("'"&$C5&"'!$F:$F"),$A5,1),INDEX(INDIRECT("'"&$C5&"'!$F:$F"),$A5-1,1)) -> 67375.91 | H5: =SUM(K5:O5) -> 40000 | I5: =SUM(P5:W5) -> 0 | J5: =G5+H5-I5 -> 107375.91 | K5: =SUMIFS(INDIRECT("'"&$C5&"'!$D:$D"),INDIRECT("'"&$C5&"'!$C:$C"),K$3,INDIRECT("'"&$C5&"'!$A:$A"),$F$2) -> 0 | L5: =SUMIFS(INDIRECT("'"&$C5&"'!$D:$D"),INDIRECT("'"&$C5&"'!$C:$C"),L$3,INDIRECT("'"&$C5&"'!$A:$A"),$F$2) -> 0 | M5: =SUMIFS(INDIRECT("'"&$C5&"'!$D:$D"),INDIRECT("'"&$C5&"'!$C:$C"),M$3,INDIRECT("'"&$C5&"'!$A:$A"),$F$2) -> 0 | N5: =SUMIFS(INDIRECT("'"&$C5&"'!$D:$D"),INDIRECT("'"&$C5&"'!$C:$C"),N$3,INDIRECT("'"&$C5&"'!$A:$A"),$F$2) -> 40000 | O5: =SUMIFS(INDIRECT("'"&$C5&"'!$D:$D"),INDIRECT("'"&$C5&"'!$C:$C"),O$3,INDIRECT("'"&$C5&"'!$A:$A"),$F$2) -> 0 | P5: =SUMIFS(INDIRECT("'"&$C5&"'!$e:$e"),INDIRECT("'"&$C5&"'!$C:$C"),P$3,INDIRECT("'"&$C5&"'!$A:$A"),$F$2) -> 0 | Q5: =SUMIFS(INDIRECT("'"&$C5&"'!$e:$e"),INDIRECT("'"&$C5&"'!$C:$C"),Q$3,INDIRECT("'"&$C5&"'!$A:$A"),$F$2) -> 0 | R5: =SUMIFS(INDIRECT("'"&$C5&"'!$e:$e"),INDIRECT("'"&$C5&"'!$C:$C"),R$3,INDIRECT("'"&$C5&"'!$A:$A"),$F$2) -> 0 | S5: =SUMIFS(INDIRECT("'"&$C5&"'!$e:$e"),INDIRECT("'"&$C5&"'!$C:$C"),S$3,INDIRECT("'"&$C5&"'!$A:$A"),$F$2) -> 0 | T5: =SUMIFS(INDIRECT("'"&$C5&"'!$e:$e"),INDIRECT("'"&$C5&"'!$C:$C"),T$3,INDIRECT("'"&$C5&"'!$A:$A"),$F$2) -> 0 | U5: =SUMIFS(INDIRECT("'"&$C5&"'!$e:$e"),INDIRECT("'"&$C5&"'!$C:$C"),U$3,INDIRECT("'"&$C5&"'!$A:$A"),$F$2) -> 0 | V5: =SUMIFS(INDIRECT("'"&$C5&"'!$e:$e"),INDIRECT("'"&$C5&"'!$C:$C"),V$3,INDIRECT("'"&$C5&"'!$A:$A"),$F$2) -> 0 | W5: =SUMIFS(INDIRECT("'"&$C5&"'!$e:$e"),INDIRECT("'"&$C5&"'!$C:$C"),W$3,INDIRECT("'"&$C5&"'!$A:$A"),$F$2) -> 0
A6: =IF(B6=0,MATCH($F$2,INDIRECT("'"&C6&"'!A:A"),1),MATCH($F$2,INDIRECT("'"&C6&"'!A:A"),0)) -> 39 | B6: =COUNTIF(INDIRECT("'"&C6&"'!A:A"),$F$2) -> 0 | C6: 3 | F6: =VLOOKUP(C6,档案!A:B,2,FALSE) -> 汉口梅苑支行149501 | G6: =IF(B6=0,INDEX(INDIRECT("'"&$C6&"'!$F:$F"),$A6,1),INDEX(INDIRECT("'"&$C6&"'!$F:$F"),$A6-1,1)) -> 9043.78 | H6: =SUM(K6:O6) -> 0 | I6: =SUM(P6:W6) -> 0 | J6: =G6+H6-I6 -> 9043.78 | K6: =SUMIFS(INDIRECT("'"&$C6&"'!$D:$D"),INDIRECT("'"&$C6&"'!$C:$C"),K$3,INDIRECT("'"&$C6&"'!$A:$A"),$F$2) -> 0 | L6: =SUMIFS(INDIRECT("'"&$C6&"'!$D:$D"),INDIRECT("'"&$C6&"'!$C:$C"),L$3,INDIRECT("'"&$C6&"'!$A:$A"),$F$2) -> 0 | M6: =SUMIFS(INDIRECT("'"&$C6&"'!$D:$D"),INDIRECT("'"&$C6&"'!$C:$C"),M$3,INDIRECT("'"&$C6&"'!$A:$A"),$F$2) -> 0 | N6: =SUMIFS(INDIRECT("'"&$C6&"'!$D:$D"),INDIRECT("'"&$C6&"'!$C:$C"),N$3,INDIRECT("'"&$C6&"'!$A:$A"),$F$2) -> 0 | O6: =SUMIFS(INDIRECT("'"&$C6&"'!$D:$D"),INDIRECT("'"&$C6&"'!$C:$C"),O$3,INDIRECT("'"&$C6&"'!$A:$A"),$F$2) -> 0 | P6: =SUMIFS(INDIRECT("'"&$C6&"'!$e:$e"),INDIRECT("'"&$C6&"'!$C:$C"),P$3,INDIRECT("'"&$C6&"'!$A:$A"),$F$2) -> 0 | Q6: =SUMIFS(INDIRECT("'"&$C6&"'!$e:$e"),INDIRECT("'"&$C6&"'!$C:$C"),Q$3,INDIRECT("'"&$C6&"'!$A:$A"),$F$2) -> 0 | R6: =SUMIFS(INDIRECT("'"&$C6&"'!$e:$e"),INDIRECT("'"&$C6&"'!$C:$C"),R$3,INDIRECT("'"&$C6&"'!$A:$A"),$F$2) -> 0 | S6: =SUMIFS(INDIRECT("'"&$C6&"'!$e:$e"),INDIRECT("'"&$C6&"'!$C:$C"),S$3,INDIRECT("'"&$C6&"'!$A:$A"),$F$2) -> 0 | T6: =SUMIFS(INDIRECT("'"&$C6&"'!$e:$e"),INDIRECT("'"&$C6&"'!$C:$C"),T$3,INDIRECT("'"&$C6&"'!$A:$A"),$F$2) -> 0 | U6: =SUMIFS(INDIRECT("'"&$C6&"'!$e:$e"),INDIRECT("'"&$C6&"'!$C:$C"),U$3,INDIRECT("'"&$C6&"'!$A:$A"),$F$2) -> 0 | V6: =SUMIFS(INDIRECT("'"&$C6&"'!$e:$e"),INDIRECT("'"&$C6&"'!$C:$C"),V$3,INDIRECT("'"&$C6&"'!$A:$A"),$F$2) -> 0 | W6: =SUMIFS(INDIRECT("'"&$C6&"'!$e:$e"),INDIRECT("'"&$C6&"'!$C:$C"),W$3,INDIRECT("'"&$C6&"'!$A:$A"),$F$2) -> 0
A7: =IF(B7=0,MATCH($F$2,INDIRECT("'"&C7&"'!A:A"),1),MATCH($F$2,INDIRECT("'"&C7&"'!A:A"),0)) -> 44 | B7: =COUNTIF(INDIRECT("'"&C7&"'!A:A"),$F$2) -> 0 | C7: 4 | F7: =VLOOKUP(C7,档案!A:B,2,FALSE) -> 光大洪山支行97500 | G7: =IF(B7=0,INDEX(INDIRECT("'"&$C7&"'!$F:$F"),$A7,1),INDEX(INDIRECT("'"&$C7&"'!$F:$F"),$A7-1,1)) -> 3475.81 | H7: =SUM(K7:O7) -> 0 | I7: =SUM(P7:W7) -> 0 | J7: =G7+H7-I7 -> 3475.81 | K7: =SUMIFS(INDIRECT("'"&$C7&"'!$D:$D"),INDIRECT("'"&$C7&"'!$C:$C"),K$3,INDIRECT("'"&$C7&"'!$A:$A"),$F$2) -> 0 | L7: =SUMIFS(INDIRECT("'"&$C7&"'!$D:$D"),INDIRECT("'"&$C7&"'!$C:$C"),L$3,INDIRECT("'"&$C7&"'!$A:$A"),$F$2) -> 0 | M7: =SUMIFS(INDIRECT("'"&$C7&"'!$D:$D"),INDIRECT("'"&$C7&"'!$C:$C"),M$3,INDIRECT("'"&$C7&"'!$A:$A"),$F$2) -> 0 | N7: =SUMIFS(INDIRECT("'"&$C7&"'!$D:$D"),INDIRECT("'"&$C7&"'!$C:$C"),N$3,INDIRECT("'"&$C7&"'!$A:$A"),$F$2) -> 0 | O7: =SUMIFS(INDIRECT("'"&$C7&"'!$D:$D"),INDIRECT("'"&$C7&"'!$C:$C"),O$3,INDIRECT("'"&$C7&"'!$A:$A"),$F$2) -> 0 | P7: =SUMIFS(INDIRECT("'"&$C7&"'!$e:$e"),INDIRECT("'"&$C7&"'!$C:$C"),P$3,INDIRECT("'"&$C7&"'!$A:$A"),$F$2) -> 0 | Q7: =SUMIFS(INDIRECT("'"&$C7&"'!$e:$e"),INDIRECT("'"&$C7&"'!$C:$C"),Q$3,INDIRECT("'"&$C7&"'!$A:$A"),$F$2) -> 0 | R7: =SUMIFS(INDIRECT("'"&$C7&"'!$e:$e"),INDIRECT("'"&$C7&"'!$C:$C"),R$3,INDIRECT("'"&$C7&"'!$A:$A"),$F$2) -> 0 | S7: =SUMIFS(INDIRECT("'"&$C7&"'!$e:$e"),INDIRECT("'"&$C7&"'!$C:$C"),S$3,INDIRECT("'"&$C7&"'!$A:$A"),$F$2) -> 0 | T7: =SUMIFS(INDIRECT("'"&$C7&"'!$e:$e"),INDIRECT("'"&$C7&"'!$C:$C"),T$3,INDIRECT("'"&$C7&"'!$A:$A"),$F$2) -> 0 | U7: =SUMIFS(INDIRECT("'"&$C7&"'!$e:$e"),INDIRECT("'"&$C7&"'!$C:$C"),U$3,INDIRECT("'"&$C7&"'!$A:$A"),$F$2) -> 0 | V7: =SUMIFS(INDIRECT("'"&$C7&"'!$e:$e"),INDIRECT("'"&$C7&"'!$C:$C"),V$3,INDIRECT("'"&$C7&"'!$A:$A"),$F$2) -> 0 | W7: =SUMIFS(INDIRECT("'"&$C7&"'!$e:$e"),INDIRECT("'"&$C7&"'!$C:$C"),W$3,INDIRECT("'"&$C7&"'!$A:$A"),$F$2) -> 0
A8: =IF(B8=0,MATCH($F$2,INDIRECT("'"&C8&"'!A:A"),1),MATCH($F$2,INDIRECT("'"&C8&"'!A:A"),0)) -> 308 | B8: =COUNTIF(INDIRECT("'"&C8&"'!A:A"),$F$2) -> 0 | C8: 5 | F8: =VLOOKUP(C8,档案!A:B,2,FALSE) -> 建设豪威银行500746（扣ETC) | G8: =IF(B8=0,INDEX(INDIRECT("'"&$C8&"'!$F:$F"),$A8,1),INDEX(INDIRECT("'"&$C8&"'!$F:$F"),$A8-1,1)) -> 12872.36 | H8: =SUM(K8:O8) -> 0 | I8: =SUM(P8:W8) -> 0 | J8: =G8+H8-I8 -> 12872.36 | K8: =SUMIFS(INDIRECT("'"&$C8&"'!$D:$D"),INDIRECT("'"&$C8&"'!$C:$C"),K$3,INDIRECT("'"&$C8&"'!$A:$A"),$F$2) -> 0 | L8: =SUMIFS(INDIRECT("'"&$C8&"'!$D:$D"),INDIRECT("'"&$C8&"'!$C:$C"),L$3,INDIRECT("'"&$C8&"'!$A:$A"),$F$2) -> 0 | M8: =SUMIFS(INDIRECT("'"&$C8&"'!$D:$D"),INDIRECT("'"&$C8&"'!$C:$C"),M$3,INDIRECT("'"&$C8&"'!$A:$A"),$F$2) -> 0 | N8: =SUMIFS(INDIRECT("'"&$C8&"'!$D:$D"),INDIRECT("'"&$C8&"'!$C:$C"),N$3,INDIRECT("'"&$C8&"'!$A:$A"),$F$2) -> 0 | O8: =SUMIFS(INDIRECT("'"&$C8&"'!$D:$D"),INDIRECT("'"&$C8&"'!$C:$C"),O$3,INDIRECT("'"&$C8&"'!$A:$A"),$F$2) -> 0 | P8: =SUMIFS(INDIRECT("'"&$C8&"'!$e:$e"),INDIRECT("'"&$C8&"'!$C:$C"),P$3,INDIRECT("'"&$C8&"'!$A:$A"),$F$2) -> 0 | Q8: =SUMIFS(INDIRECT("'"&$C8&"'!$e:$e"),INDIRECT("'"&$C8&"'!$C:$C"),Q$3,INDIRECT("'"&$C8&"'!$A:$A"),$F$2) -> 0 | R8: =SUMIFS(INDIRECT("'"&$C8&"'!$e:$e"),INDIRECT("'"&$C8&"'!$C:$C"),R$3,INDIRECT("'"&$C8&"'!$A:$A"),$F$2) -> 0 | S8: =SUMIFS(INDIRECT("'"&$C8&"'!$e:$e"),INDIRECT("'"&$C8&"'!$C:$C"),S$3,INDIRECT("'"&$C8&"'!$A:$A"),$F$2) -> 0 | T8: =SUMIFS(INDIRECT("'"&$C8&"'!$e:$e"),INDIRECT("'"&$C8&"'!$C:$C"),T$3,INDIRECT("'"&$C8&"'!$A:$A"),$F$2) -> 0 | U8: =SUMIFS(INDIRECT("'"&$C8&"'!$e:$e"),INDIRECT("'"&$C8&"'!$C:$C"),U$3,INDIRECT("'"&$C8&"'!$A:$A"),$F$2) -> 0 | V8: =SUMIFS(INDIRECT("'"&$C8&"'!$e:$e"),INDIRECT("'"&$C8&"'!$C:$C"),V$3,INDIRECT("'"&$C8&"'!$A:$A"),$F$2) -> 0 | W8: =SUMIFS(INDIRECT("'"&$C8&"'!$e:$e"),INDIRECT("'"&$C8&"'!$C:$C"),W$3,INDIRECT("'"&$C8&"'!$A:$A"),$F$2) -> 0
A9: =IF(B9=0,MATCH($F$2,INDIRECT("'"&C9&"'!A:A"),1),MATCH($F$2,INDIRECT("'"&C9&"'!A:A"),0)) -> 28 | B9: =COUNTIF(INDIRECT("'"&C9&"'!A:A"),$F$2) -> 0 | C9: 6 | F9: =VLOOKUP(C9,档案!A:B,2,FALSE) -> 交通银行洪山支行4632877 | G9: =IF(B9=0,INDEX(INDIRECT("'"&$C9&"'!$F:$F"),$A9,1),INDEX(INDIRECT("'"&$C9&"'!$F:$F"),$A9-1,1)) -> 13229.22 | H9: =SUM(K9:O9) -> 0 | I9: =SUM(P9:W9) -> 0 | J9: =G9+H9-I9 -> 13229.22 | K9: =SUMIFS(INDIRECT("'"&$C9&"'!$D:$D"),INDIRECT("'"&$C9&"'!$C:$C"),K$3,INDIRECT("'"&$C9&"'!$A:$A"),$F$2) -> 0 | L9: =SUMIFS(INDIRECT("'"&$C9&"'!$D:$D"),INDIRECT("'"&$C9&"'!$C:$C"),L$3,INDIRECT("'"&$C9&"'!$A:$A"),$F$2) -> 0 | M9: =SUMIFS(INDIRECT("'"&$C9&"'!$D:$D"),INDIRECT("'"&$C9&"'!$C:$C"),M$3,INDIRECT("'"&$C9&"'!$A:$A"),$F$2) -> 0 | N9: =SUMIFS(INDIRECT("'"&$C9&"'!$D:$D"),INDIRECT("'"&$C9&"'!$C:$C"),N$3,INDIRECT("'"&$C9&"'!$A:$A"),$F$2) -> 0 | O9: =SUMIFS(INDIRECT("'"&$C9&"'!$D:$D"),INDIRECT("'"&$C9&"'!$C:$C"),O$3,INDIRECT("'"&$C9&"'!$A:$A"),$F$2) -> 0 | P9: =SUMIFS(INDIRECT("'"&$C9&"'!$e:$e"),INDIRECT("'"&$C9&"'!$C:$C"),P$3,INDIRECT("'"&$C9&"'!$A:$A"),$F$2) -> 0 | Q9: =SUMIFS(INDIRECT("'"&$C9&"'!$e:$e"),INDIRECT("'"&$C9&"'!$C:$C"),Q$3,INDIRECT("'"&$C9&"'!$A:$A"),$F$2) -> 0 | R9: =SUMIFS(INDIRECT("'"&$C9&"'!$e:$e"),INDIRECT("'"&$C9&"'!$C:$C"),R$3,INDIRECT("'"&$C9&"'!$A:$A"),$F$2) -> 0 | S9: =SUMIFS(INDIRECT("'"&$C9&"'!$e:$e"),INDIRECT("'"&$C9&"'!$C:$C"),S$3,INDIRECT("'"&$C9&"'!$A:$A"),$F$2) -> 0 | T9: =SUMIFS(INDIRECT("'"&$C9&"'!$e:$e"),INDIRECT("'"&$C9&"'!$C:$C"),T$3,INDIRECT("'"&$C9&"'!$A:$A"),$F$2) -> 0 | U9: =SUMIFS(INDIRECT("'"&$C9&"'!$e:$e"),INDIRECT("'"&$C9&"'!$C:$C"),U$3,INDIRECT("'"&$C9&"'!$A:$A"),$F$2) -> 0 | V9: =SUMIFS(INDIRECT("'"&$C9&"'!$e:$e"),INDIRECT("'"&$C9&"'!$C:$C"),V$3,INDIRECT("'"&$C9&"'!$A:$A"),$F$2) -> 0 | W9: =SUMIFS(INDIRECT("'"&$C9&"'!$e:$e"),INDIRECT("'"&$C9&"'!$C:$C"),W$3,INDIRECT("'"&$C9&"'!$A:$A"),$F$2) -> 0
A10: =IF(B10=0,MATCH($F$2,INDIRECT("'"&C10&"'!A:A"),1),MATCH($F$2,INDIRECT("'"&C10&"'!A:A"),0)) -> 8 | B10: =COUNTIF(INDIRECT("'"&C10&"'!A:A"),$F$2) -> 0 | C10: 7 | F10: =VLOOKUP(C10,档案!A:B,2,FALSE) -> 邮政储蓄凤凰支行096669 | G10: =IF(B10=0,INDEX(INDIRECT("'"&$C10&"'!$F:$F"),$A10,1),INDEX(INDIRECT("'"&$C10&"'!$F:$F"),$A10-1,1)) -> 380.49 | H10: =SUM(K10:O10) -> 0 | I10: =SUM(P10:W10) -> 0 | J10: =G10+H10-I10 -> 380.49 | K10: =SUMIFS(INDIRECT("'"&$C10&"'!$D:$D"),INDIRECT("'"&$C10&"'!$C:$C"),K$3,INDIRECT("'"&$C10&"'!$A:$A"),$F$2) -> 0 | L10: =SUMIFS(INDIRECT("'"&$C10&"'!$D:$D"),INDIRECT("'"&$C10&"'!$C:$C"),L$3,INDIRECT("'"&$C10&"'!$A:$A"),$F$2) -> 0 | M10: =SUMIFS(INDIRECT("'"&$C10&"'!$D:$D"),INDIRECT("'"&$C10&"'!$C:$C"),M$3,INDIRECT("'"&$C10&"'!$A:$A"),$F$2) -> 0 | N10: =SUMIFS(INDIRECT("'"&$C10&"'!$D:$D"),INDIRECT("'"&$C10&"'!$C:$C"),N$3,INDIRECT("'"&$C10&"'!$A:$A"),$F$2) -> 0 | O10: =SUMIFS(INDIRECT("'"&$C10&"'!$D:$D"),INDIRECT("'"&$C10&"'!$C:$C"),O$3,INDIRECT("'"&$C10&"'!$A:$A"),$F$2) -> 0 | P10: =SUMIFS(INDIRECT("'"&$C10&"'!$e:$e"),INDIRECT("'"&$C10&"'!$C:$C"),P$3,INDIRECT("'"&$C10&"'!$A:$A"),$F$2) -> 0 | Q10: =SUMIFS(INDIRECT("'"&$C10&"'!$e:$e"),INDIRECT("'"&$C10&"'!$C:$C"),Q$3,INDIRECT("'"&$C10&"'!$A:$A"),$F$2) -> 0 | R10: =SUMIFS(INDIRECT("'"&$C10&"'!$e:$e"),INDIRECT("'"&$C10&"'!$C:$C"),R$3,INDIRECT("'"&$C10&"'!$A:$A"),$F$2) -> 0 | S10: =SUMIFS(INDIRECT("'"&$C10&"'!$e:$e"),INDIRECT("'"&$C10&"'!$C:$C"),S$3,INDIRECT("'"&$C10&"'!$A:$A"),$F$2) -> 0 | T10: =SUMIFS(INDIRECT("'"&$C10&"'!$e:$e"),INDIRECT("'"&$C10&"'!$C:$C"),T$3,INDIRECT("'"&$C10&"'!$A:$A"),$F$2) -> 0 | U10: =SUMIFS(INDIRECT("'"&$C10&"'!$e:$e"),INDIRECT("'"&$C10&"'!$C:$C"),U$3,INDIRECT("'"&$C10&"'!$A:$A"),$F$2) -> 0 | V10: =SUMIFS(INDIRECT("'"&$C10&"'!$e:$e"),INDIRECT("'"&$C10&"'!$C:$C"),V$3,INDIRECT("'"&$C10&"'!$A:$A"),$F$2) -> 0 | W10: =SUMIFS(INDIRECT("'"&$C10&"'!$e:$e"),INDIRECT("'"&$C10&"'!$C:$C"),W$3,INDIRECT("'"&$C10&"'!$A:$A"),$F$2) -> 0
A11: =IF(B11=0,MATCH($F$2,INDIRECT("'"&C11&"'!A:A"),1),MATCH($F$2,INDIRECT("'"&C11&"'!A:A"),0)) -> 30 | B11: =COUNTIF(INDIRECT("'"&C11&"'!A:A"),$F$2) -> 0 | C11: 8 | F11: =VLOOKUP(C11,档案!A:B,2,FALSE) -> 宁波银行余姚支行营业部825161 | G11: =IF(B11=0,INDEX(INDIRECT("'"&$C11&"'!$F:$F"),$A11,1),INDEX(INDIRECT("'"&$C11&"'!$F:$F"),$A11-1,1)) -> 71668.02 | H11: =SUM(K11:O11) -> 0 | I11: =SUM(P11:W11) -> 0 | J11: =G11+H11-I11 -> 71668.02 | K11: =SUMIFS(INDIRECT("'"&$C11&"'!$D:$D"),INDIRECT("'"&$C11&"'!$C:$C"),K$3,INDIRECT("'"&$C11&"'!$A:$A"),$F$2) -> 0 | L11: =SUMIFS(INDIRECT("'"&$C11&"'!$D:$D"),INDIRECT("'"&$C11&"'!$C:$C"),L$3,INDIRECT("'"&$C11&"'!$A:$A"),$F$2) -> 0 | M11: =SUMIFS(INDIRECT("'"&$C11&"'!$D:$D"),INDIRECT("'"&$C11&"'!$C:$C"),M$3,INDIRECT("'"&$C11&"'!$A:$A"),$F$2) -> 0 | N11: =SUMIFS(INDIRECT("'"&$C11&"'!$D:$D"),INDIRECT("'"&$C11&"'!$C:$C"),N$3,INDIRECT("'"&$C11&"'!$A:$A"),$F$2) -> 0 | O11: =SUMIFS(INDIRECT("'"&$C11&"'!$D:$D"),INDIRECT("'"&$C11&"'!$C:$C"),O$3,INDIRECT("'"&$C11&"'!$A:$A"),$F$2) -> 0 | P11: =SUMIFS(INDIRECT("'"&$C11&"'!$e:$e"),INDIRECT("'"&$C11&"'!$C:$C"),P$3,INDIRECT("'"&$C11&"'!$A:$A"),$F$2) -> 0 | Q11: =SUMIFS(INDIRECT("'"&$C11&"'!$e:$e"),INDIRECT("'"&$C11&"'!$C:$C"),Q$3,INDIRECT("'"&$C11&"'!$A:$A"),$F$2) -> 0 | R11: =SUMIFS(INDIRECT("'"&$C11&"'!$e:$e"),INDIRECT("'"&$C11&"'!$C:$C"),R$3,INDIRECT("'"&$C11&"'!$A:$A"),$F$2) -> 0 | S11: =SUMIFS(INDIRECT("'"&$C11&"'!$e:$e"),INDIRECT("'"&$C11&"'!$C:$C"),S$3,INDIRECT("'"&$C11&"'!$A:$A"),$F$2) -> 0 | T11: =SUMIFS(INDIRECT("'"&$C11&"'!$e:$e"),INDIRECT("'"&$C11&"'!$C:$C"),T$3,INDIRECT("'"&$C11&"'!$A:$A"),$F$2) -> 0 | U11: =SUMIFS(INDIRECT("'"&$C11&"'!$e:$e"),INDIRECT("'"&$C11&"'!$C:$C"),U$3,INDIRECT("'"&$C11&"'!$A:$A"),$F$2) -> 0 | V11: =SUMIFS(INDIRECT("'"&$C11&"'!$e:$e"),INDIRECT("'"&$C11&"'!$C:$C"),V$3,INDIRECT("'"&$C11&"'!$A:$A"),$F$2) -> 0 | W11: =SUMIFS(INDIRECT("'"&$C11&"'!$e:$e"),INDIRECT("'"&$C11&"'!$C:$C"),W$3,INDIRECT("'"&$C11&"'!$A:$A"),$F$2) -> 0
A12: =IF(B12=0,MATCH($F$2,INDIRECT("'"&C12&"'!A:A"),1),MATCH($F$2,INDIRECT("'"&C12&"'!A:A"),0)) -> 2387 | B12: =COUNTIF(INDIRECT("'"&C12&"'!A:A"),$F$2) -> 0 | C12: 9 | F12: =VLOOKUP(C12,档案!A:B,2,FALSE) -> 农商行豹澥支行310028 | G12: =IF(B12=0,INDEX(INDIRECT("'"&$C12&"'!$F:$F"),$A12,1),INDEX(INDIRECT("'"&$C12&"'!$F:$F"),$A12-1,1)) -> 380075.61 | H12: =SUM(K12:O12) -> 0 | I12: =SUM(P12:W12) -> 0 | J12: =G12+H12-I12 -> 380075.61 | K12: =SUMIFS(INDIRECT("'"&$C12&"'!$D:$D"),INDIRECT("'"&$C12&"'!$C:$C"),K$3,INDIRECT("'"&$C12&"'!$A:$A"),$F$2) -> 0 | L12: =SUMIFS(INDIRECT("'"&$C12&"'!$D:$D"),INDIRECT("'"&$C12&"'!$C:$C"),L$3,INDIRECT("'"&$C12&"'!$A:$A"),$F$2) -> 0 | M12: =SUMIFS(INDIRECT("'"&$C12&"'!$D:$D"),INDIRECT("'"&$C12&"'!$C:$C"),M$3,INDIRECT("'"&$C12&"'!$A:$A"),$F$2) -> 0 | N12: =SUMIFS(INDIRECT("'"&$C12&"'!$D:$D"),INDIRECT("'"&$C12&"'!$C:$C"),N$3,INDIRECT("'"&$C12&"'!$A:$A"),$F$2) -> 0 | O12: =SUMIFS(INDIRECT("'"&$C12&"'!$D:$D"),INDIRECT("'"&$C12&"'!$C:$C"),O$3,INDIRECT("'"&$C12&"'!$A:$A"),$F$2) -> 0 | P12: =SUMIFS(INDIRECT("'"&$C12&"'!$e:$e"),INDIRECT("'"&$C12&"'!$C:$C"),P$3,INDIRECT("'"&$C12&"'!$A:$A"),$F$2) -> 0 | Q12: =SUMIFS(INDIRECT("'"&$C12&"'!$e:$e"),INDIRECT("'"&$C12&"'!$C:$C"),Q$3,INDIRECT("'"&$C12&"'!$A:$A"),$F$2) -> 0 | R12: =SUMIFS(INDIRECT("'"&$C12&"'!$e:$e"),INDIRECT("'"&$C12&"'!$C:$C"),R$3,INDIRECT("'"&$C12&"'!$A:$A"),$F$2) -> 0 | S12: =SUMIFS(INDIRECT("'"&$C12&"'!$e:$e"),INDIRECT("'"&$C12&"'!$C:$C"),S$3,INDIRECT("'"&$C12&"'!$A:$A"),$F$2) -> 0 | T12: =SUMIFS(INDIRECT("'"&$C12&"'!$e:$e"),INDIRECT("'"&$C12&"'!$C:$C"),T$3,INDIRECT("'"&$C12&"'!$A:$A"),$F$2) -> 0 | U12: =SUMIFS(INDIRECT("'"&$C12&"'!$e:$e"),INDIRECT("'"&$C12&"'!$C:$C"),U$3,INDIRECT("'"&$C12&"'!$A:$A"),$F$2) -> 0 | V12: =SUMIFS(INDIRECT("'"&$C12&"'!$e:$e"),INDIRECT("'"&$C12&"'!$C:$C"),V$3,INDIRECT("'"&$C12&"'!$A:$A"),$F$2) -> 0 | W12: =SUMIFS(INDIRECT("'"&$C12&"'!$e:$e"),INDIRECT("'"&$C12&"'!$C:$C"),W$3,INDIRECT("'"&$C12&"'!$A:$A"),$F$2) -> 0
A13: =IF(B13=0,MATCH($F$2,INDIRECT("'"&C13&"'!A:A"),1),MATCH($F$2,INDIRECT("'"&C13&"'!A:A"),0)) -> 109 | B13: =COUNTIF(INDIRECT("'"&C13&"'!A:A"),$F$2) -> 0 | C13: 10 | F13: =VLOOKUP(C13,档案!A:B,2,FALSE) -> 工行武汉瀚城支行004604 | G13: =IF(B13=0,INDEX(INDIRECT("'"&$C13&"'!$F:$F"),$A13,1),INDEX(INDIRECT("'"&$C13&"'!$F:$F"),$A13-1,1)) -> 15856.36 | H13: =SUM(K13:O13) -> 0 | I13: =SUM(P13:W13) -> 0 | J13: =G13+H13-I13 -> 15856.36 | K13: =SUMIFS(INDIRECT("'"&$C13&"'!$D:$D"),INDIRECT("'"&$C13&"'!$C:$C"),K$3,INDIRECT("'"&$C13&"'!$A:$A"),$F$2) -> 0 | L13: =SUMIFS(INDIRECT("'"&$C13&"'!$D:$D"),INDIRECT("'"&$C13&"'!$C:$C"),L$3,INDIRECT("'"&$C13&"'!$A:$A"),$F$2) -> 0 | M13: =SUMIFS(INDIRECT("'"&$C13&"'!$D:$D"),INDIRECT("'"&$C13&"'!$C:$C"),M$3,INDIRECT("'"&$C13&"'!$A:$A"),$F$2) -> 0 | N13: =SUMIFS(INDIRECT("'"&$C13&"'!$D:$D"),INDIRECT("'"&$C13&"'!$C:$C"),N$3,INDIRECT("'"&$C13&"'!$A:$A"),$F$2) -> 0 | O13: =SUMIFS(INDIRECT("'"&$C13&"'!$D:$D"),INDIRECT("'"&$C13&"'!$C:$C"),O$3,INDIRECT("'"&$C13&"'!$A:$A"),$F$2) -> 0 | P13: =SUMIFS(INDIRECT("'"&$C13&"'!$e:$e"),INDIRECT("'"&$C13&"'!$C:$C"),P$3,INDIRECT("'"&$C13&"'!$A:$A"),$F$2) -> 0 | Q13: =SUMIFS(INDIRECT("'"&$C13&"'!$e:$e"),INDIRECT("'"&$C13&"'!$C:$C"),Q$3,INDIRECT("'"&$C13&"'!$A:$A"),$F$2) -> 0 | R13: =SUMIFS(INDIRECT("'"&$C13&"'!$e:$e"),INDIRECT("'"&$C13&"'!$C:$C"),R$3,INDIRECT("'"&$C13&"'!$A:$A"),$F$2) -> 0 | S13: =SUMIFS(INDIRECT("'"&$C13&"'!$e:$e"),INDIRECT("'"&$C13&"'!$C:$C"),S$3,INDIRECT("'"&$C13&"'!$A:$A"),$F$2) -> 0 | T13: =SUMIFS(INDIRECT("'"&$C13&"'!$e:$e"),INDIRECT("'"&$C13&"'!$C:$C"),T$3,INDIRECT("'"&$C13&"'!$A:$A"),$F$2) -> 0 | U13: =SUMIFS(INDIRECT("'"&$C13&"'!$e:$e"),INDIRECT("'"&$C13&"'!$C:$C"),U$3,INDIRECT("'"&$C13&"'!$A:$A"),$F$2) -> 0 | V13: =SUMIFS(INDIRECT("'"&$C13&"'!$e:$e"),INDIRECT("'"&$C13&"'!$C:$C"),V$3,INDIRECT("'"&$C13&"'!$A:$A"),$F$2) -> 0 | W13: =SUMIFS(INDIRECT("'"&$C13&"'!$e:$e"),INDIRECT("'"&$C13&"'!$C:$C"),W$3,INDIRECT("'"&$C13&"'!$A:$A"),$F$2) -> 0
A14: =IF(B14=0,MATCH($F$2,INDIRECT("'"&C14&"'!A:A"),1),MATCH($F$2,INDIRECT("'"&C14&"'!A:A"),0)) -> 18 | B14: =COUNTIF(INDIRECT("'"&C14&"'!A:A"),$F$2) -> 0 | C14: 11 | F14: =VLOOKUP(C14,档案!A:B,2,FALSE) -> 青海农商行农民工工资保证金954442 | G14: =IF(B14=0,INDEX(INDIRECT("'"&$C14&"'!$F:$F"),$A14,1),INDEX(INDIRECT("'"&$C14&"'!$F:$F"),$A14-1,1)) -> 316856.32 | H14: =SUM(K14:O14) -> 0 | I14: =SUM(P14:W14) -> 0 | J14: =G14+H14-I14 -> 316856.32 | K14: =SUMIFS(INDIRECT("'"&$C14&"'!$D:$D"),INDIRECT("'"&$C14&"'!$C:$C"),K$3,INDIRECT("'"&$C14&"'!$A:$A"),$F$2) -> 0 | L14: =SUMIFS(INDIRECT("'"&$C14&"'!$D:$D"),INDIRECT("'"&$C14&"'!$C:$C"),L$3,INDIRECT("'"&$C14&"'!$A:$A"),$F$2) -> 0 | M14: =SUMIFS(INDIRECT("'"&$C14&"'!$D:$D"),INDIRECT("'"&$C14&"'!$C:$C"),M$3,INDIRECT("'"&$C14&"'!$A:$A"),$F$2) -> 0 | N14: =SUMIFS(INDIRECT("'"&$C14&"'!$D:$D"),INDIRECT("'"&$C14&"'!$C:$C"),N$3,INDIRECT("'"&$C14&"'!$A:$A"),$F$2) -> 0 | O14: =SUMIFS(INDIRECT("'"&$C14&"'!$D:$D"),INDIRECT("'"&$C14&"'!$C:$C"),O$3,INDIRECT("'"&$C14&"'!$A:$A"),$F$2) -> 0 | P14: =SUMIFS(INDIRECT("'"&$C14&"'!$e:$e"),INDIRECT("'"&$C14&"'!$C:$C"),P$3,INDIRECT("'"&$C14&"'!$A:$A"),$F$2) -> 0 | Q14: =SUMIFS(INDIRECT("'"&$C14&"'!$e:$e"),INDIRECT("'"&$C14&"'!$C:$C"),Q$3,INDIRECT("'"&$C14&"'!$A:$A"),$F$2) -> 0 | R14: =SUMIFS(INDIRECT("'"&$C14&"'!$e:$e"),INDIRECT("'"&$C14&"'!$C:$C"),R$3,INDIRECT("'"&$C14&"'!$A:$A"),$F$2) -> 0 | S14: =SUMIFS(INDIRECT("'"&$C14&"'!$e:$e"),INDIRECT("'"&$C14&"'!$C:$C"),S$3,INDIRECT("'"&$C14&"'!$A:$A"),$F$2) -> 0 | T14: =SUMIFS(INDIRECT("'"&$C14&"'!$e:$e"),INDIRECT("'"&$C14&"'!$C:$C"),T$3,INDIRECT("'"&$C14&"'!$A:$A"),$F$2) -> 0 | U14: =SUMIFS(INDIRECT("'"&$C14&"'!$e:$e"),INDIRECT("'"&$C14&"'!$C:$C"),U$3,INDIRECT("'"&$C14&"'!$A:$A"),$F$2) -> 0 | V14: =SUMIFS(INDIRECT("'"&$C14&"'!$e:$e"),INDIRECT("'"&$C14&"'!$C:$C"),V$3,INDIRECT("'"&$C14&"'!$A:$A"),$F$2) -> 0 | W14: =SUMIFS(INDIRECT("'"&$C14&"'!$e:$e"),INDIRECT("'"&$C14&"'!$C:$C"),W$3,INDIRECT("'"&$C14&"'!$A:$A"),$F$2) -> 0
A15: =IF(B15=0,MATCH($F$2,INDIRECT("'"&C15&"'!A:A"),1),MATCH($F$2,INDIRECT("'"&C15&"'!A:A"),0)) -> 3 | B15: =COUNTIF(INDIRECT("'"&C15&"'!A:A"),$F$2) -> 0 | C15: 12 | F15: =VLOOKUP(C15,档案!A:B,2,FALSE) -> 中国银行鹦鹉大道支行 | G15: =IF(B15=0,INDEX(INDIRECT("'"&$C15&"'!$F:$F"),$A15,1),INDEX(INDIRECT("'"&$C15&"'!$F:$F"),$A15-1,1)) -> 0 | H15: =SUM(K15:O15) -> 0 | I15: =SUM(P15:W15) -> 0 | J15: =G15+H15-I15 -> 0 | K15: =SUMIFS(INDIRECT("'"&$C15&"'!$D:$D"),INDIRECT("'"&$C15&"'!$C:$C"),K$3,INDIRECT("'"&$C15&"'!$A:$A"),$F$2) -> 0 | L15: =SUMIFS(INDIRECT("'"&$C15&"'!$D:$D"),INDIRECT("'"&$C15&"'!$C:$C"),L$3,INDIRECT("'"&$C15&"'!$A:$A"),$F$2) -> 0 | M15: =SUMIFS(INDIRECT("'"&$C15&"'!$D:$D"),INDIRECT("'"&$C15&"'!$C:$C"),M$3,INDIRECT("'"&$C15&"'!$A:$A"),$F$2) -> 0 | N15: =SUMIFS(INDIRECT("'"&$C15&"'!$D:$D"),INDIRECT("'"&$C15&"'!$C:$C"),N$3,INDIRECT("'"&$C15&"'!$A:$A"),$F$2) -> 0 | O15: =SUMIFS(INDIRECT("'"&$C15&"'!$D:$D"),INDIRECT("'"&$C15&"'!$C:$C"),O$3,INDIRECT("'"&$C15&"'!$A:$A"),$F$2) -> 0 | P15: =SUMIFS(INDIRECT("'"&$C15&"'!$e:$e"),INDIRECT("'"&$C15&"'!$C:$C"),P$3,INDIRECT("'"&$C15&"'!$A:$A"),$F$2) -> 0 | Q15: =SUMIFS(INDIRECT("'"&$C15&"'!$e:$e"),INDIRECT("'"&$C15&"'!$C:$C"),Q$3,INDIRECT("'"&$C15&"'!$A:$A"),$F$2) -> 0 | R15: =SUMIFS(INDIRECT("'"&$C15&"'!$e:$e"),INDIRECT("'"&$C15&"'!$C:$C"),R$3,INDIRECT("'"&$C15&"'!$A:$A"),$F$2) -> 0 | S15: =SUMIFS(INDIRECT("'"&$C15&"'!$e:$e"),INDIRECT("'"&$C15&"'!$C:$C"),S$3,INDIRECT("'"&$C15&"'!$A:$A"),$F$2) -> 0 | T15: =SUMIFS(INDIRECT("'"&$C15&"'!$e:$e"),INDIRECT("'"&$C15&"'!$C:$C"),T$3,INDIRECT("'"&$C15&"'!$A:$A"),$F$2) -> 0 | U15: =SUMIFS(INDIRECT("'"&$C15&"'!$e:$e"),INDIRECT("'"&$C15&"'!$C:$C"),U$3,INDIRECT("'"&$C15&"'!$A:$A"),$F$2) -> 0 | V15: =SUMIFS(INDIRECT("'"&$C15&"'!$e:$e"),INDIRECT("'"&$C15&"'!$C:$C"),V$3,INDIRECT("'"&$C15&"'!$A:$A"),$F$2) -> 0 | W15: =SUMIFS(INDIRECT("'"&$C15&"'!$e:$e"),INDIRECT("'"&$C15&"'!$C:$C"),W$3,INDIRECT("'"&$C15&"'!$A:$A"),$F$2) -> 0
A16: =IF(B16=0,MATCH($F$2,INDIRECT("'"&C16&"'!A:A"),1),MATCH($F$2,INDIRECT("'"&C16&"'!A:A"),0)) -> 8 | B16: =COUNTIF(INDIRECT("'"&C16&"'!A:A"),$F$2) -> 0 | C16: 13 | F16: =VLOOKUP(C16,档案!A:B,2,FALSE) -> 华夏银行京汉支行948890 | G16: =IF(B16=0,INDEX(INDIRECT("'"&$C16&"'!$F:$F"),$A16,1),INDEX(INDIRECT("'"&$C16&"'!$F:$F"),$A16-1,1)) -> 20458.33 | H16: =SUM(K16:O16) -> 0 | I16: =SUM(P16:W16) -> 0 | J16: =G16+H16-I16 -> 20458.33 | K16: =SUMIFS(INDIRECT("'"&$C16&"'!$D:$D"),INDIRECT("'"&$C16&"'!$C:$C"),K$3,INDIRECT("'"&$C16&"'!$A:$A"),$F$2) -> 0 | L16: =SUMIFS(INDIRECT("'"&$C16&"'!$D:$D"),INDIRECT("'"&$C16&"'!$C:$C"),L$3,INDIRECT("'"&$C16&"'!$A:$A"),$F$2) -> 0 | M16: =SUMIFS(INDIRECT("'"&$C16&"'!$D:$D"),INDIRECT("'"&$C16&"'!$C:$C"),M$3,INDIRECT("'"&$C16&"'!$A:$A"),$F$2) -> 0 | N16: =SUMIFS(INDIRECT("'"&$C16&"'!$D:$D"),INDIRECT("'"&$C16&"'!$C:$C"),N$3,INDIRECT("'"&$C16&"'!$A:$A"),$F$2) -> 0 | O16: =SUMIFS(INDIRECT("'"&$C16&"'!$D:$D"),INDIRECT("'"&$C16&"'!$C:$C"),O$3,INDIRECT("'"&$C16&"'!$A:$A"),$F$2) -> 0 | P16: =SUMIFS(INDIRECT("'"&$C16&"'!$e:$e"),INDIRECT("'"&$C16&"'!$C:$C"),P$3,INDIRECT("'"&$C16&"'!$A:$A"),$F$2) -> 0 | Q16: =SUMIFS(INDIRECT("'"&$C16&"'!$e:$e"),INDIRECT("'"&$C16&"'!$C:$C"),Q$3,INDIRECT("'"&$C16&"'!$A:$A"),$F$2) -> 0 | R16: =SUMIFS(INDIRECT("'"&$C16&"'!$e:$e"),INDIRECT("'"&$C16&"'!$C:$C"),R$3,INDIRECT("'"&$C16&"'!$A:$A"),$F$2) -> 0 | S16: =SUMIFS(INDIRECT("'"&$C16&"'!$e:$e"),INDIRECT("'"&$C16&"'!$C:$C"),S$3,INDIRECT("'"&$C16&"'!$A:$A"),$F$2) -> 0 | T16: =SUMIFS(INDIRECT("'"&$C16&"'!$e:$e"),INDIRECT("'"&$C16&"'!$C:$C"),T$3,INDIRECT("'"&$C16&"'!$A:$A"),$F$2) -> 0 | U16: =SUMIFS(INDIRECT("'"&$C16&"'!$e:$e"),INDIRECT("'"&$C16&"'!$C:$C"),U$3,INDIRECT("'"&$C16&"'!$A:$A"),$F$2) -> 0 | V16: =SUMIFS(INDIRECT("'"&$C16&"'!$e:$e"),INDIRECT("'"&$C16&"'!$C:$C"),V$3,INDIRECT("'"&$C16&"'!$A:$A"),$F$2) -> 0 | W16: =SUMIFS(INDIRECT("'"&$C16&"'!$e:$e"),INDIRECT("'"&$C16&"'!$C:$C"),W$3,INDIRECT("'"&$C16&"'!$A:$A"),$F$2) -> 0
... A18: =IF(B18=0,MATCH($F$2,INDIRECT("'"&C18&"'!A:A"),1),MATCH($F$2,INDIRECT("'"&C18&"'!A:A"),0)) -> 18 | B18: =COUNTIF(INDIRECT("'"&C18&"'!A:A"),$F$2) -> 0 | C18: 15 | F18: =VLOOKUP(C18,档案!A:B,2,FALSE) -> 青海农商行农民工工资发放账户001680 | G18: =IF(B18=0,INDEX(INDIRECT("'"&$C18&"'!$F:$F"),$A18,1),INDEX(INDIRECT("'"&$C18&"'!$F:$F"),$A18-1,1)) -> 17.24 | H18: =SUM(K18:O18) -> 0 | I18: =SUM(P18:W18) -> 0 | J18: =G18+H18-I18 -> 17.24 | K18: =SUMIFS(INDIRECT("'"&$C18&"'!$D:$D"),INDIRECT("'"&$C18&"'!$C:$C"),K$3,INDIRECT("'"&$C18&"'!$A:$A"),$F$2) -> 0 | L18: =SUMIFS(INDIRECT("'"&$C18&"'!$D:$D"),INDIRECT("'"&$C18&"'!$C:$C"),L$3,INDIRECT("'"&$C18&"'!$A:$A"),$F$2) -> 0 | M18: =SUMIFS(INDIRECT("'"&$C18&"'!$D:$D"),INDIRECT("'"&$C18&"'!$C:$C"),M$3,INDIRECT("'"&$C18&"'!$A:$A"),$F$2) -> 0 | N18: =SUMIFS(INDIRECT("'"&$C18&"'!$D:$D"),INDIRECT("'"&$C18&"'!$C:$C"),N$3,INDIRECT("'"&$C18&"'!$A:$A"),$F$2) -> 0 | O18: =SUMIFS(INDIRECT("'"&$C18&"'!$D:$D"),INDIRECT("'"&$C18&"'!$C:$C"),O$3,INDIRECT("'"&$C18&"'!$A:$A"),$F$2) -> 0 | P18: =SUMIFS(INDIRECT("'"&$C18&"'!$e:$e"),INDIRECT("'"&$C18&"'!$C:$C"),P$3,INDIRECT("'"&$C18&"'!$A:$A"),$F$2) -> 0 | Q18: =SUMIFS(INDIRECT("'"&$C18&"'!$e:$e"),INDIRECT("'"&$C18&"'!$C:$C"),Q$3,INDIRECT("'"&$C18&"'!$A:$A"),$F$2) -> 0 | R18: =SUMIFS(INDIRECT("'"&$C18&"'!$e:$e"),INDIRECT("'"&$C18&"'!$C:$C"),R$3,INDIRECT("'"&$C18&"'!$A:$A"),$F$2) -> 0 | S18: =SUMIFS(INDIRECT("'"&$C18&"'!$e:$e"),INDIRECT("'"&$C18&"'!$C:$C"),S$3,INDIRECT("'"&$C18&"'!$A:$A"),$F$2) -> 0 | T18: =SUMIFS(INDIRECT("'"&$C18&"'!$e:$e"),INDIRECT("'"&$C18&"'!$C:$C"),T$3,INDIRECT("'"&$C18&"'!$A:$A"),$F$2) -> 0 | U18: =SUMIFS(INDIRECT("'"&$C18&"'!$e:$e"),INDIRECT("'"&$C18&"'!$C:$C"),U$3,INDIRECT("'"&$C18&"'!$A:$A"),$F$2) -> 0 | V18: =SUMIFS(INDIRECT("'"&$C18&"'!$e:$e"),INDIRECT("'"&$C18&"'!$C:$C"),V$3,INDIRECT("'"&$C18&"'!$A:$A"),$F$2) -> 0 | W18: =SUMIFS(INDIRECT("'"&$C18&"'!$e:$e"),INDIRECT("'"&$C18&"'!$C:$C"),W$3,INDIRECT("'"&$C18&"'!$A:$A"),$F$2) -> 0
A19: =IF(B19=0,MATCH($F$2,INDIRECT("'"&C19&"'!A:A"),1),MATCH($F$2,INDIRECT("'"&C19&"'!A:A"),0)) -> #REF! | B19: =COUNTIF(INDIRECT("'"&C19&"'!A:A"),$F$2) -> #REF! | F19: 小计 | G19: =SUM(G4:G18) -> 931348.47 | H19: =SUM(K19:O19) -> 40000 | I19: =SUM(P19:W19) -> 3.5 | J19: =G19+H19-I19 -> 971344.97 | K19: =SUM(K4:K18) -> 0 | L19: =SUM(L4:L18) -> 0 | M19: =SUM(M4:M18) -> 0 | N19: =SUM(N4:N18) -> 40000 | O19: =SUM(O4:O18) -> 0 | P19: =SUM(P4:P18) -> 0 | Q19: =SUM(Q4:Q18) -> 0 | R19: =SUM(R4:R18) -> 1.5 | ... W19: =SUM(W4:W18) -> 0
A20: =IF(B20=0,MATCH($F$2,INDIRECT("'"&C20&"'!A:A"),1),MATCH($F$2,INDIRECT("'"&C20&"'!A:A"),0)) -> 265 | B20: =COUNTIF(INDIRECT("'"&C20&"'!A:A"),$F$2) -> 0 | C20: 16 | E20: =VLOOKUP(C20,档案!A:B,2,FALSE) -> 电子承兑汇票 | G20: =IF(B20=0,INDEX(INDIRECT("'"&$C20&"'!$F:$F"),$A20,1),INDEX(INDIRECT("'"&$C20&"'!$F:$F"),$A20-1,1)) -> 615485.38 | H20: =SUM(K20:O20) -> 0 | I20: =SUM(P20:W20) -> 0 | J20: =G20+H20-I20 -> 615485.38 | K20: =SUMIFS(INDIRECT("'"&$C20&"'!$D:$D"),INDIRECT("'"&$C20&"'!$C:$C"),K$3,INDIRECT("'"&$C20&"'!$A:$A"),$F$2) -> 0 | L20: =SUMIFS(INDIRECT("'"&$C20&"'!$D:$D"),INDIRECT("'"&$C20&"'!$C:$C"),L$3,INDIRECT("'"&$C20&"'!$A:$A"),$F$2) -> 0 | M20: =SUMIFS(INDIRECT("'"&$C20&"'!$D:$D"),INDIRECT("'"&$C20&"'!$C:$C"),M$3,INDIRECT("'"&$C20&"'!$A:$A"),$F$2) -> 0 | N20: =SUMIFS(INDIRECT("'"&$C20&"'!$D:$D"),INDIRECT("'"&$C20&"'!$C:$C"),N$3,INDIRECT("'"&$C20&"'!$A:$A"),$F$2) -> 0 | O20: =SUMIFS(INDIRECT("'"&$C20&"'!$D:$D"),INDIRECT("'"&$C20&"'!$C:$C"),O$3,INDIRECT("'"&$C20&"'!$A:$A"),$F$2) -> 0 | P20: =SUMIFS(INDIRECT("'"&$C20&"'!$e:$e"),INDIRECT("'"&$C20&"'!$C:$C"),P$3,INDIRECT("'"&$C20&"'!$A:$A"),$F$2) -> 0 | Q20: =SUMIFS(INDIRECT("'"&$C20&"'!$e:$e"),INDIRECT("'"&$C20&"'!$C:$C"),Q$3,INDIRECT("'"&$C20&"'!$A:$A"),$F$2) -> 0 | R20: =SUMIFS(INDIRECT("'"&$C20&"'!$e:$e"),INDIRECT("'"&$C20&"'!$C:$C"),R$3,INDIRECT("'"&$C20&"'!$A:$A"),$F$2) -> 0 | S20: =SUMIFS(INDIRECT("'"&$C20&"'!$e:$e"),INDIRECT("'"&$C20&"'!$C:$C"),S$3,INDIRECT("'"&$C20&"'!$A:$A"),$F$2) -> 0 | T20: =SUMIFS(INDIRECT("'"&$C20&"'!$e:$e"),INDIRECT("'"&$C20&"'!$C:$C"),T$3,INDIRECT("'"&$C20&"'!$A:$A"),$F$2) -> 0 | U20: =SUMIFS(INDIRECT("'"&$C20&"'!$e:$e"),INDIRECT("'"&$C20&"'!$C:$C"),U$3,INDIRECT("'"&$C20&"'!$A:$A"),$F$2) -> 0 | V20: =SUMIFS(INDIRECT("'"&$C20&"'!$e:$e"),INDIRECT("'"&$C20&"'!$C:$C"),V$3,INDIRECT("'"&$C20&"'!$A:$A"),$F$2) -> 0 | W20: =SUMIFS(INDIRECT("'"&$C20&"'!$e:$e"),INDIRECT("'"&$C20&"'!$C:$C"),W$3,INDIRECT("'"&$C20&"'!$A:$A"),$F$2) -> 0
A21: =IF(B21=0,MATCH($F$2,INDIRECT("'"&C21&"'!A:A"),1),MATCH($F$2,INDIRECT("'"&C21&"'!A:A"),0)) -> 7 | B21: =COUNTIF(INDIRECT("'"&C21&"'!A:A"),$F$2) -> 0 | C21: 17 | E21: =VLOOKUP(C21,档案!A:B,2,FALSE) -> 库存现金 | G21: =IF(B21=0,INDEX(INDIRECT("'"&$C21&"'!$F:$F"),$A21,1),INDEX(INDIRECT("'"&$C21&"'!$F:$F"),$A21-1,1)) -> 305 | H21: =SUM(K21:O21) -> 0 | I21: =SUM(P21:W21) -> 0 | J21: =G21+H21-I21 -> 305 | K21: =SUMIFS(INDIRECT("'"&$C21&"'!$D:$D"),INDIRECT("'"&$C21&"'!$C:$C"),K$3,INDIRECT("'"&$C21&"'!$A:$A"),$F$2) -> 0 | L21: =SUMIFS(INDIRECT("'"&$C21&"'!$D:$D"),INDIRECT("'"&$C21&"'!$C:$C"),L$3,INDIRECT("'"&$C21&"'!$A:$A"),$F$2) -> 0 | M21: =SUMIFS(INDIRECT("'"&$C21&"'!$D:$D"),INDIRECT("'"&$C21&"'!$C:$C"),M$3,INDIRECT("'"&$C21&"'!$A:$A"),$F$2) -> 0 | N21: =SUMIFS(INDIRECT("'"&$C21&"'!$D:$D"),INDIRECT("'"&$C21&"'!$C:$C"),N$3,INDIRECT("'"&$C21&"'!$A:$A"),$F$2) -> 0 | O21: =SUMIFS(INDIRECT("'"&$C21&"'!$D:$D"),INDIRECT("'"&$C21&"'!$C:$C"),O$3,INDIRECT("'"&$C21&"'!$A:$A"),$F$2) -> 0 | P21: =SUMIFS(INDIRECT("'"&$C21&"'!$e:$e"),INDIRECT("'"&$C21&"'!$C:$C"),P$3,INDIRECT("'"&$C21&"'!$A:$A"),$F$2) -> 0 | Q21: =SUMIFS(INDIRECT("'"&$C21&"'!$e:$e"),INDIRECT("'"&$C21&"'!$C:$C"),Q$3,INDIRECT("'"&$C21&"'!$A:$A"),$F$2) -> 0 | R21: =SUMIFS(INDIRECT("'"&$C21&"'!$e:$e"),INDIRECT("'"&$C21&"'!$C:$C"),R$3,INDIRECT("'"&$C21&"'!$A:$A"),$F$2) -> 0 | S21: =SUMIFS(INDIRECT("'"&$C21&"'!$e:$e"),INDIRECT("'"&$C21&"'!$C:$C"),S$3,INDIRECT("'"&$C21&"'!$A:$A"),$F$2) -> 0 | T21: =SUMIFS(INDIRECT("'"&$C21&"'!$e:$e"),INDIRECT("'"&$C21&"'!$C:$C"),T$3,INDIRECT("'"&$C21&"'!$A:$A"),$F$2) -> 0 | U21: =SUMIFS(INDIRECT("'"&$C21&"'!$e:$e"),INDIRECT("'"&$C21&"'!$C:$C"),U$3,INDIRECT("'"&$C21&"'!$A:$A"),$F$2) -> 0 | V21: =SUMIFS(INDIRECT("'"&$C21&"'!$e:$e"),INDIRECT("'"&$C21&"'!$C:$C"),V$3,INDIRECT("'"&$C21&"'!$A:$A"),$F$2) -> 0 | W21: =SUMIFS(INDIRECT("'"&$C21&"'!$e:$e"),INDIRECT("'"&$C21&"'!$C:$C"),W$3,INDIRECT("'"&$C21&"'!$A:$A"),$F$2) -> 0
A22: =IF(B22=0,MATCH($F$2,INDIRECT("'"&C22&"'!A:A"),1),MATCH($F$2,INDIRECT("'"&C22&"'!A:A"),0)) -> #REF! | B22: =COUNTIF(INDIRECT("'"&C22&"'!A:A"),$F$2) -> #REF! | E22: 合计 | G22: =SUM(G19:G21) -> 1547138.9 | H22: =SUM(K22:O22) -> 40000 | I22: =SUM(P22:W22) -> 3.5 | J22: =G22+H22-I22 -> 1587135.4 | K22: =SUM(K19:K21) -> 0 | L22: =SUM(L19:L21) -> 0 | M22: =SUM(M19:M21) -> 0 | N22: =SUM(N19:N21) -> 40000 | O22: =SUM(O19:O21) -> 0 | P22: =SUM(P19:P21) -> 0 | Q22: =SUM(Q19:Q21) -> 0 | R22: =SUM(R19:R21) -> 1.5 | ... W22: =SUM(W19:W21) -> 0
A23: =IF(B23=0,MATCH($F$2,INDIRECT("'"&C23&"'!A:A"),1),MATCH($F$2,INDIRECT("'"&C23&"'!A:A"),0)) -> 22 | B23: =COUNTIF(INDIRECT("'"&C23&"'!A:A"),$F$2) -> 0 | C23: 18 | D23: 武汉彤烨 | E23: 银行存款 | F23: =VLOOKUP(C23,档案!A:B,2,FALSE) -> 工商银行西山支行15212 | G23: =IF(B23=0,INDEX(INDIRECT("'"&$C23&"'!$F:$F"),$A23,1),INDEX(INDIRECT("'"&$C23&"'!$F:$F"),$A23-1,1)) -> 790.72 | H23: =SUM(K23:O23) -> 0 | I23: =SUM(P23:W23) -> 0 | J23: =G23+H23-I23 -> 790.72 | K23: =SUMIFS(INDIRECT("'"&$C23&"'!$D:$D"),INDIRECT("'"&$C23&"'!$C:$C"),K$3,INDIRECT("'"&$C23&"'!$A:$A"),$F$2) -> 0 | L23: =SUMIFS(INDIRECT("'"&$C23&"'!$D:$D"),INDIRECT("'"&$C23&"'!$C:$C"),L$3,INDIRECT("'"&$C23&"'!$A:$A"),$F$2) -> 0 | M23: =SUMIFS(INDIRECT("'"&$C23&"'!$D:$D"),INDIRECT("'"&$C23&"'!$C:$C"),M$3,INDIRECT("'"&$C23&"'!$A:$A"),$F$2) -> 0 | N23: =SUMIFS(INDIRECT("'"&$C23&"'!$D:$D"),INDIRECT("'"&$C23&"'!$C:$C"),N$3,INDIRECT("'"&$C23&"'!$A:$A"),$F$2) -> 0 | O23: =SUMIFS(INDIRECT("'"&$C23&"'!$D:$D"),INDIRECT("'"&$C23&"'!$C:$C"),O$3,INDIRECT("'"&$C23&"'!$A:$A"),$F$2) -> 0 | P23: =SUMIFS(INDIRECT("'"&$C23&"'!$e:$e"),INDIRECT("'"&$C23&"'!$C:$C"),P$3,INDIRECT("'"&$C23&"'!$A:$A"),$F$2) -> 0 | Q23: =SUMIFS(INDIRECT("'"&$C23&"'!$e:$e"),INDIRECT("'"&$C23&"'!$C:$C"),Q$3,INDIRECT("'"&$C23&"'!$A:$A"),$F$2) -> 0 | R23: =SUMIFS(INDIRECT("'"&$C23&"'!$e:$e"),INDIRECT("'"&$C23&"'!$C:$C"),R$3,INDIRECT("'"&$C23&"'!$A:$A"),$F$2) -> 0 | S23: =SUMIFS(INDIRECT("'"&$C23&"'!$e:$e"),INDIRECT("'"&$C23&"'!$C:$C"),S$3,INDIRECT("'"&$C23&"'!$A:$A"),$F$2) -> 0 | T23: =SUMIFS(INDIRECT("'"&$C23&"'!$e:$e"),INDIRECT("'"&$C23&"'!$C:$C"),T$3,INDIRECT("'"&$C23&"'!$A:$A"),$F$2) -> 0 | U23: =SUMIFS(INDIRECT("'"&$C23&"'!$e:$e"),INDIRECT("'"&$C23&"'!$C:$C"),U$3,INDIRECT("'"&$C23&"'!$A:$A"),$F$2) -> 0 | V23: =SUMIFS(INDIRECT("'"&$C23&"'!$e:$e"),INDIRECT("'"&$C23&"'!$C:$C"),V$3,INDIRECT("'"&$C23&"'!$A:$A"),$F$2) -> 0 | W23: =SUMIFS(INDIRECT("'"&$C23&"'!$e:$e"),INDIRECT("'"&$C23&"'!$C:$C"),W$3,INDIRECT("'"&$C23&"'!$A:$A"),$F$2) -> 0
A24: =IF(B24=0,MATCH($F$2,INDIRECT("'"&C24&"'!A:A"),1),MATCH($F$2,INDIRECT("'"&C24&"'!A:A"),0)) -> 155 | B24: =COUNTIF(INDIRECT("'"&C24&"'!A:A"),$F$2) -> 0 | C24: 19 | F24: =VLOOKUP(C24,档案!A:B,2,FALSE) -> 建设银行绿地支行0564 | G24: =IF(B24=0,INDEX(INDIRECT("'"&$C24&"'!$F:$F"),$A24,1),INDEX(INDIRECT("'"&$C24&"'!$F:$F"),$A24-1,1)) -> 7497.59 | H24: =SUM(K24:O24) -> 0 | I24: =SUM(P24:W24) -> 0 | J24: =G24+H24-I24 -> 7497.59 | K24: =SUMIFS(INDIRECT("'"&$C24&"'!$D:$D"),INDIRECT("'"&$C24&"'!$C:$C"),K$3,INDIRECT("'"&$C24&"'!$A:$A"),$F$2) -> 0 | L24: =SUMIFS(INDIRECT("'"&$C24&"'!$D:$D"),INDIRECT("'"&$C24&"'!$C:$C"),L$3,INDIRECT("'"&$C24&"'!$A:$A"),$F$2) -> 0 | M24: =SUMIFS(INDIRECT("'"&$C24&"'!$D:$D"),INDIRECT("'"&$C24&"'!$C:$C"),M$3,INDIRECT("'"&$C24&"'!$A:$A"),$F$2) -> 0 | N24: =SUMIFS(INDIRECT("'"&$C24&"'!$D:$D"),INDIRECT("'"&$C24&"'!$C:$C"),N$3,INDIRECT("'"&$C24&"'!$A:$A"),$F$2) -> 0 | O24: =SUMIFS(INDIRECT("'"&$C24&"'!$D:$D"),INDIRECT("'"&$C24&"'!$C:$C"),O$3,INDIRECT("'"&$C24&"'!$A:$A"),$F$2) -> 0 | P24: =SUMIFS(INDIRECT("'"&$C24&"'!$e:$e"),INDIRECT("'"&$C24&"'!$C:$C"),P$3,INDIRECT("'"&$C24&"'!$A:$A"),$F$2) -> 0 | Q24: =SUMIFS(INDIRECT("'"&$C24&"'!$e:$e"),INDIRECT("'"&$C24&"'!$C:$C"),Q$3,INDIRECT("'"&$C24&"'!$A:$A"),$F$2) -> 0 | R24: =SUMIFS(INDIRECT("'"&$C24&"'!$e:$e"),INDIRECT("'"&$C24&"'!$C:$C"),R$3,INDIRECT("'"&$C24&"'!$A:$A"),$F$2) -> 0 | S24: =SUMIFS(INDIRECT("'"&$C24&"'!$e:$e"),INDIRECT("'"&$C24&"'!$C:$C"),S$3,INDIRECT("'"&$C24&"'!$A:$A"),$F$2) -> 0 | T24: =SUMIFS(INDIRECT("'"&$C24&"'!$e:$e"),INDIRECT("'"&$C24&"'!$C:$C"),T$3,INDIRECT("'"&$C24&"'!$A:$A"),$F$2) -> 0 | U24: =SUMIFS(INDIRECT("'"&$C24&"'!$e:$e"),INDIRECT("'"&$C24&"'!$C:$C"),U$3,INDIRECT("'"&$C24&"'!$A:$A"),$F$2) -> 0 | V24: =SUMIFS(INDIRECT("'"&$C24&"'!$e:$e"),INDIRECT("'"&$C24&"'!$C:$C"),V$3,INDIRECT("'"&$C24&"'!$A:$A"),$F$2) -> 0 | W24: =SUMIFS(INDIRECT("'"&$C24&"'!$e:$e"),INDIRECT("'"&$C24&"'!$C:$C"),W$3,INDIRECT("'"&$C24&"'!$A:$A"),$F$2) -> 0
A25: =IF(B25=0,MATCH($F$2,INDIRECT("'"&C25&"'!A:A"),1),MATCH($F$2,INDIRECT("'"&C25&"'!A:A"),0)) -> 191 | B25: =COUNTIF(INDIRECT("'"&C25&"'!A:A"),$F$2) -> 0 | C25: 20 | F25: =VLOOKUP(C25,档案!A:B,2,FALSE) -> 中信银行武汉东湖支行181028 | G25: =IF(B25=0,INDEX(INDIRECT("'"&$C25&"'!$F:$F"),$A25,1),INDEX(INDIRECT("'"&$C25&"'!$F:$F"),$A25-1,1)) -> 8121.22 | H25: =SUM(K25:O25) -> 0 | I25: =SUM(P25:W25) -> 0 | J25: =G25+H25-I25 -> 8121.22 | K25: =SUMIFS(INDIRECT("'"&$C25&"'!$D:$D"),INDIRECT("'"&$C25&"'!$C:$C"),K$3,INDIRECT("'"&$C25&"'!$A:$A"),$F$2) -> 0 | L25: =SUMIFS(INDIRECT("'"&$C25&"'!$D:$D"),INDIRECT("'"&$C25&"'!$C:$C"),L$3,INDIRECT("'"&$C25&"'!$A:$A"),$F$2) -> 0 | M25: =SUMIFS(INDIRECT("'"&$C25&"'!$D:$D"),INDIRECT("'"&$C25&"'!$C:$C"),M$3,INDIRECT("'"&$C25&"'!$A:$A"),$F$2) -> 0 | N25: =SUMIFS(INDIRECT("'"&$C25&"'!$D:$D"),INDIRECT("'"&$C25&"'!$C:$C"),N$3,INDIRECT("'"&$C25&"'!$A:$A"),$F$2) -> 0 | O25: =SUMIFS(INDIRECT("'"&$C25&"'!$D:$D"),INDIRECT("'"&$C25&"'!$C:$C"),O$3,INDIRECT("'"&$C25&"'!$A:$A"),$F$2) -> 0 | P25: =SUMIFS(INDIRECT("'"&$C25&"'!$e:$e"),INDIRECT("'"&$C25&"'!$C:$C"),P$3,INDIRECT("'"&$C25&"'!$A:$A"),$F$2) -> 0 | Q25: =SUMIFS(INDIRECT("'"&$C25&"'!$e:$e"),INDIRECT("'"&$C25&"'!$C:$C"),Q$3,INDIRECT("'"&$C25&"'!$A:$A"),$F$2) -> 0 | R25: =SUMIFS(INDIRECT("'"&$C25&"'!$e:$e"),INDIRECT("'"&$C25&"'!$C:$C"),R$3,INDIRECT("'"&$C25&"'!$A:$A"),$F$2) -> 0 | S25: =SUMIFS(INDIRECT("'"&$C25&"'!$e:$e"),INDIRECT("'"&$C25&"'!$C:$C"),S$3,INDIRECT("'"&$C25&"'!$A:$A"),$F$2) -> 0 | T25: =SUMIFS(INDIRECT("'"&$C25&"'!$e:$e"),INDIRECT("'"&$C25&"'!$C:$C"),T$3,INDIRECT("'"&$C25&"'!$A:$A"),$F$2) -> 0 | U25: =SUMIFS(INDIRECT("'"&$C25&"'!$e:$e"),INDIRECT("'"&$C25&"'!$C:$C"),U$3,INDIRECT("'"&$C25&"'!$A:$A"),$F$2) -> 0 | V25: =SUMIFS(INDIRECT("'"&$C25&"'!$e:$e"),INDIRECT("'"&$C25&"'!$C:$C"),V$3,INDIRECT("'"&$C25&"'!$A:$A"),$F$2) -> 0 | W25: =SUMIFS(INDIRECT("'"&$C25&"'!$e:$e"),INDIRECT("'"&$C25&"'!$C:$C"),W$3,INDIRECT("'"&$C25&"'!$A:$A"),$F$2) -> 0
A26: =IF(B26=0,MATCH($F$2,INDIRECT("'"&C26&"'!A:A"),1),MATCH($F$2,INDIRECT("'"&C26&"'!A:A"),0)) -> 8 | B26: =COUNTIF(INDIRECT("'"&C26&"'!A:A"),$F$2) -> 0 | C26: 21 | F26: =VLOOKUP(C26,档案!A:B,2,FALSE) -> 汉口银行光谷分行454891 | G26: =IF(B26=0,INDEX(INDIRECT("'"&$C26&"'!$F:$F"),$A26,1),INDEX(INDIRECT("'"&$C26&"'!$F:$F"),$A26-1,1)) -> 631.97 | H26: =SUM(K26:O26) -> 0 | I26: =SUM(P26:W26) -> 0 | J26: =G26+H26-I26 -> 631.97 | K26: =SUMIFS(INDIRECT("'"&$C26&"'!$D:$D"),INDIRECT("'"&$C26&"'!$C:$C"),K$3,INDIRECT("'"&$C26&"'!$A:$A"),$F$2) -> 0 | L26: =SUMIFS(INDIRECT("'"&$C26&"'!$D:$D"),INDIRECT("'"&$C26&"'!$C:$C"),L$3,INDIRECT("'"&$C26&"'!$A:$A"),$F$2) -> 0 | M26: =SUMIFS(INDIRECT("'"&$C26&"'!$D:$D"),INDIRECT("'"&$C26&"'!$C:$C"),M$3,INDIRECT("'"&$C26&"'!$A:$A"),$F$2) -> 0 | N26: =SUMIFS(INDIRECT("'"&$C26&"'!$D:$D"),INDIRECT("'"&$C26&"'!$C:$C"),N$3,INDIRECT("'"&$C26&"'!$A:$A"),$F$2) -> 0 | O26: =SUMIFS(INDIRECT("'"&$C26&"'!$D:$D"),INDIRECT("'"&$C26&"'!$C:$C"),O$3,INDIRECT("'"&$C26&"'!$A:$A"),$F$2) -> 0 | P26: =SUMIFS(INDIRECT("'"&$C26&"'!$e:$e"),INDIRECT("'"&$C26&"'!$C:$C"),P$3,INDIRECT("'"&$C26&"'!$A:$A"),$F$2) -> 0 | Q26: =SUMIFS(INDIRECT("'"&$C26&"'!$e:$e"),INDIRECT("'"&$C26&"'!$C:$C"),Q$3,INDIRECT("'"&$C26&"'!$A:$A"),$F$2) -> 0 | R26: =SUMIFS(INDIRECT("'"&$C26&"'!$e:$e"),INDIRECT("'"&$C26&"'!$C:$C"),R$3,INDIRECT("'"&$C26&"'!$A:$A"),$F$2) -> 0 | S26: =SUMIFS(INDIRECT("'"&$C26&"'!$e:$e"),INDIRECT("'"&$C26&"'!$C:$C"),S$3,INDIRECT("'"&$C26&"'!$A:$A"),$F$2) -> 0 | T26: =SUMIFS(INDIRECT("'"&$C26&"'!$e:$e"),INDIRECT("'"&$C26&"'!$C:$C"),T$3,INDIRECT("'"&$C26&"'!$A:$A"),$F$2) -> 0 | U26: =SUMIFS(INDIRECT("'"&$C26&"'!$e:$e"),INDIRECT("'"&$C26&"'!$C:$C"),U$3,INDIRECT("'"&$C26&"'!$A:$A"),$F$2) -> 0 | V26: =SUMIFS(INDIRECT("'"&$C26&"'!$e:$e"),INDIRECT("'"&$C26&"'!$C:$C"),V$3,INDIRECT("'"&$C26&"'!$A:$A"),$F$2) -> 0 | W26: =SUMIFS(INDIRECT("'"&$C26&"'!$e:$e"),INDIRECT("'"&$C26&"'!$C:$C"),W$3,INDIRECT("'"&$C26&"'!$A:$A"),$F$2) -> 0
A27: =IF(B27=0,MATCH($F$2,INDIRECT("'"&C27&"'!A:A"),1),MATCH($F$2,INDIRECT("'"&C27&"'!A:A"),0)) -> 3 | B27: =COUNTIF(INDIRECT("'"&C27&"'!A:A"),$F$2) -> 0 | C27: 22 | F27: =VLOOKUP(C27,档案!A:B,2,FALSE) -> 0 | G27: =IF(B27=0,INDEX(INDIRECT("'"&$C27&"'!$F:$F"),$A27,1),INDEX(INDIRECT("'"&$C27&"'!$F:$F"),$A27-1,1)) -> 0 | H27: =SUM(K27:O27) -> 0 | I27: =SUM(P27:W27) -> 0 | J27: =G27+H27-I27 -> 0 | K27: =SUMIFS(INDIRECT("'"&$C27&"'!$D:$D"),INDIRECT("'"&$C27&"'!$C:$C"),K$3,INDIRECT("'"&$C27&"'!$A:$A"),$F$2) -> 0 | L27: =SUMIFS(INDIRECT("'"&$C27&"'!$D:$D"),INDIRECT("'"&$C27&"'!$C:$C"),L$3,INDIRECT("'"&$C27&"'!$A:$A"),$F$2) -> 0 | M27: =SUMIFS(INDIRECT("'"&$C27&"'!$D:$D"),INDIRECT("'"&$C27&"'!$C:$C"),M$3,INDIRECT("'"&$C27&"'!$A:$A"),$F$2) -> 0 | N27: =SUMIFS(INDIRECT("'"&$C27&"'!$D:$D"),INDIRECT("'"&$C27&"'!$C:$C"),N$3,INDIRECT("'"&$C27&"'!$A:$A"),$F$2) -> 0 | O27: =SUMIFS(INDIRECT("'"&$C27&"'!$D:$D"),INDIRECT("'"&$C27&"'!$C:$C"),O$3,INDIRECT("'"&$C27&"'!$A:$A"),$F$2) -> 0 | P27: =SUMIFS(INDIRECT("'"&$C27&"'!$e:$e"),INDIRECT("'"&$C27&"'!$C:$C"),P$3,INDIRECT("'"&$C27&"'!$A:$A"),$F$2) -> 0 | Q27: =SUMIFS(INDIRECT("'"&$C27&"'!$e:$e"),INDIRECT("'"&$C27&"'!$C:$C"),Q$3,INDIRECT("'"&$C27&"'!$A:$A"),$F$2) -> 0 | R27: =SUMIFS(INDIRECT("'"&$C27&"'!$e:$e"),INDIRECT("'"&$C27&"'!$C:$C"),R$3,INDIRECT("'"&$C27&"'!$A:$A"),$F$2) -> 0 | S27: =SUMIFS(INDIRECT("'"&$C27&"'!$e:$e"),INDIRECT("'"&$C27&"'!$C:$C"),S$3,INDIRECT("'"&$C27&"'!$A:$A"),$F$2) -> 0 | T27: =SUMIFS(INDIRECT("'"&$C27&"'!$e:$e"),INDIRECT("'"&$C27&"'!$C:$C"),T$3,INDIRECT("'"&$C27&"'!$A:$A"),$F$2) -> 0 | U27: =SUMIFS(INDIRECT("'"&$C27&"'!$e:$e"),INDIRECT("'"&$C27&"'!$C:$C"),U$3,INDIRECT("'"&$C27&"'!$A:$A"),$F$2) -> 0 | V27: =SUMIFS(INDIRECT("'"&$C27&"'!$e:$e"),INDIRECT("'"&$C27&"'!$C:$C"),V$3,INDIRECT("'"&$C27&"'!$A:$A"),$F$2) -> 0 | W27: =SUMIFS(INDIRECT("'"&$C27&"'!$e:$e"),INDIRECT("'"&$C27&"'!$C:$C"),W$3,INDIRECT("'"&$C27&"'!$A:$A"),$F$2) -> 0
A28: =IF(B28=0,MATCH($F$2,INDIRECT("'"&C28&"'!A:A"),1),MATCH($F$2,INDIRECT("'"&C28&"'!A:A"),0)) -> 3 | B28: =COUNTIF(INDIRECT("'"&C28&"'!A:A"),$F$2) -> 0 | C28: 23 | F28: =VLOOKUP(C28,档案!A:B,2,FALSE) -> 0 | G28: =IF(B28=0,INDEX(INDIRECT("'"&$C28&"'!$F:$F"),$A28,1),INDEX(INDIRECT("'"&$C28&"'!$F:$F"),$A28-1,1)) -> 0 | H28: =SUM(K28:O28) -> 0 | I28: =SUM(P28:W28) -> 0 | J28: =G28+H28-I28 -> 0 | K28: =SUMIFS(INDIRECT("'"&$C28&"'!$D:$D"),INDIRECT("'"&$C28&"'!$C:$C"),K$3,INDIRECT("'"&$C28&"'!$A:$A"),$F$2) -> 0 | L28: =SUMIFS(INDIRECT("'"&$C28&"'!$D:$D"),INDIRECT("'"&$C28&"'!$C:$C"),L$3,INDIRECT("'"&$C28&"'!$A:$A"),$F$2) -> 0 | M28: =SUMIFS(INDIRECT("'"&$C28&"'!$D:$D"),INDIRECT("'"&$C28&"'!$C:$C"),M$3,INDIRECT("'"&$C28&"'!$A:$A"),$F$2) -> 0 | N28: =SUMIFS(INDIRECT("'"&$C28&"'!$D:$D"),INDIRECT("'"&$C28&"'!$C:$C"),N$3,INDIRECT("'"&$C28&"'!$A:$A"),$F$2) -> 0 | O28: =SUMIFS(INDIRECT("'"&$C28&"'!$D:$D"),INDIRECT("'"&$C28&"'!$C:$C"),O$3,INDIRECT("'"&$C28&"'!$A:$A"),$F$2) -> 0 | P28: =SUMIFS(INDIRECT("'"&$C28&"'!$e:$e"),INDIRECT("'"&$C28&"'!$C:$C"),P$3,INDIRECT("'"&$C28&"'!$A:$A"),$F$2) -> 0 | Q28: =SUMIFS(INDIRECT("'"&$C28&"'!$e:$e"),INDIRECT("'"&$C28&"'!$C:$C"),Q$3,INDIRECT("'"&$C28&"'!$A:$A"),$F$2) -> 0 | R28: =SUMIFS(INDIRECT("'"&$C28&"'!$e:$e"),INDIRECT("'"&$C28&"'!$C:$C"),R$3,INDIRECT("'"&$C28&"'!$A:$A"),$F$2) -> 0 | S28: =SUMIFS(INDIRECT("'"&$C28&"'!$e:$e"),INDIRECT("'"&$C28&"'!$C:$C"),S$3,INDIRECT("'"&$C28&"'!$A:$A"),$F$2) -> 0 | T28: =SUMIFS(INDIRECT("'"&$C28&"'!$e:$e"),INDIRECT("'"&$C28&"'!$C:$C"),T$3,INDIRECT("'"&$C28&"'!$A:$A"),$F$2) -> 0 | U28: =SUMIFS(INDIRECT("'"&$C28&"'!$e:$e"),INDIRECT("'"&$C28&"'!$C:$C"),U$3,INDIRECT("'"&$C28&"'!$A:$A"),$F$2) -> 0 | V28: =SUMIFS(INDIRECT("'"&$C28&"'!$e:$e"),INDIRECT("'"&$C28&"'!$C:$C"),V$3,INDIRECT("'"&$C28&"'!$A:$A"),$F$2) -> 0 | W28: =SUMIFS(INDIRECT("'"&$C28&"'!$e:$e"),INDIRECT("'"&$C28&"'!$C:$C"),W$3,INDIRECT("'"&$C28&"'!$A:$A"),$F$2) -> 0
A29: =IF(B29=0,MATCH($F$2,INDIRECT("'"&C29&"'!A:A"),1),MATCH($F$2,INDIRECT("'"&C29&"'!A:A"),0)) -> 3 | B29: =COUNTIF(INDIRECT("'"&C29&"'!A:A"),$F$2) -> 0 | C29: 24 | F29: =VLOOKUP(C29,档案!A:B,2,FALSE) -> 0 | G29: =IF(B29=0,INDEX(INDIRECT("'"&$C29&"'!$F:$F"),$A29,1),INDEX(INDIRECT("'"&$C29&"'!$F:$F"),$A29-1,1)) -> 0 | H29: =SUM(K29:O29) -> 0 | I29: =SUM(P29:W29) -> 0 | J29: =G29+H29-I29 -> 0 | K29: =SUMIFS(INDIRECT("'"&$C29&"'!$D:$D"),INDIRECT("'"&$C29&"'!$C:$C"),K$3,INDIRECT("'"&$C29&"'!$A:$A"),$F$2) -> 0 | L29: =SUMIFS(INDIRECT("'"&$C29&"'!$D:$D"),INDIRECT("'"&$C29&"'!$C:$C"),L$3,INDIRECT("'"&$C29&"'!$A:$A"),$F$2) -> 0 | M29: =SUMIFS(INDIRECT("'"&$C29&"'!$D:$D"),INDIRECT("'"&$C29&"'!$C:$C"),M$3,INDIRECT("'"&$C29&"'!$A:$A"),$F$2) -> 0 | N29: =SUMIFS(INDIRECT("'"&$C29&"'!$D:$D"),INDIRECT("'"&$C29&"'!$C:$C"),N$3,INDIRECT("'"&$C29&"'!$A:$A"),$F$2) -> 0 | O29: =SUMIFS(INDIRECT("'"&$C29&"'!$D:$D"),INDIRECT("'"&$C29&"'!$C:$C"),O$3,INDIRECT("'"&$C29&"'!$A:$A"),$F$2) -> 0 | P29: =SUMIFS(INDIRECT("'"&$C29&"'!$e:$e"),INDIRECT("'"&$C29&"'!$C:$C"),P$3,INDIRECT("'"&$C29&"'!$A:$A"),$F$2) -> 0 | Q29: =SUMIFS(INDIRECT("'"&$C29&"'!$e:$e"),INDIRECT("'"&$C29&"'!$C:$C"),Q$3,INDIRECT("'"&$C29&"'!$A:$A"),$F$2) -> 0 | R29: =SUMIFS(INDIRECT("'"&$C29&"'!$e:$e"),INDIRECT("'"&$C29&"'!$C:$C"),R$3,INDIRECT("'"&$C29&"'!$A:$A"),$F$2) -> 0 | S29: =SUMIFS(INDIRECT("'"&$C29&"'!$e:$e"),INDIRECT("'"&$C29&"'!$C:$C"),S$3,INDIRECT("'"&$C29&"'!$A:$A"),$F$2) -> 0 | T29: =SUMIFS(INDIRECT("'"&$C29&"'!$e:$e"),INDIRECT("'"&$C29&"'!$C:$C"),T$3,INDIRECT("'"&$C29&"'!$A:$A"),$F$2) -> 0 | U29: =SUMIFS(INDIRECT("'"&$C29&"'!$e:$e"),INDIRECT("'"&$C29&"'!$C:$C"),U$3,INDIRECT("'"&$C29&"'!$A:$A"),$F$2) -> 0 | V29: =SUMIFS(INDIRECT("'"&$C29&"'!$e:$e"),INDIRECT("'"&$C29&"'!$C:$C"),V$3,INDIRECT("'"&$C29&"'!$A:$A"),$F$2) -> 0 | W29: =SUMIFS(INDIRECT("'"&$C29&"'!$e:$e"),INDIRECT("'"&$C29&"'!$C:$C"),W$3,INDIRECT("'"&$C29&"'!$A:$A"),$F$2) -> 0
A30: =IF(B30=0,MATCH($F$2,INDIRECT("'"&C30&"'!A:A"),1),MATCH($F$2,INDIRECT("'"&C30&"'!A:A"),0)) -> #REF! | B30: =COUNTIF(INDIRECT("'"&C30&"'!A:A"),$F$2) -> #REF! | F30: 小计 | G30: =SUM(G23:G29) -> 17041.5 | H30: =SUM(K30:O30) -> 0 | I30: =SUM(P30:W30) -> 0 | J30: =G30+H30-I30 -> 17041.5 | K30: =SUM(K23:K29) -> 0 | L30: =SUM(L23:L29) -> 0 | M30: =SUM(M23:M29) -> 0 | N30: =SUM(N23:N29) -> 0 | O30: =SUM(O23:O29) -> 0 | P30: =SUM(P23:P29) -> 0 | Q30: =SUM(Q23:Q29) -> 0 | R30: =SUM(R23:R29) -> 0 | ... W30: =SUM(W23:W29) -> 0
A31: =IF(B31=0,MATCH($F$2,INDIRECT("'"&C31&"'!A:A"),1),MATCH($F$2,INDIRECT("'"&C31&"'!A:A"),0)) -> 16 | B31: =COUNTIF(INDIRECT("'"&C31&"'!A:A"),$F$2) -> 0 | C31: 25 | E31: =VLOOKUP(C31,档案!A:B,2,FALSE) -> 电子承兑汇票 | G31: =IF(B31=0,INDEX(INDIRECT("'"&$C31&"'!$F:$F"),$A31,1),INDEX(INDIRECT("'"&$C31&"'!$F:$F"),$A31-1,1)) -> 0 | H31: =SUM(K31:O31) -> 0 | I31: =SUM(P31:W31) -> 0 | J31: =G31+H31-I31 -> 0 | K31: =SUMIFS(INDIRECT("'"&$C31&"'!$D:$D"),INDIRECT("'"&$C31&"'!$C:$C"),K$3,INDIRECT("'"&$C31&"'!$A:$A"),$F$2) -> 0 | L31: =SUMIFS(INDIRECT("'"&$C31&"'!$D:$D"),INDIRECT("'"&$C31&"'!$C:$C"),L$3,INDIRECT("'"&$C31&"'!$A:$A"),$F$2) -> 0 | M31: =SUMIFS(INDIRECT("'"&$C31&"'!$D:$D"),INDIRECT("'"&$C31&"'!$C:$C"),M$3,INDIRECT("'"&$C31&"'!$A:$A"),$F$2) -> 0 | N31: =SUMIFS(INDIRECT("'"&$C31&"'!$D:$D"),INDIRECT("'"&$C31&"'!$C:$C"),N$3,INDIRECT("'"&$C31&"'!$A:$A"),$F$2) -> 0 | O31: =SUMIFS(INDIRECT("'"&$C31&"'!$D:$D"),INDIRECT("'"&$C31&"'!$C:$C"),O$3,INDIRECT("'"&$C31&"'!$A:$A"),$F$2) -> 0 | P31: =SUMIFS(INDIRECT("'"&$C31&"'!$e:$e"),INDIRECT("'"&$C31&"'!$C:$C"),P$3,INDIRECT("'"&$C31&"'!$A:$A"),$F$2) -> 0 | Q31: =SUMIFS(INDIRECT("'"&$C31&"'!$e:$e"),INDIRECT("'"&$C31&"'!$C:$C"),Q$3,INDIRECT("'"&$C31&"'!$A:$A"),$F$2) -> 0 | R31: =SUMIFS(INDIRECT("'"&$C31&"'!$e:$e"),INDIRECT("'"&$C31&"'!$C:$C"),R$3,INDIRECT("'"&$C31&"'!$A:$A"),$F$2) -> 0 | S31: =SUMIFS(INDIRECT("'"&$C31&"'!$e:$e"),INDIRECT("'"&$C31&"'!$C:$C"),S$3,INDIRECT("'"&$C31&"'!$A:$A"),$F$2) -> 0 | T31: =SUMIFS(INDIRECT("'"&$C31&"'!$e:$e"),INDIRECT("'"&$C31&"'!$C:$C"),T$3,INDIRECT("'"&$C31&"'!$A:$A"),$F$2) -> 0 | U31: =SUMIFS(INDIRECT("'"&$C31&"'!$e:$e"),INDIRECT("'"&$C31&"'!$C:$C"),U$3,INDIRECT("'"&$C31&"'!$A:$A"),$F$2) -> 0 | V31: =SUMIFS(INDIRECT("'"&$C31&"'!$e:$e"),INDIRECT("'"&$C31&"'!$C:$C"),V$3,INDIRECT("'"&$C31&"'!$A:$A"),$F$2) -> 0 | W31: =SUMIFS(INDIRECT("'"&$C31&"'!$e:$e"),INDIRECT("'"&$C31&"'!$C:$C"),W$3,INDIRECT("'"&$C31&"'!$A:$A"),$F$2) -> 0
A32: =IF(B32=0,MATCH($F$2,INDIRECT("'"&C32&"'!A:A"),1),MATCH($F$2,INDIRECT("'"&C32&"'!A:A"),0)) -> 3 | B32: =COUNTIF(INDIRECT("'"&C32&"'!A:A"),$F$2) -> 0 | C32: 26 | E32: =VLOOKUP(C32,档案!A:B,2,FALSE) -> 库存现金 | G32: =IF(B32=0,INDEX(INDIRECT("'"&$C32&"'!$F:$F"),$A32,1),INDEX(INDIRECT("'"&$C32&"'!$F:$F"),$A32-1,1)) -> 0 | H32: =SUM(K32:O32) -> 0 | I32: =SUM(P32:W32) -> 0 | J32: =G32+H32-I32 -> 0 | K32: =SUMIFS(INDIRECT("'"&$C32&"'!$D:$D"),INDIRECT("'"&$C32&"'!$C:$C"),K$3,INDIRECT("'"&$C32&"'!$A:$A"),$F$2) -> 0 | L32: =SUMIFS(INDIRECT("'"&$C32&"'!$D:$D"),INDIRECT("'"&$C32&"'!$C:$C"),L$3,INDIRECT("'"&$C32&"'!$A:$A"),$F$2) -> 0 | M32: =SUMIFS(INDIRECT("'"&$C32&"'!$D:$D"),INDIRECT("'"&$C32&"'!$C:$C"),M$3,INDIRECT("'"&$C32&"'!$A:$A"),$F$2) -> 0 | N32: =SUMIFS(INDIRECT("'"&$C32&"'!$D:$D"),INDIRECT("'"&$C32&"'!$C:$C"),N$3,INDIRECT("'"&$C32&"'!$A:$A"),$F$2) -> 0 | O32: =SUMIFS(INDIRECT("'"&$C32&"'!$D:$D"),INDIRECT("'"&$C32&"'!$C:$C"),O$3,INDIRECT("'"&$C32&"'!$A:$A"),$F$2) -> 0 | P32: =SUMIFS(INDIRECT("'"&$C32&"'!$e:$e"),INDIRECT("'"&$C32&"'!$C:$C"),P$3,INDIRECT("'"&$C32&"'!$A:$A"),$F$2) -> 0 | Q32: =SUMIFS(INDIRECT("'"&$C32&"'!$e:$e"),INDIRECT("'"&$C32&"'!$C:$C"),Q$3,INDIRECT("'"&$C32&"'!$A:$A"),$F$2) -> 0 | R32: =SUMIFS(INDIRECT("'"&$C32&"'!$e:$e"),INDIRECT("'"&$C32&"'!$C:$C"),R$3,INDIRECT("'"&$C32&"'!$A:$A"),$F$2) -> 0 | S32: =SUMIFS(INDIRECT("'"&$C32&"'!$e:$e"),INDIRECT("'"&$C32&"'!$C:$C"),S$3,INDIRECT("'"&$C32&"'!$A:$A"),$F$2) -> 0 | T32: =SUMIFS(INDIRECT("'"&$C32&"'!$e:$e"),INDIRECT("'"&$C32&"'!$C:$C"),T$3,INDIRECT("'"&$C32&"'!$A:$A"),$F$2) -> 0 | U32: =SUMIFS(INDIRECT("'"&$C32&"'!$e:$e"),INDIRECT("'"&$C32&"'!$C:$C"),U$3,INDIRECT("'"&$C32&"'!$A:$A"),$F$2) -> 0 | V32: =SUMIFS(INDIRECT("'"&$C32&"'!$e:$e"),INDIRECT("'"&$C32&"'!$C:$C"),V$3,INDIRECT("'"&$C32&"'!$A:$A"),$F$2) -> 0 | W32: =SUMIFS(INDIRECT("'"&$C32&"'!$e:$e"),INDIRECT("'"&$C32&"'!$C:$C"),W$3,INDIRECT("'"&$C32&"'!$A:$A"),$F$2) -> 0
A33: =IF(B33=0,MATCH($F$2,INDIRECT("'"&C33&"'!A:A"),1),MATCH($F$2,INDIRECT("'"&C33&"'!A:A"),0)) -> #REF! | B33: =COUNTIF(INDIRECT("'"&C33&"'!A:A"),$F$2) -> #REF! | E33: 合计 | G33: =SUM(G30:G32) -> 17041.5 | H33: =SUM(K33:O33) -> 0 | I33: =SUM(P33:W33) -> 0 | J33: =G33+H33-I33 -> 17041.5 | K33: =SUM(K30:K32) -> 0 | L33: =SUM(L30:L32) -> 0 | M33: =SUM(M30:M32) -> 0 | N33: =SUM(N30:N32) -> 0 | O33: =SUM(O30:O32) -> 0 | P33: =SUM(P30:P32) -> 0 | Q33: =SUM(Q30:Q32) -> 0 | R33: =SUM(R30:R32) -> 0 | ... W33: =SUM(W30:W32) -> 0
A34: =IF(B34=0,MATCH($F$2,INDIRECT("'"&C34&"'!A:A"),1),MATCH($F$2,INDIRECT("'"&C34&"'!A:A"),0)) -> 424 | B34: =COUNTIF(INDIRECT("'"&C34&"'!A:A"),$F$2) -> 1 | C34: 27 | D34: 湖北开明 | E34: 银行存款 | F34: =VLOOKUP(C34,档案!A:B,2,FALSE) -> 邮政凤凰路支行 | G34: =IF(B34=0,INDEX(INDIRECT("'"&$C34&"'!$F:$F"),$A34,1),INDEX(INDIRECT("'"&$C34&"'!$F:$F"),$A34-1,1)) -> 54054.19 | H34: =SUM(K34:O34) -> 0 | I34: =SUM(P34:W34) -> 39525 | J34: =G34+H34-I34 -> 14529.19 | K34: =SUMIFS(INDIRECT("'"&$C34&"'!$D:$D"),INDIRECT("'"&$C34&"'!$C:$C"),K$3,INDIRECT("'"&$C34&"'!$A:$A"),$F$2) -> 0 | L34: =SUMIFS(INDIRECT("'"&$C34&"'!$D:$D"),INDIRECT("'"&$C34&"'!$C:$C"),L$3,INDIRECT("'"&$C34&"'!$A:$A"),$F$2) -> 0 | M34: =SUMIFS(INDIRECT("'"&$C34&"'!$D:$D"),INDIRECT("'"&$C34&"'!$C:$C"),M$3,INDIRECT("'"&$C34&"'!$A:$A"),$F$2) -> 0 | N34: =SUMIFS(INDIRECT("'"&$C34&"'!$D:$D"),INDIRECT("'"&$C34&"'!$C:$C"),N$3,INDIRECT("'"&$C34&"'!$A:$A"),$F$2) -> 0 | O34: =SUMIFS(INDIRECT("'"&$C34&"'!$D:$D"),INDIRECT("'"&$C34&"'!$C:$C"),O$3,INDIRECT("'"&$C34&"'!$A:$A"),$F$2) -> 0 | P34: =SUMIFS(INDIRECT("'"&$C34&"'!$e:$e"),INDIRECT("'"&$C34&"'!$C:$C"),P$3,INDIRECT("'"&$C34&"'!$A:$A"),$F$2) -> 0 | Q34: =SUMIFS(INDIRECT("'"&$C34&"'!$e:$e"),INDIRECT("'"&$C34&"'!$C:$C"),Q$3,INDIRECT("'"&$C34&"'!$A:$A"),$F$2) -> 0 | R34: =SUMIFS(INDIRECT("'"&$C34&"'!$e:$e"),INDIRECT("'"&$C34&"'!$C:$C"),R$3,INDIRECT("'"&$C34&"'!$A:$A"),$F$2) -> 0 | S34: =SUMIFS(INDIRECT("'"&$C34&"'!$e:$e"),INDIRECT("'"&$C34&"'!$C:$C"),S$3,INDIRECT("'"&$C34&"'!$A:$A"),$F$2) -> 39525 | T34: =SUMIFS(INDIRECT("'"&$C34&"'!$e:$e"),INDIRECT("'"&$C34&"'!$C:$C"),T$3,INDIRECT("'"&$C34&"'!$A:$A"),$F$2) -> 0 | U34: =SUMIFS(INDIRECT("'"&$C34&"'!$e:$e"),INDIRECT("'"&$C34&"'!$C:$C"),U$3,INDIRECT("'"&$C34&"'!$A:$A"),$F$2) -> 0 | V34: =SUMIFS(INDIRECT("'"&$C34&"'!$e:$e"),INDIRECT("'"&$C34&"'!$C:$C"),V$3,INDIRECT("'"&$C34&"'!$A:$A"),$F$2) -> 0 | W34: =SUMIFS(INDIRECT("'"&$C34&"'!$e:$e"),INDIRECT("'"&$C34&"'!$C:$C"),W$3,INDIRECT("'"&$C34&"'!$A:$A"),$F$2) -> 0
A35: =IF(B35=0,MATCH($F$2,INDIRECT("'"&C35&"'!A:A"),1),MATCH($F$2,INDIRECT("'"&C35&"'!A:A"),0)) -> 6 | B35: =COUNTIF(INDIRECT("'"&C35&"'!A:A"),$F$2) -> 0 | C35: 28 | F35: =VLOOKUP(C35,档案!A:B,2,FALSE) -> 农商行开发区支行604928 | G35: =IF(B35=0,INDEX(INDIRECT("'"&$C35&"'!$F:$F"),$A35,1),INDEX(INDIRECT("'"&$C35&"'!$F:$F"),$A35-1,1)) -> 3015.61 | H35: =SUM(K35:O35) -> 0 | I35: =SUM(P35:W35) -> 0 | J35: =G35+H35-I35 -> 3015.61 | K35: =SUMIFS(INDIRECT("'"&$C35&"'!$D:$D"),INDIRECT("'"&$C35&"'!$C:$C"),K$3,INDIRECT("'"&$C35&"'!$A:$A"),$F$2) -> 0 | L35: =SUMIFS(INDIRECT("'"&$C35&"'!$D:$D"),INDIRECT("'"&$C35&"'!$C:$C"),L$3,INDIRECT("'"&$C35&"'!$A:$A"),$F$2) -> 0 | M35: =SUMIFS(INDIRECT("'"&$C35&"'!$D:$D"),INDIRECT("'"&$C35&"'!$C:$C"),M$3,INDIRECT("'"&$C35&"'!$A:$A"),$F$2) -> 0 | N35: =SUMIFS(INDIRECT("'"&$C35&"'!$D:$D"),INDIRECT("'"&$C35&"'!$C:$C"),N$3,INDIRECT("'"&$C35&"'!$A:$A"),$F$2) -> 0 | O35: =SUMIFS(INDIRECT("'"&$C35&"'!$D:$D"),INDIRECT("'"&$C35&"'!$C:$C"),O$3,INDIRECT("'"&$C35&"'!$A:$A"),$F$2) -> 0 | P35: =SUMIFS(INDIRECT("'"&$C35&"'!$e:$e"),INDIRECT("'"&$C35&"'!$C:$C"),P$3,INDIRECT("'"&$C35&"'!$A:$A"),$F$2) -> 0 | Q35: =SUMIFS(INDIRECT("'"&$C35&"'!$e:$e"),INDIRECT("'"&$C35&"'!$C:$C"),Q$3,INDIRECT("'"&$C35&"'!$A:$A"),$F$2) -> 0 | R35: =SUMIFS(INDIRECT("'"&$C35&"'!$e:$e"),INDIRECT("'"&$C35&"'!$C:$C"),R$3,INDIRECT("'"&$C35&"'!$A:$A"),$F$2) -> 0 | S35: =SUMIFS(INDIRECT("'"&$C35&"'!$e:$e"),INDIRECT("'"&$C35&"'!$C:$C"),S$3,INDIRECT("'"&$C35&"'!$A:$A"),$F$2) -> 0 | T35: =SUMIFS(INDIRECT("'"&$C35&"'!$e:$e"),INDIRECT("'"&$C35&"'!$C:$C"),T$3,INDIRECT("'"&$C35&"'!$A:$A"),$F$2) -> 0 | U35: =SUMIFS(INDIRECT("'"&$C35&"'!$e:$e"),INDIRECT("'"&$C35&"'!$C:$C"),U$3,INDIRECT("'"&$C35&"'!$A:$A"),$F$2) -> 0 | V35: =SUMIFS(INDIRECT("'"&$C35&"'!$e:$e"),INDIRECT("'"&$C35&"'!$C:$C"),V$3,INDIRECT("'"&$C35&"'!$A:$A"),$F$2) -> 0 | W35: =SUMIFS(INDIRECT("'"&$C35&"'!$e:$e"),INDIRECT("'"&$C35&"'!$C:$C"),W$3,INDIRECT("'"&$C35&"'!$A:$A"),$F$2) -> 0
A36: =IF(B36=0,MATCH($F$2,INDIRECT("'"&C36&"'!A:A"),1),MATCH($F$2,INDIRECT("'"&C36&"'!A:A"),0)) -> 190 | B36: =COUNTIF(INDIRECT("'"&C36&"'!A:A"),$F$2) -> 0 | C36: 29 | F36: =VLOOKUP(C36,档案!A:B,2,FALSE) -> 工行西山支行004096 | G36: =IF(B36=0,INDEX(INDIRECT("'"&$C36&"'!$F:$F"),$A36,1),INDEX(INDIRECT("'"&$C36&"'!$F:$F"),$A36-1,1)) -> 7649.18 | H36: =SUM(K36:O36) -> 0 | I36: =SUM(P36:W36) -> 0 | J36: =G36+H36-I36 -> 7649.18 | K36: =SUMIFS(INDIRECT("'"&$C36&"'!$D:$D"),INDIRECT("'"&$C36&"'!$C:$C"),K$3,INDIRECT("'"&$C36&"'!$A:$A"),$F$2) -> 0 | L36: =SUMIFS(INDIRECT("'"&$C36&"'!$D:$D"),INDIRECT("'"&$C36&"'!$C:$C"),L$3,INDIRECT("'"&$C36&"'!$A:$A"),$F$2) -> 0 | M36: =SUMIFS(INDIRECT("'"&$C36&"'!$D:$D"),INDIRECT("'"&$C36&"'!$C:$C"),M$3,INDIRECT("'"&$C36&"'!$A:$A"),$F$2) -> 0 | N36: =SUMIFS(INDIRECT("'"&$C36&"'!$D:$D"),INDIRECT("'"&$C36&"'!$C:$C"),N$3,INDIRECT("'"&$C36&"'!$A:$A"),$F$2) -> 0 | O36: =SUMIFS(INDIRECT("'"&$C36&"'!$D:$D"),INDIRECT("'"&$C36&"'!$C:$C"),O$3,INDIRECT("'"&$C36&"'!$A:$A"),$F$2) -> 0 | P36: =SUMIFS(INDIRECT("'"&$C36&"'!$e:$e"),INDIRECT("'"&$C36&"'!$C:$C"),P$3,INDIRECT("'"&$C36&"'!$A:$A"),$F$2) -> 0 | Q36: =SUMIFS(INDIRECT("'"&$C36&"'!$e:$e"),INDIRECT("'"&$C36&"'!$C:$C"),Q$3,INDIRECT("'"&$C36&"'!$A:$A"),$F$2) -> 0 | R36: =SUMIFS(INDIRECT("'"&$C36&"'!$e:$e"),INDIRECT("'"&$C36&"'!$C:$C"),R$3,INDIRECT("'"&$C36&"'!$A:$A"),$F$2) -> 0 | S36: =SUMIFS(INDIRECT("'"&$C36&"'!$e:$e"),INDIRECT("'"&$C36&"'!$C:$C"),S$3,INDIRECT("'"&$C36&"'!$A:$A"),$F$2) -> 0 | T36: =SUMIFS(INDIRECT("'"&$C36&"'!$e:$e"),INDIRECT("'"&$C36&"'!$C:$C"),T$3,INDIRECT("'"&$C36&"'!$A:$A"),$F$2) -> 0 | U36: =SUMIFS(INDIRECT("'"&$C36&"'!$e:$e"),INDIRECT("'"&$C36&"'!$C:$C"),U$3,INDIRECT("'"&$C36&"'!$A:$A"),$F$2) -> 0 | V36: =SUMIFS(INDIRECT("'"&$C36&"'!$e:$e"),INDIRECT("'"&$C36&"'!$C:$C"),V$3,INDIRECT("'"&$C36&"'!$A:$A"),$F$2) -> 0 | W36: =SUMIFS(INDIRECT("'"&$C36&"'!$e:$e"),INDIRECT("'"&$C36&"'!$C:$C"),W$3,INDIRECT("'"&$C36&"'!$A:$A"),$F$2) -> 0
A37: =IF(B37=0,MATCH($F$2,INDIRECT("'"&C37&"'!A:A"),1),MATCH($F$2,INDIRECT("'"&C37&"'!A:A"),0)) -> 52 | B37: =COUNTIF(INDIRECT("'"&C37&"'!A:A"),$F$2) -> 0 | C37: 30 | F37: =VLOOKUP(C37,档案!A:B,2,FALSE) -> 工行虹桥支行54786 | G37: =IF(B37=0,INDEX(INDIRECT("'"&$C37&"'!$F:$F"),$A37,1),INDEX(INDIRECT("'"&$C37&"'!$F:$F"),$A37-1,1)) -> 64.68 | H37: =SUM(K37:O37) -> 0 | I37: =SUM(P37:W37) -> 0 | J37: =G37+H37-I37 -> 64.68 | K37: =SUMIFS(INDIRECT("'"&$C37&"'!$D:$D"),INDIRECT("'"&$C37&"'!$C:$C"),K$3,INDIRECT("'"&$C37&"'!$A:$A"),$F$2) -> 0 | L37: =SUMIFS(INDIRECT("'"&$C37&"'!$D:$D"),INDIRECT("'"&$C37&"'!$C:$C"),L$3,INDIRECT("'"&$C37&"'!$A:$A"),$F$2) -> 0 | M37: =SUMIFS(INDIRECT("'"&$C37&"'!$D:$D"),INDIRECT("'"&$C37&"'!$C:$C"),M$3,INDIRECT("'"&$C37&"'!$A:$A"),$F$2) -> 0 | N37: =SUMIFS(INDIRECT("'"&$C37&"'!$D:$D"),INDIRECT("'"&$C37&"'!$C:$C"),N$3,INDIRECT("'"&$C37&"'!$A:$A"),$F$2) -> 0 | O37: =SUMIFS(INDIRECT("'"&$C37&"'!$D:$D"),INDIRECT("'"&$C37&"'!$C:$C"),O$3,INDIRECT("'"&$C37&"'!$A:$A"),$F$2) -> 0 | P37: =SUMIFS(INDIRECT("'"&$C37&"'!$e:$e"),INDIRECT("'"&$C37&"'!$C:$C"),P$3,INDIRECT("'"&$C37&"'!$A:$A"),$F$2) -> 0 | Q37: =SUMIFS(INDIRECT("'"&$C37&"'!$e:$e"),INDIRECT("'"&$C37&"'!$C:$C"),Q$3,INDIRECT("'"&$C37&"'!$A:$A"),$F$2) -> 0 | R37: =SUMIFS(INDIRECT("'"&$C37&"'!$e:$e"),INDIRECT("'"&$C37&"'!$C:$C"),R$3,INDIRECT("'"&$C37&"'!$A:$A"),$F$2) -> 0 | S37: =SUMIFS(INDIRECT("'"&$C37&"'!$e:$e"),INDIRECT("'"&$C37&"'!$C:$C"),S$3,INDIRECT("'"&$C37&"'!$A:$A"),$F$2) -> 0 | T37: =SUMIFS(INDIRECT("'"&$C37&"'!$e:$e"),INDIRECT("'"&$C37&"'!$C:$C"),T$3,INDIRECT("'"&$C37&"'!$A:$A"),$F$2) -> 0 | U37: =SUMIFS(INDIRECT("'"&$C37&"'!$e:$e"),INDIRECT("'"&$C37&"'!$C:$C"),U$3,INDIRECT("'"&$C37&"'!$A:$A"),$F$2) -> 0 | V37: =SUMIFS(INDIRECT("'"&$C37&"'!$e:$e"),INDIRECT("'"&$C37&"'!$C:$C"),V$3,INDIRECT("'"&$C37&"'!$A:$A"),$F$2) -> 0 | W37: =SUMIFS(INDIRECT("'"&$C37&"'!$e:$e"),INDIRECT("'"&$C37&"'!$C:$C"),W$3,INDIRECT("'"&$C37&"'!$A:$A"),$F$2) -> 0
A38: =IF(B38=0,MATCH($F$2,INDIRECT("'"&C38&"'!A:A"),1),MATCH($F$2,INDIRECT("'"&C38&"'!A:A"),0)) -> 976 | B38: =COUNTIF(INDIRECT("'"&C38&"'!A:A"),$F$2) -> 0 | C38: 31 | F38: =VLOOKUP(C38,档案!A:B,2,FALSE) -> 中国银行鄂州分行0592794 | G38: =IF(B38=0,INDEX(INDIRECT("'"&$C38&"'!$F:$F"),$A38,1),INDEX(INDIRECT("'"&$C38&"'!$F:$F"),$A38-1,1)) -> 148184.84 | H38: =SUM(K38:O38) -> 0 | I38: =SUM(P38:W38) -> 0 | J38: =G38+H38-I38 -> 148184.84 | K38: =SUMIFS(INDIRECT("'"&$C38&"'!$D:$D"),INDIRECT("'"&$C38&"'!$C:$C"),K$3,INDIRECT("'"&$C38&"'!$A:$A"),$F$2) -> 0 | L38: =SUMIFS(INDIRECT("'"&$C38&"'!$D:$D"),INDIRECT("'"&$C38&"'!$C:$C"),L$3,INDIRECT("'"&$C38&"'!$A:$A"),$F$2) -> 0 | M38: =SUMIFS(INDIRECT("'"&$C38&"'!$D:$D"),INDIRECT("'"&$C38&"'!$C:$C"),M$3,INDIRECT("'"&$C38&"'!$A:$A"),$F$2) -> 0 | N38: =SUMIFS(INDIRECT("'"&$C38&"'!$D:$D"),INDIRECT("'"&$C38&"'!$C:$C"),N$3,INDIRECT("'"&$C38&"'!$A:$A"),$F$2) -> 0 | O38: =SUMIFS(INDIRECT("'"&$C38&"'!$D:$D"),INDIRECT("'"&$C38&"'!$C:$C"),O$3,INDIRECT("'"&$C38&"'!$A:$A"),$F$2) -> 0 | P38: =SUMIFS(INDIRECT("'"&$C38&"'!$e:$e"),INDIRECT("'"&$C38&"'!$C:$C"),P$3,INDIRECT("'"&$C38&"'!$A:$A"),$F$2) -> 0 | Q38: =SUMIFS(INDIRECT("'"&$C38&"'!$e:$e"),INDIRECT("'"&$C38&"'!$C:$C"),Q$3,INDIRECT("'"&$C38&"'!$A:$A"),$F$2) -> 0 | R38: =SUMIFS(INDIRECT("'"&$C38&"'!$e:$e"),INDIRECT("'"&$C38&"'!$C:$C"),R$3,INDIRECT("'"&$C38&"'!$A:$A"),$F$2) -> 0 | S38: =SUMIFS(INDIRECT("'"&$C38&"'!$e:$e"),INDIRECT("'"&$C38&"'!$C:$C"),S$3,INDIRECT("'"&$C38&"'!$A:$A"),$F$2) -> 0 | T38: =SUMIFS(INDIRECT("'"&$C38&"'!$e:$e"),INDIRECT("'"&$C38&"'!$C:$C"),T$3,INDIRECT("'"&$C38&"'!$A:$A"),$F$2) -> 0 | U38: =SUMIFS(INDIRECT("'"&$C38&"'!$e:$e"),INDIRECT("'"&$C38&"'!$C:$C"),U$3,INDIRECT("'"&$C38&"'!$A:$A"),$F$2) -> 0 | V38: =SUMIFS(INDIRECT("'"&$C38&"'!$e:$e"),INDIRECT("'"&$C38&"'!$C:$C"),V$3,INDIRECT("'"&$C38&"'!$A:$A"),$F$2) -> 0 | W38: =SUMIFS(INDIRECT("'"&$C38&"'!$e:$e"),INDIRECT("'"&$C38&"'!$C:$C"),W$3,INDIRECT("'"&$C38&"'!$A:$A"),$F$2) -> 0
A39: =IF(B39=0,MATCH($F$2,INDIRECT("'"&C39&"'!A:A"),1),MATCH($F$2,INDIRECT("'"&C39&"'!A:A"),0)) -> 3 | B39: =COUNTIF(INDIRECT("'"&C39&"'!A:A"),$F$2) -> 0 | C39: 32 | F39: =VLOOKUP(C39,档案!A:B,2,FALSE) -> 0 | G39: =IF(B39=0,INDEX(INDIRECT("'"&$C39&"'!$F:$F"),$A39,1),INDEX(INDIRECT("'"&$C39&"'!$F:$F"),$A39-1,1)) -> 0 | H39: =SUM(K39:O39) -> 0 | I39: =SUM(P39:W39) -> 0 | J39: =G39+H39-I39 -> 0 | K39: =SUMIFS(INDIRECT("'"&$C39&"'!$D:$D"),INDIRECT("'"&$C39&"'!$C:$C"),K$3,INDIRECT("'"&$C39&"'!$A:$A"),$F$2) -> 0 | L39: =SUMIFS(INDIRECT("'"&$C39&"'!$D:$D"),INDIRECT("'"&$C39&"'!$C:$C"),L$3,INDIRECT("'"&$C39&"'!$A:$A"),$F$2) -> 0 | M39: =SUMIFS(INDIRECT("'"&$C39&"'!$D:$D"),INDIRECT("'"&$C39&"'!$C:$C"),M$3,INDIRECT("'"&$C39&"'!$A:$A"),$F$2) -> 0 | N39: =SUMIFS(INDIRECT("'"&$C39&"'!$D:$D"),INDIRECT("'"&$C39&"'!$C:$C"),N$3,INDIRECT("'"&$C39&"'!$A:$A"),$F$2) -> 0 | O39: =SUMIFS(INDIRECT("'"&$C39&"'!$D:$D"),INDIRECT("'"&$C39&"'!$C:$C"),O$3,INDIRECT("'"&$C39&"'!$A:$A"),$F$2) -> 0 | P39: =SUMIFS(INDIRECT("'"&$C39&"'!$e:$e"),INDIRECT("'"&$C39&"'!$C:$C"),P$3,INDIRECT("'"&$C39&"'!$A:$A"),$F$2) -> 0 | Q39: =SUMIFS(INDIRECT("'"&$C39&"'!$e:$e"),INDIRECT("'"&$C39&"'!$C:$C"),Q$3,INDIRECT("'"&$C39&"'!$A:$A"),$F$2) -> 0 | R39: =SUMIFS(INDIRECT("'"&$C39&"'!$e:$e"),INDIRECT("'"&$C39&"'!$C:$C"),R$3,INDIRECT("'"&$C39&"'!$A:$A"),$F$2) -> 0 | S39: =SUMIFS(INDIRECT("'"&$C39&"'!$e:$e"),INDIRECT("'"&$C39&"'!$C:$C"),S$3,INDIRECT("'"&$C39&"'!$A:$A"),$F$2) -> 0 | T39: =SUMIFS(INDIRECT("'"&$C39&"'!$e:$e"),INDIRECT("'"&$C39&"'!$C:$C"),T$3,INDIRECT("'"&$C39&"'!$A:$A"),$F$2) -> 0 | U39: =SUMIFS(INDIRECT("'"&$C39&"'!$e:$e"),INDIRECT("'"&$C39&"'!$C:$C"),U$3,INDIRECT("'"&$C39&"'!$A:$A"),$F$2) -> 0 | V39: =SUMIFS(INDIRECT("'"&$C39&"'!$e:$e"),INDIRECT("'"&$C39&"'!$C:$C"),V$3,INDIRECT("'"&$C39&"'!$A:$A"),$F$2) -> 0 | W39: =SUMIFS(INDIRECT("'"&$C39&"'!$e:$e"),INDIRECT("'"&$C39&"'!$C:$C"),W$3,INDIRECT("'"&$C39&"'!$A:$A"),$F$2) -> 0
A40: =IF(B40=0,MATCH($F$2,INDIRECT("'"&C40&"'!A:A"),1),MATCH($F$2,INDIRECT("'"&C40&"'!A:A"),0)) -> 3 | B40: =COUNTIF(INDIRECT("'"&C40&"'!A:A"),$F$2) -> 0 | C40: 33 | F40: =VLOOKUP(C40,档案!A:B,2,FALSE) -> 0 | G40: =IF(B40=0,INDEX(INDIRECT("'"&$C40&"'!$F:$F"),$A40,1),INDEX(INDIRECT("'"&$C40&"'!$F:$F"),$A40-1,1)) -> 0 | H40: =SUM(K40:O40) -> 0 | I40: =SUM(P40:W40) -> 0 | J40: =G40+H40-I40 -> 0 | K40: =SUMIFS(INDIRECT("'"&$C40&"'!$D:$D"),INDIRECT("'"&$C40&"'!$C:$C"),K$3,INDIRECT("'"&$C40&"'!$A:$A"),$F$2) -> 0 | L40: =SUMIFS(INDIRECT("'"&$C40&"'!$D:$D"),INDIRECT("'"&$C40&"'!$C:$C"),L$3,INDIRECT("'"&$C40&"'!$A:$A"),$F$2) -> 0 | M40: =SUMIFS(INDIRECT("'"&$C40&"'!$D:$D"),INDIRECT("'"&$C40&"'!$C:$C"),M$3,INDIRECT("'"&$C40&"'!$A:$A"),$F$2) -> 0 | N40: =SUMIFS(INDIRECT("'"&$C40&"'!$D:$D"),INDIRECT("'"&$C40&"'!$C:$C"),N$3,INDIRECT("'"&$C40&"'!$A:$A"),$F$2) -> 0 | O40: =SUMIFS(INDIRECT("'"&$C40&"'!$D:$D"),INDIRECT("'"&$C40&"'!$C:$C"),O$3,INDIRECT("'"&$C40&"'!$A:$A"),$F$2) -> 0 | P40: =SUMIFS(INDIRECT("'"&$C40&"'!$e:$e"),INDIRECT("'"&$C40&"'!$C:$C"),P$3,INDIRECT("'"&$C40&"'!$A:$A"),$F$2) -> 0 | Q40: =SUMIFS(INDIRECT("'"&$C40&"'!$e:$e"),INDIRECT("'"&$C40&"'!$C:$C"),Q$3,INDIRECT("'"&$C40&"'!$A:$A"),$F$2) -> 0 | R40: =SUMIFS(INDIRECT("'"&$C40&"'!$e:$e"),INDIRECT("'"&$C40&"'!$C:$C"),R$3,INDIRECT("'"&$C40&"'!$A:$A"),$F$2) -> 0 | S40: =SUMIFS(INDIRECT("'"&$C40&"'!$e:$e"),INDIRECT("'"&$C40&"'!$C:$C"),S$3,INDIRECT("'"&$C40&"'!$A:$A"),$F$2) -> 0 | T40: =SUMIFS(INDIRECT("'"&$C40&"'!$e:$e"),INDIRECT("'"&$C40&"'!$C:$C"),T$3,INDIRECT("'"&$C40&"'!$A:$A"),$F$2) -> 0 | U40: =SUMIFS(INDIRECT("'"&$C40&"'!$e:$e"),INDIRECT("'"&$C40&"'!$C:$C"),U$3,INDIRECT("'"&$C40&"'!$A:$A"),$F$2) -> 0 | V40: =SUMIFS(INDIRECT("'"&$C40&"'!$e:$e"),INDIRECT("'"&$C40&"'!$C:$C"),V$3,INDIRECT("'"&$C40&"'!$A:$A"),$F$2) -> 0 | W40: =SUMIFS(INDIRECT("'"&$C40&"'!$e:$e"),INDIRECT("'"&$C40&"'!$C:$C"),W$3,INDIRECT("'"&$C40&"'!$A:$A"),$F$2) -> 0
A41: =IF(B41=0,MATCH($F$2,INDIRECT("'"&C41&"'!A:A"),1),MATCH($F$2,INDIRECT("'"&C41&"'!A:A"),0)) -> 3 | B41: =COUNTIF(INDIRECT("'"&C41&"'!A:A"),$F$2) -> 0 | C41: 34 | F41: =VLOOKUP(C41,档案!A:B,2,FALSE) -> 0 | G41: =IF(B41=0,INDEX(INDIRECT("'"&$C41&"'!$F:$F"),$A41,1),INDEX(INDIRECT("'"&$C41&"'!$F:$F"),$A41-1,1)) -> 0 | H41: =SUM(K41:O41) -> 0 | I41: =SUM(P41:W41) -> 0 | J41: =G41+H41-I41 -> 0 | K41: =SUMIFS(INDIRECT("'"&$C41&"'!$D:$D"),INDIRECT("'"&$C41&"'!$C:$C"),K$3,INDIRECT("'"&$C41&"'!$A:$A"),$F$2) -> 0 | L41: =SUMIFS(INDIRECT("'"&$C41&"'!$D:$D"),INDIRECT("'"&$C41&"'!$C:$C"),L$3,INDIRECT("'"&$C41&"'!$A:$A"),$F$2) -> 0 | M41: =SUMIFS(INDIRECT("'"&$C41&"'!$D:$D"),INDIRECT("'"&$C41&"'!$C:$C"),M$3,INDIRECT("'"&$C41&"'!$A:$A"),$F$2) -> 0 | N41: =SUMIFS(INDIRECT("'"&$C41&"'!$D:$D"),INDIRECT("'"&$C41&"'!$C:$C"),N$3,INDIRECT("'"&$C41&"'!$A:$A"),$F$2) -> 0 | O41: =SUMIFS(INDIRECT("'"&$C41&"'!$D:$D"),INDIRECT("'"&$C41&"'!$C:$C"),O$3,INDIRECT("'"&$C41&"'!$A:$A"),$F$2) -> 0 | P41: =SUMIFS(INDIRECT("'"&$C41&"'!$e:$e"),INDIRECT("'"&$C41&"'!$C:$C"),P$3,INDIRECT("'"&$C41&"'!$A:$A"),$F$2) -> 0 | Q41: =SUMIFS(INDIRECT("'"&$C41&"'!$e:$e"),INDIRECT("'"&$C41&"'!$C:$C"),Q$3,INDIRECT("'"&$C41&"'!$A:$A"),$F$2) -> 0 | R41: =SUMIFS(INDIRECT("'"&$C41&"'!$e:$e"),INDIRECT("'"&$C41&"'!$C:$C"),R$3,INDIRECT("'"&$C41&"'!$A:$A"),$F$2) -> 0 | S41: =SUMIFS(INDIRECT("'"&$C41&"'!$e:$e"),INDIRECT("'"&$C41&"'!$C:$C"),S$3,INDIRECT("'"&$C41&"'!$A:$A"),$F$2) -> 0 | T41: =SUMIFS(INDIRECT("'"&$C41&"'!$e:$e"),INDIRECT("'"&$C41&"'!$C:$C"),T$3,INDIRECT("'"&$C41&"'!$A:$A"),$F$2) -> 0 | U41: =SUMIFS(INDIRECT("'"&$C41&"'!$e:$e"),INDIRECT("'"&$C41&"'!$C:$C"),U$3,INDIRECT("'"&$C41&"'!$A:$A"),$F$2) -> 0 | V41: =SUMIFS(INDIRECT("'"&$C41&"'!$e:$e"),INDIRECT("'"&$C41&"'!$C:$C"),V$3,INDIRECT("'"&$C41&"'!$A:$A"),$F$2) -> 0 | W41: =SUMIFS(INDIRECT("'"&$C41&"'!$e:$e"),INDIRECT("'"&$C41&"'!$C:$C"),W$3,INDIRECT("'"&$C41&"'!$A:$A"),$F$2) -> 0
A42: =IF(B42=0,MATCH($F$2,INDIRECT("'"&C42&"'!A:A"),1),MATCH($F$2,INDIRECT("'"&C42&"'!A:A"),0)) -> 3 | B42: =COUNTIF(INDIRECT("'"&C42&"'!A:A"),$F$2) -> 0 | C42: 35 | F42: =VLOOKUP(C42,档案!A:B,2,FALSE) -> 0 | G42: =IF(B42=0,INDEX(INDIRECT("'"&$C42&"'!$F:$F"),$A42,1),INDEX(INDIRECT("'"&$C42&"'!$F:$F"),$A42-1,1)) -> 0 | H42: =SUM(K42:O42) -> 0 | I42: =SUM(P42:W42) -> 0 | J42: =G42+H42-I42 -> 0 | K42: =SUMIFS(INDIRECT("'"&$C42&"'!$D:$D"),INDIRECT("'"&$C42&"'!$C:$C"),K$3,INDIRECT("'"&$C42&"'!$A:$A"),$F$2) -> 0 | L42: =SUMIFS(INDIRECT("'"&$C42&"'!$D:$D"),INDIRECT("'"&$C42&"'!$C:$C"),L$3,INDIRECT("'"&$C42&"'!$A:$A"),$F$2) -> 0 | M42: =SUMIFS(INDIRECT("'"&$C42&"'!$D:$D"),INDIRECT("'"&$C42&"'!$C:$C"),M$3,INDIRECT("'"&$C42&"'!$A:$A"),$F$2) -> 0 | N42: =SUMIFS(INDIRECT("'"&$C42&"'!$D:$D"),INDIRECT("'"&$C42&"'!$C:$C"),N$3,INDIRECT("'"&$C42&"'!$A:$A"),$F$2) -> 0 | O42: =SUMIFS(INDIRECT("'"&$C42&"'!$D:$D"),INDIRECT("'"&$C42&"'!$C:$C"),O$3,INDIRECT("'"&$C42&"'!$A:$A"),$F$2) -> 0 | P42: =SUMIFS(INDIRECT("'"&$C42&"'!$e:$e"),INDIRECT("'"&$C42&"'!$C:$C"),P$3,INDIRECT("'"&$C42&"'!$A:$A"),$F$2) -> 0 | Q42: =SUMIFS(INDIRECT("'"&$C42&"'!$e:$e"),INDIRECT("'"&$C42&"'!$C:$C"),Q$3,INDIRECT("'"&$C42&"'!$A:$A"),$F$2) -> 0 | R42: =SUMIFS(INDIRECT("'"&$C42&"'!$e:$e"),INDIRECT("'"&$C42&"'!$C:$C"),R$3,INDIRECT("'"&$C42&"'!$A:$A"),$F$2) -> 0 | S42: =SUMIFS(INDIRECT("'"&$C42&"'!$e:$e"),INDIRECT("'"&$C42&"'!$C:$C"),S$3,INDIRECT("'"&$C42&"'!$A:$A"),$F$2) -> 0 | T42: =SUMIFS(INDIRECT("'"&$C42&"'!$e:$e"),INDIRECT("'"&$C42&"'!$C:$C"),T$3,INDIRECT("'"&$C42&"'!$A:$A"),$F$2) -> 0 | U42: =SUMIFS(INDIRECT("'"&$C42&"'!$e:$e"),INDIRECT("'"&$C42&"'!$C:$C"),U$3,INDIRECT("'"&$C42&"'!$A:$A"),$F$2) -> 0 | V42: =SUMIFS(INDIRECT("'"&$C42&"'!$e:$e"),INDIRECT("'"&$C42&"'!$C:$C"),V$3,INDIRECT("'"&$C42&"'!$A:$A"),$F$2) -> 0 | W42: =SUMIFS(INDIRECT("'"&$C42&"'!$e:$e"),INDIRECT("'"&$C42&"'!$C:$C"),W$3,INDIRECT("'"&$C42&"'!$A:$A"),$F$2) -> 0
A43: =IF(B43=0,MATCH($F$2,INDIRECT("'"&C43&"'!A:A"),1),MATCH($F$2,INDIRECT("'"&C43&"'!A:A"),0)) -> #REF! | B43: =COUNTIF(INDIRECT("'"&C43&"'!A:A"),$F$2) -> #REF! | F43: 小计 | G43: =SUM(G34:G42) -> 212968.5 | H43: =SUM(K43:O43) -> 0 | I43: =SUM(P43:W43) -> 39525 | J43: =G43+H43-I43 -> 173443.5 | K43: =SUM(K34:K42) -> 0 | L43: =SUM(L34:L42) -> 0 | M43: =SUM(M34:M42) -> 0 | N43: =SUM(N34:N42) -> 0 | O43: =SUM(O34:O42) -> 0 | P43: =SUM(P34:P42) -> 0 | Q43: =SUM(Q34:Q42) -> 0 | R43: =SUM(R34:R42) -> 0 | ... W43: =SUM(W34:W42) -> 0
A44: =IF(B44=0,MATCH($F$2,INDIRECT("'"&C44&"'!A:A"),1),MATCH($F$2,INDIRECT("'"&C44&"'!A:A"),0)) -> 70 | B44: =COUNTIF(INDIRECT("'"&C44&"'!A:A"),$F$2) -> 0 | C44: 36 | E44: =VLOOKUP(C44,档案!A:B,2,FALSE) -> 电子承兑汇票 | G44: =IF(B44=0,INDEX(INDIRECT("'"&$C44&"'!$F:$F"),$A44,1),INDEX(INDIRECT("'"&$C44&"'!$F:$F"),$A44-1,1)) -> 53359.74 | H44: =SUM(K44:O44) -> 0 | I44: =SUM(P44:W44) -> 0 | J44: =G44+H44-I44 -> 53359.74 | K44: =SUMIFS(INDIRECT("'"&$C44&"'!$D:$D"),INDIRECT("'"&$C44&"'!$C:$C"),K$3,INDIRECT("'"&$C44&"'!$A:$A"),$F$2) -> 0 | L44: =SUMIFS(INDIRECT("'"&$C44&"'!$D:$D"),INDIRECT("'"&$C44&"'!$C:$C"),L$3,INDIRECT("'"&$C44&"'!$A:$A"),$F$2) -> 0 | M44: =SUMIFS(INDIRECT("'"&$C44&"'!$D:$D"),INDIRECT("'"&$C44&"'!$C:$C"),M$3,INDIRECT("'"&$C44&"'!$A:$A"),$F$2) -> 0 | N44: =SUMIFS(INDIRECT("'"&$C44&"'!$D:$D"),INDIRECT("'"&$C44&"'!$C:$C"),N$3,INDIRECT("'"&$C44&"'!$A:$A"),$F$2) -> 0 | O44: =SUMIFS(INDIRECT("'"&$C44&"'!$D:$D"),INDIRECT("'"&$C44&"'!$C:$C"),O$3,INDIRECT("'"&$C44&"'!$A:$A"),$F$2) -> 0 | P44: =SUMIFS(INDIRECT("'"&$C44&"'!$e:$e"),INDIRECT("'"&$C44&"'!$C:$C"),P$3,INDIRECT("'"&$C44&"'!$A:$A"),$F$2) -> 0 | Q44: =SUMIFS(INDIRECT("'"&$C44&"'!$e:$e"),INDIRECT("'"&$C44&"'!$C:$C"),Q$3,INDIRECT("'"&$C44&"'!$A:$A"),$F$2) -> 0 | R44: =SUMIFS(INDIRECT("'"&$C44&"'!$e:$e"),INDIRECT("'"&$C44&"'!$C:$C"),R$3,INDIRECT("'"&$C44&"'!$A:$A"),$F$2) -> 0 | S44: =SUMIFS(INDIRECT("'"&$C44&"'!$e:$e"),INDIRECT("'"&$C44&"'!$C:$C"),S$3,INDIRECT("'"&$C44&"'!$A:$A"),$F$2) -> 0 | T44: =SUMIFS(INDIRECT("'"&$C44&"'!$e:$e"),INDIRECT("'"&$C44&"'!$C:$C"),T$3,INDIRECT("'"&$C44&"'!$A:$A"),$F$2) -> 0 | U44: =SUMIFS(INDIRECT("'"&$C44&"'!$e:$e"),INDIRECT("'"&$C44&"'!$C:$C"),U$3,INDIRECT("'"&$C44&"'!$A:$A"),$F$2) -> 0 | V44: =SUMIFS(INDIRECT("'"&$C44&"'!$e:$e"),INDIRECT("'"&$C44&"'!$C:$C"),V$3,INDIRECT("'"&$C44&"'!$A:$A"),$F$2) -> 0 | W44: =SUMIFS(INDIRECT("'"&$C44&"'!$e:$e"),INDIRECT("'"&$C44&"'!$C:$C"),W$3,INDIRECT("'"&$C44&"'!$A:$A"),$F$2) -> 0
A45: =IF(B45=0,MATCH($F$2,INDIRECT("'"&C45&"'!A:A"),1),MATCH($F$2,INDIRECT("'"&C45&"'!A:A"),0)) -> 3 | B45: =COUNTIF(INDIRECT("'"&C45&"'!A:A"),$F$2) -> 0 | C45: 37 | E45: =VLOOKUP(C45,档案!A:B,2,FALSE) -> 库存现金 | G45: =IF(B45=0,INDEX(INDIRECT("'"&$C45&"'!$F:$F"),$A45,1),INDEX(INDIRECT("'"&$C45&"'!$F:$F"),$A45-1,1)) -> 0 | H45: =SUM(K45:O45) -> 0 | I45: =SUM(P45:W45) -> 0 | J45: =G45+H45-I45 -> 0 | K45: =SUMIFS(INDIRECT("'"&$C45&"'!$D:$D"),INDIRECT("'"&$C45&"'!$C:$C"),K$3,INDIRECT("'"&$C45&"'!$A:$A"),$F$2) -> 0 | L45: =SUMIFS(INDIRECT("'"&$C45&"'!$D:$D"),INDIRECT("'"&$C45&"'!$C:$C"),L$3,INDIRECT("'"&$C45&"'!$A:$A"),$F$2) -> 0 | M45: =SUMIFS(INDIRECT("'"&$C45&"'!$D:$D"),INDIRECT("'"&$C45&"'!$C:$C"),M$3,INDIRECT("'"&$C45&"'!$A:$A"),$F$2) -> 0 | N45: =SUMIFS(INDIRECT("'"&$C45&"'!$D:$D"),INDIRECT("'"&$C45&"'!$C:$C"),N$3,INDIRECT("'"&$C45&"'!$A:$A"),$F$2) -> 0 | O45: =SUMIFS(INDIRECT("'"&$C45&"'!$D:$D"),INDIRECT("'"&$C45&"'!$C:$C"),O$3,INDIRECT("'"&$C45&"'!$A:$A"),$F$2) -> 0 | P45: =SUMIFS(INDIRECT("'"&$C45&"'!$e:$e"),INDIRECT("'"&$C45&"'!$C:$C"),P$3,INDIRECT("'"&$C45&"'!$A:$A"),$F$2) -> 0 | Q45: =SUMIFS(INDIRECT("'"&$C45&"'!$e:$e"),INDIRECT("'"&$C45&"'!$C:$C"),Q$3,INDIRECT("'"&$C45&"'!$A:$A"),$F$2) -> 0 | R45: =SUMIFS(INDIRECT("'"&$C45&"'!$e:$e"),INDIRECT("'"&$C45&"'!$C:$C"),R$3,INDIRECT("'"&$C45&"'!$A:$A"),$F$2) -> 0 | S45: =SUMIFS(INDIRECT("'"&$C45&"'!$e:$e"),INDIRECT("'"&$C45&"'!$C:$C"),S$3,INDIRECT("'"&$C45&"'!$A:$A"),$F$2) -> 0 | T45: =SUMIFS(INDIRECT("'"&$C45&"'!$e:$e"),INDIRECT("'"&$C45&"'!$C:$C"),T$3,INDIRECT("'"&$C45&"'!$A:$A"),$F$2) -> 0 | U45: =SUMIFS(INDIRECT("'"&$C45&"'!$e:$e"),INDIRECT("'"&$C45&"'!$C:$C"),U$3,INDIRECT("'"&$C45&"'!$A:$A"),$F$2) -> 0 | V45: =SUMIFS(INDIRECT("'"&$C45&"'!$e:$e"),INDIRECT("'"&$C45&"'!$C:$C"),V$3,INDIRECT("'"&$C45&"'!$A:$A"),$F$2) -> 0 | W45: =SUMIFS(INDIRECT("'"&$C45&"'!$e:$e"),INDIRECT("'"&$C45&"'!$C:$C"),W$3,INDIRECT("'"&$C45&"'!$A:$A"),$F$2) -> 0
A46: =IF(B46=0,MATCH($F$2,INDIRECT("'"&C46&"'!A:A"),1),MATCH($F$2,INDIRECT("'"&C46&"'!A:A"),0)) -> #REF! | B46: =COUNTIF(INDIRECT("'"&C46&"'!A:A"),$F$2) -> #REF! | E46: 合计 | G46: =SUM(G43:G45) -> 266328.24 | H46: =SUM(K46:O46) -> 0 | I46: =SUM(P46:W46) -> 39525 | J46: =G46+H46-I46 -> 226803.24 | K46: =SUM(K43:K45) -> 0 | L46: =SUM(L43:L45) -> 0 | M46: =SUM(M43:M45) -> 0 | N46: =SUM(N43:N45) -> 0 | O46: =SUM(O43:O45) -> 0 | P46: =SUM(P43:P45) -> 0 | Q46: =SUM(Q43:Q45) -> 0 | R46: =SUM(R43:R45) -> 0 | ... W46: =SUM(W43:W45) -> 0
A47: =IF(B47=0,MATCH($F$2,INDIRECT("'"&C47&"'!A:A"),1),MATCH($F$2,INDIRECT("'"&C47&"'!A:A"),0)) -> 34 | B47: =COUNTIF(INDIRECT("'"&C47&"'!A:A"),$F$2) -> 0 | C47: 38 | D47: 武汉信茂 | E47: 银行存款 | F47: =VLOOKUP(C47,档案!A:B,2,FALSE) -> 浦发银行光谷支行01894 | G47: =IF(B47=0,INDEX(INDIRECT("'"&$C47&"'!$F:$F"),$A47,1),INDEX(INDIRECT("'"&$C47&"'!$F:$F"),$A47-1,1)) -> 10647.75 | H47: =SUM(K47:O47) -> 0 | I47: =SUM(P47:W47) -> 0 | J47: =G47+H47-I47 -> 10647.75 | K47: =SUMIFS(INDIRECT("'"&$C47&"'!$D:$D"),INDIRECT("'"&$C47&"'!$C:$C"),K$3,INDIRECT("'"&$C47&"'!$A:$A"),$F$2) -> 0 | L47: =SUMIFS(INDIRECT("'"&$C47&"'!$D:$D"),INDIRECT("'"&$C47&"'!$C:$C"),L$3,INDIRECT("'"&$C47&"'!$A:$A"),$F$2) -> 0 | M47: =SUMIFS(INDIRECT("'"&$C47&"'!$D:$D"),INDIRECT("'"&$C47&"'!$C:$C"),M$3,INDIRECT("'"&$C47&"'!$A:$A"),$F$2) -> 0 | N47: =SUMIFS(INDIRECT("'"&$C47&"'!$D:$D"),INDIRECT("'"&$C47&"'!$C:$C"),N$3,INDIRECT("'"&$C47&"'!$A:$A"),$F$2) -> 0 | O47: =SUMIFS(INDIRECT("'"&$C47&"'!$D:$D"),INDIRECT("'"&$C47&"'!$C:$C"),O$3,INDIRECT("'"&$C47&"'!$A:$A"),$F$2) -> 0 | P47: =SUMIFS(INDIRECT("'"&$C47&"'!$e:$e"),INDIRECT("'"&$C47&"'!$C:$C"),P$3,INDIRECT("'"&$C47&"'!$A:$A"),$F$2) -> 0 | Q47: =SUMIFS(INDIRECT("'"&$C47&"'!$e:$e"),INDIRECT("'"&$C47&"'!$C:$C"),Q$3,INDIRECT("'"&$C47&"'!$A:$A"),$F$2) -> 0 | R47: =SUMIFS(INDIRECT("'"&$C47&"'!$e:$e"),INDIRECT("'"&$C47&"'!$C:$C"),R$3,INDIRECT("'"&$C47&"'!$A:$A"),$F$2) -> 0 | S47: =SUMIFS(INDIRECT("'"&$C47&"'!$e:$e"),INDIRECT("'"&$C47&"'!$C:$C"),S$3,INDIRECT("'"&$C47&"'!$A:$A"),$F$2) -> 0 | T47: =SUMIFS(INDIRECT("'"&$C47&"'!$e:$e"),INDIRECT("'"&$C47&"'!$C:$C"),T$3,INDIRECT("'"&$C47&"'!$A:$A"),$F$2) -> 0 | U47: =SUMIFS(INDIRECT("'"&$C47&"'!$e:$e"),INDIRECT("'"&$C47&"'!$C:$C"),U$3,INDIRECT("'"&$C47&"'!$A:$A"),$F$2) -> 0 | V47: =SUMIFS(INDIRECT("'"&$C47&"'!$e:$e"),INDIRECT("'"&$C47&"'!$C:$C"),V$3,INDIRECT("'"&$C47&"'!$A:$A"),$F$2) -> 0 | W47: =SUMIFS(INDIRECT("'"&$C47&"'!$e:$e"),INDIRECT("'"&$C47&"'!$C:$C"),W$3,INDIRECT("'"&$C47&"'!$A:$A"),$F$2) -> 0
A48: =IF(B48=0,MATCH($F$2,INDIRECT("'"&C48&"'!A:A"),1),MATCH($F$2,INDIRECT("'"&C48&"'!A:A"),0)) -> 3 | B48: =COUNTIF(INDIRECT("'"&C48&"'!A:A"),$F$2) -> 0 | C48: 39 | F48: =VLOOKUP(C48,档案!A:B,2,FALSE) -> 0 | G48: =IF(B48=0,INDEX(INDIRECT("'"&$C48&"'!$F:$F"),$A48,1),INDEX(INDIRECT("'"&$C48&"'!$F:$F"),$A48-1,1)) -> 0 | H48: =SUM(K48:O48) -> 0 | I48: =SUM(P48:W48) -> 0 | J48: =G48+H48-I48 -> 0 | K48: =SUMIFS(INDIRECT("'"&$C48&"'!$D:$D"),INDIRECT("'"&$C48&"'!$C:$C"),K$3,INDIRECT("'"&$C48&"'!$A:$A"),$F$2) -> 0 | L48: =SUMIFS(INDIRECT("'"&$C48&"'!$D:$D"),INDIRECT("'"&$C48&"'!$C:$C"),L$3,INDIRECT("'"&$C48&"'!$A:$A"),$F$2) -> 0 | M48: =SUMIFS(INDIRECT("'"&$C48&"'!$D:$D"),INDIRECT("'"&$C48&"'!$C:$C"),M$3,INDIRECT("'"&$C48&"'!$A:$A"),$F$2) -> 0 | N48: =SUMIFS(INDIRECT("'"&$C48&"'!$D:$D"),INDIRECT("'"&$C48&"'!$C:$C"),N$3,INDIRECT("'"&$C48&"'!$A:$A"),$F$2) -> 0 | O48: =SUMIFS(INDIRECT("'"&$C48&"'!$D:$D"),INDIRECT("'"&$C48&"'!$C:$C"),O$3,INDIRECT("'"&$C48&"'!$A:$A"),$F$2) -> 0 | P48: =SUMIFS(INDIRECT("'"&$C48&"'!$e:$e"),INDIRECT("'"&$C48&"'!$C:$C"),P$3,INDIRECT("'"&$C48&"'!$A:$A"),$F$2) -> 0 | Q48: =SUMIFS(INDIRECT("'"&$C48&"'!$e:$e"),INDIRECT("'"&$C48&"'!$C:$C"),Q$3,INDIRECT("'"&$C48&"'!$A:$A"),$F$2) -> 0 | R48: =SUMIFS(INDIRECT("'"&$C48&"'!$e:$e"),INDIRECT("'"&$C48&"'!$C:$C"),R$3,INDIRECT("'"&$C48&"'!$A:$A"),$F$2) -> 0 | S48: =SUMIFS(INDIRECT("'"&$C48&"'!$e:$e"),INDIRECT("'"&$C48&"'!$C:$C"),S$3,INDIRECT("'"&$C48&"'!$A:$A"),$F$2) -> 0 | T48: =SUMIFS(INDIRECT("'"&$C48&"'!$e:$e"),INDIRECT("'"&$C48&"'!$C:$C"),T$3,INDIRECT("'"&$C48&"'!$A:$A"),$F$2) -> 0 | U48: =SUMIFS(INDIRECT("'"&$C48&"'!$e:$e"),INDIRECT("'"&$C48&"'!$C:$C"),U$3,INDIRECT("'"&$C48&"'!$A:$A"),$F$2) -> 0 | V48: =SUMIFS(INDIRECT("'"&$C48&"'!$e:$e"),INDIRECT("'"&$C48&"'!$C:$C"),V$3,INDIRECT("'"&$C48&"'!$A:$A"),$F$2) -> 0 | W48: =SUMIFS(INDIRECT("'"&$C48&"'!$e:$e"),INDIRECT("'"&$C48&"'!$C:$C"),W$3,INDIRECT("'"&$C48&"'!$A:$A"),$F$2) -> 0
A49: =IF(B49=0,MATCH($F$2,INDIRECT("'"&C49&"'!A:A"),1),MATCH($F$2,INDIRECT("'"&C49&"'!A:A"),0)) -> 3 | B49: =COUNTIF(INDIRECT("'"&C49&"'!A:A"),$F$2) -> 0 | C49: 40 | F49: =VLOOKUP(C49,档案!A:B,2,FALSE) -> 0 | G49: =IF(B49=0,INDEX(INDIRECT("'"&$C49&"'!$F:$F"),$A49,1),INDEX(INDIRECT("'"&$C49&"'!$F:$F"),$A49-1,1)) -> 0 | H49: =SUM(K49:O49) -> 0 | I49: =SUM(P49:W49) -> 0 | J49: =G49+H49-I49 -> 0 | K49: =SUMIFS(INDIRECT("'"&$C49&"'!$D:$D"),INDIRECT("'"&$C49&"'!$C:$C"),K$3,INDIRECT("'"&$C49&"'!$A:$A"),$F$2) -> 0 | L49: =SUMIFS(INDIRECT("'"&$C49&"'!$D:$D"),INDIRECT("'"&$C49&"'!$C:$C"),L$3,INDIRECT("'"&$C49&"'!$A:$A"),$F$2) -> 0 | M49: =SUMIFS(INDIRECT("'"&$C49&"'!$D:$D"),INDIRECT("'"&$C49&"'!$C:$C"),M$3,INDIRECT("'"&$C49&"'!$A:$A"),$F$2) -> 0 | N49: =SUMIFS(INDIRECT("'"&$C49&"'!$D:$D"),INDIRECT("'"&$C49&"'!$C:$C"),N$3,INDIRECT("'"&$C49&"'!$A:$A"),$F$2) -> 0 | O49: =SUMIFS(INDIRECT("'"&$C49&"'!$D:$D"),INDIRECT("'"&$C49&"'!$C:$C"),O$3,INDIRECT("'"&$C49&"'!$A:$A"),$F$2) -> 0 | P49: =SUMIFS(INDIRECT("'"&$C49&"'!$e:$e"),INDIRECT("'"&$C49&"'!$C:$C"),P$3,INDIRECT("'"&$C49&"'!$A:$A"),$F$2) -> 0 | Q49: =SUMIFS(INDIRECT("'"&$C49&"'!$e:$e"),INDIRECT("'"&$C49&"'!$C:$C"),Q$3,INDIRECT("'"&$C49&"'!$A:$A"),$F$2) -> 0 | R49: =SUMIFS(INDIRECT("'"&$C49&"'!$e:$e"),INDIRECT("'"&$C49&"'!$C:$C"),R$3,INDIRECT("'"&$C49&"'!$A:$A"),$F$2) -> 0 | S49: =SUMIFS(INDIRECT("'"&$C49&"'!$e:$e"),INDIRECT("'"&$C49&"'!$C:$C"),S$3,INDIRECT("'"&$C49&"'!$A:$A"),$F$2) -> 0 | T49: =SUMIFS(INDIRECT("'"&$C49&"'!$e:$e"),INDIRECT("'"&$C49&"'!$C:$C"),T$3,INDIRECT("'"&$C49&"'!$A:$A"),$F$2) -> 0 | U49: =SUMIFS(INDIRECT("'"&$C49&"'!$e:$e"),INDIRECT("'"&$C49&"'!$C:$C"),U$3,INDIRECT("'"&$C49&"'!$A:$A"),$F$2) -> 0 | V49: =SUMIFS(INDIRECT("'"&$C49&"'!$e:$e"),INDIRECT("'"&$C49&"'!$C:$C"),V$3,INDIRECT("'"&$C49&"'!$A:$A"),$F$2) -> 0 | W49: =SUMIFS(INDIRECT("'"&$C49&"'!$e:$e"),INDIRECT("'"&$C49&"'!$C:$C"),W$3,INDIRECT("'"&$C49&"'!$A:$A"),$F$2) -> 0
A50: =IF(B50=0,MATCH($F$2,INDIRECT("'"&C50&"'!A:A"),1),MATCH($F$2,INDIRECT("'"&C50&"'!A:A"),0)) -> 3 | B50: =COUNTIF(INDIRECT("'"&C50&"'!A:A"),$F$2) -> 0 | C50: 41 | F50: =VLOOKUP(C50,档案!A:B,2,FALSE) -> 0 | G50: =IF(B50=0,INDEX(INDIRECT("'"&$C50&"'!$F:$F"),$A50,1),INDEX(INDIRECT("'"&$C50&"'!$F:$F"),$A50-1,1)) -> 0 | H50: =SUM(K50:O50) -> 0 | I50: =SUM(P50:W50) -> 0 | J50: =G50+H50-I50 -> 0 | K50: =SUMIFS(INDIRECT("'"&$C50&"'!$D:$D"),INDIRECT("'"&$C50&"'!$C:$C"),K$3,INDIRECT("'"&$C50&"'!$A:$A"),$F$2) -> 0 | L50: =SUMIFS(INDIRECT("'"&$C50&"'!$D:$D"),INDIRECT("'"&$C50&"'!$C:$C"),L$3,INDIRECT("'"&$C50&"'!$A:$A"),$F$2) -> 0 | M50: =SUMIFS(INDIRECT("'"&$C50&"'!$D:$D"),INDIRECT("'"&$C50&"'!$C:$C"),M$3,INDIRECT("'"&$C50&"'!$A:$A"),$F$2) -> 0 | N50: =SUMIFS(INDIRECT("'"&$C50&"'!$D:$D"),INDIRECT("'"&$C50&"'!$C:$C"),N$3,INDIRECT("'"&$C50&"'!$A:$A"),$F$2) -> 0 | O50: =SUMIFS(INDIRECT("'"&$C50&"'!$D:$D"),INDIRECT("'"&$C50&"'!$C:$C"),O$3,INDIRECT("'"&$C50&"'!$A:$A"),$F$2) -> 0 | P50: =SUMIFS(INDIRECT("'"&$C50&"'!$e:$e"),INDIRECT("'"&$C50&"'!$C:$C"),P$3,INDIRECT("'"&$C50&"'!$A:$A"),$F$2) -> 0 | Q50: =SUMIFS(INDIRECT("'"&$C50&"'!$e:$e"),INDIRECT("'"&$C50&"'!$C:$C"),Q$3,INDIRECT("'"&$C50&"'!$A:$A"),$F$2) -> 0 | R50: =SUMIFS(INDIRECT("'"&$C50&"'!$e:$e"),INDIRECT("'"&$C50&"'!$C:$C"),R$3,INDIRECT("'"&$C50&"'!$A:$A"),$F$2) -> 0 | S50: =SUMIFS(INDIRECT("'"&$C50&"'!$e:$e"),INDIRECT("'"&$C50&"'!$C:$C"),S$3,INDIRECT("'"&$C50&"'!$A:$A"),$F$2) -> 0 | T50: =SUMIFS(INDIRECT("'"&$C50&"'!$e:$e"),INDIRECT("'"&$C50&"'!$C:$C"),T$3,INDIRECT("'"&$C50&"'!$A:$A"),$F$2) -> 0 | U50: =SUMIFS(INDIRECT("'"&$C50&"'!$e:$e"),INDIRECT("'"&$C50&"'!$C:$C"),U$3,INDIRECT("'"&$C50&"'!$A:$A"),$F$2) -> 0 | V50: =SUMIFS(INDIRECT("'"&$C50&"'!$e:$e"),INDIRECT("'"&$C50&"'!$C:$C"),V$3,INDIRECT("'"&$C50&"'!$A:$A"),$F$2) -> 0 | W50: =SUMIFS(INDIRECT("'"&$C50&"'!$e:$e"),INDIRECT("'"&$C50&"'!$C:$C"),W$3,INDIRECT("'"&$C50&"'!$A:$A"),$F$2) -> 0
A51: =IF(B51=0,MATCH($F$2,INDIRECT("'"&C51&"'!A:A"),1),MATCH($F$2,INDIRECT("'"&C51&"'!A:A"),0)) -> #REF! | B51: =COUNTIF(INDIRECT("'"&C51&"'!A:A"),$F$2) -> #REF! | F51: 小计 | G51: =SUM(G47:G50) -> 10647.75 | H51: =SUM(K51:O51) -> 0 | I51: =SUM(P51:W51) -> 0 | J51: =G51+H51-I51 -> 10647.75 | K51: =SUM(K47:K50) -> 0 | L51: =SUM(L47:L50) -> 0 | M51: =SUM(M47:M50) -> 0 | N51: =SUM(N47:N50) -> 0 | O51: =SUM(O47:O50) -> 0 | P51: =SUM(P47:P50) -> 0 | Q51: =SUM(Q47:Q50) -> 0 | R51: =SUM(R47:R50) -> 0 | ... W51: =SUM(W47:W50) -> 0
A52: =IF(B52=0,MATCH($F$2,INDIRECT("'"&C52&"'!A:A"),1),MATCH($F$2,INDIRECT("'"&C52&"'!A:A"),0)) -> 13 | B52: =COUNTIF(INDIRECT("'"&C52&"'!A:A"),$F$2) -> 0 | C52: 42 | E52: =VLOOKUP(C52,档案!A:B,2,FALSE) -> 电子承兑汇票 | G52: =IF(B52=0,INDEX(INDIRECT("'"&$C52&"'!$F:$F"),$A52,1),INDEX(INDIRECT("'"&$C52&"'!$F:$F"),$A52-1,1)) -> 0 | H52: =SUM(K52:O52) -> 0 | I52: =SUM(P52:W52) -> 0 | J52: =G52+H52-I52 -> 0 | K52: =SUMIFS(INDIRECT("'"&$C52&"'!$D:$D"),INDIRECT("'"&$C52&"'!$C:$C"),K$3,INDIRECT("'"&$C52&"'!$A:$A"),$F$2) -> 0 | L52: =SUMIFS(INDIRECT("'"&$C52&"'!$D:$D"),INDIRECT("'"&$C52&"'!$C:$C"),L$3,INDIRECT("'"&$C52&"'!$A:$A"),$F$2) -> 0 | M52: =SUMIFS(INDIRECT("'"&$C52&"'!$D:$D"),INDIRECT("'"&$C52&"'!$C:$C"),M$3,INDIRECT("'"&$C52&"'!$A:$A"),$F$2) -> 0 | N52: =SUMIFS(INDIRECT("'"&$C52&"'!$D:$D"),INDIRECT("'"&$C52&"'!$C:$C"),N$3,INDIRECT("'"&$C52&"'!$A:$A"),$F$2) -> 0 | O52: =SUMIFS(INDIRECT("'"&$C52&"'!$D:$D"),INDIRECT("'"&$C52&"'!$C:$C"),O$3,INDIRECT("'"&$C52&"'!$A:$A"),$F$2) -> 0 | P52: =SUMIFS(INDIRECT("'"&$C52&"'!$e:$e"),INDIRECT("'"&$C52&"'!$C:$C"),P$3,INDIRECT("'"&$C52&"'!$A:$A"),$F$2) -> 0 | Q52: =SUMIFS(INDIRECT("'"&$C52&"'!$e:$e"),INDIRECT("'"&$C52&"'!$C:$C"),Q$3,INDIRECT("'"&$C52&"'!$A:$A"),$F$2) -> 0 | R52: =SUMIFS(INDIRECT("'"&$C52&"'!$e:$e"),INDIRECT("'"&$C52&"'!$C:$C"),R$3,INDIRECT("'"&$C52&"'!$A:$A"),$F$2) -> 0 | S52: =SUMIFS(INDIRECT("'"&$C52&"'!$e:$e"),INDIRECT("'"&$C52&"'!$C:$C"),S$3,INDIRECT("'"&$C52&"'!$A:$A"),$F$2) -> 0 | T52: =SUMIFS(INDIRECT("'"&$C52&"'!$e:$e"),INDIRECT("'"&$C52&"'!$C:$C"),T$3,INDIRECT("'"&$C52&"'!$A:$A"),$F$2) -> 0 | U52: =SUMIFS(INDIRECT("'"&$C52&"'!$e:$e"),INDIRECT("'"&$C52&"'!$C:$C"),U$3,INDIRECT("'"&$C52&"'!$A:$A"),$F$2) -> 0 | V52: =SUMIFS(INDIRECT("'"&$C52&"'!$e:$e"),INDIRECT("'"&$C52&"'!$C:$C"),V$3,INDIRECT("'"&$C52&"'!$A:$A"),$F$2) -> 0 | W52: =SUMIFS(INDIRECT("'"&$C52&"'!$e:$e"),INDIRECT("'"&$C52&"'!$C:$C"),W$3,INDIRECT("'"&$C52&"'!$A:$A"),$F$2) -> 0
A53: =IF(B53=0,MATCH($F$2,INDIRECT("'"&C53&"'!A:A"),1),MATCH($F$2,INDIRECT("'"&C53&"'!A:A"),0)) -> 3 | B53: =COUNTIF(INDIRECT("'"&C53&"'!A:A"),$F$2) -> 0 | C53: 43 | E53: =VLOOKUP(C53,档案!A:B,2,FALSE) -> 库存现金 | G53: =IF(B53=0,INDEX(INDIRECT("'"&$C53&"'!$F:$F"),$A53,1),INDEX(INDIRECT("'"&$C53&"'!$F:$F"),$A53-1,1)) -> 0 | H53: =SUM(K53:O53) -> 0 | I53: =SUM(P53:W53) -> 0 | J53: =G53+H53-I53 -> 0 | K53: =SUMIFS(INDIRECT("'"&$C53&"'!$D:$D"),INDIRECT("'"&$C53&"'!$C:$C"),K$3,INDIRECT("'"&$C53&"'!$A:$A"),$F$2) -> 0 | L53: =SUMIFS(INDIRECT("'"&$C53&"'!$D:$D"),INDIRECT("'"&$C53&"'!$C:$C"),L$3,INDIRECT("'"&$C53&"'!$A:$A"),$F$2) -> 0 | M53: =SUMIFS(INDIRECT("'"&$C53&"'!$D:$D"),INDIRECT("'"&$C53&"'!$C:$C"),M$3,INDIRECT("'"&$C53&"'!$A:$A"),$F$2) -> 0 | N53: =SUMIFS(INDIRECT("'"&$C53&"'!$D:$D"),INDIRECT("'"&$C53&"'!$C:$C"),N$3,INDIRECT("'"&$C53&"'!$A:$A"),$F$2) -> 0 | O53: =SUMIFS(INDIRECT("'"&$C53&"'!$D:$D"),INDIRECT("'"&$C53&"'!$C:$C"),O$3,INDIRECT("'"&$C53&"'!$A:$A"),$F$2) -> 0 | P53: =SUMIFS(INDIRECT("'"&$C53&"'!$e:$e"),INDIRECT("'"&$C53&"'!$C:$C"),P$3,INDIRECT("'"&$C53&"'!$A:$A"),$F$2) -> 0 | Q53: =SUMIFS(INDIRECT("'"&$C53&"'!$e:$e"),INDIRECT("'"&$C53&"'!$C:$C"),Q$3,INDIRECT("'"&$C53&"'!$A:$A"),$F$2) -> 0 | R53: =SUMIFS(INDIRECT("'"&$C53&"'!$e:$e"),INDIRECT("'"&$C53&"'!$C:$C"),R$3,INDIRECT("'"&$C53&"'!$A:$A"),$F$2) -> 0 | S53: =SUMIFS(INDIRECT("'"&$C53&"'!$e:$e"),INDIRECT("'"&$C53&"'!$C:$C"),S$3,INDIRECT("'"&$C53&"'!$A:$A"),$F$2) -> 0 | T53: =SUMIFS(INDIRECT("'"&$C53&"'!$e:$e"),INDIRECT("'"&$C53&"'!$C:$C"),T$3,INDIRECT("'"&$C53&"'!$A:$A"),$F$2) -> 0 | U53: =SUMIFS(INDIRECT("'"&$C53&"'!$e:$e"),INDIRECT("'"&$C53&"'!$C:$C"),U$3,INDIRECT("'"&$C53&"'!$A:$A"),$F$2) -> 0 | V53: =SUMIFS(INDIRECT("'"&$C53&"'!$e:$e"),INDIRECT("'"&$C53&"'!$C:$C"),V$3,INDIRECT("'"&$C53&"'!$A:$A"),$F$2) -> 0 | W53: =SUMIFS(INDIRECT("'"&$C53&"'!$e:$e"),INDIRECT("'"&$C53&"'!$C:$C"),W$3,INDIRECT("'"&$C53&"'!$A:$A"),$F$2) -> 0
A54: =IF(B54=0,MATCH($F$2,INDIRECT("'"&C54&"'!A:A"),1),MATCH($F$2,INDIRECT("'"&C54&"'!A:A"),0)) -> #REF! | B54: =COUNTIF(INDIRECT("'"&C54&"'!A:A"),$F$2) -> #REF! | E54: 合计 | G54: =SUM(G51:G53) -> 10647.75 | H54: =SUM(K54:O54) -> 0 | I54: =SUM(P54:W54) -> 0 | J54: =G54+H54-I54 -> 10647.75 | K54: =SUM(K51:K53) -> 0 | L54: =SUM(L51:L53) -> 0 | M54: =SUM(M51:M53) -> 0 | N54: =SUM(N51:N53) -> 0 | O54: =SUM(O51:O53) -> 0 | P54: =SUM(P51:P53) -> 0 | Q54: =SUM(Q51:Q53) -> 0 | R54: =SUM(R51:R53) -> 0 | ... W54: =SUM(W51:W53) -> 0
A55: =IF(B55=0,MATCH($F$2,INDIRECT("'"&C55&"'!A:A"),1),MATCH($F$2,INDIRECT("'"&C55&"'!A:A"),0)) -> 180 | B55: =COUNTIF(INDIRECT("'"&C55&"'!A:A"),$F$2) -> 0 | C55: 44 | D55: 个体户 | E55: 银行存款 | F55: =VLOOKUP(C55,档案!A:B,2,FALSE) -> 王先梅 邮储银行4262 | G55: =IF(B55=0,INDEX(INDIRECT("'"&$C55&"'!$F:$F"),$A55,1),INDEX(INDIRECT("'"&$C55&"'!$F:$F"),$A55-1,1)) -> 51552.55 | H55: =SUM(K55:O55) -> 0 | I55: =SUM(P55:W55) -> 0 | J55: =G55+H55-I55 -> 51552.55 | K55: =SUMIFS(INDIRECT("'"&$C55&"'!$D:$D"),INDIRECT("'"&$C55&"'!$C:$C"),K$3,INDIRECT("'"&$C55&"'!$A:$A"),$F$2) -> 0 | L55: =SUMIFS(INDIRECT("'"&$C55&"'!$D:$D"),INDIRECT("'"&$C55&"'!$C:$C"),L$3,INDIRECT("'"&$C55&"'!$A:$A"),$F$2) -> 0 | M55: =SUMIFS(INDIRECT("'"&$C55&"'!$D:$D"),INDIRECT("'"&$C55&"'!$C:$C"),M$3,INDIRECT("'"&$C55&"'!$A:$A"),$F$2) -> 0 | N55: =SUMIFS(INDIRECT("'"&$C55&"'!$D:$D"),INDIRECT("'"&$C55&"'!$C:$C"),N$3,INDIRECT("'"&$C55&"'!$A:$A"),$F$2) -> 0 | O55: =SUMIFS(INDIRECT("'"&$C55&"'!$D:$D"),INDIRECT("'"&$C55&"'!$C:$C"),O$3,INDIRECT("'"&$C55&"'!$A:$A"),$F$2) -> 0 | P55: =SUMIFS(INDIRECT("'"&$C55&"'!$e:$e"),INDIRECT("'"&$C55&"'!$C:$C"),P$3,INDIRECT("'"&$C55&"'!$A:$A"),$F$2) -> 0 | Q55: =SUMIFS(INDIRECT("'"&$C55&"'!$e:$e"),INDIRECT("'"&$C55&"'!$C:$C"),Q$3,INDIRECT("'"&$C55&"'!$A:$A"),$F$2) -> 0 | R55: =SUMIFS(INDIRECT("'"&$C55&"'!$e:$e"),INDIRECT("'"&$C55&"'!$C:$C"),R$3,INDIRECT("'"&$C55&"'!$A:$A"),$F$2) -> 0 | S55: =SUMIFS(INDIRECT("'"&$C55&"'!$e:$e"),INDIRECT("'"&$C55&"'!$C:$C"),S$3,INDIRECT("'"&$C55&"'!$A:$A"),$F$2) -> 0 | T55: =SUMIFS(INDIRECT("'"&$C55&"'!$e:$e"),INDIRECT("'"&$C55&"'!$C:$C"),T$3,INDIRECT("'"&$C55&"'!$A:$A"),$F$2) -> 0 | U55: =SUMIFS(INDIRECT("'"&$C55&"'!$e:$e"),INDIRECT("'"&$C55&"'!$C:$C"),U$3,INDIRECT("'"&$C55&"'!$A:$A"),$F$2) -> 0 | V55: =SUMIFS(INDIRECT("'"&$C55&"'!$e:$e"),INDIRECT("'"&$C55&"'!$C:$C"),V$3,INDIRECT("'"&$C55&"'!$A:$A"),$F$2) -> 0 | W55: =SUMIFS(INDIRECT("'"&$C55&"'!$e:$e"),INDIRECT("'"&$C55&"'!$C:$C"),W$3,INDIRECT("'"&$C55&"'!$A:$A"),$F$2) -> 0
A56: =IF(B56=0,MATCH($F$2,INDIRECT("'"&C56&"'!A:A"),1),MATCH($F$2,INDIRECT("'"&C56&"'!A:A"),0)) -> 16 | B56: =COUNTIF(INDIRECT("'"&C56&"'!A:A"),$F$2) -> 0 | C56: 45 | F56: =VLOOKUP(C56,档案!A:B,2,FALSE) -> 林家祥 邮储银行7677 | G56: =IF(B56=0,INDEX(INDIRECT("'"&$C56&"'!$F:$F"),$A56,1),INDEX(INDIRECT("'"&$C56&"'!$F:$F"),$A56-1,1)) -> 413.83 | H56: =SUM(K56:O56) -> 0 | I56: =SUM(P56:W56) -> 0 | J56: =G56+H56-I56 -> 413.83 | K56: =SUMIFS(INDIRECT("'"&$C56&"'!$D:$D"),INDIRECT("'"&$C56&"'!$C:$C"),K$3,INDIRECT("'"&$C56&"'!$A:$A"),$F$2) -> 0 | L56: =SUMIFS(INDIRECT("'"&$C56&"'!$D:$D"),INDIRECT("'"&$C56&"'!$C:$C"),L$3,INDIRECT("'"&$C56&"'!$A:$A"),$F$2) -> 0 | M56: =SUMIFS(INDIRECT("'"&$C56&"'!$D:$D"),INDIRECT("'"&$C56&"'!$C:$C"),M$3,INDIRECT("'"&$C56&"'!$A:$A"),$F$2) -> 0 | N56: =SUMIFS(INDIRECT("'"&$C56&"'!$D:$D"),INDIRECT("'"&$C56&"'!$C:$C"),N$3,INDIRECT("'"&$C56&"'!$A:$A"),$F$2) -> 0 | O56: =SUMIFS(INDIRECT("'"&$C56&"'!$D:$D"),INDIRECT("'"&$C56&"'!$C:$C"),O$3,INDIRECT("'"&$C56&"'!$A:$A"),$F$2) -> 0 | P56: =SUMIFS(INDIRECT("'"&$C56&"'!$e:$e"),INDIRECT("'"&$C56&"'!$C:$C"),P$3,INDIRECT("'"&$C56&"'!$A:$A"),$F$2) -> 0 | Q56: =SUMIFS(INDIRECT("'"&$C56&"'!$e:$e"),INDIRECT("'"&$C56&"'!$C:$C"),Q$3,INDIRECT("'"&$C56&"'!$A:$A"),$F$2) -> 0 | R56: =SUMIFS(INDIRECT("'"&$C56&"'!$e:$e"),INDIRECT("'"&$C56&"'!$C:$C"),R$3,INDIRECT("'"&$C56&"'!$A:$A"),$F$2) -> 0 | S56: =SUMIFS(INDIRECT("'"&$C56&"'!$e:$e"),INDIRECT("'"&$C56&"'!$C:$C"),S$3,INDIRECT("'"&$C56&"'!$A:$A"),$F$2) -> 0 | T56: =SUMIFS(INDIRECT("'"&$C56&"'!$e:$e"),INDIRECT("'"&$C56&"'!$C:$C"),T$3,INDIRECT("'"&$C56&"'!$A:$A"),$F$2) -> 0 | U56: =SUMIFS(INDIRECT("'"&$C56&"'!$e:$e"),INDIRECT("'"&$C56&"'!$C:$C"),U$3,INDIRECT("'"&$C56&"'!$A:$A"),$F$2) -> 0 | V56: =SUMIFS(INDIRECT("'"&$C56&"'!$e:$e"),INDIRECT("'"&$C56&"'!$C:$C"),V$3,INDIRECT("'"&$C56&"'!$A:$A"),$F$2) -> 0 | W56: =SUMIFS(INDIRECT("'"&$C56&"'!$e:$e"),INDIRECT("'"&$C56&"'!$C:$C"),W$3,INDIRECT("'"&$C56&"'!$A:$A"),$F$2) -> 0
A57: =IF(B57=0,MATCH($F$2,INDIRECT("'"&C57&"'!A:A"),1),MATCH($F$2,INDIRECT("'"&C57&"'!A:A"),0)) -> 23 | B57: =COUNTIF(INDIRECT("'"&C57&"'!A:A"),$F$2) -> 0 | C57: 46 | F57: =VLOOKUP(C57,档案!A:B,2,FALSE) -> 湖北岚丹农民工发放账户01679 | G57: =IF(B57=0,INDEX(INDIRECT("'"&$C57&"'!$F:$F"),$A57,1),INDEX(INDIRECT("'"&$C57&"'!$F:$F"),$A57-1,1)) -> 2474.83 | H57: =SUM(K57:O57) -> 0 | I57: =SUM(P57:W57) -> 0 | J57: =G57+H57-I57 -> 2474.83 | K57: =SUMIFS(INDIRECT("'"&$C57&"'!$D:$D"),INDIRECT("'"&$C57&"'!$C:$C"),K$3,INDIRECT("'"&$C57&"'!$A:$A"),$F$2) -> 0 | L57: =SUMIFS(INDIRECT("'"&$C57&"'!$D:$D"),INDIRECT("'"&$C57&"'!$C:$C"),L$3,INDIRECT("'"&$C57&"'!$A:$A"),$F$2) -> 0 | M57: =SUMIFS(INDIRECT("'"&$C57&"'!$D:$D"),INDIRECT("'"&$C57&"'!$C:$C"),M$3,INDIRECT("'"&$C57&"'!$A:$A"),$F$2) -> 0 | N57: =SUMIFS(INDIRECT("'"&$C57&"'!$D:$D"),INDIRECT("'"&$C57&"'!$C:$C"),N$3,INDIRECT("'"&$C57&"'!$A:$A"),$F$2) -> 0 | O57: =SUMIFS(INDIRECT("'"&$C57&"'!$D:$D"),INDIRECT("'"&$C57&"'!$C:$C"),O$3,INDIRECT("'"&$C57&"'!$A:$A"),$F$2) -> 0 | P57: =SUMIFS(INDIRECT("'"&$C57&"'!$e:$e"),INDIRECT("'"&$C57&"'!$C:$C"),P$3,INDIRECT("'"&$C57&"'!$A:$A"),$F$2) -> 0 | Q57: =SUMIFS(INDIRECT("'"&$C57&"'!$e:$e"),INDIRECT("'"&$C57&"'!$C:$C"),Q$3,INDIRECT("'"&$C57&"'!$A:$A"),$F$2) -> 0 | R57: =SUMIFS(INDIRECT("'"&$C57&"'!$e:$e"),INDIRECT("'"&$C57&"'!$C:$C"),R$3,INDIRECT("'"&$C57&"'!$A:$A"),$F$2) -> 0 | S57: =SUMIFS(INDIRECT("'"&$C57&"'!$e:$e"),INDIRECT("'"&$C57&"'!$C:$C"),S$3,INDIRECT("'"&$C57&"'!$A:$A"),$F$2) -> 0 | T57: =SUMIFS(INDIRECT("'"&$C57&"'!$e:$e"),INDIRECT("'"&$C57&"'!$C:$C"),T$3,INDIRECT("'"&$C57&"'!$A:$A"),$F$2) -> 0 | U57: =SUMIFS(INDIRECT("'"&$C57&"'!$e:$e"),INDIRECT("'"&$C57&"'!$C:$C"),U$3,INDIRECT("'"&$C57&"'!$A:$A"),$F$2) -> 0 | V57: =SUMIFS(INDIRECT("'"&$C57&"'!$e:$e"),INDIRECT("'"&$C57&"'!$C:$C"),V$3,INDIRECT("'"&$C57&"'!$A:$A"),$F$2) -> 0 | W57: =SUMIFS(INDIRECT("'"&$C57&"'!$e:$e"),INDIRECT("'"&$C57&"'!$C:$C"),W$3,INDIRECT("'"&$C57&"'!$A:$A"),$F$2) -> 0
A58: =IF(B58=0,MATCH($F$2,INDIRECT("'"&C58&"'!A:A"),1),MATCH($F$2,INDIRECT("'"&C58&"'!A:A"),0)) -> 22 | B58: =COUNTIF(INDIRECT("'"&C58&"'!A:A"),$F$2) -> 0 | C58: 47 | F58: =VLOOKUP(C58,档案!A:B,2,FALSE) -> 岚丹电子承兑汇票 | G58: =IF(B58=0,INDEX(INDIRECT("'"&$C58&"'!$F:$F"),$A58,1),INDEX(INDIRECT("'"&$C58&"'!$F:$F"),$A58-1,1)) -> 0 | H58: =SUM(K58:O58) -> 0 | I58: =SUM(P58:W58) -> 0 | J58: =G58+H58-I58 -> 0 | K58: =SUMIFS(INDIRECT("'"&$C58&"'!$D:$D"),INDIRECT("'"&$C58&"'!$C:$C"),K$3,INDIRECT("'"&$C58&"'!$A:$A"),$F$2) -> 0 | L58: =SUMIFS(INDIRECT("'"&$C58&"'!$D:$D"),INDIRECT("'"&$C58&"'!$C:$C"),L$3,INDIRECT("'"&$C58&"'!$A:$A"),$F$2) -> 0 | M58: =SUMIFS(INDIRECT("'"&$C58&"'!$D:$D"),INDIRECT("'"&$C58&"'!$C:$C"),M$3,INDIRECT("'"&$C58&"'!$A:$A"),$F$2) -> 0 | N58: =SUMIFS(INDIRECT("'"&$C58&"'!$D:$D"),INDIRECT("'"&$C58&"'!$C:$C"),N$3,INDIRECT("'"&$C58&"'!$A:$A"),$F$2) -> 0 | O58: =SUMIFS(INDIRECT("'"&$C58&"'!$D:$D"),INDIRECT("'"&$C58&"'!$C:$C"),O$3,INDIRECT("'"&$C58&"'!$A:$A"),$F$2) -> 0 | P58: =SUMIFS(INDIRECT("'"&$C58&"'!$e:$e"),INDIRECT("'"&$C58&"'!$C:$C"),P$3,INDIRECT("'"&$C58&"'!$A:$A"),$F$2) -> 0 | Q58: =SUMIFS(INDIRECT("'"&$C58&"'!$e:$e"),INDIRECT("'"&$C58&"'!$C:$C"),Q$3,INDIRECT("'"&$C58&"'!$A:$A"),$F$2) -> 0 | R58: =SUMIFS(INDIRECT("'"&$C58&"'!$e:$e"),INDIRECT("'"&$C58&"'!$C:$C"),R$3,INDIRECT("'"&$C58&"'!$A:$A"),$F$2) -> 0 | S58: =SUMIFS(INDIRECT("'"&$C58&"'!$e:$e"),INDIRECT("'"&$C58&"'!$C:$C"),S$3,INDIRECT("'"&$C58&"'!$A:$A"),$F$2) -> 0 | T58: =SUMIFS(INDIRECT("'"&$C58&"'!$e:$e"),INDIRECT("'"&$C58&"'!$C:$C"),T$3,INDIRECT("'"&$C58&"'!$A:$A"),$F$2) -> 0 | U58: =SUMIFS(INDIRECT("'"&$C58&"'!$e:$e"),INDIRECT("'"&$C58&"'!$C:$C"),U$3,INDIRECT("'"&$C58&"'!$A:$A"),$F$2) -> 0 | V58: =SUMIFS(INDIRECT("'"&$C58&"'!$e:$e"),INDIRECT("'"&$C58&"'!$C:$C"),V$3,INDIRECT("'"&$C58&"'!$A:$A"),$F$2) -> 0 | W58: =SUMIFS(INDIRECT("'"&$C58&"'!$e:$e"),INDIRECT("'"&$C58&"'!$C:$C"),W$3,INDIRECT("'"&$C58&"'!$A:$A"),$F$2) -> 0
A59: =IF(B59=0,MATCH($F$2,INDIRECT("'"&C59&"'!A:A"),1),MATCH($F$2,INDIRECT("'"&C59&"'!A:A"),0)) -> 12 | B59: =COUNTIF(INDIRECT("'"&C59&"'!A:A"),$F$2) -> 0 | C59: 48 | F59: =VLOOKUP(C59,档案!A:B,2,FALSE) -> 湖北岚丹农民工账户53528 | G59: =IF(B59=0,INDEX(INDIRECT("'"&$C59&"'!$F:$F"),$A59,1),INDEX(INDIRECT("'"&$C59&"'!$F:$F"),$A59-1,1)) -> 126516.66 | H59: =SUM(K59:O59) -> 0 | I59: =SUM(P59:W59) -> 0 | J59: =G59+H59-I59 -> 126516.66 | K59: =SUMIFS(INDIRECT("'"&$C59&"'!$D:$D"),INDIRECT("'"&$C59&"'!$C:$C"),K$3,INDIRECT("'"&$C59&"'!$A:$A"),$F$2) -> 0 | L59: =SUMIFS(INDIRECT("'"&$C59&"'!$D:$D"),INDIRECT("'"&$C59&"'!$C:$C"),L$3,INDIRECT("'"&$C59&"'!$A:$A"),$F$2) -> 0 | M59: =SUMIFS(INDIRECT("'"&$C59&"'!$D:$D"),INDIRECT("'"&$C59&"'!$C:$C"),M$3,INDIRECT("'"&$C59&"'!$A:$A"),$F$2) -> 0 | N59: =SUMIFS(INDIRECT("'"&$C59&"'!$D:$D"),INDIRECT("'"&$C59&"'!$C:$C"),N$3,INDIRECT("'"&$C59&"'!$A:$A"),$F$2) -> 0 | O59: =SUMIFS(INDIRECT("'"&$C59&"'!$D:$D"),INDIRECT("'"&$C59&"'!$C:$C"),O$3,INDIRECT("'"&$C59&"'!$A:$A"),$F$2) -> 0 | P59: =SUMIFS(INDIRECT("'"&$C59&"'!$e:$e"),INDIRECT("'"&$C59&"'!$C:$C"),P$3,INDIRECT("'"&$C59&"'!$A:$A"),$F$2) -> 0 | Q59: =SUMIFS(INDIRECT("'"&$C59&"'!$e:$e"),INDIRECT("'"&$C59&"'!$C:$C"),Q$3,INDIRECT("'"&$C59&"'!$A:$A"),$F$2) -> 0 | R59: =SUMIFS(INDIRECT("'"&$C59&"'!$e:$e"),INDIRECT("'"&$C59&"'!$C:$C"),R$3,INDIRECT("'"&$C59&"'!$A:$A"),$F$2) -> 0 | S59: =SUMIFS(INDIRECT("'"&$C59&"'!$e:$e"),INDIRECT("'"&$C59&"'!$C:$C"),S$3,INDIRECT("'"&$C59&"'!$A:$A"),$F$2) -> 0 | T59: =SUMIFS(INDIRECT("'"&$C59&"'!$e:$e"),INDIRECT("'"&$C59&"'!$C:$C"),T$3,INDIRECT("'"&$C59&"'!$A:$A"),$F$2) -> 0 | U59: =SUMIFS(INDIRECT("'"&$C59&"'!$e:$e"),INDIRECT("'"&$C59&"'!$C:$C"),U$3,INDIRECT("'"&$C59&"'!$A:$A"),$F$2) -> 0 | V59: =SUMIFS(INDIRECT("'"&$C59&"'!$e:$e"),INDIRECT("'"&$C59&"'!$C:$C"),V$3,INDIRECT("'"&$C59&"'!$A:$A"),$F$2) -> 0 | W59: =SUMIFS(INDIRECT("'"&$C59&"'!$e:$e"),INDIRECT("'"&$C59&"'!$C:$C"),W$3,INDIRECT("'"&$C59&"'!$A:$A"),$F$2) -> 0
A60: =IF(B60=0,MATCH($F$2,INDIRECT("'"&C60&"'!A:A"),1),MATCH($F$2,INDIRECT("'"&C60&"'!A:A"),0)) -> #REF! | B60: =COUNTIF(INDIRECT("'"&C60&"'!A:A"),$F$2) -> #REF! | F60: 小计 | G60: =SUM(G55:G59) -> 180957.87 | H60: =SUM(K60:O60) -> 0 | I60: =SUM(P60:W60) -> 0 | J60: =G60+H60-I60 -> 180957.87 | K60: =SUM(K55:K59) -> 0 | L60: =SUM(L55:L59) -> 0 | M60: =SUM(M55:M59) -> 0 | N60: =SUM(N55:N59) -> 0 | O60: =SUM(O55:O59) -> 0 | P60: =SUM(P55:P59) -> 0 | Q60: =SUM(Q55:Q59) -> 0 | R60: =SUM(R55:R59) -> 0 | ... W60: =SUM(W55:W59) -> 0
A61: =IF(B61=0,MATCH($F$2,INDIRECT("'"&C61&"'!A:A"),1),MATCH($F$2,INDIRECT("'"&C61&"'!A:A"),0)) -> 6 | B61: =COUNTIF(INDIRECT("'"&C61&"'!A:A"),$F$2) -> 0 | C61: 50 | E61: =VLOOKUP(C61,档案!A:B,2,FALSE) -> 库存现金 | G61: =IF(B61=0,INDEX(INDIRECT("'"&$C61&"'!$F:$F"),$A61,1),INDEX(INDIRECT("'"&$C61&"'!$F:$F"),$A61-1,1)) -> 0 | H61: =SUM(K61:O61) -> 0 | I61: =SUM(P61:W61) -> 0 | J61: =G61+H61-I61 -> 0 | K61: =SUMIFS(INDIRECT("'"&$C61&"'!$D:$D"),INDIRECT("'"&$C61&"'!$C:$C"),K$3,INDIRECT("'"&$C61&"'!$A:$A"),$F$2) -> 0 | L61: =SUMIFS(INDIRECT("'"&$C61&"'!$D:$D"),INDIRECT("'"&$C61&"'!$C:$C"),L$3,INDIRECT("'"&$C61&"'!$A:$A"),$F$2) -> 0 | M61: =SUMIFS(INDIRECT("'"&$C61&"'!$D:$D"),INDIRECT("'"&$C61&"'!$C:$C"),M$3,INDIRECT("'"&$C61&"'!$A:$A"),$F$2) -> 0 | N61: =SUMIFS(INDIRECT("'"&$C61&"'!$D:$D"),INDIRECT("'"&$C61&"'!$C:$C"),N$3,INDIRECT("'"&$C61&"'!$A:$A"),$F$2) -> 0 | O61: =SUMIFS(INDIRECT("'"&$C61&"'!$D:$D"),INDIRECT("'"&$C61&"'!$C:$C"),O$3,INDIRECT("'"&$C61&"'!$A:$A"),$F$2) -> 0 | P61: =SUMIFS(INDIRECT("'"&$C61&"'!$e:$e"),INDIRECT("'"&$C61&"'!$C:$C"),P$3,INDIRECT("'"&$C61&"'!$A:$A"),$F$2) -> 0 | Q61: =SUMIFS(INDIRECT("'"&$C61&"'!$e:$e"),INDIRECT("'"&$C61&"'!$C:$C"),Q$3,INDIRECT("'"&$C61&"'!$A:$A"),$F$2) -> 0 | R61: =SUMIFS(INDIRECT("'"&$C61&"'!$e:$e"),INDIRECT("'"&$C61&"'!$C:$C"),R$3,INDIRECT("'"&$C61&"'!$A:$A"),$F$2) -> 0 | S61: =SUMIFS(INDIRECT("'"&$C61&"'!$e:$e"),INDIRECT("'"&$C61&"'!$C:$C"),S$3,INDIRECT("'"&$C61&"'!$A:$A"),$F$2) -> 0 | T61: =SUMIFS(INDIRECT("'"&$C61&"'!$e:$e"),INDIRECT("'"&$C61&"'!$C:$C"),T$3,INDIRECT("'"&$C61&"'!$A:$A"),$F$2) -> 0 | U61: =SUMIFS(INDIRECT("'"&$C61&"'!$e:$e"),INDIRECT("'"&$C61&"'!$C:$C"),U$3,INDIRECT("'"&$C61&"'!$A:$A"),$F$2) -> 0 | V61: =SUMIFS(INDIRECT("'"&$C61&"'!$e:$e"),INDIRECT("'"&$C61&"'!$C:$C"),V$3,INDIRECT("'"&$C61&"'!$A:$A"),$F$2) -> 0 | W61: =SUMIFS(INDIRECT("'"&$C61&"'!$e:$e"),INDIRECT("'"&$C61&"'!$C:$C"),W$3,INDIRECT("'"&$C61&"'!$A:$A"),$F$2) -> 0
E62: 合计 | G62: =SUM(G60:G61) -> 180957.87 | H62: =SUM(K62:O62) -> 0 | I62: =SUM(P62:W62) -> 0 | J62: =G62+H62-I62 -> 180957.87 | K62: =SUM(K60:K61) -> 0 | L62: =SUM(L60:L61) -> 0 | M62: =SUM(M60:M61) -> 0 | N62: =SUM(N60:N61) -> 0 | O62: =SUM(O60:O61) -> 0 | P62: =SUM(P60:P61) -> 0 | Q62: =SUM(Q60:Q61) -> 0 | R62: =SUM(R60:R61) -> 0 | ... W62: =SUM(W60:W61) -> 0
D63: 总计 | F63: 银行存款 | G63: =SUMIF($F3:$F62,"小计",G3:G62) -> 1352964.1 | H63: =SUM(K63:O63) -> 40000 | I63: =SUM(P63:W63) -> 39528.5 | J63: =G63+H63-I63 -> 1353435.6 | K63: =SUMIF($F3:$F62,"小计",K3:K62) -> 0 | L63: =SUMIF($F3:$F62,"小计",L3:L62) -> 0 | M63: =SUMIF($F3:$F62,"小计",M3:M62) -> 0 | N63: =SUMIF($F3:$F62,"小计",N3:N62) -> 40000 | O63: =SUMIF($F3:$F62,"小计",O3:O62) -> 0 | P63: =SUMIF($F3:$F62,"小计",P3:P62) -> 0 | Q63: =SUMIF($F3:$F62,"小计",Q3:Q62) -> 0 | R63: =SUMIF($F3:$F62,"小计",R3:R62) -> 1.5 | ... W63: =SUMIF($F3:$F62,"小计",W3:W62) -> 0
F64: 电子承兑汇票 | G64: =SUMIF($E3:$E62,"电子承兑汇票",G3:G62) -> 668845.12 | H64: =SUM(K64:O64) -> 0 | I64: =SUM(P64:W64) -> 0 | J64: =G64+H64-I64 -> 668845.12 | K64: =SUMIF($E3:$E62,"电子承兑汇票",K3:K62) -> 0 | L64: =SUMIF($E3:$E62,"电子承兑汇票",L3:L62) -> 0 | M64: =SUMIF($E3:$E62,"电子承兑汇票",M3:M62) -> 0 | N64: =SUMIF($E3:$E62,"电子承兑汇票",N3:N62) -> 0 | O64: =SUMIF($E3:$E62,"电子承兑汇票",O3:O62) -> 0 | P64: =SUMIF($E3:$E62,"电子承兑汇票",P3:P62) -> 0 | Q64: =SUMIF($E3:$E62,"电子承兑汇票",Q3:Q62) -> 0 | R64: =SUMIF($E3:$E62,"电子承兑汇票",R3:R62) -> 0 | ... W64: =SUMIF($E3:$E62,"电子承兑汇票",W3:W62) -> 0
F65: 库存现金 | G65: =SUMIF($E3:$E62,"库存现金",G3:G62) -> 305 | H65: =SUM(K65:O65) -> 0 | I65: =SUM(P65:W65) -> 0 | J65: =G65+H65-I65 -> 305 | K65: =SUMIF($E3:$E62,"库存现金",K3:K62) -> 0 | L65: =SUMIF($E3:$E62,"库存现金",L3:L62) -> 0 | M65: =SUMIF($E3:$E62,"库存现金",M3:M62) -> 0 | N65: =SUMIF($E3:$E62,"库存现金",N3:N62) -> 0 | O65: =SUMIF($E3:$E62,"库存现金",O3:O62) -> 0 | P65: =SUMIF($E3:$E62,"库存现金",P3:P62) -> 0 | Q65: =SUMIF($E3:$E62,"库存现金",Q3:Q62) -> 0 | R65: =SUMIF($E3:$E62,"库存现金",R3:R62) -> 0 | ... W65: =SUMIF($E3:$E62,"库存现金",W3:W62) -> 0
F66: 总计 | G66: =SUM(G63:G65) -> 2022114.2 | H66: =SUM(K66:O66) -> 40000 | I66: =SUM(P66:W66) -> 39528.5 | J66: =G66+H66-I66 -> 2022585.7 | K66: =SUM(K63:K65) -> 0 | L66: =SUM(L63:L65) -> 0 | M66: =SUM(M63:M65) -> 0 | N66: =SUM(N63:N65) -> 40000 | O66: =SUM(O63:O65) -> 0 | P66: =SUM(P63:P65) -> 0 | Q66: =SUM(Q63:Q65) -> 0 | R66: =SUM(R63:R65) -> 1.5 | ... W66: =SUM(W63:W65) -> 0
A67: =IF(B67=0,MATCH($F$2,INDIRECT("'"&C67&"'!A:A"),1),MATCH($F$2,INDIRECT("'"&C67&"'!A:A"),0)) -> 13 | B67: =COUNTIF(INDIRECT("'"&C67&"'!A:A"),$F$2) -> 0 | C67: 51 | D67: 工会户 | F67: 工行西山支行029092 | G67: =IF(B67=0,INDEX(INDIRECT("'"&$C67&"'!$F:$F"),$A67,1),INDEX(INDIRECT("'"&$C67&"'!$F:$F"),$A67-1,1)) -> 207.35 | H67: =SUM(K67:O67) -> 0 | I67: =SUM(P67:W67) -> 0 | J67: =G67+H67-I67 -> 207.35 | K67: =SUMIFS(INDIRECT("'"&$C67&"'!$D:$D"),INDIRECT("'"&$C67&"'!$C:$C"),K$3,INDIRECT("'"&$C67&"'!$A:$A"),$F$2) -> 0 | L67: =SUMIFS(INDIRECT("'"&$C67&"'!$D:$D"),INDIRECT("'"&$C67&"'!$C:$C"),L$3,INDIRECT("'"&$C67&"'!$A:$A"),$F$2) -> 0 | M67: =SUMIFS(INDIRECT("'"&$C67&"'!$D:$D"),INDIRECT("'"&$C67&"'!$C:$C"),M$3,INDIRECT("'"&$C67&"'!$A:$A"),$F$2) -> 0 | N67: =SUMIFS(INDIRECT("'"&$C67&"'!$D:$D"),INDIRECT("'"&$C67&"'!$C:$C"),N$3,INDIRECT("'"&$C67&"'!$A:$A"),$F$2) -> 0 | O67: =SUMIFS(INDIRECT("'"&$C67&"'!$D:$D"),INDIRECT("'"&$C67&"'!$C:$C"),O$3,INDIRECT("'"&$C67&"'!$A:$A"),$F$2) -> 0 | P67: =SUMIFS(INDIRECT("'"&$C67&"'!$e:$e"),INDIRECT("'"&$C67&"'!$C:$C"),P$3,INDIRECT("'"&$C67&"'!$A:$A"),$F$2) -> 0 | Q67: =SUMIFS(INDIRECT("'"&$C67&"'!$e:$e"),INDIRECT("'"&$C67&"'!$C:$C"),Q$3,INDIRECT("'"&$C67&"'!$A:$A"),$F$2) -> 0 | R67: =SUMIFS(INDIRECT("'"&$C67&"'!$e:$e"),INDIRECT("'"&$C67&"'!$C:$C"),R$3,INDIRECT("'"&$C67&"'!$A:$A"),$F$2) -> 0 | S67: =SUMIFS(INDIRECT("'"&$C67&"'!$e:$e"),INDIRECT("'"&$C67&"'!$C:$C"),S$3,INDIRECT("'"&$C67&"'!$A:$A"),$F$2) -> 0 | T67: =SUMIFS(INDIRECT("'"&$C67&"'!$e:$e"),INDIRECT("'"&$C67&"'!$C:$C"),T$3,INDIRECT("'"&$C67&"'!$A:$A"),$F$2) -> 0 | U67: =SUMIFS(INDIRECT("'"&$C67&"'!$e:$e"),INDIRECT("'"&$C67&"'!$C:$C"),U$3,INDIRECT("'"&$C67&"'!$A:$A"),$F$2) -> 0 | V67: =SUMIFS(INDIRECT("'"&$C67&"'!$e:$e"),INDIRECT("'"&$C67&"'!$C:$C"),V$3,INDIRECT("'"&$C67&"'!$A:$A"),$F$2) -> 0 | W67: =SUMIFS(INDIRECT("'"&$C67&"'!$e:$e"),INDIRECT("'"&$C67&"'!$C:$C"),W$3,INDIRECT("'"&$C67&"'!$A:$A"),$F$2) -> 0
A68: =IF(B68=0,MATCH($F$2,INDIRECT("'"&C68&"'!A:A"),1),MATCH($F$2,INDIRECT("'"&C68&"'!A:A"),0)) -> 3 | B68: =COUNTIF(INDIRECT("'"&C68&"'!A:A"),$F$2) -> 0 | C68: 52 | D68: 王娟个人现金 | F68: 库存现金 | G68: =IF(B68=0,INDEX(INDIRECT("'"&$C68&"'!$F:$F"),$A68,1),INDEX(INDIRECT("'"&$C68&"'!$F:$F"),$A68-1,1)) -> 0 | H68: =SUM(K68:O68) -> 0 | I68: =SUM(P68:W68) -> 0 | J68: =G68+H68-I68 -> 0 | K68: =SUMIFS(INDIRECT("'"&$C68&"'!$D:$D"),INDIRECT("'"&$C68&"'!$C:$C"),K$3,INDIRECT("'"&$C68&"'!$A:$A"),$F$2) -> 0 | L68: =SUMIFS(INDIRECT("'"&$C68&"'!$D:$D"),INDIRECT("'"&$C68&"'!$C:$C"),L$3,INDIRECT("'"&$C68&"'!$A:$A"),$F$2) -> 0 | M68: =SUMIFS(INDIRECT("'"&$C68&"'!$D:$D"),INDIRECT("'"&$C68&"'!$C:$C"),M$3,INDIRECT("'"&$C68&"'!$A:$A"),$F$2) -> 0 | N68: =SUMIFS(INDIRECT("'"&$C68&"'!$D:$D"),INDIRECT("'"&$C68&"'!$C:$C"),N$3,INDIRECT("'"&$C68&"'!$A:$A"),$F$2) -> 0 | O68: =SUMIFS(INDIRECT("'"&$C68&"'!$D:$D"),INDIRECT("'"&$C68&"'!$C:$C"),O$3,INDIRECT("'"&$C68&"'!$A:$A"),$F$2) -> 0 | P68: =SUMIFS(INDIRECT("'"&$C68&"'!$e:$e"),INDIRECT("'"&$C68&"'!$C:$C"),P$3,INDIRECT("'"&$C68&"'!$A:$A"),$F$2) -> 0 | Q68: =SUMIFS(INDIRECT("'"&$C68&"'!$e:$e"),INDIRECT("'"&$C68&"'!$C:$C"),Q$3,INDIRECT("'"&$C68&"'!$A:$A"),$F$2) -> 0 | R68: =SUMIFS(INDIRECT("'"&$C68&"'!$e:$e"),INDIRECT("'"&$C68&"'!$C:$C"),R$3,INDIRECT("'"&$C68&"'!$A:$A"),$F$2) -> 0 | S68: =SUMIFS(INDIRECT("'"&$C68&"'!$e:$e"),INDIRECT("'"&$C68&"'!$C:$C"),S$3,INDIRECT("'"&$C68&"'!$A:$A"),$F$2) -> 0 | T68: =SUMIFS(INDIRECT("'"&$C68&"'!$e:$e"),INDIRECT("'"&$C68&"'!$C:$C"),T$3,INDIRECT("'"&$C68&"'!$A:$A"),$F$2) -> 0 | U68: =SUMIFS(INDIRECT("'"&$C68&"'!$e:$e"),INDIRECT("'"&$C68&"'!$C:$C"),U$3,INDIRECT("'"&$C68&"'!$A:$A"),$F$2) -> 0 | V68: =SUMIFS(INDIRECT("'"&$C68&"'!$e:$e"),INDIRECT("'"&$C68&"'!$C:$C"),V$3,INDIRECT("'"&$C68&"'!$A:$A"),$F$2) -> 0 | W68: =SUMIFS(INDIRECT("'"&$C68&"'!$e:$e"),INDIRECT("'"&$C68&"'!$C:$C"),W$3,INDIRECT("'"&$C68&"'!$A:$A"),$F$2) -> 0
A69: =IF(B69=0,MATCH($F$2,INDIRECT("'"&C69&"'!A:A"),1),MATCH($F$2,INDIRECT("'"&C69&"'!A:A"),0)) -> 192 | B69: =COUNTIF(INDIRECT("'"&C69&"'!A:A"),$F$2) -> 1 | C69: 53 | D69: 岚丹 | F69: 中信银行武汉东湖支行068761 | G69: =IF(B69=0,INDEX(INDIRECT("'"&$C69&"'!$F:$F"),$A69,1),INDEX(INDIRECT("'"&$C69&"'!$F:$F"),$A69-1,1)) -> 14589.75 | H69: =SUM(K69:O69) -> 8000 | I69: =SUM(P69:W69) -> 0 | J69: =G69+H69-I69 -> 22589.75 | K69: =SUMIFS(INDIRECT("'"&$C69&"'!$D:$D"),INDIRECT("'"&$C69&"'!$C:$C"),K$3,INDIRECT("'"&$C69&"'!$A:$A"),$F$2) -> 0 | L69: =SUMIFS(INDIRECT("'"&$C69&"'!$D:$D"),INDIRECT("'"&$C69&"'!$C:$C"),L$3,INDIRECT("'"&$C69&"'!$A:$A"),$F$2) -> 8000 | M69: =SUMIFS(INDIRECT("'"&$C69&"'!$D:$D"),INDIRECT("'"&$C69&"'!$C:$C"),M$3,INDIRECT("'"&$C69&"'!$A:$A"),$F$2) -> 0 | N69: =SUMIFS(INDIRECT("'"&$C69&"'!$D:$D"),INDIRECT("'"&$C69&"'!$C:$C"),N$3,INDIRECT("'"&$C69&"'!$A:$A"),$F$2) -> 0 | O69: =SUMIFS(INDIRECT("'"&$C69&"'!$D:$D"),INDIRECT("'"&$C69&"'!$C:$C"),O$3,INDIRECT("'"&$C69&"'!$A:$A"),$F$2) -> 0 | P69: =SUMIFS(INDIRECT("'"&$C69&"'!$e:$e"),INDIRECT("'"&$C69&"'!$C:$C"),P$3,INDIRECT("'"&$C69&"'!$A:$A"),$F$2) -> 0 | Q69: =SUMIFS(INDIRECT("'"&$C69&"'!$e:$e"),INDIRECT("'"&$C69&"'!$C:$C"),Q$3,INDIRECT("'"&$C69&"'!$A:$A"),$F$2) -> 0 | R69: =SUMIFS(INDIRECT("'"&$C69&"'!$e:$e"),INDIRECT("'"&$C69&"'!$C:$C"),R$3,INDIRECT("'"&$C69&"'!$A:$A"),$F$2) -> 0 | S69: =SUMIFS(INDIRECT("'"&$C69&"'!$e:$e"),INDIRECT("'"&$C69&"'!$C:$C"),S$3,INDIRECT("'"&$C69&"'!$A:$A"),$F$2) -> 0 | T69: =SUMIFS(INDIRECT("'"&$C69&"'!$e:$e"),INDIRECT("'"&$C69&"'!$C:$C"),T$3,INDIRECT("'"&$C69&"'!$A:$A"),$F$2) -> 0 | U69: =SUMIFS(INDIRECT("'"&$C69&"'!$e:$e"),INDIRECT("'"&$C69&"'!$C:$C"),U$3,INDIRECT("'"&$C69&"'!$A:$A"),$F$2) -> 0 | V69: =SUMIFS(INDIRECT("'"&$C69&"'!$e:$e"),INDIRECT("'"&$C69&"'!$C:$C"),V$3,INDIRECT("'"&$C69&"'!$A:$A"),$F$2) -> 0 | W69: =SUMIFS(INDIRECT("'"&$C69&"'!$e:$e"),INDIRECT("'"&$C69&"'!$C:$C"),W$3,INDIRECT("'"&$C69&"'!$A:$A"),$F$2) -> 0

Sheet 日期汇总
B1: 时间段资金收付汇总表
A2: 45200 | M2: 单位：元
A3: 45230 | B3: =SUMIF($A$4:$A$379,"<="&$A$3,B$4:B$379)-SUMIF($A$4:$A$379,"<"&$A$2,B$4:B$379) -> 0 | C3: =SUMIF($A$4:$A$379,"<="&$A$3,C$4:C$379)-SUMIF($A$4:$A$379,"<"&$A$2,C$4:C$379) -> 0 | D3: =SUMIF($A$4:$A$379,"<="&$A$3,D$4:D$379)-SUMIF($A$4:$A$379,"<"&$A$2,D$4:D$379) -> 0 | E3: =SUMIF($A$4:$A$379,"<="&$A$3,E$4:E$379)-SUMIF($A$4:$A$379,"<"&$A$2,E$4:E$379) -> 0 | F3: =SUMIF($A$4:$A$379,"<="&$A$3,F$4:F$379)-SUMIF($A$4:$A$379,"<"&$A$2,F$4:F$379) -> 0 | G3: =SUMIF($A$4:$A$379,"<="&$A$3,G$4:G$379)-SUMIF($A$4:$A$379,"<"&$A$2,G$4:G$379) -> 0 | H3: =SUMIF($A$4:$A$379,"<="&$A$3,H$4:H$379)-SUMIF($A$4:$A$379,"<"&$A$2,H$4:H$379) -> 0 | I3: =SUMIF($A$4:$A$379,"<="&$A$3,I$4:I$379)-SUMIF($A$4:$A$379,"<"&$A$2,I$4:I$379) -> 0 | ... N3: =SUMIF($A$4:$A$379,"<="&$A$3,N$4:N$379)-SUMIF($A$4:$A$379,"<"&$A$2,N$4:N$379) -> 0
A4: 日期 | B4: 营业回款 | C4: 投标保证金回款 | D4: 借款到账 | E4: 其他收款 | F4: 他行转入或存现 | G4: 付货款 | H4: 付投标保证金 | I4: 付日常费用 | J4: 还借款及利息 | K4: 其他付款 | L4: 转出他行或提现 | M4: 收款小计 | N4: 付款小计
A5: 44927 | B5: =SUMIFS(流水汇总!$K:$K,流水汇总!$H:$H,$A5,流水汇总!$J:$J,B$4) -> 0 | C5: =SUMIFS(流水汇总!$K:$K,流水汇总!$H:$H,$A5,流水汇总!$J:$J,C$4) -> 0 | D5: =SUMIFS(流水汇总!$K:$K,流水汇总!$H:$H,$A5,流水汇总!$J:$J,D$4) -> 0 | E5: =SUMIFS(流水汇总!$K:$K,流水汇总!$H:$H,$A5,流水汇总!$J:$J,E$4) -> 0 | F5: =SUMIFS(流水汇总!$K:$K,流水汇总!$H:$H,$A5,流水汇总!$J:$J,F$4) -> 0 | G5: =SUMIFS(流水汇总!$L:$L,流水汇总!$H:$H,$A5,流水汇总!$J:$J,G$4) -> 0 | H5: =SUMIFS(流水汇总!$L:$L,流水汇总!$H:$H,$A5,流水汇总!$J:$J,H$4) -> 0 | I5: =SUMIFS(流水汇总!$L:$L,流水汇总!$H:$H,$A5,流水汇总!$J:$J,I$4) -> 0 | J5: =SUMIFS(流水汇总!$L:$L,流水汇总!$H:$H,$A5,流水汇总!$J:$J,J$4) -> 0 | K5: =SUMIFS(流水汇总!$L:$L,流水汇总!$H:$H,$A5,流水汇总!$J:$J,K$4) -> 0 | L5: =SUMIFS(流水汇总!$L:$L,流水汇总!$H:$H,$A5,流水汇总!$J:$J,L$4) -> 0 | M5: =SUM(B5:F5) -> 0 | N5: =SUM(G5:L5) -> 0
A6: =A5+1 -> 44928 | B6: =SUMIFS(流水汇总!$K:$K,流水汇总!$H:$H,$A6,流水汇总!$J:$J,B$4) -> 0 | C6: =SUMIFS(流水汇总!$K:$K,流水汇总!$H:$H,$A6,流水汇总!$J:$J,C$4) -> 0 | D6: =SUMIFS(流水汇总!$K:$K,流水汇总!$H:$H,$A6,流水汇总!$J:$J,D$4) -> 0 | E6: =SUMIFS(流水汇总!$K:$K,流水汇总!$H:$H,$A6,流水汇总!$J:$J,E$4) -> 0 | F6: =SUMIFS(流水汇总!$K:$K,流水汇总!$H:$H,$A6,流水汇总!$J:$J,F$4) -> 0 | G6: =SUMIFS(流水汇总!$L:$L,流水汇总!$H:$H,$A6,流水汇总!$J:$J,G$4) -> 0 | H6: =SUMIFS(流水汇总!$L:$L,流水汇总!$H:$H,$A6,流水汇总!$J:$J,H$4) -> 0 | I6: =SUMIFS(流水汇总!$L:$L,流水汇总!$H:$H,$A6,流水汇总!$J:$J,I$4) -> 0 | J6: =SUMIFS(流水汇总!$L:$L,流水汇总!$H:$H,$A6,流水汇总!$J:$J,J$4) -> 0 | K6: =SUMIFS(流水汇总!$L:$L,流水汇总!$H:$H,$A6,流水汇总!$J:$J,K$4) -> 0 | L6: =SUMIFS(流水汇总!$L:$L,流水汇总!$H:$H,$A6,流水汇总!$J:$J,L$4) -> 0 | M6: =SUM(B6:F6) -> 0 | N6: =SUM(G6:L6) -> 0
A7: =A6+1 -> 44929 | B7: =SUMIFS(流水汇总!$K:$K,流水汇总!$H:$H,$A7,流水汇总!$J:$J,B$4) -> 0 | C7: =SUMIFS(流水汇总!$K:$K,流水汇总!$H:$H,$A7,流水汇总!$J:$J,C$4) -> 0 | D7: =SUMIFS(流水汇总!$K:$K,流水汇总!$H:$H,$A7,流水汇总!$J:$J,D$4) -> 0 | E7: =SUMIFS(流水汇总!$K:$K,流水汇总!$H:$H,$A7,流水汇总!$J:$J,E$4) -> 0 | F7: =SUMIFS(流水汇总!$K:$K,流水汇总!$H:$H,$A7,流水汇总!$J:$J,F$4) -> 0 | G7: =SUMIFS(流水汇总!$L:$L,流水汇总!$H:$H,$A7,流水汇总!$J:$J,G$4) -> 0 | H7: =SUMIFS(流水汇总!$L:$L,流水汇总!$H:$H,$A7,流水汇总!$J:$J,H$4) -> 0 | I7: =SUMIFS(流水汇总!$L:$L,流水汇总!$H:$H,$A7,流水汇总!$J:$J,I$4) -> 0 | J7: =SUMIFS(流水汇总!$L:$L,流水汇总!$H:$H,$A7,流水汇总!$J:$J,J$4) -> 0 | K7: =SUMIFS(流水汇总!$L:$L,流水汇总!$H:$H,$A7,流水汇总!$J:$J,K$4) -> 0 | L7: =SUMIFS(流水汇总!$L:$L,流水汇总!$H:$H,$A7,流水汇总!$J:$J,L$4) -> 0 | M7: =SUM(B7:F7) -> 0 | N7: =SUM(G7:L7) -> 0
A8: =A7+1 -> 44930 | B8: =SUMIFS(流水汇总!$K:$K,流水汇总!$H:$H,$A8,流水汇总!$J:$J,B$4) -> 0 | C8: =SUMIFS(流水汇总!$K:$K,流水汇总!$H:$H,$A8,流水汇总!$J:$J,C$4) -> 0 | D8: =SUMIFS(流水汇总!$K:$K,流水汇总!$H:$H,$A8,流水汇总!$J:$J,D$4) -> 0 | E8: =SUMIFS(流水汇总!$K:$K,流水汇总!$H:$H,$A8,流水汇总!$J:$J,E$4) -> 0 | F8: =SUMIFS(流水汇总!$K:$K,流水汇总!$H:$H,$A8,流水汇总!$J:$J,F$4) -> 0 | G8: =SUMIFS(流水汇总!$L:$L,流水汇总!$H:$H,$A8,流水汇总!$J:$J,G$4) -> 0 | H8: =SUMIFS(流水汇总!$L:$L,流水汇总!$H:$H,$A8,流水汇总!$J:$J,H$4) -> 0 | I8: =SUMIFS(流水汇总!$L:$L,流水汇总!$H:$H,$A8,流水汇总!$J:$J,I$4) -> 0 | J8: =SUMIFS(流水汇总!$L:$L,流水汇总!$H:$H,$A8,流水汇总!$J:$J,J$4) -> 0 | K8: =SUMIFS(流水汇总!$L:$L,流水汇总!$H:$H,$A8,流水汇总!$J:$J,K$4) -> 0 | L8: =SUMIFS(流水汇总!$L:$L,流水汇总!$H:$H,$A8,流水汇总!$J:$J,L$4) -> 0 | M8: =SUM(B8:F8) -> 0 | N8: =SUM(G8:L8) -> 0
A9: =A8+1 -> 44931 | B9: =SUMIFS(流水汇总!$K:$K,流水汇总!$H:$H,$A9,流水汇总!$J:$J,B$4) -> 0 | C9: =SUMIFS(流水汇总!$K:$K,流水汇总!$H:$H,$A9,流水汇总!$J:$J,C$4) -> 0 | D9: =SUMIFS(流水汇总!$K:$K,流水汇总!$H:$H,$A9,流水汇总!$J:$J,D$4) -> 0 | E9: =SUMIFS(流水汇总!$K:$K,流水汇总!$H:$H,$A9,流水汇总!$J:$J,E$4) -> 0 | F9: =SUMIFS(流水汇总!$K:$K,流水汇总!$H:$H,$A9,流水汇总!$J:$J,F$4) -> 0 | G9: =SUMIFS(流水汇总!$L:$L,流水汇总!$H:$H,$A9,流水汇总!$J:$J,G$4) -> 0 | H9: =SUMIFS(流水汇总!$L:$L,流水汇总!$H:$H,$A9,流水汇总!$J:$J,H$4) -> 0 | I9: =SUMIFS(流水汇总!$L:$L,流水汇总!$H:$H,$A9,流水汇总!$J:$J,I$4) -> 0 | J9: =SUMIFS(流水汇总!$L:$L,流水汇总!$H:$H,$A9,流水汇总!$J:$J,J$4) -> 0 | K9: =SUMIFS(流水汇总!$L:$L,流水汇总!$H:$H,$A9,流水汇总!$J:$J,K$4) -> 0 | L9: =SUMIFS(流水汇总!$L:$L,流水汇总!$H:$H,$A9,流水汇总!$J:$J,L$4) -> 0 | M9: =SUM(B9:F9) -> 0 | N9: =SUM(G9:L9) -> 0
A10: =A9+1 -> 44932 | B10: =SUMIFS(流水汇总!$K:$K,流水汇总!$H:$H,$A10,流水汇总!$J:$J,B$4) -> 0 | C10: =SUMIFS(流水汇总!$K:$K,流水汇总!$H:$H,$A10,流水汇总!$J:$J,C$4) -> 0 | D10: =SUMIFS(流水汇总!$K:$K,流水汇总!$H:$H,$A10,流水汇总!$J:$J,D$4) -> 0 | E10: =SUMIFS(流水汇总!$K:$K,流水汇总!$H:$H,$A10,流水汇总!$J:$J,E$4) -> 0 | F10: =SUMIFS(流水汇总!$K:$K,流水汇总!$H:$H,$A10,流水汇总!$J:$J,F$4) -> 0 | G10: =SUMIFS(流水汇总!$L:$L,流水汇总!$H:$H,$A10,流水汇总!$J:$J,G$4) -> 0 | H10: =SUMIFS(流水汇总!$L:$L,流水汇总!$H:$H,$A10,流水汇总!$J:$J,H$4) -> 0 | I10: =SUMIFS(流水汇总!$L:$L,流水汇总!$H:$H,$A10,流水汇总!$J:$J,I$4) -> 0 | J10: =SUMIFS(流水汇总!$L:$L,流水汇总!$H:$H,$A10,流水汇总!$J:$J,J$4) -> 0 | K10: =SUMIFS(流水汇总!$L:$L,流水汇总!$H:$H,$A10,流水汇总!$J:$J,K$4) -> 0 | L10: =SUMIFS(流水汇总!$L:$L,流水汇总!$H:$H,$A10,流水汇总!$J:$J,L$4) -> 0 | M10: =SUM(B10:F10) -> 0 | N10: =SUM(G10:L10) -> 0
A11: =A10+1 -> 44933 | B11: =SUMIFS(流水汇总!$K:$K,流水汇总!$H:$H,$A11,流水汇总!$J:$J,B$4) -> 0 | C11: =SUMIFS(流水汇总!$K:$K,流水汇总!$H:$H,$A11,流水汇总!$J:$J,C$4) -> 0 | D11: =SUMIFS(流水汇总!$K:$K,流水汇总!$H:$H,$A11,流水汇总!$J:$J,D$4) -> 0 | E11: =SUMIFS(流水汇总!$K:$K,流水汇总!$H:$H,$A11,流水汇总!$J:$J,E$4) -> 0 | F11: =SUMIFS(流水汇总!$K:$K,流水汇总!$H:$H,$A11,流水汇总!$J:$J,F$4) -> 0 | G11: =SUMIFS(流水汇总!$L:$L,流水汇总!$H:$H,$A11,流水汇总!$J:$J,G$4) -> 0 | H11: =SUMIFS(流水汇总!$L:$L,流水汇总!$H:$H,$A11,流水汇总!$J:$J,H$4) -> 0 | I11: =SUMIFS(流水汇总!$L:$L,流水汇总!$H:$H,$A11,流水汇总!$J:$J,I$4) -> 0 | J11: =SUMIFS(流水汇总!$L:$L,流水汇总!$H:$H,$A11,流水汇总!$J:$J,J$4) -> 0 | K11: =SUMIFS(流水汇总!$L:$L,流水汇总!$H:$H,$A11,流水汇总!$J:$J,K$4) -> 0 | L11: =SUMIFS(流水汇总!$L:$L,流水汇总!$H:$H,$A11,流水汇总!$J:$J,L$4) -> 0 | M11: =SUM(B11:F11) -> 0 | N11: =SUM(G11:L11) -> 0
A12: =A11+1 -> 44934 | B12: =SUMIFS(流水汇总!$K:$K,流水汇总!$H:$H,$A12,流水汇总!$J:$J,B$4) -> 0 | C12: =SUMIFS(流水汇总!$K:$K,流水汇总!$H:$H,$A12,流水汇总!$J:$J,C$4) -> 0 | D12: =SUMIFS(流水汇总!$K:$K,流水汇总!$H:$H,$A12,流水汇总!$J:$J,D$4) -> 0 | E12: =SUMIFS(流水汇总!$K:$K,流水汇总!$H:$H,$A12,流水汇总!$J:$J,E$4) -> 0 | F12: =SUMIFS(流水汇总!$K:$K,流水汇总!$H:$H,$A12,流水汇总!$J:$J,F$4) -> 0 | G12: =SUMIFS(流水汇总!$L:$L,流水汇总!$H:$H,$A12,流水汇总!$J:$J,G$4) -> 0 | H12: =SUMIFS(流水汇总!$L:$L,流水汇总!$H:$H,$A12,流水汇总!$J:$J,H$4) -> 0 | I12: =SUMIFS(流水汇总!$L:$L,流水汇总!$H:$H,$A12,流水汇总!$J:$J,I$4) -> 0 | J12: =SUMIFS(流水汇总!$L:$L,流水汇总!$H:$H,$A12,流水汇总!$J:$J,J$4) -> 0 | K12: =SUMIFS(流水汇总!$L:$L,流水汇总!$H:$H,$A12,流水汇总!$J:$J,K$4) -> 0 | L12: =SUMIFS(流水汇总!$L:$L,流水汇总!$H:$H,$A12,流水汇总!$J:$J,L$4) -> 0 | M12: =SUM(B12:F12) -> 0 | N12: =SUM(G12:L12) -> 0
A13: =A12+1 -> 44935 | B13: =SUMIFS(流水汇总!$K:$K,流水汇总!$H:$H,$A13,流水汇总!$J:$J,B$4) -> 0 | C13: =SUMIFS(流水汇总!$K:$K,流水汇总!$H:$H,$A13,流水汇总!$J:$J,C$4) -> 0 | D13: =SUMIFS(流水汇总!$K:$K,流水汇总!$H:$H,$A13,流水汇总!$J:$J,D$4) -> 0 | E13: =SUMIFS(流水汇总!$K:$K,流水汇总!$H:$H,$A13,流水汇总!$J:$J,E$4) -> 0 | F13: =SUMIFS(流水汇总!$K:$K,流水汇总!$H:$H,$A13,流水汇总!$J:$J,F$4) -> 0 | G13: =SUMIFS(流水汇总!$L:$L,流水汇总!$H:$H,$A13,流水汇总!$J:$J,G$4) -> 0 | H13: =SUMIFS(流水汇总!$L:$L,流水汇总!$H:$H,$A13,流水汇总!$J:$J,H$4) -> 0 | I13: =SUMIFS(流水汇总!$L:$L,流水汇总!$H:$H,$A13,流水汇总!$J:$J,I$4) -> 0 | J13: =SUMIFS(流水汇总!$L:$L,流水汇总!$H:$H,$A13,流水汇总!$J:$J,J$4) -> 0 | K13: =SUMIFS(流水汇总!$L:$L,流水汇总!$H:$H,$A13,流水汇总!$J:$J,K$4) -> 0 | L13: =SUMIFS(流水汇总!$L:$L,流水汇总!$H:$H,$A13,流水汇总!$J:$J,L$4) -> 0 | M13: =SUM(B13:F13) -> 0 | N13: =SUM(G13:L13) -> 0
A14: =A13+1 -> 44936 | B14: =SUMIFS(流水汇总!$K:$K,流水汇总!$H:$H,$A14,流水汇总!$J:$J,B$4) -> 0 | C14: =SUMIFS(流水汇总!$K:$K,流水汇总!$H:$H,$A14,流水汇总!$J:$J,C$4) -> 0 | D14: =SUMIFS(流水汇总!$K:$K,流水汇总!$H:$H,$A14,流水汇总!$J:$J,D$4) -> 0 | E14: =SUMIFS(流水汇总!$K:$K,流水汇总!$H:$H,$A14,流水汇总!$J:$J,E$4) -> 0 | F14: =SUMIFS(流水汇总!$K:$K,流水汇总!$H:$H,$A14,流水汇总!$J:$J,F$4) -> 0 | G14: =SUMIFS(流水汇总!$L:$L,流水汇总!$H:$H,$A14,流水汇总!$J:$J,G$4) -> 0 | H14: =SUMIFS(流水汇总!$L:$L,流水汇总!$H:$H,$A14,流水汇总!$J:$J,H$4) -> 0 | I14: =SUMIFS(流水汇总!$L:$L,流水汇总!$H:$H,$A14,流水汇总!$J:$J,I$4) -> 0 | J14: =SUMIFS(流水汇总!$L:$L,流水汇总!$H:$H,$A14,流水汇总!$J:$J,J$4) -> 0 | K14: =SUMIFS(流水汇总!$L:$L,流水汇总!$H:$H,$A14,流水汇总!$J:$J,K$4) -> 0 | L14: =SUMIFS(流水汇总!$L:$L,流水汇总!$H:$H,$A14,流水汇总!$J:$J,L$4) -> 0 | M14: =SUM(B14:F14) -> 0 | N14: =SUM(G14:L14) -> 0
A15: =A14+1 -> 44937 | B15: =SUMIFS(流水汇总!$K:$K,流水汇总!$H:$H,$A15,流水汇总!$J:$J,B$4) -> 0 | C15: =SUMIFS(流水汇总!$K:$K,流水汇总!$H:$H,$A15,流水汇总!$J:$J,C$4) -> 0 | D15: =SUMIFS(流水汇总!$K:$K,流水汇总!$H:$H,$A15,流水汇总!$J:$J,D$4) -> 0 | E15: =SUMIFS(流水汇总!$K:$K,流水汇总!$H:$H,$A15,流水汇总!$J:$J,E$4) -> 0 | F15: =SUMIFS(流水汇总!$K:$K,流水汇总!$H:$H,$A15,流水汇总!$J:$J,F$4) -> 0 | G15: =SUMIFS(流水汇总!$L:$L,流水汇总!$H:$H,$A15,流水汇总!$J:$J,G$4) -> 0 | H15: =SUMIFS(流水汇总!$L:$L,流水汇总!$H:$H,$A15,流水汇总!$J:$J,H$4) -> 0 | I15: =SUMIFS(流水汇总!$L:$L,流水汇总!$H:$H,$A15,流水汇总!$J:$J,I$4) -> 0 | J15: =SUMIFS(流水汇总!$L:$L,流水汇总!$H:$H,$A15,流水汇总!$J:$J,J$4) -> 0 | K15: =SUMIFS(流水汇总!$L:$L,流水汇总!$H:$H,$A15,流水汇总!$J:$J,K$4) -> 0 | L15: =SUMIFS(流水汇总!$L:$L,流水汇总!$H:$H,$A15,流水汇总!$J:$J,L$4) -> 0 | M15: =SUM(B15:F15) -> 0 | N15: =SUM(G15:L15) -> 0
A16: =A15+1 -> 44938 | B16: =SUMIFS(流水汇总!$K:$K,流水汇总!$H:$H,$A16,流水汇总!$J:$J,B$4) -> 0 | C16: =SUMIFS(流水汇总!$K:$K,流水汇总!$H:$H,$A16,流水汇总!$J:$J,C$4) -> 0 | D16: =SUMIFS(流水汇总!$K:$K,流水汇总!$H:$H,$A16,流水汇总!$J:$J,D$4) -> 0 | E16: =SUMIFS(流水汇总!$K:$K,流水汇总!$H:$H,$A16,流水汇总!$J:$J,E$4) -> 0 | F16: =SUMIFS(流水汇总!$K:$K,流水汇总!$H:$H,$A16,流水汇总!$J:$J,F$4) -> 0 | G16: =SUMIFS(流水汇总!$L:$L,流水汇总!$H:$H,$A16,流水汇总!$J:$J,G$4) -> 0 | H16: =SUMIFS(流水汇总!$L:$L,流水汇总!$H:$H,$A16,流水汇总!$J:$J,H$4) -> 0 | I16: =SUMIFS(流水汇总!$L:$L,流水汇总!$H:$H,$A16,流水汇总!$J:$J,I$4) -> 0 | J16: =SUMIFS(流水汇总!$L:$L,流水汇总!$H:$H,$A16,流水汇总!$J:$J,J$4) -> 0 | K16: =SUMIFS(流水汇总!$L:$L,流水汇总!$H:$H,$A16,流水汇总!$J:$J,K$4) -> 0 | L16: =SUMIFS(流水汇总!$L:$L,流水汇总!$H:$H,$A16,流水汇总!$J:$J,L$4) -> 0 | M16: =SUM(B16:F16) -> 0 | N16: =SUM(G16:L16) -> 0
A17: =A16+1 -> 44939 | B17: =SUMIFS(流水汇总!$K:$K,流水汇总!$H:$H,$A17,流水汇总!$J:$J,B$4) -> 0 | C17: =SUMIFS(流水汇总!$K:$K,流水汇总!$H:$H,$A17,流水汇总!$J:$J,C$4) -> 0 | D17: =SUMIFS(流水汇总!$K:$K,流水汇总!$H:$H,$A17,流水汇总!$J:$J,D$4) -> 0 | E17: =SUMIFS(流水汇总!$K:$K,流水汇总!$H:$H,$A17,流水汇总!$J:$J,E$4) -> 0 | F17: =SUMIFS(流水汇总!$K:$K,流水汇总!$H:$H,$A17,流水汇总!$J:$J,F$4) -> 0 | G17: =SUMIFS(流水汇总!$L:$L,流水汇总!$H:$H,$A17,流水汇总!$J:$J,G$4) -> 0 | H17: =SUMIFS(流水汇总!$L:$L,流水汇总!$H:$H,$A17,流水汇总!$J:$J,H$4) -> 0 | I17: =SUMIFS(流水汇总!$L:$L,流水汇总!$H:$H,$A17,流水汇总!$J:$J,I$4) -> 0 | J17: =SUMIFS(流水汇总!$L:$L,流水汇总!$H:$H,$A17,流水汇总!$J:$J,J$4) -> 0 | K17: =SUMIFS(流水汇总!$L:$L,流水汇总!$H:$H,$A17,流水汇总!$J:$J,K$4) -> 0 | L17: =SUMIFS(流水汇总!$L:$L,流水汇总!$H:$H,$A17,流水汇总!$J:$J,L$4) -> 0 | M17: =SUM(B17:F17) -> 0 | N17: =SUM(G17:L17) -> 0
... A369: =A368+1 -> 45291 | B369: =SUMIFS(流水汇总!$K:$K,流水汇总!$H:$H,$A369,流水汇总!$J:$J,B$4) -> 0 | C369: =SUMIFS(流水汇总!$K:$K,流水汇总!$H:$H,$A369,流水汇总!$J:$J,C$4) -> 0 | D369: =SUMIFS(流水汇总!$K:$K,流水汇总!$H:$H,$A369,流水汇总!$J:$J,D$4) -> 0 | E369: =SUMIFS(流水汇总!$K:$K,流水汇总!$H:$H,$A369,流水汇总!$J:$J,E$4) -> 0 | F369: =SUMIFS(流水汇总!$K:$K,流水汇总!$H:$H,$A369,流水汇总!$J:$J,F$4) -> 0 | G369: =SUMIFS(流水汇总!$L:$L,流水汇总!$H:$H,$A369,流水汇总!$J:$J,G$4) -> 0 | H369: =SUMIFS(流水汇总!$L:$L,流水汇总!$H:$H,$A369,流水汇总!$J:$J,H$4) -> 0 | I369: =SUMIFS(流水汇总!$L:$L,流水汇总!$H:$H,$A369,流水汇总!$J:$J,I$4) -> 0 | J369: =SUMIFS(流水汇总!$L:$L,流水汇总!$H:$H,$A369,流水汇总!$J:$J,J$4) -> 0 | K369: =SUMIFS(流水汇总!$L:$L,流水汇总!$H:$H,$A369,流水汇总!$J:$J,K$4) -> 0 | L369: =SUMIFS(流水汇总!$L:$L,流水汇总!$H:$H,$A369,流水汇总!$J:$J,L$4) -> 0 | M369: =SUM(B369:F369) -> 0 | N369: =SUM(G369:L369) -> 0

Sheet 流水汇总
A1: 表 | B1: 行数 | D1: 换表 | E1: 表行 | F1: 公司 | G1: 资金户名 | H1: 日期 | I1: 摘要 | J1: 收支类别 | K1: 收款金额 | L1: 付款金额 | M1: 余额 | N1: 备注
A2: =档案!A2 -> 1 | B2: =COUNTA(INDIRECT("'"&A2&"'!a:a")) -> 159 | D2: 1 | E2: 3 | F2: =VLOOKUP(D2,档案!A:C,3,FALSE) -> 武汉开明 | G2: =VLOOKUP(D2,档案!A:B,2,FALSE) -> 华夏银行汉正街支行186346 | H2: =INDEX(INDIRECT("'"&$D2&"'!A:g"),$E2,COLUMN()-7) -> 45658 | I2: =INDEX(INDIRECT("'"&$D2&"'!A:g"),$E2,COLUMN()-7) -> 期初余额 | J2: =INDEX(INDIRECT("'"&$D2&"'!A:g"),$E2,COLUMN()-7) -> 0 | K2: =INDEX(INDIRECT("'"&$D2&"'!A:g"),$E2,COLUMN()-7) -> 0 | L2: =INDEX(INDIRECT("'"&$D2&"'!A:g"),$E2,COLUMN()-7) -> 0 | M2: =INDEX(INDIRECT("'"&$D2&"'!A:g"),$E2,COLUMN()-7) -> 45511.67 | N2: =INDEX(INDIRECT("'"&$D2&"'!A:g"),$E2,COLUMN()-7) -> 0
A3: =档案!A3 -> 2 | B3: =COUNTA(INDIRECT("'"&A3&"'!a:a")) -> 740 | D3: =IF(E2>=VLOOKUP(D2,A:B,2,FALSE),D2+1,D2) -> 1 | E3: =IF(E2>=VLOOKUP(D2,A:B,2,FALSE),3,E2+1) -> 4 | F3: =VLOOKUP(D3,档案!A:C,3,FALSE) -> 武汉开明 | G3: =VLOOKUP(D3,档案!A:B,2,FALSE) -> 华夏银行汉正街支行186346 | H3: =INDEX(INDIRECT("'"&$D3&"'!A:g"),$E3,COLUMN()-7) -> 45659 | I3: =INDEX(INDIRECT("'"&$D3&"'!A:g"),$E3,COLUMN()-7) -> 收到内蒙古天皓水泥集团有限公司银行承兑汇票提示付款 | J3: =INDEX(INDIRECT("'"&$D3&"'!A:g"),$E3,COLUMN()-7) -> 他行转入或存现 | K3: =INDEX(INDIRECT("'"&$D3&"'!A:g"),$E3,COLUMN()-7) -> 14238.81 | L3: =INDEX(INDIRECT("'"&$D3&"'!A:g"),$E3,COLUMN()-7) -> 0 | M3: =INDEX(INDIRECT("'"&$D3&"'!A:g"),$E3,COLUMN()-7) -> 59750.48 | N3: =INDEX(INDIRECT("'"&$D3&"'!A:g"),$E3,COLUMN()-7) -> 0
A4: =档案!A4 -> 3 | B4: =COUNTA(INDIRECT("'"&A4&"'!a:a")) -> 39 | D4: =IF(E3>=VLOOKUP(D3,A:B,2,FALSE),D3+1,D3) -> 1 | E4: =IF(E3>=VLOOKUP(D3,A:B,2,FALSE),3,E3+1) -> 5 | F4: =VLOOKUP(D4,档案!A:C,3,FALSE) -> 武汉开明 | G4: =VLOOKUP(D4,档案!A:B,2,FALSE) -> 华夏银行汉正街支行186346 | H4: =INDEX(INDIRECT("'"&$D4&"'!A:g"),$E4,COLUMN()-7) -> 45672 | I4: =INDEX(INDIRECT("'"&$D4&"'!A:g"),$E4,COLUMN()-7) -> 收到江西亚东水泥有限公司维修费 | J4: =INDEX(INDIRECT("'"&$D4&"'!A:g"),$E4,COLUMN()-7) -> 营业回款 | K4: =INDEX(INDIRECT("'"&$D4&"'!A:g"),$E4,COLUMN()-7) -> 78000 | L4: =INDEX(INDIRECT("'"&$D4&"'!A:g"),$E4,COLUMN()-7) -> 0 | M4: =INDEX(INDIRECT("'"&$D4&"'!A:g"),$E4,COLUMN()-7) -> 137750.48 | N4: =INDEX(INDIRECT("'"&$D4&"'!A:g"),$E4,COLUMN()-7) -> 0
A5: =档案!A5 -> 4 | B5: =COUNTA(INDIRECT("'"&A5&"'!a:a")) -> 44 | D5: =IF(E4>=VLOOKUP(D4,A:B,2,FALSE),D4+1,D4) -> 1 | E5: =IF(E4>=VLOOKUP(D4,A:B,2,FALSE),3,E4+1) -> 6 | F5: =VLOOKUP(D5,档案!A:C,3,FALSE) -> 武汉开明 | G5: =VLOOKUP(D5,档案!A:B,2,FALSE) -> 华夏银行汉正街支行186346 | H5: =INDEX(INDIRECT("'"&$D5&"'!A:g"),$E5,COLUMN()-7) -> 45672 | I5: =INDEX(INDIRECT("'"&$D5&"'!A:g"),$E5,COLUMN()-7) -> 转武汉浦发 | J5: =INDEX(INDIRECT("'"&$D5&"'!A:g"),$E5,COLUMN()-7) -> 转出他行或提现 | K5: =INDEX(INDIRECT("'"&$D5&"'!A:g"),$E5,COLUMN()-7) -> 0 | L5: =INDEX(INDIRECT("'"&$D5&"'!A:g"),$E5,COLUMN()-7) -> 120000 | M5: =INDEX(INDIRECT("'"&$D5&"'!A:g"),$E5,COLUMN()-7) -> 17750.48 | N5: =INDEX(INDIRECT("'"&$D5&"'!A:g"),$E5,COLUMN()-7) -> 0
A6: =档案!A6 -> 5 | B6: =COUNTA(INDIRECT("'"&A6&"'!a:a")) -> 308 | D6: =IF(E5>=VLOOKUP(D5,A:B,2,FALSE),D5+1,D5) -> 1 | E6: =IF(E5>=VLOOKUP(D5,A:B,2,FALSE),3,E5+1) -> 7 | F6: =VLOOKUP(D6,档案!A:C,3,FALSE) -> 武汉开明 | G6: =VLOOKUP(D6,档案!A:B,2,FALSE) -> 华夏银行汉正街支行186346 | H6: =INDEX(INDIRECT("'"&$D6&"'!A:g"),$E6,COLUMN()-7) -> 45672 | I6: =INDEX(INDIRECT("'"&$D6&"'!A:g"),$E6,COLUMN()-7) -> 手续费 | J6: =INDEX(INDIRECT("'"&$D6&"'!A:g"),$E6,COLUMN()-7) -> 付日常费用 | K6: =INDEX(INDIRECT("'"&$D6&"'!A:g"),$E6,COLUMN()-7) -> 0 | L6: =INDEX(INDIRECT("'"&$D6&"'!A:g"),$E6,COLUMN()-7) -> 10.5 | M6: =INDEX(INDIRECT("'"&$D6&"'!A:g"),$E6,COLUMN()-7) -> 17739.98 | N6: =INDEX(INDIRECT("'"&$D6&"'!A:g"),$E6,COLUMN()-7) -> 0
A7: =档案!A7 -> 6 | B7: =COUNTA(INDIRECT("'"&A7&"'!a:a")) -> 28 | D7: =IF(E6>=VLOOKUP(D6,A:B,2,FALSE),D6+1,D6) -> 1 | E7: =IF(E6>=VLOOKUP(D6,A:B,2,FALSE),3,E6+1) -> 8 | F7: =VLOOKUP(D7,档案!A:C,3,FALSE) -> 武汉开明 | G7: =VLOOKUP(D7,档案!A:B,2,FALSE) -> 华夏银行汉正街支行186346 | H7: =INDEX(INDIRECT("'"&$D7&"'!A:g"),$E7,COLUMN()-7) -> 45678 | I7: =INDEX(INDIRECT("'"&$D7&"'!A:g"),$E7,COLUMN()-7) -> 收到宜良红狮水泥有限公司货款 | J7: =INDEX(INDIRECT("'"&$D7&"'!A:g"),$E7,COLUMN()-7) -> 营业回款 | K7: =INDEX(INDIRECT("'"&$D7&"'!A:g"),$E7,COLUMN()-7) -> 100000 | L7: =INDEX(INDIRECT("'"&$D7&"'!A:g"),$E7,COLUMN()-7) -> 0 | M7: =INDEX(INDIRECT("'"&$D7&"'!A:g"),$E7,COLUMN()-7) -> 117739.98 | N7: =INDEX(INDIRECT("'"&$D7&"'!A:g"),$E7,COLUMN()-7) -> 0
A8: =档案!A8 -> 7 | B8: =COUNTA(INDIRECT("'"&A8&"'!a:a")) -> 8 | D8: =IF(E7>=VLOOKUP(D7,A:B,2,FALSE),D7+1,D7) -> 1 | E8: =IF(E7>=VLOOKUP(D7,A:B,2,FALSE),3,E7+1) -> 9 | F8: =VLOOKUP(D8,档案!A:C,3,FALSE) -> 武汉开明 | G8: =VLOOKUP(D8,档案!A:B,2,FALSE) -> 华夏银行汉正街支行186346 | H8: =INDEX(INDIRECT("'"&$D8&"'!A:g"),$E8,COLUMN()-7) -> 45679 | I8: =INDEX(INDIRECT("'"&$D8&"'!A:g"),$E8,COLUMN()-7) -> 收到湖南耒阳南方水泥有限公司货款 | J8: =INDEX(INDIRECT("'"&$D8&"'!A:g"),$E8,COLUMN()-7) -> 营业回款 | K8: =INDEX(INDIRECT("'"&$D8&"'!A:g"),$E8,COLUMN()-7) -> 18242 | L8: =INDEX(INDIRECT("'"&$D8&"'!A:g"),$E8,COLUMN()-7) -> 0 | M8: =INDEX(INDIRECT("'"&$D8&"'!A:g"),$E8,COLUMN()-7) -> 135981.98 | N8: =INDEX(INDIRECT("'"&$D8&"'!A:g"),$E8,COLUMN()-7) -> 0
A9: =档案!A9 -> 8 | B9: =COUNTA(INDIRECT("'"&A9&"'!a:a")) -> 30 | D9: =IF(E8>=VLOOKUP(D8,A:B,2,FALSE),D8+1,D8) -> 1 | E9: =IF(E8>=VLOOKUP(D8,A:B,2,FALSE),3,E8+1) -> 10 | F9: =VLOOKUP(D9,档案!A:C,3,FALSE) -> 武汉开明 | G9: =VLOOKUP(D9,档案!A:B,2,FALSE) -> 华夏银行汉正街支行186346 | H9: =INDEX(INDIRECT("'"&$D9&"'!A:g"),$E9,COLUMN()-7) -> 45679 | I9: =INDEX(INDIRECT("'"&$D9&"'!A:g"),$E9,COLUMN()-7) -> 收到山东鲁碧集团有限公司货款 | J9: =INDEX(INDIRECT("'"&$D9&"'!A:g"),$E9,COLUMN()-7) -> 营业回款 | K9: =INDEX(INDIRECT("'"&$D9&"'!A:g"),$E9,COLUMN()-7) -> 9952 | L9: =INDEX(INDIRECT("'"&$D9&"'!A:g"),$E9,COLUMN()-7) -> 0 | M9: =INDEX(INDIRECT("'"&$D9&"'!A:g"),$E9,COLUMN()-7) -> 145933.98 | N9: =INDEX(INDIRECT("'"&$D9&"'!A:g"),$E9,COLUMN()-7) -> 0
A10: =档案!A10 -> 9 | B10: =COUNTA(INDIRECT("'"&A10&"'!a:a")) -> 2387 | D10: =IF(E9>=VLOOKUP(D9,A:B,2,FALSE),D9+1,D9) -> 1 | E10: =IF(E9>=VLOOKUP(D9,A:B,2,FALSE),3,E9+1) -> 11 | F10: =VLOOKUP(D10,档案!A:C,3,FALSE) -> 武汉开明 | G10: =VLOOKUP(D10,档案!A:B,2,FALSE) -> 华夏银行汉正街支行186346 | H10: =INDEX(INDIRECT("'"&$D10&"'!A:g"),$E10,COLUMN()-7) -> 45679 | I10: =INDEX(INDIRECT("'"&$D10&"'!A:g"),$E10,COLUMN()-7) -> 转武汉开明农商行 | J10: =INDEX(INDIRECT("'"&$D10&"'!A:g"),$E10,COLUMN()-7) -> 转出他行或提现 | K10: =INDEX(INDIRECT("'"&$D10&"'!A:g"),$E10,COLUMN()-7) -> 0 | L10: =INDEX(INDIRECT("'"&$D10&"'!A:g"),$E10,COLUMN()-7) -> 140000 | M10: =INDEX(INDIRECT("'"&$D10&"'!A:g"),$E10,COLUMN()-7) -> 5933.98 | N10: =INDEX(INDIRECT("'"&$D10&"'!A:g"),$E10,COLUMN()-7) -> 0
A11: =档案!A11 -> 10 | B11: =COUNTA(INDIRECT("'"&A11&"'!a:a")) -> 109 | D11: =IF(E10>=VLOOKUP(D10,A:B,2,FALSE),D10+1,D10) -> 1 | E11: =IF(E10>=VLOOKUP(D10,A:B,2,FALSE),3,E10+1) -> 12 | F11: =VLOOKUP(D11,档案!A:C,3,FALSE) -> 武汉开明 | G11: =VLOOKUP(D11,档案!A:B,2,FALSE) -> 华夏银行汉正街支行186346 | H11: =INDEX(INDIRECT("'"&$D11&"'!A:g"),$E11,COLUMN()-7) -> 45679 | I11: =INDEX(INDIRECT("'"&$D11&"'!A:g"),$E11,COLUMN()-7) -> 手续费 | J11: =INDEX(INDIRECT("'"&$D11&"'!A:g"),$E11,COLUMN()-7) -> 付日常费用 | K11: =INDEX(INDIRECT("'"&$D11&"'!A:g"),$E11,COLUMN()-7) -> 0 | L11: =INDEX(INDIRECT("'"&$D11&"'!A:g"),$E11,COLUMN()-7) -> 10.5 | M11: =INDEX(INDIRECT("'"&$D11&"'!A:g"),$E11,COLUMN()-7) -> 5923.48 | N11: =INDEX(INDIRECT("'"&$D11&"'!A:g"),$E11,COLUMN()-7) -> 0
A12: =档案!A12 -> 11 | B12: =COUNTA(INDIRECT("'"&A12&"'!a:a")) -> 18 | D12: =IF(E11>=VLOOKUP(D11,A:B,2,FALSE),D11+1,D11) -> 1 | E12: =IF(E11>=VLOOKUP(D11,A:B,2,FALSE),3,E11+1) -> 13 | F12: =VLOOKUP(D12,档案!A:C,3,FALSE) -> 武汉开明 | G12: =VLOOKUP(D12,档案!A:B,2,FALSE) -> 华夏银行汉正街支行186346 | H12: =INDEX(INDIRECT("'"&$D12&"'!A:g"),$E12,COLUMN()-7) -> 45680 | I12: =INDEX(INDIRECT("'"&$D12&"'!A:g"),$E12,COLUMN()-7) -> 收到崇阳县昌华实业有限公司货款 | J12: =INDEX(INDIRECT("'"&$D12&"'!A:g"),$E12,COLUMN()-7) -> 营业回款 | K12: =INDEX(INDIRECT("'"&$D12&"'!A:g"),$E12,COLUMN()-7) -> 50000 | L12: =INDEX(INDIRECT("'"&$D12&"'!A:g"),$E12,COLUMN()-7) -> 0 | M12: =INDEX(INDIRECT("'"&$D12&"'!A:g"),$E12,COLUMN()-7) -> 55923.48 | N12: =INDEX(INDIRECT("'"&$D12&"'!A:g"),$E12,COLUMN()-7) -> 0
A13: =档案!A13 -> 12 | B13: =COUNTA(INDIRECT("'"&A13&"'!a:a")) -> 2 | D13: =IF(E12>=VLOOKUP(D12,A:B,2,FALSE),D12+1,D12) -> 1 | E13: =IF(E12>=VLOOKUP(D12,A:B,2,FALSE),3,E12+1) -> 14 | F13: =VLOOKUP(D13,档案!A:C,3,FALSE) -> 武汉开明 | G13: =VLOOKUP(D13,档案!A:B,2,FALSE) -> 华夏银行汉正街支行186346 | H13: =INDEX(INDIRECT("'"&$D13&"'!A:g"),$E13,COLUMN()-7) -> 45680 | I13: =INDEX(INDIRECT("'"&$D13&"'!A:g"),$E13,COLUMN()-7) -> 收到新疆蒙鑫水泥有限公司奇台分公司货款 | J13: =INDEX(INDIRECT("'"&$D13&"'!A:g"),$E13,COLUMN()-7) -> 营业回款 | K13: =INDEX(INDIRECT("'"&$D13&"'!A:g"),$E13,COLUMN()-7) -> 2470 | L13: =INDEX(INDIRECT("'"&$D13&"'!A:g"),$E13,COLUMN()-7) -> 0 | M13: =INDEX(INDIRECT("'"&$D13&"'!A:g"),$E13,COLUMN()-7) -> 58393.48 | N13: =INDEX(INDIRECT("'"&$D13&"'!A:g"),$E13,COLUMN()-7) -> 0
A14: =档案!A14 -> 13 | B14: =COUNTA(INDIRECT("'"&A14&"'!a:a")) -> 8 | D14: =IF(E13>=VLOOKUP(D13,A:B,2,FALSE),D13+1,D13) -> 1 | E14: =IF(E13>=VLOOKUP(D13,A:B,2,FALSE),3,E13+1) -> 15 | F14: =VLOOKUP(D14,档案!A:C,3,FALSE) -> 武汉开明 | G14: =VLOOKUP(D14,档案!A:B,2,FALSE) -> 华夏银行汉正街支行186346 | H14: =INDEX(INDIRECT("'"&$D14&"'!A:g"),$E14,COLUMN()-7) -> 45683 | I14: =INDEX(INDIRECT("'"&$D14&"'!A:g"),$E14,COLUMN()-7) -> 收到山东申丰水泥集团有限公司货款 | J14: =INDEX(INDIRECT("'"&$D14&"'!A:g"),$E14,COLUMN()-7) -> 营业回款 | K14: =INDEX(INDIRECT("'"&$D14&"'!A:g"),$E14,COLUMN()-7) -> 126.59 | L14: =INDEX(INDIRECT("'"&$D14&"'!A:g"),$E14,COLUMN()-7) -> 0 | M14: =INDEX(INDIRECT("'"&$D14&"'!A:g"),$E14,COLUMN()-7) -> 58520.07 | N14: =INDEX(INDIRECT("'"&$D14&"'!A:g"),$E14,COLUMN()-7) -> 0
... A43: =档案!A43 -> 42 | B43: =COUNTA(INDIRECT("'"&A43&"'!a:a")) -> 13 | D43: =IF(E42>=VLOOKUP(D42,A:B,2,FALSE),D42+1,D42) -> 1 | E43: =IF(E42>=VLOOKUP(D42,A:B,2,FALSE),3,E42+1) -> 44 | F43: =VLOOKUP(D43,档案!A:C,3,FALSE) -> 武汉开明 | G43: =VLOOKUP(D43,档案!A:B,2,FALSE) -> 华夏银行汉正街支行186346 | H43: =INDEX(INDIRECT("'"&$D43&"'!A:g"),$E43,COLUMN()-7) -> 45770 | I43: =INDEX(INDIRECT("'"&$D43&"'!A:g"),$E43,COLUMN()-7) -> 收到无为华塑矿业有限公司修理费 | J43: =INDEX(INDIRECT("'"&$D43&"'!A:g"),$E43,COLUMN()-7) -> 营业回款 | K43: =INDEX(INDIRECT("'"&$D43&"'!A:g"),$E43,COLUMN()-7) -> 8000 | L43: =INDEX(INDIRECT("'"&$D43&"'!A:g"),$E43,COLUMN()-7) -> 0 | M43: =INDEX(INDIRECT("'"&$D43&"'!A:g"),$E43,COLUMN()-7) -> 60542.29 | N43: =INDEX(INDIRECT("'"&$D43&"'!A:g"),$E43,COLUMN()-7) -> 0
A44: =档案!A44 -> 43 | B44: =COUNTA(INDIRECT("'"&A44&"'!a:a")) -> 3 | D44: =IF(E43>=VLOOKUP(D43,A:B,2,FALSE),D43+1,D43) -> 1 | E44: =IF(E43>=VLOOKUP(D43,A:B,2,FALSE),3,E43+1) -> 45 | F44: =VLOOKUP(D44,档案!A:C,3,FALSE) -> 武汉开明 | G44: =VLOOKUP(D44,档案!A:B,2,FALSE) -> 华夏银行汉正街支行186346 | H44: =INDEX(INDIRECT("'"&$D44&"'!A:g"),$E44,COLUMN()-7) -> 45771 | I44: =INDEX(INDIRECT("'"&$D44&"'!A:g"),$E44,COLUMN()-7) -> 收到嘉峪关祁连山水泥有限公司货款 | J44: =INDEX(INDIRECT("'"&$D44&"'!A:g"),$E44,COLUMN()-7) -> 营业回款 | K44: =INDEX(INDIRECT("'"&$D44&"'!A:g"),$E44,COLUMN()-7) -> 34800 | L44: =INDEX(INDIRECT("'"&$D44&"'!A:g"),$E44,COLUMN()-7) -> 0 | M44: =INDEX(INDIRECT("'"&$D44&"'!A:g"),$E44,COLUMN()-7) -> 95342.29 | N44: =INDEX(INDIRECT("'"&$D44&"'!A:g"),$E44,COLUMN()-7) -> 0 | Q44: 是
A45: =档案!A45 -> 44 | B45: =COUNTA(INDIRECT("'"&A45&"'!a:a")) -> 180 | D45: =IF(E44>=VLOOKUP(D44,A:B,2,FALSE),D44+1,D44) -> 1 | E45: =IF(E44>=VLOOKUP(D44,A:B,2,FALSE),3,E44+1) -> 46 | F45: =VLOOKUP(D45,档案!A:C,3,FALSE) -> 武汉开明 | G45: =VLOOKUP(D45,档案!A:B,2,FALSE) -> 华夏银行汉正街支行186346 | H45: =INDEX(INDIRECT("'"&$D45&"'!A:g"),$E45,COLUMN()-7) -> 45771 | I45: =INDEX(INDIRECT("'"&$D45&"'!A:g"),$E45,COLUMN()-7) -> 手续费 | J45: =INDEX(INDIRECT("'"&$D45&"'!A:g"),$E45,COLUMN()-7) -> 付日常费用 | K45: =INDEX(INDIRECT("'"&$D45&"'!A:g"),$E45,COLUMN()-7) -> 0 | L45: =INDEX(INDIRECT("'"&$D45&"'!A:g"),$E45,COLUMN()-7) -> 4.5 | M45: =INDEX(INDIRECT("'"&$D45&"'!A:g"),$E45,COLUMN()-7) -> 95337.79 | N45: =INDEX(INDIRECT("'"&$D45&"'!A:g"),$E45,COLUMN()-7) -> 0
A46: =档案!A46 -> 45 | B46: =COUNTA(INDIRECT("'"&A46&"'!a:a")) -> 16 | D46: =IF(E45>=VLOOKUP(D45,A:B,2,FALSE),D45+1,D45) -> 1 | E46: =IF(E45>=VLOOKUP(D45,A:B,2,FALSE),3,E45+1) -> 47 | F46: =VLOOKUP(D46,档案!A:C,3,FALSE) -> 武汉开明 | G46: =VLOOKUP(D46,档案!A:B,2,FALSE) -> 华夏银行汉正街支行186346 | H46: =INDEX(INDIRECT("'"&$D46&"'!A:g"),$E46,COLUMN()-7) -> 45771 | I46: =INDEX(INDIRECT("'"&$D46&"'!A:g"),$E46,COLUMN()-7) -> 收到四川省星船城水泥股份有限公司维修款 | J46: =INDEX(INDIRECT("'"&$D46&"'!A:g"),$E46,COLUMN()-7) -> 营业回款 | K46: =INDEX(INDIRECT("'"&$D46&"'!A:g"),$E46,COLUMN()-7) -> 35820 | L46: =INDEX(INDIRECT("'"&$D46&"'!A:g"),$E46,COLUMN()-7) -> 0 | M46: =INDEX(INDIRECT("'"&$D46&"'!A:g"),$E46,COLUMN()-7) -> 131157.79 | N46: =INDEX(INDIRECT("'"&$D46&"'!A:g"),$E46,COLUMN()-7) -> 0
A47: =档案!A47 -> 46 | B47: =COUNTA(INDIRECT("'"&A47&"'!a:a")) -> 23 | D47: =IF(E46>=VLOOKUP(D46,A:B,2,FALSE),D46+1,D46) -> 1 | E47: =IF(E46>=VLOOKUP(D46,A:B,2,FALSE),3,E46+1) -> 48 | F47: =VLOOKUP(D47,档案!A:C,3,FALSE) -> 武汉开明 | G47: =VLOOKUP(D47,档案!A:B,2,FALSE) -> 华夏银行汉正街支行186346 | H47: =INDEX(INDIRECT("'"&$D47&"'!A:g"),$E47,COLUMN()-7) -> 45771 | I47: =INDEX(INDIRECT("'"&$D47&"'!A:g"),$E47,COLUMN()-7) -> 收到宜良红狮水泥有限公司货款 | J47: =INDEX(INDIRECT("'"&$D47&"'!A:g"),$E47,COLUMN()-7) -> 营业回款 | K47: =INDEX(INDIRECT("'"&$D47&"'!A:g"),$E47,COLUMN()-7) -> 50000 | L47: =INDEX(INDIRECT("'"&$D47&"'!A:g"),$E47,COLUMN()-7) -> 0 | M47: =INDEX(INDIRECT("'"&$D47&"'!A:g"),$E47,COLUMN()-7) -> 181157.79 | N47: =INDEX(INDIRECT("'"&$D47&"'!A:g"),$E47,COLUMN()-7) -> 0
A48: =档案!A48 -> 47 | B48: =COUNTA(INDIRECT("'"&A48&"'!a:a")) -> 22 | D48: =IF(E47>=VLOOKUP(D47,A:B,2,FALSE),D47+1,D47) -> 1 | E48: =IF(E47>=VLOOKUP(D47,A:B,2,FALSE),3,E47+1) -> 49 | F48: =VLOOKUP(D48,档案!A:C,3,FALSE) -> 武汉开明 | G48: =VLOOKUP(D48,档案!A:B,2,FALSE) -> 华夏银行汉正街支行186346 | H48: =INDEX(INDIRECT("'"&$D48&"'!A:g"),$E48,COLUMN()-7) -> 45771 | I48: =INDEX(INDIRECT("'"&$D48&"'!A:g"),$E48,COLUMN()-7) -> 转武汉农商行 | J48: =INDEX(INDIRECT("'"&$D48&"'!A:g"),$E48,COLUMN()-7) -> 转出他行或提现 | K48: =INDEX(INDIRECT("'"&$D48&"'!A:g"),$E48,COLUMN()-7) -> 0 | L48: =INDEX(INDIRECT("'"&$D48&"'!A:g"),$E48,COLUMN()-7) -> 140000 | M48: =INDEX(INDIRECT("'"&$D48&"'!A:g"),$E48,COLUMN()-7) -> 41157.79 | N48: =INDEX(INDIRECT("'"&$D48&"'!A:g"),$E48,COLUMN()-7) -> 0
A49: =档案!A49 -> 48 | B49: =COUNTA(INDIRECT("'"&A49&"'!a:a")) -> 12 | D49: =IF(E48>=VLOOKUP(D48,A:B,2,FALSE),D48+1,D48) -> 1 | E49: =IF(E48>=VLOOKUP(D48,A:B,2,FALSE),3,E48+1) -> 50 | F49: =VLOOKUP(D49,档案!A:C,3,FALSE) -> 武汉开明 | G49: =VLOOKUP(D49,档案!A:B,2,FALSE) -> 华夏银行汉正街支行186346 | H49: =INDEX(INDIRECT("'"&$D49&"'!A:g"),$E49,COLUMN()-7) -> 45772 | I49: =INDEX(INDIRECT("'"&$D49&"'!A:g"),$E49,COLUMN()-7) -> 转武汉农商行 | J49: =INDEX(INDIRECT("'"&$D49&"'!A:g"),$E49,COLUMN()-7) -> 转出他行或提现 | K49: =INDEX(INDIRECT("'"&$D49&"'!A:g"),$E49,COLUMN()-7) -> 0 | L49: =INDEX(INDIRECT("'"&$D49&"'!A:g"),$E49,COLUMN()-7) -> 40000 | M49: =INDEX(INDIRECT("'"&$D49&"'!A:g"),$E49,COLUMN()-7) -> 1157.79 | N49: =INDEX(INDIRECT("'"&$D49&"'!A:g"),$E49,COLUMN()-7) -> 0
A50: =档案!#REF! -> #REF! | B50: =COUNTA(INDIRECT("'"&A50&"'!a:a")) -> 1 | D50: =IF(E49>=VLOOKUP(D49,A:B,2,FALSE),D49+1,D49) -> 1 | E50: =IF(E49>=VLOOKUP(D49,A:B,2,FALSE),3,E49+1) -> 51 | F50: =VLOOKUP(D50,档案!A:C,3,FALSE) -> 武汉开明 | G50: =VLOOKUP(D50,档案!A:B,2,FALSE) -> 华夏银行汉正街支行186346 | H50: =INDEX(INDIRECT("'"&$D50&"'!A:g"),$E50,COLUMN()-7) -> 45771 | I50: =INDEX(INDIRECT("'"&$D50&"'!A:g"),$E50,COLUMN()-7) -> 手续费 | J50: =INDEX(INDIRECT("'"&$D50&"'!A:g"),$E50,COLUMN()-7) -> 付日常费用 | K50: =INDEX(INDIRECT("'"&$D50&"'!A:g"),$E50,COLUMN()-7) -> 0 | L50: =INDEX(INDIRECT("'"&$D50&"'!A:g"),$E50,COLUMN()-7) -> 3 | M50: =INDEX(INDIRECT("'"&$D50&"'!A:g"),$E50,COLUMN()-7) -> 1154.79 | N50: =INDEX(INDIRECT("'"&$D50&"'!A:g"),$E50,COLUMN()-7) -> 0
A51: =档案!A50 -> 50 | B51: =COUNTA(INDIRECT("'"&A51&"'!a:a")) -> 6 | D51: =IF(E50>=VLOOKUP(D50,A:B,2,FALSE),D50+1,D50) -> 1 | E51: =IF(E50>=VLOOKUP(D50,A:B,2,FALSE),3,E50+1) -> 52 | F51: =VLOOKUP(D51,档案!A:C,3,FALSE) -> 武汉开明 | G51: =VLOOKUP(D51,档案!A:B,2,FALSE) -> 华夏银行汉正街支行186346 | H51: =INDEX(INDIRECT("'"&$D51&"'!A:g"),$E51,COLUMN()-7) -> 45797 | I51: =INDEX(INDIRECT("'"&$D51&"'!A:g"),$E51,COLUMN()-7) -> 收到山东申丰水泥集团有限公司货款 | J51: =INDEX(INDIRECT("'"&$D51&"'!A:g"),$E51,COLUMN()-7) -> 营业回款 | K51: =INDEX(INDIRECT("'"&$D51&"'!A:g"),$E51,COLUMN()-7) -> 49.56 | L51: =INDEX(INDIRECT("'"&$D51&"'!A:g"),$E51,COLUMN()-7) -> 0 | M51: =INDEX(INDIRECT("'"&$D51&"'!A:g"),$E51,COLUMN()-7) -> 1204.35 | N51: =INDEX(INDIRECT("'"&$D51&"'!A:g"),$E51,COLUMN()-7) -> 0
A52: =档案!A51 -> 51 | B52: =COUNTA(INDIRECT("'"&A52&"'!a:a")) -> 13 | D52: =IF(E51>=VLOOKUP(D51,A:B,2,FALSE),D51+1,D51) -> 1 | E52: =IF(E51>=VLOOKUP(D51,A:B,2,FALSE),3,E51+1) -> 53 | F52: =VLOOKUP(D52,档案!A:C,3,FALSE) -> 武汉开明 | G52: =VLOOKUP(D52,档案!A:B,2,FALSE) -> 华夏银行汉正街支行186346 | H52: =INDEX(INDIRECT("'"&$D52&"'!A:g"),$E52,COLUMN()-7) -> 45804 | I52: =INDEX(INDIRECT("'"&$D52&"'!A:g"),$E52,COLUMN()-7) -> 收到库尔勒天山水泥有限责任公司修理费 | J52: =INDEX(INDIRECT("'"&$D52&"'!A:g"),$E52,COLUMN()-7) -> 营业回款 | K52: =INDEX(INDIRECT("'"&$D52&"'!A:g"),$E52,COLUMN()-7) -> 2650 | L52: =INDEX(INDIRECT("'"&$D52&"'!A:g"),$E52,COLUMN()-7) -> 0 | M52: =INDEX(INDIRECT("'"&$D52&"'!A:g"),$E52,COLUMN()-7) -> 3854.35 | N52: =INDEX(INDIRECT("'"&$D52&"'!A:g"),$E52,COLUMN()-7) -> 0
A53: =档案!A52 -> 52 | B53: =COUNTA(INDIRECT("'"&A53&"'!a:a")) -> 3 | D53: =IF(E52>=VLOOKUP(D52,A:B,2,FALSE),D52+1,D52) -> 1 | E53: =IF(E52>=VLOOKUP(D52,A:B,2,FALSE),3,E52+1) -> 54 | F53: =VLOOKUP(D53,档案!A:C,3,FALSE) -> 武汉开明 | G53: =VLOOKUP(D53,档案!A:B,2,FALSE) -> 华夏银行汉正街支行186346 | H53: =INDEX(INDIRECT("'"&$D53&"'!A:g"),$E53,COLUMN()-7) -> 45804 | I53: =INDEX(INDIRECT("'"&$D53&"'!A:g"),$E53,COLUMN()-7) -> 收到库尔勒天山水泥有限责任公司退保证金 | J53: =INDEX(INDIRECT("'"&$D53&"'!A:g"),$E53,COLUMN()-7) -> 营业回款 | K53: =INDEX(INDIRECT("'"&$D53&"'!A:g"),$E53,COLUMN()-7) -> 1500 | L53: =INDEX(INDIRECT("'"&$D53&"'!A:g"),$E53,COLUMN()-7) -> 0 | M53: =INDEX(INDIRECT("'"&$D53&"'!A:g"),$E53,COLUMN()-7) -> 5354.35 | N53: =INDEX(INDIRECT("'"&$D53&"'!A:g"),$E53,COLUMN()-7) -> 0
A54: =档案!A53 -> 53 | B54: =COUNTA(INDIRECT("'"&A54&"'!a:a")) -> 192 | D54: =IF(E53>=VLOOKUP(D53,A:B,2,FALSE),D53+1,D53) -> 1 | E54: =IF(E53>=VLOOKUP(D53,A:B,2,FALSE),3,E53+1) -> 55 | F54: =VLOOKUP(D54,档案!A:C,3,FALSE) -> 武汉开明 | G54: =VLOOKUP(D54,档案!A:B,2,FALSE) -> 华夏银行汉正街支行186346 | H54: =INDEX(INDIRECT("'"&$D54&"'!A:g"),$E54,COLUMN()-7) -> 45804 | I54: =INDEX(INDIRECT("'"&$D54&"'!A:g"),$E54,COLUMN()-7) -> 收到库尔勒天山水泥有限责任公司退保证金 | J54: =INDEX(INDIRECT("'"&$D54&"'!A:g"),$E54,COLUMN()-7) -> 营业回款 | K54: =INDEX(INDIRECT("'"&$D54&"'!A:g"),$E54,COLUMN()-7) -> 4000 | L54: =INDEX(INDIRECT("'"&$D54&"'!A:g"),$E54,COLUMN()-7) -> 0 | M54: =INDEX(INDIRECT("'"&$D54&"'!A:g"),$E54,COLUMN()-7) -> 9354.35 | N54: =INDEX(INDIRECT("'"&$D54&"'!A:g"),$E54,COLUMN()-7) -> 0
A55: =档案!A54 -> 0 | B55: =COUNTA(INDIRECT("'"&A55&"'!a:a")) -> 1 | D55: =IF(E54>=VLOOKUP(D54,A:B,2,FALSE),D54+1,D54) -> 1 | E55: =IF(E54>=VLOOKUP(D54,A:B,2,FALSE),3,E54+1) -> 56 | F55: =VLOOKUP(D55,档案!A:C,3,FALSE) -> 武汉开明 | G55: =VLOOKUP(D55,档案!A:B,2,FALSE) -> 华夏银行汉正街支行186346 | H55: =INDEX(INDIRECT("'"&$D55&"'!A:g"),$E55,COLUMN()-7) -> 45804 | I55: =INDEX(INDIRECT("'"&$D55&"'!A:g"),$E55,COLUMN()-7) -> 收到库尔勒天山水泥有限责任公司修理费 | J55: =INDEX(INDIRECT("'"&$D55&"'!A:g"),$E55,COLUMN()-7) -> 营业回款 | K55: =INDEX(INDIRECT("'"&$D55&"'!A:g"),$E55,COLUMN()-7) -> 30000 | L55: =INDEX(INDIRECT("'"&$D55&"'!A:g"),$E55,COLUMN()-7) -> 0 | M55: =INDEX(INDIRECT("'"&$D55&"'!A:g"),$E55,COLUMN()-7) -> 39354.35 | N55: =INDEX(INDIRECT("'"&$D55&"'!A:g"),$E55,COLUMN()-7) -> 0
A56: =档案!A55 -> 0 | B56: =COUNTA(INDIRECT("'"&A56&"'!a:a")) -> 1 | D56: =IF(E55>=VLOOKUP(D55,A:B,2,FALSE),D55+1,D55) -> 1 | E56: =IF(E55>=VLOOKUP(D55,A:B,2,FALSE),3,E55+1) -> 57 | F56: =VLOOKUP(D56,档案!A:C,3,FALSE) -> 武汉开明 | G56: =VLOOKUP(D56,档案!A:B,2,FALSE) -> 华夏银行汉正街支行186346 | H56: =INDEX(INDIRECT("'"&$D56&"'!A:g"),$E56,COLUMN()-7) -> 45805 | I56: =INDEX(INDIRECT("'"&$D56&"'!A:g"),$E56,COLUMN()-7) -> 收到湖北双环科技股份有限公司质保金 | J56: =INDEX(INDIRECT("'"&$D56&"'!A:g"),$E56,COLUMN()-7) -> 营业回款 | K56: =INDEX(INDIRECT("'"&$D56&"'!A:g"),$E56,COLUMN()-7) -> 244 | L56: =INDEX(INDIRECT("'"&$D56&"'!A:g"),$E56,COLUMN()-7) -> 0 | M56: =INDEX(INDIRECT("'"&$D56&"'!A:g"),$E56,COLUMN()-7) -> 39598.35 | N56: =INDEX(INDIRECT("'"&$D56&"'!A:g"),$E56,COLUMN()-7) -> 0
A57: =档案!A56 -> 0 | B57: =COUNTA(INDIRECT("'"&A57&"'!a:a")) -> 1 | D57: =IF(E56>=VLOOKUP(D56,A:B,2,FALSE),D56+1,D56) -> 1 | E57: =IF(E56>=VLOOKUP(D56,A:B,2,FALSE),3,E56+1) -> 58 | F57: =VLOOKUP(D57,档案!A:C,3,FALSE) -> 武汉开明 | G57: =VLOOKUP(D57,档案!A:B,2,FALSE) -> 华夏银行汉正街支行186346 | H57: =INDEX(INDIRECT("'"&$D57&"'!A:g"),$E57,COLUMN()-7) -> 45806 | I57: =INDEX(INDIRECT("'"&$D57&"'!A:g"),$E57,COLUMN()-7) -> 收到宜良红狮水泥有限公司货款 | J57: =INDEX(INDIRECT("'"&$D57&"'!A:g"),$E57,COLUMN()-7) -> 营业回款 | K57: =INDEX(INDIRECT("'"&$D57&"'!A:g"),$E57,COLUMN()-7) -> 22478.75 | L57: =INDEX(INDIRECT("'"&$D57&"'!A:g"),$E57,COLUMN()-7) -> 0 | M57: =INDEX(INDIRECT("'"&$D57&"'!A:g"),$E57,COLUMN()-7) -> 62077.1 | N57: =INDEX(INDIRECT("'"&$D57&"'!A:g"),$E57,COLUMN()-7) -> 0
A58: =档案!A57 -> 0 | B58: =COUNTA(INDIRECT("'"&A58&"'!a:a")) -> 1 | D58: =IF(E57>=VLOOKUP(D57,A:B,2,FALSE),D57+1,D57) -> 1 | E58: =IF(E57>=VLOOKUP(D57,A:B,2,FALSE),3,E57+1) -> 59 | F58: =VLOOKUP(D58,档案!A:C,3,FALSE) -> 武汉开明 | G58: =VLOOKUP(D58,档案!A:B,2,FALSE) -> 华夏银行汉正街支行186346 | H58: =INDEX(INDIRECT("'"&$D58&"'!A:g"),$E58,COLUMN()-7) -> 45807 | I58: =INDEX(INDIRECT("'"&$D58&"'!A:g"),$E58,COLUMN()-7) -> 转湖北邮政 | J58: =INDEX(INDIRECT("'"&$D58&"'!A:g"),$E58,COLUMN()-7) -> 转出他行或提现 | K58: =INDEX(INDIRECT("'"&$D58&"'!A:g"),$E58,COLUMN()-7) -> 0 | L58: =INDEX(INDIRECT("'"&$D58&"'!A:g"),$E58,COLUMN()-7) -> 59000 | M58: =INDEX(INDIRECT("'"&$D58&"'!A:g"),$E58,COLUMN()-7) -> 3077.1 | N58: =INDEX(INDIRECT("'"&$D58&"'!A:g"),$E58,COLUMN()-7) -> 0
A59: =档案!A58 -> 0 | B59: =COUNTA(INDIRECT("'"&A59&"'!a:a")) -> 1 | D59: =IF(E58>=VLOOKUP(D58,A:B,2,FALSE),D58+1,D58) -> 1 | E59: =IF(E58>=VLOOKUP(D58,A:B,2,FALSE),3,E58+1) -> 60 | F59: =VLOOKUP(D59,档案!A:C,3,FALSE) -> 武汉开明 | G59: =VLOOKUP(D59,档案!A:B,2,FALSE) -> 华夏银行汉正街支行186346 | H59: =INDEX(INDIRECT("'"&$D59&"'!A:g"),$E59,COLUMN()-7) -> 45807 | I59: =INDEX(INDIRECT("'"&$D59&"'!A:g"),$E59,COLUMN()-7) -> 手续费 | J59: =INDEX(INDIRECT("'"&$D59&"'!A:g"),$E59,COLUMN()-7) -> 付日常费用 | K59: =INDEX(INDIRECT("'"&$D59&"'!A:g"),$E59,COLUMN()-7) -> 0 | L59: =INDEX(INDIRECT("'"&$D59&"'!A:g"),$E59,COLUMN()-7) -> 3 | M59: =INDEX(INDIRECT("'"&$D59&"'!A:g"),$E59,COLUMN()-7) -> 3074.1 | N59: =INDEX(INDIRECT("'"&$D59&"'!A:g"),$E59,COLUMN()-7) -> 0
A60: =档案!A59 -> 0 | B60: =COUNTA(INDIRECT("'"&A60&"'!a:a")) -> 1 | D60: =IF(E59>=VLOOKUP(D59,A:B,2,FALSE),D59+1,D59) -> 1 | E60: =IF(E59>=VLOOKUP(D59,A:B,2,FALSE),3,E59+1) -> 61 | F60: =VLOOKUP(D60,档案!A:C,3,FALSE) -> 武汉开明 | G60: =VLOOKUP(D60,档案!A:B,2,FALSE) -> 华夏银行汉正街支行186346 | H60: =INDEX(INDIRECT("'"&$D60&"'!A:g"),$E60,COLUMN()-7) -> 45807 | I60: =INDEX(INDIRECT("'"&$D60&"'!A:g"),$E60,COLUMN()-7) -> 手续费 | J60: =INDEX(INDIRECT("'"&$D60&"'!A:g"),$E60,COLUMN()-7) -> 付日常费用 | K60: =INDEX(INDIRECT("'"&$D60&"'!A:g"),$E60,COLUMN()-7) -> 0 | L60: =INDEX(INDIRECT("'"&$D60&"'!A:g"),$E60,COLUMN()-7) -> 1.5 | M60: =INDEX(INDIRECT("'"&$D60&"'!A:g"),$E60,COLUMN()-7) -> 3072.6 | N60: =INDEX(INDIRECT("'"&$D60&"'!A:g"),$E60,COLUMN()-7) -> 0
A61: =档案!A60 -> 0 | B61: =COUNTA(INDIRECT("'"&A61&"'!a:a")) -> 1 | D61: =IF(E60>=VLOOKUP(D60,A:B,2,FALSE),D60+1,D60) -> 1 | E61: =IF(E60>=VLOOKUP(D60,A:B,2,FALSE),3,E60+1) -> 62 | F61: =VLOOKUP(D61,档案!A:C,3,FALSE) -> 武汉开明 | G61: =VLOOKUP(D61,档案!A:B,2,FALSE) -> 华夏银行汉正街支行186346 | H61: =INDEX(INDIRECT("'"&$D61&"'!A:g"),$E61,COLUMN()-7) -> 45807 | I61: =INDEX(INDIRECT("'"&$D61&"'!A:g"),$E61,COLUMN()-7) -> 生产部李权智用款莱芜钢铁托轮轴承采购费付山东万古轴承有限公司（付现金）--公司 | J61: =INDEX(INDIRECT("'"&$D61&"'!A:g"),$E61,COLUMN()-7) -> 项目成本 | K61: =INDEX(INDIRECT("'"&$D61&"'!A:g"),$E61,COLUMN()-7) -> 0 | L61: =INDEX(INDIRECT("'"&$D61&"'!A:g"),$E61,COLUMN()-7) -> 2089.75 | M61: =INDEX(INDIRECT("'"&$D61&"'!A:g"),$E61,COLUMN()-7) -> 982.85 | N61: =INDEX(INDIRECT("'"&$D61&"'!A:g"),$E61,COLUMN()-7) -> 0
A62: =档案!A61 -> 0 | B62: =COUNTA(INDIRECT("'"&A62&"'!a:a")) -> 1 | D62: =IF(E61>=VLOOKUP(D61,A:B,2,FALSE),D61+1,D61) -> 1 | E62: =IF(E61>=VLOOKUP(D61,A:B,2,FALSE),3,E61+1) -> 63 | F62: =VLOOKUP(D62,档案!A:C,3,FALSE) -> 武汉开明 | G62: =VLOOKUP(D62,档案!A:B,2,FALSE) -> 华夏银行汉正街支行186346 | H62: =INDEX(INDIRECT("'"&$D62&"'!A:g"),$E62,COLUMN()-7) -> 45811 | I62: =INDEX(INDIRECT("'"&$D62&"'!A:g"),$E62,COLUMN()-7) -> 收到微众银行小微贷款放款户转来贷款 | J62: =INDEX(INDIRECT("'"&$D62&"'!A:g"),$E62,COLUMN()-7) -> 借款到账 | K62: =INDEX(INDIRECT("'"&$D62&"'!A:g"),$E62,COLUMN()-7) -> 1000000 | L62: =INDEX(INDIRECT("'"&$D62&"'!A:g"),$E62,COLUMN()-7) -> 0 | M62: =INDEX(INDIRECT("'"&$D62&"'!A:g"),$E62,COLUMN()-7) -> 1000982.8 | N62: =INDEX(INDIRECT("'"&$D62&"'!A:g"),$E62,COLUMN()-7) -> 0
... A3507: =档案!A3506 -> 0 | B3507: =COUNTA(INDIRECT("'"&A3507&"'!a:a")) -> 1 | D3507: =IF(E3506>=VLOOKUP(D3506,A:B,2,FALSE),D3506+1,D3506) -> 9 | E3507: =IF(E3506>=VLOOKUP(D3506,A:B,2,FALSE),3,E3506+1) -> 2168 | F3507: =VLOOKUP(D3507,档案!A:C,3,FALSE) -> 武汉开明 | G3507: =VLOOKUP(D3507,档案!A:B,2,FALSE) -> 农商行豹澥支行310028 | H3507: =INDEX(INDIRECT("'"&$D3507&"'!A:g"),$E3507,COLUMN()-7) -> 45939 | I3507: =INDEX(INDIRECT("'"&$D3507&"'!A:g"),$E3507,COLUMN()-7) -> ETC扣款 | J3507: =INDEX(INDIRECT("'"&$D3507&"'!A:g"),$E3507,COLUMN()-7) -> 项目成本 | K3507: =INDEX(INDIRECT("'"&$D3507&"'!A:g"),$E3507,COLUMN()-7) -> 0 | L3507: =INDEX(INDIRECT("'"&$D3507&"'!A:g"),$E3507,COLUMN()-7) -> 65.55 | M3507: =INDEX(INDIRECT("'"&$D3507&"'!A:g"),$E3507,COLUMN()-7) -> 11650.86 | N3507: =INDEX(INDIRECT("'"&$D3507&"'!A:g"),$E3507,COLUMN()-7) -> 0
A3508: =档案!A3507 -> 0 | B3508: =COUNTA(INDIRECT("'"&A3508&"'!a:a")) -> 1 | D3508: =IF(E3507>=VLOOKUP(D3507,A:B,2,FALSE),D3507+1,D3507) -> 9 | E3508: =IF(E3507>=VLOOKUP(D3507,A:B,2,FALSE),3,E3507+1) -> 2169 | F3508: =VLOOKUP(D3508,档案!A:C,3,FALSE) -> 武汉开明 | G3508: =VLOOKUP(D3508,档案!A:B,2,FALSE) -> 农商行豹澥支行310028 | H3508: =INDEX(INDIRECT("'"&$D3508&"'!A:g"),$E3508,COLUMN()-7) -> 45939 | I3508: =INDEX(INDIRECT("'"&$D3508&"'!A:g"),$E3508,COLUMN()-7) -> ETC扣款 | J3508: =INDEX(INDIRECT("'"&$D3508&"'!A:g"),$E3508,COLUMN()-7) -> 项目成本 | K3508: =INDEX(INDIRECT("'"&$D3508&"'!A:g"),$E3508,COLUMN()-7) -> 0 | L3508: =INDEX(INDIRECT("'"&$D3508&"'!A:g"),$E3508,COLUMN()-7) -> 9.5 | M3508: =INDEX(INDIRECT("'"&$D3508&"'!A:g"),$E3508,COLUMN()-7) -> 11641.36
A3509: =档案!A3508 -> 0 | B3509: =COUNTA(INDIRECT("'"&A3509&"'!a:a")) -> 1 | D3509: =IF(E3508>=VLOOKUP(D3508,A:B,2,FALSE),D3508+1,D3508) -> 9 | E3509: =IF(E3508>=VLOOKUP(D3508,A:B,2,FALSE),3,E3508+1) -> 2170 | F3509: =VLOOKUP(D3509,档案!A:C,3,FALSE) -> 武汉开明 | G3509: =VLOOKUP(D3509,档案!A:B,2,FALSE) -> 农商行豹澥支行310028 | H3509: =INDEX(INDIRECT("'"&$D3509&"'!A:g"),$E3509,COLUMN()-7) -> 45940 | I3509: =INDEX(INDIRECT("'"&$D3509&"'!A:g"),$E3509,COLUMN()-7) -> ETC扣款 | J3509: =INDEX(INDIRECT("'"&$D3509&"'!A:g"),$E3509,COLUMN()-7) -> 项目成本 | K3509: =INDEX(INDIRECT("'"&$D3509&"'!A:g"),$E3509,COLUMN()-7) -> 0 | L3509: =INDEX(INDIRECT("'"&$D3509&"'!A:g"),$E3509,COLUMN()-7) -> 59.85 | M3509: =INDEX(INDIRECT("'"&$D3509&"'!A:g"),$E3509,COLUMN()-7) -> 11581.51 | N3509: =INDEX(INDIRECT("'"&$D3509&"'!A:g"),$E3509,COLUMN()-7) -> 0
A3510: =档案!A3509 -> 0 | B3510: =COUNTA(INDIRECT("'"&A3510&"'!a:a")) -> 1 | D3510: =IF(E3509>=VLOOKUP(D3509,A:B,2,FALSE),D3509+1,D3509) -> 9 | E3510: =IF(E3509>=VLOOKUP(D3509,A:B,2,FALSE),3,E3509+1) -> 2171 | F3510: =VLOOKUP(D3510,档案!A:C,3,FALSE) -> 武汉开明 | G3510: =VLOOKUP(D3510,档案!A:B,2,FALSE) -> 农商行豹澥支行310028 | H3510: =INDEX(INDIRECT("'"&$D3510&"'!A:g"),$E3510,COLUMN()-7) -> 45940 | I3510: =INDEX(INDIRECT("'"&$D3510&"'!A:g"),$E3510,COLUMN()-7) -> 收到武汉国兰商贸有限公司贴现款（原票金额139630，手续费1210，实收138420） | J3510: =INDEX(INDIRECT("'"&$D3510&"'!A:g"),$E3510,COLUMN()-7) -> 他行转入或存现 | K3510: =INDEX(INDIRECT("'"&$D3510&"'!A:g"),$E3510,COLUMN()-7) -> 138420 | L3510: =INDEX(INDIRECT("'"&$D3510&"'!A:g"),$E3510,COLUMN()-7) -> 0 | M3510: =INDEX(INDIRECT("'"&$D3510&"'!A:g"),$E3510,COLUMN()-7) -> 150001.51 | N3510: =INDEX(INDIRECT("'"&$D3510&"'!A:g"),$E3510,COLUMN()-7) -> 0
A3511: =档案!A3510 -> 0 | B3511: =COUNTA(INDIRECT("'"&A3511&"'!a:a")) -> 1 | D3511: =IF(E3510>=VLOOKUP(D3510,A:B,2,FALSE),D3510+1,D3510) -> 9 | E3511: =IF(E3510>=VLOOKUP(D3510,A:B,2,FALSE),3,E3510+1) -> 2172 | F3511: =VLOOKUP(D3511,档案!A:C,3,FALSE) -> 武汉开明 | G3511: =VLOOKUP(D3511,档案!A:B,2,FALSE) -> 农商行豹澥支行310028 | H3511: =INDEX(INDIRECT("'"&$D3511&"'!A:g"),$E3511,COLUMN()-7) -> 45940 | I3511: =INDEX(INDIRECT("'"&$D3511&"'!A:g"),$E3511,COLUMN()-7) -> 生产部张月用款新洋丰外协人员工资(总金额60320.6元，10.10号支付59334元）付堵志波--个人 | J3511: =INDEX(INDIRECT("'"&$D3511&"'!A:g"),$E3511,COLUMN()-7) -> 项目成本 | K3511: =INDEX(INDIRECT("'"&$D3511&"'!A:g"),$E3511,COLUMN()-7) -> 0 | L3511: =INDEX(INDIRECT("'"&$D3511&"'!A:g"),$E3511,COLUMN()-7) -> 59334 | M3511: =INDEX(INDIRECT("'"&$D3511&"'!A:g"),$E3511,COLUMN()-7) -> 90667.51 | N3511: =INDEX(INDIRECT("'"&$D3511&"'!A:g"),$E3511,COLUMN()-7) -> 0
A3512: =档案!A3511 -> 0 | B3512: =COUNTA(INDIRECT("'"&A3512&"'!a:a")) -> 1 | D3512: =IF(E3511>=VLOOKUP(D3511,A:B,2,FALSE),D3511+1,D3511) -> 9 | E3512: =IF(E3511>=VLOOKUP(D3511,A:B,2,FALSE),3,E3511+1) -> 2173 | F3512: =VLOOKUP(D3512,档案!A:C,3,FALSE) -> 武汉开明 | G3512: =VLOOKUP(D3512,档案!A:B,2,FALSE) -> 农商行豹澥支行310028 | H3512: =INDEX(INDIRECT("'"&$D3512&"'!A:g"),$E3512,COLUMN()-7) -> 45940 | I3512: =INDEX(INDIRECT("'"&$D3512&"'!A:g"),$E3512,COLUMN()-7) -> 综合部蒋霞用款新疆宜化项目人员17人雇主责任险付中国太平洋财产保险股份有限公司上海分公司 | J3512: =INDEX(INDIRECT("'"&$D3512&"'!A:g"),$E3512,COLUMN()-7) -> 付日常费用 | K3512: =INDEX(INDIRECT("'"&$D3512&"'!A:g"),$E3512,COLUMN()-7) -> 0 | L3512: =INDEX(INDIRECT("'"&$D3512&"'!A:g"),$E3512,COLUMN()-7) -> 4750 | M3512: =INDEX(INDIRECT("'"&$D3512&"'!A:g"),$E3512,COLUMN()-7) -> 85917.51 | N3512: =INDEX(INDIRECT("'"&$D3512&"'!A:g"),$E3512,COLUMN()-7) -> 0
A3513: =档案!A3512 -> 0 | B3513: =COUNTA(INDIRECT("'"&A3513&"'!a:a")) -> 1 | D3513: =IF(E3512>=VLOOKUP(D3512,A:B,2,FALSE),D3512+1,D3512) -> 9 | E3513: =IF(E3512>=VLOOKUP(D3512,A:B,2,FALSE),3,E3512+1) -> 2174 | F3513: =VLOOKUP(D3513,档案!A:C,3,FALSE) -> 武汉开明 | G3513: =VLOOKUP(D3513,档案!A:B,2,FALSE) -> 农商行豹澥支行310028 | H3513: =INDEX(INDIRECT("'"&$D3513&"'!A:g"),$E3513,COLUMN()-7) -> 45940 | I3513: =INDEX(INDIRECT("'"&$D3513&"'!A:g"),$E3513,COLUMN()-7) -> 综合部蒋霞用款鄂A4Z5Y0全险4772.61元(去年是人保，今年继续选择人保则为续保，保费会划算一些)，保险日期：2025.10.12-2026.10.12，另返现400元付中国人民财产保险股份有限公司武汉市新洲支公司 | J3513: =INDEX(INDIRECT("'"&$D3513&"'!A:g"),$E3513,COLUMN()-7) -> 付日常费用 | K3513: =INDEX(INDIRECT("'"&$D3513&"'!A:g"),$E3513,COLUMN()-7) -> 0 | L3513: =INDEX(INDIRECT("'"&$D3513&"'!A:g"),$E3513,COLUMN()-7) -> 4772.61 | M3513: =INDEX(INDIRECT("'"&$D3513&"'!A:g"),$E3513,COLUMN()-7) -> 81144.9 | N3513: =INDEX(INDIRECT("'"&$D3513&"'!A:g"),$E3513,COLUMN()-7) -> 0
A3514: =档案!A3513 -> 0 | B3514: =COUNTA(INDIRECT("'"&A3514&"'!a:a")) -> 1 | D3514: =IF(E3513>=VLOOKUP(D3513,A:B,2,FALSE),D3513+1,D3513) -> 9 | E3514: =IF(E3513>=VLOOKUP(D3513,A:B,2,FALSE),3,E3513+1) -> 2175 | F3514: =VLOOKUP(D3514,档案!A:C,3,FALSE) -> 武汉开明 | G3514: =VLOOKUP(D3514,档案!A:B,2,FALSE) -> 农商行豹澥支行310028 | H3514: =INDEX(INDIRECT("'"&$D3514&"'!A:g"),$E3514,COLUMN()-7) -> 45940 | I3514: =INDEX(INDIRECT("'"&$D3514&"'!A:g"),$E3514,COLUMN()-7) -> ETC扣款 | J3514: =INDEX(INDIRECT("'"&$D3514&"'!A:g"),$E3514,COLUMN()-7) -> 项目成本 | K3514: =INDEX(INDIRECT("'"&$D3514&"'!A:g"),$E3514,COLUMN()-7) -> 0 | L3514: =INDEX(INDIRECT("'"&$D3514&"'!A:g"),$E3514,COLUMN()-7) -> 138.7 | M3514: =INDEX(INDIRECT("'"&$D3514&"'!A:g"),$E3514,COLUMN()-7) -> 81006.2 | N3514: =INDEX(INDIRECT("'"&$D3514&"'!A:g"),$E3514,COLUMN()-7) -> 0
A3515: =档案!A3514 -> 0 | B3515: =COUNTA(INDIRECT("'"&A3515&"'!a:a")) -> 1 | D3515: =IF(E3514>=VLOOKUP(D3514,A:B,2,FALSE),D3514+1,D3514) -> 9 | E3515: =IF(E3514>=VLOOKUP(D3514,A:B,2,FALSE),3,E3514+1) -> 2176 | F3515: =VLOOKUP(D3515,档案!A:C,3,FALSE) -> 武汉开明 | G3515: =VLOOKUP(D3515,档案!A:B,2,FALSE) -> 农商行豹澥支行310028 | H3515: =INDEX(INDIRECT("'"&$D3515&"'!A:g"),$E3515,COLUMN()-7) -> 45941 | I3515: =INDEX(INDIRECT("'"&$D3515&"'!A:g"),$E3515,COLUMN()-7) -> 销售部陈涛报销2025.8月差旅费--个人 | J3515: =INDEX(INDIRECT("'"&$D3515&"'!A:g"),$E3515,COLUMN()-7) -> 付日常费用 | K3515: =INDEX(INDIRECT("'"&$D3515&"'!A:g"),$E3515,COLUMN()-7) -> 0 | L3515: =INDEX(INDIRECT("'"&$D3515&"'!A:g"),$E3515,COLUMN()-7) -> 4911.8 | M3515: =INDEX(INDIRECT("'"&$D3515&"'!A:g"),$E3515,COLUMN()-7) -> 76094.4 | N3515: =INDEX(INDIRECT("'"&$D3515&"'!A:g"),$E3515,COLUMN()-7) -> 0
A3516: =档案!A3515 -> 0 | B3516: =COUNTA(INDIRECT("'"&A3516&"'!a:a")) -> 1 | D3516: =IF(E3515>=VLOOKUP(D3515,A:B,2,FALSE),D3515+1,D3515) -> 9 | E3516: =IF(E3515>=VLOOKUP(D3515,A:B,2,FALSE),3,E3515+1) -> 2177 | F3516: =VLOOKUP(D3516,档案!A:C,3,FALSE) -> 武汉开明 | G3516: =VLOOKUP(D3516,档案!A:B,2,FALSE) -> 农商行豹澥支行310028 | H3516: =INDEX(INDIRECT("'"&$D3516&"'!A:g"),$E3516,COLUMN()-7) -> 45941 | I3516: =INDEX(INDIRECT("'"&$D3516&"'!A:g"),$E3516,COLUMN()-7) -> 销售部刘江波报销新疆伊犁钢铁9月差旅费--个人 | J3516: =INDEX(INDIRECT("'"&$D3516&"'!A:g"),$E3516,COLUMN()-7) -> 付日常费用 | K3516: =INDEX(INDIRECT("'"&$D3516&"'!A:g"),$E3516,COLUMN()-7) -> 0 | L3516: =INDEX(INDIRECT("'"&$D3516&"'!A:g"),$E3516,COLUMN()-7) -> 3466.43 | M3516: =INDEX(INDIRECT("'"&$D3516&"'!A:g"),$E3516,COLUMN()-7) -> 72627.97 | N3516: =INDEX(INDIRECT("'"&$D3516&"'!A:g"),$E3516,COLUMN()-7) -> 0
A3517: =档案!A3516 -> 0 | B3517: =COUNTA(INDIRECT("'"&A3517&"'!a:a")) -> 1 | D3517: =IF(E3516>=VLOOKUP(D3516,A:B,2,FALSE),D3516+1,D3516) -> 9 | E3517: =IF(E3516>=VLOOKUP(D3516,A:B,2,FALSE),3,E3516+1) -> 2178 | F3517: =VLOOKUP(D3517,档案!A:C,3,FALSE) -> 武汉开明 | G3517: =VLOOKUP(D3517,档案!A:B,2,FALSE) -> 农商行豹澥支行310028 | H3517: =INDEX(INDIRECT("'"&$D3517&"'!A:g"),$E3517,COLUMN()-7) -> 45941 | I3517: =INDEX(INDIRECT("'"&$D3517&"'!A:g"),$E3517,COLUMN()-7) -> 销售部叶涛报销内蒙古君正，双环等项目8月差旅费--个人 | J3517: =INDEX(INDIRECT("'"&$D3517&"'!A:g"),$E3517,COLUMN()-7) -> 付日常费用 | K3517: =INDEX(INDIRECT("'"&$D3517&"'!A:g"),$E3517,COLUMN()-7) -> 0 | L3517: =INDEX(INDIRECT("'"&$D3517&"'!A:g"),$E3517,COLUMN()-7) -> 2341.5 | M3517: =INDEX(INDIRECT("'"&$D3517&"'!A:g"),$E3517,COLUMN()-7) -> 70286.47 | N3517: =INDEX(INDIRECT("'"&$D3517&"'!A:g"),$E3517,COLUMN()-7) -> 0
A3518: =档案!A3517 -> 0 | B3518: =COUNTA(INDIRECT("'"&A3518&"'!a:a")) -> 1 | D3518: =IF(E3517>=VLOOKUP(D3517,A:B,2,FALSE),D3517+1,D3517) -> 9 | E3518: =IF(E3517>=VLOOKUP(D3517,A:B,2,FALSE),3,E3517+1) -> 2179 | F3518: =VLOOKUP(D3518,档案!A:C,3,FALSE) -> 武汉开明 | G3518: =VLOOKUP(D3518,档案!A:B,2,FALSE) -> 农商行豹澥支行310028 | H3518: =INDEX(INDIRECT("'"&$D3518&"'!A:g"),$E3518,COLUMN()-7) -> 45941 | I3518: =INDEX(INDIRECT("'"&$D3518&"'!A:g"),$E3518,COLUMN()-7) -> 销售部牛国庆报销2025.8月差旅费--个人 | J3518: =INDEX(INDIRECT("'"&$D3518&"'!A:g"),$E3518,COLUMN()-7) -> 付日常费用 | K3518: =INDEX(INDIRECT("'"&$D3518&"'!A:g"),$E3518,COLUMN()-7) -> 0 | L3518: =INDEX(INDIRECT("'"&$D3518&"'!A:g"),$E3518,COLUMN()-7) -> 6895.77 | M3518: =INDEX(INDIRECT("'"&$D3518&"'!A:g"),$E3518,COLUMN()-7) -> 63390.7 | N3518: =INDEX(INDIRECT("'"&$D3518&"'!A:g"),$E3518,COLUMN()-7) -> 0
A3519: =档案!A3518 -> 0 | B3519: =COUNTA(INDIRECT("'"&A3519&"'!a:a")) -> 1 | D3519: =IF(E3518>=VLOOKUP(D3518,A:B,2,FALSE),D3518+1,D3518) -> 9 | E3519: =IF(E3518>=VLOOKUP(D3518,A:B,2,FALSE),3,E3518+1) -> 2180 | F3519: =VLOOKUP(D3519,档案!A:C,3,FALSE) -> 武汉开明 | G3519: =VLOOKUP(D3519,档案!A:B,2,FALSE) -> 农商行豹澥支行310028 | H3519: =INDEX(INDIRECT("'"&$D3519&"'!A:g"),$E3519,COLUMN()-7) -> 45941 | I3519: =INDEX(INDIRECT("'"&$D3519&"'!A:g"),$E3519,COLUMN()-7) -> 销售部管厚良报销2025.8月差旅费--个人 | J3519: =INDEX(INDIRECT("'"&$D3519&"'!A:g"),$E3519,COLUMN()-7) -> 付日常费用 | K3519: =INDEX(INDIRECT("'"&$D3519&"'!A:g"),$E3519,COLUMN()-7) -> 0 | L3519: =INDEX(INDIRECT("'"&$D3519&"'!A:g"),$E3519,COLUMN()-7) -> 491.15 | M3519: =INDEX(INDIRECT("'"&$D3519&"'!A:g"),$E3519,COLUMN()-7) -> 62899.55 | N3519: =INDEX(INDIRECT("'"&$D3519&"'!A:g"),$E3519,COLUMN()-7) -> 0
A3520: =档案!A3519 -> 0 | B3520: =COUNTA(INDIRECT("'"&A3520&"'!a:a")) -> 1 | D3520: =IF(E3519>=VLOOKUP(D3519,A:B,2,FALSE),D3519+1,D3519) -> 9 | E3520: =IF(E3519>=VLOOKUP(D3519,A:B,2,FALSE),3,E3519+1) -> 2181 | F3520: =VLOOKUP(D3520,档案!A:C,3,FALSE) -> 武汉开明 | G3520: =VLOOKUP(D3520,档案!A:B,2,FALSE) -> 农商行豹澥支行310028 | H3520: =INDEX(INDIRECT("'"&$D3520&"'!A:g"),$E3520,COLUMN()-7) -> 45941 | I3520: =INDEX(INDIRECT("'"&$D3520&"'!A:g"),$E3520,COLUMN()-7) -> 生产部陈艳华报销9.15-9.23芜湖新兴铸管交通费--个人 | J3520: =INDEX(INDIRECT("'"&$D3520&"'!A:g"),$E3520,COLUMN()-7) -> 付日常费用 | K3520: =INDEX(INDIRECT("'"&$D3520&"'!A:g"),$E3520,COLUMN()-7) -> 0 | L3520: =INDEX(INDIRECT("'"&$D3520&"'!A:g"),$E3520,COLUMN()-7) -> 334 | M3520: =INDEX(INDIRECT("'"&$D3520&"'!A:g"),$E3520,COLUMN()-7) -> 62565.55 | N3520: =INDEX(INDIRECT("'"&$D3520&"'!A:g"),$E3520,COLUMN()-7) -> 0
... A4455: =档案!A4454 -> 0 | B4455: =COUNTA(INDIRECT("'"&A4455&"'!a:a")) -> 1 | D4455: =IF(E4454>=VLOOKUP(D4454,A:B,2,FALSE),D4454+1,D4454) -> 20 | E4455: =IF(E4454>=VLOOKUP(D4454,A:B,2,FALSE),3,E4454+1) -> 136 | F4455: =VLOOKUP(D4455,档案!A:C,3,FALSE) -> 武汉彤烨 | G4455: =VLOOKUP(D4455,档案!A:B,2,FALSE) -> 中信银行武汉东湖支行181028 | H4455: =INDEX(INDIRECT("'"&$D4455&"'!A:g"),$E4455,COLUMN()-7) -> 45903 | I4455: =INDEX(INDIRECT("'"&$D4455&"'!A:g"),$E4455,COLUMN()-7) -> 转武汉华夏 | J4455: =INDEX(INDIRECT("'"&$D4455&"'!A:g"),$E4455,COLUMN()-7) -> 转出他行或提现 | K4455: =INDEX(INDIRECT("'"&$D4455&"'!A:g"),$E4455,COLUMN()-7) -> 0 | L4455: =INDEX(INDIRECT("'"&$D4455&"'!A:g"),$E4455,COLUMN()-7) -> 1500000 | M4455: =INDEX(INDIRECT("'"&$D4455&"'!A:g"),$E4455,COLUMN()-7) -> 2001818.8 | N4455: =INDEX(INDIRECT("'"&$D4455&"'!A:g"),$E4455,COLUMN()-7) -> 0
A4456: =档案!A4455 -> 0 | B4456: =COUNTA(INDIRECT("'"&A4456&"'!a:a")) -> 1 | D4456: =IF(E4455>=VLOOKUP(D4455,A:B,2,FALSE),D4455+1,D4455) -> 20 | E4456: =IF(E4455>=VLOOKUP(D4455,A:B,2,FALSE),3,E4455+1) -> 137 | F4456: =VLOOKUP(D4456,档案!A:C,3,FALSE) -> 武汉彤烨 | G4456: =VLOOKUP(D4456,档案!A:B,2,FALSE) -> 中信银行武汉东湖支行181028 | H4456: =INDEX(INDIRECT("'"&$D4456&"'!A:g"),$E4456,COLUMN()-7) -> 45903 | I4456: =INDEX(INDIRECT("'"&$D4456&"'!A:g"),$E4456,COLUMN()-7) -> 转武汉浦发 | J4456: =INDEX(INDIRECT("'"&$D4456&"'!A:g"),$E4456,COLUMN()-7) -> 转出他行或提现 | K4456: =INDEX(INDIRECT("'"&$D4456&"'!A:g"),$E4456,COLUMN()-7) -> 0 | L4456: 290 | M4456: =INDEX(INDIRECT("'"&$D4456&"'!A:g"),$E4456,COLUMN()-7) -> 1818.78 | N4456: =INDEX(INDIRECT("'"&$D4456&"'!A:g"),$E4456,COLUMN()-7) -> 0
A4457: =档案!A4456 -> 0 | B4457: =COUNTA(INDIRECT("'"&A4457&"'!a:a")) -> 1 | D4457: =IF(E4456>=VLOOKUP(D4456,A:B,2,FALSE),D4456+1,D4456) -> 20 | E4457: =IF(E4456>=VLOOKUP(D4456,A:B,2,FALSE),3,E4456+1) -> 138 | F4457: =VLOOKUP(D4457,档案!A:C,3,FALSE) -> 武汉彤烨 | G4457: =VLOOKUP(D4457,档案!A:B,2,FALSE) -> 中信银行武汉东湖支行181028 | H4457: =INDEX(INDIRECT("'"&$D4457&"'!A:g"),$E4457,COLUMN()-7) -> 45903 | I4457: =INDEX(INDIRECT("'"&$D4457&"'!A:g"),$E4457,COLUMN()-7) -> 收到湖北邮政转款 | J4457: =INDEX(INDIRECT("'"&$D4457&"'!A:g"),$E4457,COLUMN()-7) -> 他行转入或存现 | K4457: =INDEX(INDIRECT("'"&$D4457&"'!A:g"),$E4457,COLUMN()-7) -> 1900000 | L4457: =INDEX(INDIRECT("'"&$D4457&"'!A:g"),$E4457,COLUMN()-7) -> 0 | M4457: =INDEX(INDIRECT("'"&$D4457&"'!A:g"),$E4457,COLUMN()-7) -> 1901818.8 | N4457: =INDEX(INDIRECT("'"&$D4457&"'!A:g"),$E4457,COLUMN()-7) -> 0
A4458: =档案!A4457 -> 0 | B4458: =COUNTA(INDIRECT("'"&A4458&"'!a:a")) -> 1 | D4458: =IF(E4457>=VLOOKUP(D4457,A:B,2,FALSE),D4457+1,D4457) -> 20 | E4458: =IF(E4457>=VLOOKUP(D4457,A:B,2,FALSE),3,E4457+1) -> 139 | F4458: =VLOOKUP(D4458,档案!A:C,3,FALSE) -> 武汉彤烨 | G4458: =VLOOKUP(D4458,档案!A:B,2,FALSE) -> 中信银行武汉东湖支行181028 | H4458: =INDEX(INDIRECT("'"&$D4458&"'!A:g"),$E4458,COLUMN()-7) -> 45903 | I4458: =INDEX(INDIRECT("'"&$D4458&"'!A:g"),$E4458,COLUMN()-7) -> 收到湖北邮政转款 | J4458: =INDEX(INDIRECT("'"&$D4458&"'!A:g"),$E4458,COLUMN()-7) -> 他行转入或存现 | K4458: =INDEX(INDIRECT("'"&$D4458&"'!A:g"),$E4458,COLUMN()-7) -> 1600000 | L4458: =INDEX(INDIRECT("'"&$D4458&"'!A:g"),$E4458,COLUMN()-7) -> 0 | M4458: =INDEX(INDIRECT("'"&$D4458&"'!A:g"),$E4458,COLUMN()-7) -> 3501818.8 | N4458: =INDEX(INDIRECT("'"&$D4458&"'!A:g"),$E4458,COLUMN()-7) -> 0
A4459: =档案!A4458 -> 0 | B4459: =COUNTA(INDIRECT("'"&A4459&"'!a:a")) -> 1 | D4459: =IF(E4458>=VLOOKUP(D4458,A:B,2,FALSE),D4458+1,D4458) -> 20 | E4459: =IF(E4458>=VLOOKUP(D4458,A:B,2,FALSE),3,E4458+1) -> 140 | F4459: =VLOOKUP(D4459,档案!A:C,3,FALSE) -> 武汉彤烨 | G4459: =VLOOKUP(D4459,档案!A:B,2,FALSE) -> 中信银行武汉东湖支行181028 | H4459: =INDEX(INDIRECT("'"&$D4459&"'!A:g"),$E4459,COLUMN()-7) -> 45903 | I4459: =INDEX(INDIRECT("'"&$D4459&"'!A:g"),$E4459,COLUMN()-7) -> 转武汉华夏 | J4459: =INDEX(INDIRECT("'"&$D4459&"'!A:g"),$E4459,COLUMN()-7) -> 转出他行或提现 | K4459: =INDEX(INDIRECT("'"&$D4459&"'!A:g"),$E4459,COLUMN()-7) -> 0 | L4459: =INDEX(INDIRECT("'"&$D4459&"'!A:g"),$E4459,COLUMN()-7) -> 1850000 | M4459: =INDEX(INDIRECT("'"&$D4459&"'!A:g"),$E4459,COLUMN()-7) -> 1651818.8 | N4459: =INDEX(INDIRECT("'"&$D4459&"'!A:g"),$E4459,COLUMN()-7) -> 0
A4460: =档案!A4459 -> 0 | B4460: =COUNTA(INDIRECT("'"&A4460&"'!a:a")) -> 1 | D4460: =IF(E4459>=VLOOKUP(D4459,A:B,2,FALSE),D4459+1,D4459) -> 20 | E4460: =IF(E4459>=VLOOKUP(D4459,A:B,2,FALSE),3,E4459+1) -> 141 | F4460: =VLOOKUP(D4460,档案!A:C,3,FALSE) -> 武汉彤烨 | G4460: =VLOOKUP(D4460,档案!A:B,2,FALSE) -> 中信银行武汉东湖支行181028 | H4460: =INDEX(INDIRECT("'"&$D4460&"'!A:g"),$E4460,COLUMN()-7) -> 45903 | I4460: =INDEX(INDIRECT("'"&$D4460&"'!A:g"),$E4460,COLUMN()-7) -> 转武汉浦发 | J4460: =INDEX(INDIRECT("'"&$D4460&"'!A:g"),$E4460,COLUMN()-7) -> 转出他行或提现 | K4460: =INDEX(INDIRECT("'"&$D4460&"'!A:g"),$E4460,COLUMN()-7) -> 0 | L4460: =INDEX(INDIRECT("'"&$D4460&"'!A:g"),$E4460,COLUMN()-7) -> 1650000 | M4460: =INDEX(INDIRECT("'"&$D4460&"'!A:g"),$E4460,COLUMN()-7) -> 1818.78 | N4460: =INDEX(INDIRECT("'"&$D4460&"'!A:g"),$E4460,COLUMN()-7) -> 0
A4461: =档案!A4460 -> 0 | B4461: =COUNTA(INDIRECT("'"&A4461&"'!a:a")) -> 1 | D4461: =IF(E4460>=VLOOKUP(D4460,A:B,2,FALSE),D4460+1,D4460) -> 20 | E4461: =IF(E4460>=VLOOKUP(D4460,A:B,2,FALSE),3,E4460+1) -> 142 | F4461: =VLOOKUP(D4461,档案!A:C,3,FALSE) -> 武汉彤烨 | G4461: =VLOOKUP(D4461,档案!A:B,2,FALSE) -> 中信银行武汉东湖支行181028 | H4461: =INDEX(INDIRECT("'"&$D4461&"'!A:g"),$E4461,COLUMN()-7) -> 45904 | I4461: =INDEX(INDIRECT("'"&$D4461&"'!A:g"),$E4461,COLUMN()-7) -> 收到湖北邮政转款 | J4461: =INDEX(INDIRECT("'"&$D4461&"'!A:g"),$E4461,COLUMN()-7) -> 他行转入或存现 | K4461: =INDEX(INDIRECT("'"&$D4461&"'!A:g"),$E4461,COLUMN()-7) -> 1500000 | L4461: =INDEX(INDIRECT("'"&$D4461&"'!A:g"),$E4461,COLUMN()-7) -> 0 | M4461: =INDEX(INDIRECT("'"&$D4461&"'!A:g"),$E4461,COLUMN()-7) -> 1501818.8 | N4461: =INDEX(INDIRECT("'"&$D4461&"'!A:g"),$E4461,COLUMN()-7) -> 0
A4462: =档案!A4461 -> 0 | B4462: =COUNTA(INDIRECT("'"&A4462&"'!a:a")) -> 1 | D4462: =IF(E4461>=VLOOKUP(D4461,A:B,2,FALSE),D4461+1,D4461) -> 20 | E4462: =IF(E4461>=VLOOKUP(D4461,A:B,2,FALSE),3,E4461+1) -> 143 | F4462: =VLOOKUP(D4462,档案!A:C,3,FALSE) -> 武汉彤烨 | G4462: =VLOOKUP(D4462,档案!A:B,2,FALSE) -> 中信银行武汉东湖支行181028 | H4462: =INDEX(INDIRECT("'"&$D4462&"'!A:g"),$E4462,COLUMN()-7) -> 45904 | I4462: =INDEX(INDIRECT("'"&$D4462&"'!A:g"),$E4462,COLUMN()-7) -> 转湖北岚丹中信 | J4462: =INDEX(INDIRECT("'"&$D4462&"'!A:g"),$E4462,COLUMN()-7) -> 转出他行或提现 | K4462: =INDEX(INDIRECT("'"&$D4462&"'!A:g"),$E4462,COLUMN()-7) -> 0 | L4462: =INDEX(INDIRECT("'"&$D4462&"'!A:g"),$E4462,COLUMN()-7) -> 1500000 | M4462: =INDEX(INDIRECT("'"&$D4462&"'!A:g"),$E4462,COLUMN()-7) -> 1818.78 | N4462: =INDEX(INDIRECT("'"&$D4462&"'!A:g"),$E4462,COLUMN()-7) -> 0
A4463: =档案!A4462 -> 0 | B4463: =COUNTA(INDIRECT("'"&A4463&"'!a:a")) -> 1 | D4463: =IF(E4462>=VLOOKUP(D4462,A:B,2,FALSE),D4462+1,D4462) -> 20 | E4463: =IF(E4462>=VLOOKUP(D4462,A:B,2,FALSE),3,E4462+1) -> 144 | F4463: =VLOOKUP(D4463,档案!A:C,3,FALSE) -> 武汉彤烨 | G4463: =VLOOKUP(D4463,档案!A:B,2,FALSE) -> 中信银行武汉东湖支行181028 | H4463: =INDEX(INDIRECT("'"&$D4463&"'!A:g"),$E4463,COLUMN()-7) -> 45904 | I4463: =INDEX(INDIRECT("'"&$D4463&"'!A:g"),$E4463,COLUMN()-7) -> 收到湖北邮政转款 | J4463: =INDEX(INDIRECT("'"&$D4463&"'!A:g"),$E4463,COLUMN()-7) -> 他行转入或存现 | K4463: =INDEX(INDIRECT("'"&$D4463&"'!A:g"),$E4463,COLUMN()-7) -> 750000 | L4463: =INDEX(INDIRECT("'"&$D4463&"'!A:g"),$E4463,COLUMN()-7) -> 0 | M4463: =INDEX(INDIRECT("'"&$D4463&"'!A:g"),$E4463,COLUMN()-7) -> 751818.78 | N4463: =INDEX(INDIRECT("'"&$D4463&"'!A:g"),$E4463,COLUMN()-7) -> 0
A4464: =档案!A4463 -> 0 | B4464: =COUNTA(INDIRECT("'"&A4464&"'!a:a")) -> 1 | D4464: =IF(E4463>=VLOOKUP(D4463,A:B,2,FALSE),D4463+1,D4463) -> 20 | E4464: =IF(E4463>=VLOOKUP(D4463,A:B,2,FALSE),3,E4463+1) -> 145 | F4464: =VLOOKUP(D4464,档案!A:C,3,FALSE) -> 武汉彤烨 | G4464: =VLOOKUP(D4464,档案!A:B,2,FALSE) -> 中信银行武汉东湖支行181028 | H4464: =INDEX(INDIRECT("'"&$D4464&"'!A:g"),$E4464,COLUMN()-7) -> 45904 | I4464: =INDEX(INDIRECT("'"&$D4464&"'!A:g"),$E4464,COLUMN()-7) -> 收到湖北邮政转款 | J4464: =INDEX(INDIRECT("'"&$D4464&"'!A:g"),$E4464,COLUMN()-7) -> 他行转入或存现 | K4464: =INDEX(INDIRECT("'"&$D4464&"'!A:g"),$E4464,COLUMN()-7) -> 750000 | L4464: =INDEX(INDIRECT("'"&$D4464&"'!A:g"),$E4464,COLUMN()-7) -> 0 | M4464: =INDEX(INDIRECT("'"&$D4464&"'!A:g"),$E4464,COLUMN()-7) -> 1501818.8 | N4464: =INDEX(INDIRECT("'"&$D4464&"'!A:g"),$E4464,COLUMN()-7) -> 0
A4465: =档案!A4464 -> 0 | B4465: =COUNTA(INDIRECT("'"&A4465&"'!a:a")) -> 1 | D4465: =IF(E4464>=VLOOKUP(D4464,A:B,2,FALSE),D4464+1,D4464) -> 20 | E4465: =IF(E4464>=VLOOKUP(D4464,A:B,2,FALSE),3,E4464+1) -> 146 | F4465: =VLOOKUP(D4465,档案!A:C,3,FALSE) -> 武汉彤烨 | G4465: =VLOOKUP(D4465,档案!A:B,2,FALSE) -> 中信银行武汉东湖支行181028 | H4465: =INDEX(INDIRECT("'"&$D4465&"'!A:g"),$E4465,COLUMN()-7) -> 45904 | I4465: =INDEX(INDIRECT("'"&$D4465&"'!A:g"),$E4465,COLUMN()-7) -> 转湖北岚丹中信 | J4465: =INDEX(INDIRECT("'"&$D4465&"'!A:g"),$E4465,COLUMN()-7) -> 转出他行或提现 | K4465: =INDEX(INDIRECT("'"&$D4465&"'!A:g"),$E4465,COLUMN()-7) -> 0 | L4465: =INDEX(INDIRECT("'"&$D4465&"'!A:g"),$E4465,COLUMN()-7) -> 1000000 | M4465: =INDEX(INDIRECT("'"&$D4465&"'!A:g"),$E4465,COLUMN()-7) -> 501818.78 | N4465: =INDEX(INDIRECT("'"&$D4465&"'!A:g"),$E4465,COLUMN()-7) -> 0
A4466: =档案!A4465 -> 0 | B4466: =COUNTA(INDIRECT("'"&A4466&"'!a:a")) -> 1 | D4466: =IF(E4465>=VLOOKUP(D4465,A:B,2,FALSE),D4465+1,D4465) -> 20 | E4466: =IF(E4465>=VLOOKUP(D4465,A:B,2,FALSE),3,E4465+1) -> 147 | F4466: =VLOOKUP(D4466,档案!A:C,3,FALSE) -> 武汉彤烨 | G4466: =VLOOKUP(D4466,档案!A:B,2,FALSE) -> 中信银行武汉东湖支行181028 | H4466: =INDEX(INDIRECT("'"&$D4466&"'!A:g"),$E4466,COLUMN()-7) -> 45904 | I4466: =INDEX(INDIRECT("'"&$D4466&"'!A:g"),$E4466,COLUMN()-7) -> 转湖北中行 | J4466: =INDEX(INDIRECT("'"&$D4466&"'!A:g"),$E4466,COLUMN()-7) -> 转出他行或提现 | K4466: =INDEX(INDIRECT("'"&$D4466&"'!A:g"),$E4466,COLUMN()-7) -> 0 | L4466: =INDEX(INDIRECT("'"&$D4466&"'!A:g"),$E4466,COLUMN()-7) -> 150000 | M4466: =INDEX(INDIRECT("'"&$D4466&"'!A:g"),$E4466,COLUMN()-7) -> 351818.78 | N4466: =INDEX(INDIRECT("'"&$D4466&"'!A:g"),$E4466,COLUMN()-7) -> 0
A4467: =档案!A4466 -> 0 | B4467: =COUNTA(INDIRECT("'"&A4467&"'!a:a")) -> 1 | D4467: =IF(E4466>=VLOOKUP(D4466,A:B,2,FALSE),D4466+1,D4466) -> 20 | E4467: =IF(E4466>=VLOOKUP(D4466,A:B,2,FALSE),3,E4466+1) -> 148 | F4467: =VLOOKUP(D4467,档案!A:C,3,FALSE) -> 武汉彤烨 | G4467: =VLOOKUP(D4467,档案!A:B,2,FALSE) -> 中信银行武汉东湖支行181028 | H4467: =INDEX(INDIRECT("'"&$D4467&"'!A:g"),$E4467,COLUMN()-7) -> 45905 | I4467: =INDEX(INDIRECT("'"&$D4467&"'!A:g"),$E4467,COLUMN()-7) -> 收到湖北邮政转款 | J4467: =INDEX(INDIRECT("'"&$D4467&"'!A:g"),$E4467,COLUMN()-7) -> 他行转入或存现 | K4467: =INDEX(INDIRECT("'"&$D4467&"'!A:g"),$E4467,COLUMN()-7) -> 500000 | L4467: =INDEX(INDIRECT("'"&$D4467&"'!A:g"),$E4467,COLUMN()-7) -> 0 | M4467: =INDEX(INDIRECT("'"&$D4467&"'!A:g"),$E4467,COLUMN()-7) -> 851818.78 | N4467: =INDEX(INDIRECT("'"&$D4467&"'!A:g"),$E4467,COLUMN()-7) -> 0
A4468: =档案!A4467 -> 0 | B4468: =COUNTA(INDIRECT("'"&A4468&"'!a:a")) -> 1 | D4468: =IF(E4467>=VLOOKUP(D4467,A:B,2,FALSE),D4467+1,D4467) -> 20 | E4468: =IF(E4467>=VLOOKUP(D4467,A:B,2,FALSE),3,E4467+1) -> 149 | F4468: =VLOOKUP(D4468,档案!A:C,3,FALSE) -> 武汉彤烨 | G4468: =VLOOKUP(D4468,档案!A:B,2,FALSE) -> 中信银行武汉东湖支行181028 | H4468: =INDEX(INDIRECT("'"&$D4468&"'!A:g"),$E4468,COLUMN()-7) -> 45905 | I4468: =INDEX(INDIRECT("'"&$D4468&"'!A:g"),$E4468,COLUMN()-7) -> 转武汉农商行 | J4468: =INDEX(INDIRECT("'"&$D4468&"'!A:g"),$E4468,COLUMN()-7) -> 转出他行或提现 | K4468: =INDEX(INDIRECT("'"&$D4468&"'!A:g"),$E4468,COLUMN()-7) -> 0 | L4468: =INDEX(INDIRECT("'"&$D4468&"'!A:g"),$E4468,COLUMN()-7) -> 200000 | M4468: =INDEX(INDIRECT("'"&$D4468&"'!A:g"),$E4468,COLUMN()-7) -> 651818.78 | N4468: =INDEX(INDIRECT("'"&$D4468&"'!A:g"),$E4468,COLUMN()-7) -> 0
... A6911: =档案!A6910 -> 0 | B6911: =COUNTA(INDIRECT("'"&A6911&"'!a:a")) -> 1 | D6911: =IF(E6910>=VLOOKUP(D6910,A:B,2,FALSE),D6910+1,D6910) -> #N/A | E6911: =IF(E6910>=VLOOKUP(D6910,A:B,2,FALSE),3,E6910+1) -> #N/A | F6911: =VLOOKUP(D6911,档案!A:C,3,FALSE) -> #N/A | G6911: =VLOOKUP(D6911,档案!A:B,2,FALSE) -> #N/A | H6911: =INDEX(INDIRECT("'"&$D6911&"'!A:g"),$E6911,COLUMN()-7) -> #N/A | I6911: =INDEX(INDIRECT("'"&$D6911&"'!A:g"),$E6911,COLUMN()-7) -> #N/A | J6911: =INDEX(INDIRECT("'"&$D6911&"'!A:g"),$E6911,COLUMN()-7) -> #N/A | K6911: =INDEX(INDIRECT("'"&$D6911&"'!A:g"),$E6911,COLUMN()-7) -> #N/A | L6911: =INDEX(INDIRECT("'"&$D6911&"'!A:g"),$E6911,COLUMN()-7) -> #N/A | M6911: =INDEX(INDIRECT("'"&$D6911&"'!A:g"),$E6911,COLUMN()-7) -> #N/A | N6911: =INDEX(INDIRECT("'"&$D6911&"'!A:g"),$E6911,COLUMN()-7) -> #N/A

Sheet 单日流水
F1: 资金流水明细表
F2: 报告日期 | G2: 45397 | M2: 单位：元
A3: 表 | B3: 首行 | C3: 行数 | D3: 换表 | E3: 表行 | F3: 公司 | G3: 资金户名 | H3: 日期 | I3: 摘要 | J3: 收支类别 | K3: 收款金额 | L3: 付款金额 | M3: 余额 | N3: 备注
H4: =G2 -> 45397 | I4: 昨日余额 | M4: =SUM(档案!G:G) -> #N/A
A5: =D5 -> 1 | B5: =IF(C5=0,MATCH($G$2,INDIRECT("'"&A5&"'!A:A"),1),MATCH($G$2,INDIRECT("'"&A5&"'!A:A"),0)) -> 1 | C5: =COUNTIF(INDIRECT("'"&A5&"'!A:A"),$G$2) -> 0 | D5: 1 | E5: =IF(C5=0,0,B5+COUNTIF(A$4:A5,A5)-1) -> 0 | F5: =VLOOKUP(D5,档案!A:C,3,FALSE) -> 武汉开明 | G5: =VLOOKUP(D5,档案!A:B,2,FALSE) -> 华夏银行汉正街支行186346 | H5: {=IF(C5=0,"",INDEX(INDIRECT("'"&$D5&"'!A:g"),$E5,COLUMN()-7))} | I5: {=IF(C5=0,"",INDEX(INDIRECT("'"&$D5&"'!A:g"),$E5,COLUMN()-7))} | J5: {=IF(C5=0,"",INDEX(INDIRECT("'"&$D5&"'!A:g"),$E5,COLUMN()-7))} | K5: {=IF(C5=0,0,INDEX(INDIRECT("'"&$D5&"'!A:g"),$E5,COLUMN()-7))} -> 0 | L5: {=IF(C5=0,0,INDEX(INDIRECT("'"&$D5&"'!A:g"),$E5,COLUMN()-7))} -> 0 | M5: =M4+K5-L5 -> #N/A | N5: {=IF(C5=0,0,INDEX(INDIRECT("'"&$D5&"'!A:g"),$E5,COLUMN()-7))} -> 0
A6: =D6 -> 11 | B6: =IF(C6=0,MATCH($G$2,INDIRECT("'"&A6&"'!A:A"),1),MATCH($G$2,INDIRECT("'"&A6&"'!A:A"),0)) -> #N/A | C6: =COUNTIF(INDIRECT("'"&A6&"'!A:A"),$G$2) -> 0 | D6: =IF(COUNTIF(A$4:A5,A5)<C5,D5,IF(COUNTIF(INDIRECT("'"&D5+1&"'!A:A"),$G$2)>0,D5+1,IF(COUNTIF(INDIRECT("'"&D5+2&"'!A:A"),$G$2)>0,D5+2,IF(COUNTIF(INDIRECT("'"&D5+3&"'!A:A"),$G$2)>0,D5+3,IF(COUNTIF(INDIRECT("'"&D5+4&"'!A:A"),$G$2)>0,D5+4,IF(COUNTIF(INDIRECT("'"&D5+5&"'!A:A"),$G$2)>0,D5+5,IF(COUNTIF(INDIRECT("'"&D5+6&"'!A:A"),$G$2)>0,D5+6,IF(COUNTIF(INDIRECT("'"&D5+7&"'!A:A"),$G$2)>0,D5+7,IF(COUNTIF(INDIRECT("'"&D5+8&"'!A:A"),$G$2)>0,D5+8,IF(COUNTIF(INDIRECT("'"&D5+9&"'!A:A"),$G$2)>0,D5+9,D5+10)))))))))) -> 11 | E6: =IF(C6=0,0,B6+COUNTIF(A$4:A6,A6)-1) -> 0 | F6: =VLOOKUP(D6,档案!A:C,3,FALSE) -> 武汉开明 | G6: =VLOOKUP(D6,档案!A:B,2,FALSE) -> 青海农商行农民工工资保证金954442 | H6: {=IF(C6=0,"",INDEX(INDIRECT("'"&$D6&"'!A:g"),$E6,COLUMN()-7))} | I6: {=IF(C6=0,"",INDEX(INDIRECT("'"&$D6&"'!A:g"),$E6,COLUMN()-7))} | J6: {=IF(C6=0,"",INDEX(INDIRECT("'"&$D6&"'!A:g"),$E6,COLUMN()-7))} | K6: {=IF(C6=0,0,INDEX(INDIRECT("'"&$D6&"'!A:g"),$E6,COLUMN()-7))} -> 0 | L6: {=IF(C6=0,0,INDEX(INDIRECT("'"&$D6&"'!A:g"),$E6,COLUMN()-7))} -> 0 | M6: =M5+K6-L6 -> #N/A | N6: {=IF(C6=0,0,INDEX(INDIRECT("'"&$D6&"'!A:g"),$E6,COLUMN()-7))} -> 0
A7: =D7 -> 21 | B7: =IF(C7=0,MATCH($G$2,INDIRECT("'"&A7&"'!A:A"),1),MATCH($G$2,INDIRECT("'"&A7&"'!A:A"),0)) -> 1 | C7: =COUNTIF(INDIRECT("'"&A7&"'!A:A"),$G$2) -> 0 | D7: =IF(COUNTIF(A$4:A6,A6)<C6,D6,IF(COUNTIF(INDIRECT("'"&D6+1&"'!A:A"),$G$2)>0,D6+1,IF(COUNTIF(INDIRECT("'"&D6+2&"'!A:A"),$G$2)>0,D6+2,IF(COUNTIF(INDIRECT("'"&D6+3&"'!A:A"),$G$2)>0,D6+3,IF(COUNTIF(INDIRECT("'"&D6+4&"'!A:A"),$G$2)>0,D6+4,IF(COUNTIF(INDIRECT("'"&D6+5&"'!A:A"),$G$2)>0,D6+5,IF(COUNTIF(INDIRECT("'"&D6+6&"'!A:A"),$G$2)>0,D6+6,IF(COUNTIF(INDIRECT("'"&D6+7&"'!A:A"),$G$2)>0,D6+7,IF(COUNTIF(INDIRECT("'"&D6+8&"'!A:A"),$G$2)>0,D6+8,IF(COUNTIF(INDIRECT("'"&D6+9&"'!A:A"),$G$2)>0,D6+9,D6+10)))))))))) -> 21 | E7: =IF(C7=0,0,B7+COUNTIF(A$4:A7,A7)-1) -> 0 | F7: =VLOOKUP(D7,档案!A:C,3,FALSE) -> 武汉彤烨 | G7: =VLOOKUP(D7,档案!A:B,2,FALSE) -> 汉口银行光谷分行454891 | H7: {=IF(C7=0,"",INDEX(INDIRECT("'"&$D7&"'!A:g"),$E7,COLUMN()-7))} | I7: {=IF(C7=0,"",INDEX(INDIRECT("'"&$D7&"'!A:g"),$E7,COLUMN()-7))} | J7: {=IF(C7=0,"",INDEX(INDIRECT("'"&$D7&"'!A:g"),$E7,COLUMN()-7))} | K7: {=IF(C7=0,0,INDEX(INDIRECT("'"&$D7&"'!A:g"),$E7,COLUMN()-7))} -> 0 | L7: {=IF(C7=0,0,INDEX(INDIRECT("'"&$D7&"'!A:g"),$E7,COLUMN()-7))} -> 0 | M7: =M6+K7-L7 -> #N/A | N7: {=IF(C7=0,0,INDEX(INDIRECT("'"&$D7&"'!A:g"),$E7,COLUMN()-7))} -> 0
A8: =D8 -> 31 | B8: =IF(C8=0,MATCH($G$2,INDIRECT("'"&A8&"'!A:A"),1),MATCH($G$2,INDIRECT("'"&A8&"'!A:A"),0)) -> 1 | C8: =COUNTIF(INDIRECT("'"&A8&"'!A:A"),$G$2) -> 0 | D8: =IF(COUNTIF(A$4:A7,A7)<C7,D7,IF(COUNTIF(INDIRECT("'"&D7+1&"'!A:A"),$G$2)>0,D7+1,IF(COUNTIF(INDIRECT("'"&D7+2&"'!A:A"),$G$2)>0,D7+2,IF(COUNTIF(INDIRECT("'"&D7+3&"'!A:A"),$G$2)>0,D7+3,IF(COUNTIF(INDIRECT("'"&D7+4&"'!A:A"),$G$2)>0,D7+4,IF(COUNTIF(INDIRECT("'"&D7+5&"'!A:A"),$G$2)>0,D7+5,IF(COUNTIF(INDIRECT("'"&D7+6&"'!A:A"),$G$2)>0,D7+6,IF(COUNTIF(INDIRECT("'"&D7+7&"'!A:A"),$G$2)>0,D7+7,IF(COUNTIF(INDIRECT("'"&D7+8&"'!A:A"),$G$2)>0,D7+8,IF(COUNTIF(INDIRECT("'"&D7+9&"'!A:A"),$G$2)>0,D7+9,D7+10)))))))))) -> 31 | E8: =IF(C8=0,0,B8+COUNTIF(A$4:A8,A8)-1) -> 0 | F8: =VLOOKUP(D8,档案!A:C,3,FALSE) -> 湖北开明 | G8: =VLOOKUP(D8,档案!A:B,2,FALSE) -> 中国银行鄂州分行0592794 | H8: {=IF(C8=0,"",INDEX(INDIRECT("'"&$D8&"'!A:g"),$E8,COLUMN()-7))} | I8: {=IF(C8=0,"",INDEX(INDIRECT("'"&$D8&"'!A:g"),$E8,COLUMN()-7))} | J8: {=IF(C8=0,"",INDEX(INDIRECT("'"&$D8&"'!A:g"),$E8,COLUMN()-7))} | K8: {=IF(C8=0,0,INDEX(INDIRECT("'"&$D8&"'!A:g"),$E8,COLUMN()-7))} -> 0 | L8: {=IF(C8=0,0,INDEX(INDIRECT("'"&$D8&"'!A:g"),$E8,COLUMN()-7))} -> 0 | M8: =M7+K8-L8 -> #N/A | N8: {=IF(C8=0,0,INDEX(INDIRECT("'"&$D8&"'!A:g"),$E8,COLUMN()-7))} -> 0
A9: =D9 -> 41 | B9: =IF(C9=0,MATCH($G$2,INDIRECT("'"&A9&"'!A:A"),1),MATCH($G$2,INDIRECT("'"&A9&"'!A:A"),0)) -> 3 | C9: =COUNTIF(INDIRECT("'"&A9&"'!A:A"),$G$2) -> 0 | D9: =IF(COUNTIF(A$4:A8,A8)<C8,D8,IF(COUNTIF(INDIRECT("'"&D8+1&"'!A:A"),$G$2)>0,D8+1,IF(COUNTIF(INDIRECT("'"&D8+2&"'!A:A"),$G$2)>0,D8+2,IF(COUNTIF(INDIRECT("'"&D8+3&"'!A:A"),$G$2)>0,D8+3,IF(COUNTIF(INDIRECT("'"&D8+4&"'!A:A"),$G$2)>0,D8+4,IF(COUNTIF(INDIRECT("'"&D8+5&"'!A:A"),$G$2)>0,D8+5,IF(COUNTIF(INDIRECT("'"&D8+6&"'!A:A"),$G$2)>0,D8+6,IF(COUNTIF(INDIRECT("'"&D8+7&"'!A:A"),$G$2)>0,D8+7,IF(COUNTIF(INDIRECT("'"&D8+8&"'!A:A"),$G$2)>0,D8+8,IF(COUNTIF(INDIRECT("'"&D8+9&"'!A:A"),$G$2)>0,D8+9,D8+10)))))))))) -> 41 | E9: =IF(C9=0,0,B9+COUNTIF(A$4:A9,A9)-1) -> 0 | F9: =VLOOKUP(D9,档案!A:C,3,FALSE) -> 武汉信茂 | G9: =VLOOKUP(D9,档案!A:B,2,FALSE) -> 0 | H9: {=IF(C9=0,"",INDEX(INDIRECT("'"&$D9&"'!A:g"),$E9,COLUMN()-7))} | I9: {=IF(C9=0,"",INDEX(INDIRECT("'"&$D9&"'!A:g"),$E9,COLUMN()-7))} | J9: {=IF(C9=0,"",INDEX(INDIRECT("'"&$D9&"'!A:g"),$E9,COLUMN()-7))} | K9: {=IF(C9=0,0,INDEX(INDIRECT("'"&$D9&"'!A:g"),$E9,COLUMN()-7))} -> 0 | L9: {=IF(C9=0,0,INDEX(INDIRECT("'"&$D9&"'!A:g"),$E9,COLUMN()-7))} -> 0 | M9: =M8+K9-L9 -> #N/A | N9: {=IF(C9=0,0,INDEX(INDIRECT("'"&$D9&"'!A:g"),$E9,COLUMN()-7))} -> 0
A10: =D10 -> 51 | B10: =IF(C10=0,MATCH($G$2,INDIRECT("'"&A10&"'!A:A"),1),MATCH($G$2,INDIRECT("'"&A10&"'!A:A"),0)) -> 1 | C10: =COUNTIF(INDIRECT("'"&A10&"'!A:A"),$G$2) -> 0 | D10: =IF(COUNTIF(A$4:A9,A9)<C9,D9,IF(COUNTIF(INDIRECT("'"&D9+1&"'!A:A"),$G$2)>0,D9+1,IF(COUNTIF(INDIRECT("'"&D9+2&"'!A:A"),$G$2)>0,D9+2,IF(COUNTIF(INDIRECT("'"&D9+3&"'!A:A"),$G$2)>0,D9+3,IF(COUNTIF(INDIRECT("'"&D9+4&"'!A:A"),$G$2)>0,D9+4,IF(COUNTIF(INDIRECT("'"&D9+5&"'!A:A"),$G$2)>0,D9+5,IF(COUNTIF(INDIRECT("'"&D9+6&"'!A:A"),$G$2)>0,D9+6,IF(COUNTIF(INDIRECT("'"&D9+7&"'!A:A"),$G$2)>0,D9+7,IF(COUNTIF(INDIRECT("'"&D9+8&"'!A:A"),$G$2)>0,D9+8,IF(COUNTIF(INDIRECT("'"&D9+9&"'!A:A"),$G$2)>0,D9+9,D9+10)))))))))) -> 51 | E10: =IF(C10=0,0,B10+COUNTIF(A$4:A10,A10)-1) -> 0 | F10: =VLOOKUP(D10,档案!A:C,3,FALSE) -> 0 | G10: =VLOOKUP(D10,档案!A:B,2,FALSE) -> 工会工行西山支行029092 | H10: {=IF(C10=0,"",INDEX(INDIRECT("'"&$D10&"'!A:g"),$E10,COLUMN()-7))} | I10: {=IF(C10=0,"",INDEX(INDIRECT("'"&$D10&"'!A:g"),$E10,COLUMN()-7))} | J10: {=IF(C10=0,"",INDEX(INDIRECT("'"&$D10&"'!A:g"),$E10,COLUMN()-7))} | K10: {=IF(C10=0,0,INDEX(INDIRECT("'"&$D10&"'!A:g"),$E10,COLUMN()-7))} -> 0 | L10: {=IF(C10=0,0,INDEX(INDIRECT("'"&$D10&"'!A:g"),$E10,COLUMN()-7))} -> 0 | M10: =M9+K10-L10 -> #N/A | N10: {=IF(C10=0,0,INDEX(INDIRECT("'"&$D10&"'!A:g"),$E10,COLUMN()-7))} -> 0
A11: =D11 -> #REF! | B11: =IF(C11=0,MATCH($G$2,INDIRECT("'"&A11&"'!A:A"),1),MATCH($G$2,INDIRECT("'"&A11&"'!A:A"),0)) -> #REF! | C11: =COUNTIF(INDIRECT("'"&A11&"'!A:A"),$G$2) -> #REF! | D11: =IF(COUNTIF(A$4:A10,A10)<C10,D10,IF(COUNTIF(INDIRECT("'"&D10+1&"'!A:A"),$G$2)>0,D10+1,IF(COUNTIF(INDIRECT("'"&D10+2&"'!A:A"),$G$2)>0,D10+2,IF(COUNTIF(INDIRECT("'"&D10+3&"'!A:A"),$G$2)>0,D10+3,IF(COUNTIF(INDIRECT("'"&D10+4&"'!A:A"),$G$2)>0,D10+4,IF(COUNTIF(INDIRECT("'"&D10+5&"'!A:A"),$G$2)>0,D10+5,IF(COUNTIF(INDIRECT("'"&D10+6&"'!A:A"),$G$2)>0,D10+6,IF(COUNTIF(INDIRECT("'"&D10+7&"'!A:A"),$G$2)>0,D10+7,IF(COUNTIF(INDIRECT("'"&D10+8&"'!A:A"),$G$2)>0,D10+8,IF(COUNTIF(INDIRECT("'"&D10+9&"'!A:A"),$G$2)>0,D10+9,D10+10)))))))))) -> #REF! | E11: =IF(C11=0,0,B11+COUNTIF(A$4:A11,A11)-1) -> #REF! | F11: =VLOOKUP(D11,档案!A:C,3,FALSE) -> #REF! | G11: =VLOOKUP(D11,档案!A:B,2,FALSE) -> #REF! | H11: {=IF(C11=0,"",INDEX(INDIRECT("'"&$D11&"'!A:g"),$E11,COLUMN()-7))} -> #REF! | I11: {=IF(C11=0,"",INDEX(INDIRECT("'"&$D11&"'!A:g"),$E11,COLUMN()-7))} -> #REF! | J11: {=IF(C11=0,"",INDEX(INDIRECT("'"&$D11&"'!A:g"),$E11,COLUMN()-7))} -> #REF! | K11: {=IF(C11=0,0,INDEX(INDIRECT("'"&$D11&"'!A:g"),$E11,COLUMN()-7))} -> #REF! | L11: {=IF(C11=0,0,INDEX(INDIRECT("'"&$D11&"'!A:g"),$E11,COLUMN()-7))} -> #REF! | M11: =M10+K11-L11 -> #N/A | N11: {=IF(C11=0,0,INDEX(INDIRECT("'"&$D11&"'!A:g"),$E11,COLUMN()-7))} -> #REF!
A12: =D12 -> #REF! | B12: =IF(C12=0,MATCH($G$2,INDIRECT("'"&A12&"'!A:A"),1),MATCH($G$2,INDIRECT("'"&A12&"'!A:A"),0)) -> #REF! | C12: =COUNTIF(INDIRECT("'"&A12&"'!A:A"),$G$2) -> #REF! | D12: =IF(COUNTIF(A$4:A11,A11)<C11,D11,IF(COUNTIF(INDIRECT("'"&D11+1&"'!A:A"),$G$2)>0,D11+1,IF(COUNTIF(INDIRECT("'"&D11+2&"'!A:A"),$G$2)>0,D11+2,IF(COUNTIF(INDIRECT("'"&D11+3&"'!A:A"),$G$2)>0,D11+3,IF(COUNTIF(INDIRECT("'"&D11+4&"'!A:A"),$G$2)>0,D11+4,IF(COUNTIF(INDIRECT("'"&D11+5&"'!A:A"),$G$2)>0,D11+5,IF(COUNTIF(INDIRECT("'"&D11+6&"'!A:A"),$G$2)>0,D11+6,IF(COUNTIF(INDIRECT("'"&D11+7&"'!A:A"),$G$2)>0,D11+7,IF(COUNTIF(INDIRECT("'"&D11+8&"'!A:A"),$G$2)>0,D11+8,IF(COUNTIF(INDIRECT("'"&D11+9&"'!A:A"),$G$2)>0,D11+9,D11+10)))))))))) -> #REF! | E12: =IF(C12=0,0,B12+COUNTIF(A$4:A12,A12)-1) -> #REF! | F12: =VLOOKUP(D12,档案!A:C,3,FALSE) -> #REF! | G12: =VLOOKUP(D12,档案!A:B,2,FALSE) -> #REF! | H12: {=IF(C12=0,"",INDEX(INDIRECT("'"&$D12&"'!A:g"),$E12,COLUMN()-7))} -> #REF! | I12: {=IF(C12=0,"",INDEX(INDIRECT("'"&$D12&"'!A:g"),$E12,COLUMN()-7))} -> #REF! | J12: {=IF(C12=0,"",INDEX(INDIRECT("'"&$D12&"'!A:g"),$E12,COLUMN()-7))} -> #REF! | K12: {=IF(C12=0,0,INDEX(INDIRECT("'"&$D12&"'!A:g"),$E12,COLUMN()-7))} -> #REF! | L12: {=IF(C12=0,0,INDEX(INDIRECT("'"&$D12&"'!A:g"),$E12,COLUMN()-7))} -> #REF! | M12: =M11+K12-L12 -> #N/A | N12: {=IF(C12=0,0,INDEX(INDIRECT("'"&$D12&"'!A:g"),$E12,COLUMN()-7))} -> #REF!
A13: =D13 -> #REF! | B13: =IF(C13=0,MATCH($G$2,INDIRECT("'"&A13&"'!A:A"),1),MATCH($G$2,INDIRECT("'"&A13&"'!A:A"),0)) -> #REF! | C13: =COUNTIF(INDIRECT("'"&A13&"'!A:A"),$G$2) -> #REF! | D13: =IF(COUNTIF(A$4:A12,A12)<C12,D12,IF(COUNTIF(INDIRECT("'"&D12+1&"'!A:A"),$G$2)>0,D12+1,IF(COUNTIF(INDIRECT("'"&D12+2&"'!A:A"),$G$2)>0,D12+2,IF(COUNTIF(INDIRECT("'"&D12+3&"'!A:A"),$G$2)>0,D12+3,IF(COUNTIF(INDIRECT("'"&D12+4&"'!A:A"),$G$2)>0,D12+4,IF(COUNTIF(INDIRECT("'"&D12+5&"'!A:A"),$G$2)>0,D12+5,IF(COUNTIF(INDIRECT("'"&D12+6&"'!A:A"),$G$2)>0,D12+6,IF(COUNTIF(INDIRECT("'"&D12+7&"'!A:A"),$G$2)>0,D12+7,IF(COUNTIF(INDIRECT("'"&D12+8&"'!A:A"),$G$2)>0,D12+8,IF(COUNTIF(INDIRECT("'"&D12+9&"'!A:A"),$G$2)>0,D12+9,D12+10)))))))))) -> #REF! | E13: =IF(C13=0,0,B13+COUNTIF(A$4:A13,A13)-1) -> #REF! | F13: =VLOOKUP(D13,档案!A:C,3,FALSE) -> #REF! | G13: =VLOOKUP(D13,档案!A:B,2,FALSE) -> #REF! | H13: {=IF(C13=0,"",INDEX(INDIRECT("'"&$D13&"'!A:g"),$E13,COLUMN()-7))} -> #REF! | I13: {=IF(C13=0,"",INDEX(INDIRECT("'"&$D13&"'!A:g"),$E13,COLUMN()-7))} -> #REF! | J13: {=IF(C13=0,"",INDEX(INDIRECT("'"&$D13&"'!A:g"),$E13,COLUMN()-7))} -> #REF! | K13: {=IF(C13=0,0,INDEX(INDIRECT("'"&$D13&"'!A:g"),$E13,COLUMN()-7))} -> #REF! | L13: {=IF(C13=0,0,INDEX(INDIRECT("'"&$D13&"'!A:g"),$E13,COLUMN()-7))} -> #REF! | M13: =M12+K13-L13 -> #N/A | N13: {=IF(C13=0,0,INDEX(INDIRECT("'"&$D13&"'!A:g"),$E13,COLUMN()-7))} -> #REF!
A14: =D14 -> #REF! | B14: =IF(C14=0,MATCH($G$2,INDIRECT("'"&A14&"'!A:A"),1),MATCH($G$2,INDIRECT("'"&A14&"'!A:A"),0)) -> #REF! | C14: =COUNTIF(INDIRECT("'"&A14&"'!A:A"),$G$2) -> #REF! | D14: =IF(COUNTIF(A$4:A13,A13)<C13,D13,IF(COUNTIF(INDIRECT("'"&D13+1&"'!A:A"),$G$2)>0,D13+1,IF(COUNTIF(INDIRECT("'"&D13+2&"'!A:A"),$G$2)>0,D13+2,IF(COUNTIF(INDIRECT("'"&D13+3&"'!A:A"),$G$2)>0,D13+3,IF(COUNTIF(INDIRECT("'"&D13+4&"'!A:A"),$G$2)>0,D13+4,IF(COUNTIF(INDIRECT("'"&D13+5&"'!A:A"),$G$2)>0,D13+5,IF(COUNTIF(INDIRECT("'"&D13+6&"'!A:A"),$G$2)>0,D13+6,IF(COUNTIF(INDIRECT("'"&D13+7&"'!A:A"),$G$2)>0,D13+7,IF(COUNTIF(INDIRECT("'"&D13+8&"'!A:A"),$G$2)>0,D13+8,IF(COUNTIF(INDIRECT("'"&D13+9&"'!A:A"),$G$2)>0,D13+9,D13+10)))))))))) -> #REF! | E14: =IF(C14=0,0,B14+COUNTIF(A$4:A14,A14)-1) -> #REF! | F14: =VLOOKUP(D14,档案!A:C,3,FALSE) -> #REF! | G14: =VLOOKUP(D14,档案!A:B,2,FALSE) -> #REF! | H14: {=IF(C14=0,"",INDEX(INDIRECT("'"&$D14&"'!A:g"),$E14,COLUMN()-7))} -> #REF! | I14: {=IF(C14=0,"",INDEX(INDIRECT("'"&$D14&"'!A:g"),$E14,COLUMN()-7))} -> #REF! | J14: {=IF(C14=0,"",INDEX(INDIRECT("'"&$D14&"'!A:g"),$E14,COLUMN()-7))} -> #REF! | K14: {=IF(C14=0,0,INDEX(INDIRECT("'"&$D14&"'!A:g"),$E14,COLUMN()-7))} -> #REF! | L14: {=IF(C14=0,0,INDEX(INDIRECT("'"&$D14&"'!A:g"),$E14,COLUMN()-7))} -> #REF! | M14: =M13+K14-L14 -> #N/A | N14: {=IF(C14=0,0,INDEX(INDIRECT("'"&$D14&"'!A:g"),$E14,COLUMN()-7))} -> #REF!
A15: =D15 -> #REF! | B15: =IF(C15=0,MATCH($G$2,INDIRECT("'"&A15&"'!A:A"),1),MATCH($G$2,INDIRECT("'"&A15&"'!A:A"),0)) -> #REF! | C15: =COUNTIF(INDIRECT("'"&A15&"'!A:A"),$G$2) -> #REF! | D15: =IF(COUNTIF(A$4:A14,A14)<C14,D14,IF(COUNTIF(INDIRECT("'"&D14+1&"'!A:A"),$G$2)>0,D14+1,IF(COUNTIF(INDIRECT("'"&D14+2&"'!A:A"),$G$2)>0,D14+2,IF(COUNTIF(INDIRECT("'"&D14+3&"'!A:A"),$G$2)>0,D14+3,IF(COUNTIF(INDIRECT("'"&D14+4&"'!A:A"),$G$2)>0,D14+4,IF(COUNTIF(INDIRECT("'"&D14+5&"'!A:A"),$G$2)>0,D14+5,IF(COUNTIF(INDIRECT("'"&D14+6&"'!A:A"),$G$2)>0,D14+6,IF(COUNTIF(INDIRECT("'"&D14+7&"'!A:A"),$G$2)>0,D14+7,IF(COUNTIF(INDIRECT("'"&D14+8&"'!A:A"),$G$2)>0,D14+8,IF(COUNTIF(INDIRECT("'"&D14+9&"'!A:A"),$G$2)>0,D14+9,D14+10)))))))))) -> #REF! | E15: =IF(C15=0,0,B15+COUNTIF(A$4:A15,A15)-1) -> #REF! | F15: =VLOOKUP(D15,档案!A:C,3,FALSE) -> #REF! | G15: =VLOOKUP(D15,档案!A:B,2,FALSE) -> #REF! | H15: {=IF(C15=0,"",INDEX(INDIRECT("'"&$D15&"'!A:g"),$E15,COLUMN()-7))} -> #REF! | I15: {=IF(C15=0,"",INDEX(INDIRECT("'"&$D15&"'!A:g"),$E15,COLUMN()-7))} -> #REF! | J15: {=IF(C15=0,"",INDEX(INDIRECT("'"&$D15&"'!A:g"),$E15,COLUMN()-7))} -> #REF! | K15: {=IF(C15=0,0,INDEX(INDIRECT("'"&$D15&"'!A:g"),$E15,COLUMN()-7))} -> #REF! | L15: {=IF(C15=0,0,INDEX(INDIRECT("'"&$D15&"'!A:g"),$E15,COLUMN()-7))} -> #REF! | M15: =M14+K15-L15 -> #N/A | N15: {=IF(C15=0,0,INDEX(INDIRECT("'"&$D15&"'!A:g"),$E15,COLUMN()-7))} -> #REF!
A16: =D16 -> #REF! | B16: =IF(C16=0,MATCH($G$2,INDIRECT("'"&A16&"'!A:A"),1),MATCH($G$2,INDIRECT("'"&A16&"'!A:A"),0)) -> #REF! | C16: =COUNTIF(INDIRECT("'"&A16&"'!A:A"),$G$2) -> #REF! | D16: =IF(COUNTIF(A$4:A15,A15)<C15,D15,IF(COUNTIF(INDIRECT("'"&D15+1&"'!A:A"),$G$2)>0,D15+1,IF(COUNTIF(INDIRECT("'"&D15+2&"'!A:A"),$G$2)>0,D15+2,IF(COUNTIF(INDIRECT("'"&D15+3&"'!A:A"),$G$2)>0,D15+3,IF(COUNTIF(INDIRECT("'"&D15+4&"'!A:A"),$G$2)>0,D15+4,IF(COUNTIF(INDIRECT("'"&D15+5&"'!A:A"),$G$2)>0,D15+5,IF(COUNTIF(INDIRECT("'"&D15+6&"'!A:A"),$G$2)>0,D15+6,IF(COUNTIF(INDIRECT("'"&D15+7&"'!A:A"),$G$2)>0,D15+7,IF(COUNTIF(INDIRECT("'"&D15+8&"'!A:A"),$G$2)>0,D15+8,IF(COUNTIF(INDIRECT("'"&D15+9&"'!A:A"),$G$2)>0,D15+9,D15+10)))))))))) -> #REF! | E16: =IF(C16=0,0,B16+COUNTIF(A$4:A16,A16)-1) -> #REF! | F16: =VLOOKUP(D16,档案!A:C,3,FALSE) -> #REF! | G16: =VLOOKUP(D16,档案!A:B,2,FALSE) -> #REF! | H16: {=IF(C16=0,"",INDEX(INDIRECT("'"&$D16&"'!A:g"),$E16,COLUMN()-7))} -> #REF! | I16: {=IF(C16=0,"",INDEX(INDIRECT("'"&$D16&"'!A:g"),$E16,COLUMN()-7))} -> #REF! | J16: {=IF(C16=0,"",INDEX(INDIRECT("'"&$D16&"'!A:g"),$E16,COLUMN()-7))} -> #REF! | K16: {=IF(C16=0,0,INDEX(INDIRECT("'"&$D16&"'!A:g"),$E16,COLUMN()-7))} -> #REF! | L16: {=IF(C16=0,0,INDEX(INDIRECT("'"&$D16&"'!A:g"),$E16,COLUMN()-7))} -> #REF! | M16: =M15+K16-L16 -> #N/A | N16: {=IF(C16=0,0,INDEX(INDIRECT("'"&$D16&"'!A:g"),$E16,COLUMN()-7))} -> #REF!
A17: =D17 -> #REF! | B17: =IF(C17=0,MATCH($G$2,INDIRECT("'"&A17&"'!A:A"),1),MATCH($G$2,INDIRECT("'"&A17&"'!A:A"),0)) -> #REF! | C17: =COUNTIF(INDIRECT("'"&A17&"'!A:A"),$G$2) -> #REF! | D17: =IF(COUNTIF(A$4:A16,A16)<C16,D16,IF(COUNTIF(INDIRECT("'"&D16+1&"'!A:A"),$G$2)>0,D16+1,IF(COUNTIF(INDIRECT("'"&D16+2&"'!A:A"),$G$2)>0,D16+2,IF(COUNTIF(INDIRECT("'"&D16+3&"'!A:A"),$G$2)>0,D16+3,IF(COUNTIF(INDIRECT("'"&D16+4&"'!A:A"),$G$2)>0,D16+4,IF(COUNTIF(INDIRECT("'"&D16+5&"'!A:A"),$G$2)>0,D16+5,IF(COUNTIF(INDIRECT("'"&D16+6&"'!A:A"),$G$2)>0,D16+6,IF(COUNTIF(INDIRECT("'"&D16+7&"'!A:A"),$G$2)>0,D16+7,IF(COUNTIF(INDIRECT("'"&D16+8&"'!A:A"),$G$2)>0,D16+8,IF(COUNTIF(INDIRECT("'"&D16+9&"'!A:A"),$G$2)>0,D16+9,D16+10)))))))))) -> #REF! | E17: =IF(C17=0,0,B17+COUNTIF(A$4:A17,A17)-1) -> #REF! | F17: =VLOOKUP(D17,档案!A:C,3,FALSE) -> #REF! | G17: =VLOOKUP(D17,档案!A:B,2,FALSE) -> #REF! | H17: {=IF(C17=0,"",INDEX(INDIRECT("'"&$D17&"'!A:g"),$E17,COLUMN()-7))} -> #REF! | I17: {=IF(C17=0,"",INDEX(INDIRECT("'"&$D17&"'!A:g"),$E17,COLUMN()-7))} -> #REF! | J17: {=IF(C17=0,"",INDEX(INDIRECT("'"&$D17&"'!A:g"),$E17,COLUMN()-7))} -> #REF! | K17: {=IF(C17=0,0,INDEX(INDIRECT("'"&$D17&"'!A:g"),$E17,COLUMN()-7))} -> #REF! | L17: {=IF(C17=0,0,INDEX(INDIRECT("'"&$D17&"'!A:g"),$E17,COLUMN()-7))} -> #REF! | M17: =M16+K17-L17 -> #N/A | N17: {=IF(C17=0,0,INDEX(INDIRECT("'"&$D17&"'!A:g"),$E17,COLUMN()-7))} -> #REF!
... A94: =D94 -> #REF! | B94: =IF(C94=0,MATCH($G$2,INDIRECT("'"&A94&"'!A:A"),1),MATCH($G$2,INDIRECT("'"&A94&"'!A:A"),0)) -> #REF! | C94: =COUNTIF(INDIRECT("'"&A94&"'!A:A"),$G$2) -> #REF! | D94: =IF(COUNTIF(A$4:A93,A93)<C93,D93,IF(COUNTIF(INDIRECT("'"&D93+1&"'!A:A"),$G$2)>0,D93+1,IF(COUNTIF(INDIRECT("'"&D93+2&"'!A:A"),$G$2)>0,D93+2,IF(COUNTIF(INDIRECT("'"&D93+3&"'!A:A"),$G$2)>0,D93+3,IF(COUNTIF(INDIRECT("'"&D93+4&"'!A:A"),$G$2)>0,D93+4,IF(COUNTIF(INDIRECT("'"&D93+5&"'!A:A"),$G$2)>0,D93+5,IF(COUNTIF(INDIRECT("'"&D93+6&"'!A:A"),$G$2)>0,D93+6,IF(COUNTIF(INDIRECT("'"&D93+7&"'!A:A"),$G$2)>0,D93+7,IF(COUNTIF(INDIRECT("'"&D93+8&"'!A:A"),$G$2)>0,D93+8,IF(COUNTIF(INDIRECT("'"&D93+9&"'!A:A"),$G$2)>0,D93+9,D93+10)))))))))) -> #REF! | E94: =IF(C94=0,0,B94+COUNTIF(A$4:A94,A94)-1) -> #REF! | F94: =VLOOKUP(D94,档案!A:C,3,FALSE) -> #REF! | G94: =VLOOKUP(D94,档案!A:B,2,FALSE) -> #REF! | H94: {=IF(C94=0,"",INDEX(INDIRECT("'"&$D94&"'!A:g"),$E94,COLUMN()-7))} -> #REF! | I94: {=IF(C94=0,"",INDEX(INDIRECT("'"&$D94&"'!A:g"),$E94,COLUMN()-7))} -> #REF! | J94: {=IF(C94=0,"",INDEX(INDIRECT("'"&$D94&"'!A:g"),$E94,COLUMN()-7))} -> #REF! | K94: {=IF(C94=0,0,INDEX(INDIRECT("'"&$D94&"'!A:g"),$E94,COLUMN()-7))} -> #REF! | L94: {=IF(C94=0,0,INDEX(INDIRECT("'"&$D94&"'!A:g"),$E94,COLUMN()-7))} -> #REF! | M94: =M93+K94-L94 -> #N/A | N94: {=IF(C94=0,0,INDEX(INDIRECT("'"&$D94&"'!A:g"),$E94,COLUMN()-7))} -> #REF!

Sheet 9
A1: 9 | B1: =VLOOKUP(A1,档案!A:B,2,FALSE)&"流水明细" -> 农商行豹澥支行310028流水明细
A2: 日期 | B2: 摘要 | C2: 收支类别 | D2: 收款金额 | E2: 付款金额 | F2: 余额 | G2: 备注
A3: 45658 | B3: 期初余额 | F3: 758026
A4: 45659 | B4: 付曾江利2024年11月工资 | C4: 付日常费用 | E4: 7347.01 | F4: =F3+D4-E4 -> 750678.99
A5: 45659 | B5: 销售部王炳熙报销11月招待费 | C5: 项目成本 | E5: 483 | F5: =F4+D5-E5 -> 750195.99
A6: 45660 | B6: 综合部蒋霞报销青海资料员配备台式电脑采购费，快递费--个人 | C6: 付日常费用 | E6: 2340.4 | F6: =F5+D6-E6 -> 747855.59
A7: 45660 | B7: 综合部蒋霞报销2024.7-11月外出办事交通费--个人 | C7: 付日常费用 | E7: 201.6 | F7: =F6+D7-E7 -> 747653.99
A8: 45660 | B8: 商务部周奇报销重碱车间新增碳化塔（设备、电气、仪表、工艺管道）安装项目预算费用--个人 | C8: 项目成本 | E8: 700 | F8: =F7+D8-E8 -> 746953.99
A9: 45660 | B9: 商务部周奇报销青海发投轻、重灰汽轴修复项目广联达预算费--个人 | C9: 项目成本 | E9: 850 | F9: =F8+D9-E9 -> 746103.99
A10: 45660 | B10: 商务部周奇报销螃蟹，臭桂鱼小林总--个人 | C10: 项目成本 | E10: 1540 | F10: =F9+D10-E10 -> 744563.99
A11: 45660 | B11: 销售部周嘉琦报销湘钢动力厂招待费及烟--个人 | C11: 项目成本 | E11: 1390 | F11: =F10+D11-E11 -> 743173.99
A12: 45660 | B12: 商务部肖登伍报销青海发投招标文件打印费，住宿费，生活用品--个人 | C12: 项目成本 | E12: 633 | F12: =F11+D12-E12 -> 742540.99
A13: 45660 | B13: 商务部肖登伍报销青海发投12.10-12.18差旅费--个人 | C13: 项目成本 | E13: 2083.82 | F13: =F12+D13-E13 -> 740457.17
A14: 45660 | B14: 商务部肖登伍报销内蒙古看现场11.26-11.30差旅费--个人 | C14: 项目成本 | E14: 1701.99 | F14: =F13+D14-E14 -> 738755.18
A15: 45660 | B15: 生产部黄国恩报销12.12-12.13山西晋中考试回日照钢铁交通费--个人 | C15: 项目成本 | E15: 311.5 | F15: =F14+D15-E15 -> 738443.68
... A47: 45667 | B47: ETC扣款 | C47: 项目成本 | E47: 218.47 | F47: =F46+D47-E47 -> 232369.35
A48: 45667 | B48: 收到武汉浦发转款 | C48: 他行转入或存现 | D48: 300000 | F48: =F47+D48-E48 -> 532369.35
A49: 45667 | B49: 综合部蒋霞用款武汉开明与丁超期案二审开庭传票公告费付刘梦君--个人 | C49: 付日常费用 | E49: 140 | F49: =F48+D49-E49 -> 532229.35
A50: 45667 | B50: 综合部蒋霞报销湖北开明，武汉开明2025年1月办公费--个人 | C50: 付日常费用 | E50: 835.18 | F50: =F49+D50-E50 -> 531394.17
A51: 45667 | B51: 综合部蒋霞报销10.5国庆寄合同周英柱快递费--个人 | C51: 付日常费用 | E51: 13 | F51: =F50+D51-E51 -> 531381.17
A52: 45667 | B52: 生产部周英柱报销伊犁钢铁12.17-12.18差旅费--公司 | C52: 项目成本 | E52: 1141 | F52: =F51+D52-E52 -> 530240.17
A53: 45667 | B53: 销售部燕志远报销12.5-12.6原料厂设备招待费--个人 | C53: 项目成本 | E53: 256 | F53: =F52+D53-E53 -> 529984.17
A54: 45667 | B54: 销售部燕志远报销12.20北港新材料招待费--个人 | C54: 项目成本 | E54: 300 | F54: =F53+D54-E54 -> 529684.17
A55: 45667 | B55: 商务部熊艳用款2024.12招待费付林小意--个人 | C55: 项目成本 | E55: 1500 | F55: =F54+D55-E55 -> 528184.17
A56: 45667 | B56: 生产部林家祥报销伊犁钢铁1.6-1.8交通费--个人 | C56: 项目成本 | E56: 694 | F56: =F55+D56-E56 -> 527490.17
A57: 45667 | B57: 生产部喻志明报销湘潭瑞通12.18-12.19交通费--个人 | C57: 项目成本 | E57: 441.5 | F57: =F56+D57-E57 -> 527048.67
A58: 45667 | B58: 生产部饶凯报销江西亚东12.17交通费--个人 | C58: 项目成本 | E58: 103.1 | F58: =F57+D58-E58 -> 526945.57
A59: 45667 | B59: 生产部马全花用款青海发投11.20-12.10打印费及装订费付德令哈宏冉图文广告店（个体工商户）--个人 | C59: 项目成本 | E59: 627.8 | F59: =F58+D59-E59 -> 526317.77
A60: 45667 | B60: 生产部李权智用款江西亚东外协人员杜宏工资--个人 | C60: 项目成本 | E60: 7425 | F60: =F59+D60-E60 -> 518892.77
... A77: 45670 | B77: ETC扣款 | C77: 项目成本 | E77: 35.15 | F77: =F76+D77-E77 -> 164617.39
A78: 45670 | B78: 收到李权智转款(周英柱租木板押金) | C78: 其他收款 | D78: 1080 | F78: =F77+D78-E78 -> 165697.39
A79: 45670 | B79: ETC扣款 | C79: 项目成本 | E79: 128.25 | F79: =F78+D79-E79 -> 165569.14
A80: 45671 | B80: 收到武汉瑞收农业科技有限公司贴现款（原合计金额461200，扣手续费4700） | C80: 他行转入或存现 | D80: 456500 | F80: =F79+D80-E80 -> 622069.14
A81: 45671 | B81: 销售部伍平报销11.10-12.1江苏永钢，九江萍钢等项目差旅费--个人 | C81: 项目成本 | E81: 3776.5 | F81: =F80+D81-E81 -> 618292.64
A82: 45671 | B82: 销售部伍平报销12.7-1.1江苏永钢等项目差旅费--个人 | C82: 项目成本 | E82: 4401 | F82: =F81+D82-E82 -> 613891.64
A83: 45671 | B83: 销售部吕战宇报销12.7-12.12德令哈差旅费--个人 | C83: 项目成本 | E83: 1091.5 | F83: =F82+D83-E83 -> 612800.14
A84: 45671 | B84: 销售部燕志远报销12.1-12.4北海到武汉交通费--个人 | C84: 项目成本 | E84: 1250 | F84: =F83+D84-E84 -> 611550.14
A85: 45671 | B85: 销售部周嘉琦报销12.1湘潭-12.3武汉交通费--个人 | C85: 项目成本 | E85: 430 | F85: =F84+D85-E85 -> 611120.14
A86: 45671 | B86: 销售部杨春龙报销11.30武汉-12.23武汉差旅费--个人 | C86: 项目成本 | E86: 5586.88 | F86: =F85+D86-E86 -> 605533.26
A87: 45671 | B87: 销售部杨春龙报销12.7号日照钢铁体检费--个人 | C87: 项目成本 | E87: 110 | F87: =F86+D87-E87 -> 605423.26
A88: 45671 | B88: 付武汉公司2024.11月员工生活费 | C88: 付日常费用 | E88: 11621 | F88: =F87+D88-E88 -> 593802.26
A89: 45671 | B89: 转王先梅邮政 | C89: 转出他行或提现 | E89: 50000 | F89: =F88+D89-E89 -> 543802.26
A90: 45671 | B90: 转湖北工行西山支行 | C90: 转出他行或提现 | E90: 250000 | F90: =F89+D90-E90 -> 293802.26
A91: 45671 | B91: 转武汉光大 | C91: 转出他行或提现 | E91: 60000 | F91: =F90+D91-E91 -> 233802.26
