Workbook
Name 收支类别: [1]资金账户!$K$3:$W$3

Sheet 总表
A1: 2026年3-9月份期资金使用计划表
A2: 项目内容 | B2: 26年3-9月计划金额 | C2: 25年3-9月实际金额
A3: 1、销售回款（2023及以前） | B3: =8269029.42*10%+1437623.09*50% -> 1545714.5 | C3: 0
A4: 2、销售回款（2024） | B4: =3890399.61*60% -> 2334239.8 | C4: ='25年实际'!J5 -> 11933112
A5: 3、销售回款（2025） | B5: =2437266.86*0.7+3790321.13*0.5 -> 3601247.4 | C5: ='25年实际'!J6 -> 1603895.7
A6: 4、销售回款（2026） | B6: =待完工项目!V25 -> 1333373.8
A7: 5、保证金回款（2026) | B7: =687751.86*10% -> 68775.186 | C7: ='25年实际'!J7 -> 2190511.6
A8: 6、其他回款（借支、付款 退回等） | B8: =20000*6 -> 120000 | C8: ='25年实际'!J8 -> 319280.99
A9: 7、旧物、利息及补贴收入 | B9: 100000 | C9: ='25年实际'!J9 -> 689425.91
A10: 8、贷款增加 | B10: 0 | C10: ='25年实际'!J10 -> 1800000
A11: 合计 | B11: =SUM(B3:B10) -> 9103350.6 | C11: =SUM(C3:C10) -> 18536226
A12: 项目内容 | B12: 26年3-9月 | C12: 25年3-9月
A13: 1、日常费用支出 | B13: =450000*6 -> 2700000 | C13: ='25年实际'!J13 -> 2575502.7
A14: 2、项目成本支出 | B14: =8000000*0.8 -> 6400000 | C14: ='25年实际'!J14 -> 15713420
A15: 3、保证金支出 | B15: 2000000 | C15: ='25年实际'!J15 -> 1868812.7
A16: 4、还本金额及利息 | B16: =380000*2+330000*4 -> 2080000 | C16: ='25年实际'!J16 -> 2437950
A17: 其中：当期本金 | B17: =B16*54% -> 1123200 | C17: ='25年实际'!J17 -> 1186493.8
A18: ：利息 | B18: =B16*46% -> 956800 | C18: ='25年实际'!J18 -> 1251456.3
A19: 5、贷款居间及过桥费 | B19: 0 | C19: ='25年实际'!J19 -> 363000
A20: 6、贴现 | B20: =20000*6 -> 120000 | C20: ='25年实际'!J20 -> 46457.83
A21: 7、其他支出（借支+押金） | B21: 200000 | C21: ='25年实际'!J21 -> 131450
A22: 8、购置车辆 | B22: 33000 | C22: ='25年实际'!J22 -> 0
A23: 9、其他（林总+小张总） | B23: =50000*6 -> 300000 | C23: ='25年实际'!J23 -> 794500
A24: 合计 | B24: =SUM(B13:B16)+B19+B20+B21+B23+B22 -> 13833000 | C24: =SUM(C13:C16)+C19+C20+C21+C23+C22 -> 23931093
B25: =B11-B24 -> -4729649.4 | C25: =C11-C24 -> -5394866.7
A26: 业绩需求： | B26: =-B25/0.2/0.8 -> 29560309

Sheet 25年实际
A1: 2025年3-9月份
A2: 资金总流入 | B2: 项目内容 | C2: 3月 | D2: 4月 | E2: 5月 | F2: 6月 | G2: 7月 | H2: 8月 | I2: 9月 | J2: 合计 | K2: 占比
B3: 1、销售回款（2024） | C3: 1386467.1 | D3: 999601.37 | E3: 981783.12 | F3: 1906978.8 | G3: 3850709.6 | H3: 4551712.6 | I3: 3749078.8 | J3: =SUM(C3:I3) -> 17426331
B4: 1、销售回款（2025） | C4: 2216588.1 | D4: 2606168.1 | E4: 2446647.7 | F4: 1011623.5 | G4: 1950708.5 | H4: 1287899.4 | I4: 2017372.7 | J4: =SUM(C4:I4) -> 13537008 | K4: =J4/J11 -> 0.7303001
B5: 其中 ：2025年回2024年及以前合同款 | C5: =C4-C6 -> 2173588.1 | D5: =D4-D6 -> 2248784.1 | E5: =E4-E6 -> 2446647.7 | F5: =F4-F6 -> 850473.46 | G5: =G4-G6 -> 1810108.5 | H5: =H4-H6 -> 996799.39 | I5: =I4-I6 -> 1406711 | J5: =SUM(C5:I5) -> 11933112 | K5: =J5/J4 -> 0.88151771
B6: ： 2025年回2025年合同款 | C6: 43000 | D6: 357384 | E6: 0 | F6: 161150 | G6: 140600 | H6: 291100 | I6: 610661.67 | J6: =SUM(C6:I6) -> 1603895.7 | K6: =J6/J4 -> 0.11848229
B7: 2、保证金回款（2025) | C7: 163700 | D7: 92000.27 | E7: 146400 | F7: 1039498 | G7: 316590 | H7: 135000 | I7: 297323.3 | J7: =SUM(C7:I7) -> 2190511.6 | K7: =J7/J11 -> 0.11817462
B8: 3、其他回款（借支、付款 退回等） | C8: 18268.91 | D8: 99160.61 | E8: 102093.74 | F8: 22769.51 | G8: 43145.04 | H8: 3566.26 | I8: 30276.92 | J8: =SUM(C8:I8) -> 319280.99 | K8: =J8/J11 -> 0.017224703
B9: 4、旧物、利息及补贴收入 | C9: 69424.54 | D9: 75166.7 | E9: 76644.92 | F9: 79364.92 | G9: 10000 | H9: 132266 | I9: 246558.83 | J9: =SUM(C9:I9) -> 689425.91 | K9: =J9/J11 -> 0.037193434
B10: 5、贷款增加 | C10: 0 | D10: =-2000000+2200000-3800000+2000000 -> -1600000 | E10: =1000000-700000 -> 300000 | F10: =3000000+1000000 -> 4000000 | G10: 2000000 | H10: =1800000-2000000 -> -200000 | I10: =2900000-8000000+7900000-6000000+500000 -> -2700000 | J10: =SUM(C10:I10) -> 1800000 | K10: =J10/J11 -> 0.097107143
B11: 合计 | C11: =C4+SUM(C7:C10) -> 2467981.6 | D11: =D4+SUM(D7:D10) -> 1272495.7 | E11: =E4+SUM(E7:E10) -> 3071786.4 | F11: =F4+SUM(F7:F10) -> 6153255.9 | G11: =G4+SUM(G7:G10) -> 4320443.5 | H11: =H4+SUM(H7:H10) -> 1358731.6 | I11: =I4+SUM(I7:I10) -> -108468.25 | J11: =J4+SUM(J7:J10) -> 18536226 | K11: 1
A12: 资金总流出 | B12: 项目内容 | C12: 3月 | D12: 4月 | E12: 5月 | F12: 6月 | G12: 7月 | H12: 8月 | I12: 9月 | J12: 合计
B13: 1、日常费用支出 | C13: 106028.95 | D13: 872381.25 | E13: 83147.73 | F13: 673960.85 | G13: 77660.31 | H13: 403317.69 | I13: 359005.9 | J13: =SUM(C13:I13) -> 2575502.7 | K13: =J13/J24 -> 0.10762161
B14: 2、项目成本支出 | C14: 1129950.1 | D14: 1861772.7 | E14: 2525944.8 | F14: 2132243.7 | G14: 4138552.2 | H14: 2232474.6 | I14: 1692481.8 | J14: =SUM(C14:I14) -> 15713420 | K14: =J14/J24 -> 0.65661104
B15: 3、保证金支出 | C15: 397075 | D15: 485960 | E15: 254900 | F15: 291000 | G15: 255000 | H15: 149877.67 | I15: 35000 | J15: =SUM(C15:I15) -> 1868812.7 | K15: =J15/J24 -> 0.078091404
B16: 4、还本金额及利息 | C16: 360666.7 | D16: 310789.24 | E16: 300132.98 | F16: 372570.63 | G16: 310950.06 | H16: 334485.34 | I16: 448355.07 | J16: =SUM(C16:I16) -> 2437950 | K16: =J16/J24 -> 0.10187374
B17: 其中：当期本金 | C17: 161596.79 | D17: 161808.78 | E17: 162036.1 | F17: 162278.86 | G17: 162537.07 | H17: 162810.83 | I17: 213425.32 | J17: =SUM(C17:I17) -> 1186493.8 | K17: =J17/J16 -> 0.48667681
B18: ：利息 | C18: 199069.91 | D18: 148980.46 | E18: 138096.88 | F18: 210291.77 | G18: 148412.99 | H18: 171674.51 | I18: 234929.75 | J18: =SUM(C18:I18) -> 1251456.3 | K18: =J18/J16 -> 0.51332319
B19: 5、贷款居间及过桥费 | C19: 0 | D19: 0 | E19: 0 | F19: 0 | G19: 0 | H19: 41000 | I19: 322000 | J19: =SUM(C19:I19) -> 363000 | K19: =J19/J24 -> 0.015168551
B20: 6、贴现（贴现总额14033207.31元） | C20: 0 | D20: 11160 | E20: 10609.83 | F20: 0 | G20: 9268 | H20: 4160 | I20: 11260 | J20: =SUM(C20:I20) -> 46457.83 | K20: =J20/J24 -> 0.0019413167
B21: 7、其他支出（借支+押金） | C21: 0 | D21: 6000 | E21: 91750 | F21: 7000 | G21: 16700 | H21: 10000 | I21: 0 | J21: =SUM(C21:I21) -> 131450 | K21: =J21/J24 -> 0.005492854
B22: 8、购置房产 | C22: 0 | D22: 0 | E22: 0 | F22: 0 | G22: 0 | H22: 0 | I22: 0 | J22: =SUM(C22:I22) -> 0 | K22: =J22/J24 -> 0
B23: 9、其他（林总+小张总） | C23: 120000 | D23: 120000 | E23: 0 | F23: 152000 | G23: 150000 | H23: 50000 | I23: 202500 | J23: =SUM(C23:I23) -> 794500 | K23: =J23/J24 -> 0.033199486
B24: 合计 | C24: =SUM(C13:C16)+C19+C20+C21+C23+C22 -> 2113720.8 | D24: =SUM(D13:D16)+D19+D20+D21+D23+D22 -> 3668063.2 | E24: =SUM(E13:E16)+E19+E20+E21+E23+E22 -> 3266485.4 | F24: =SUM(F13:F16)+F19+F20+F21+F23+F22 -> 3628775.2 | G24: =SUM(G13:G16)+G19+G20+G21+G23+G22 -> 4958130.6 | H24: =SUM(H13:H16)+H19+H20+H21+H23+H22 -> 3225315.3 | I24: =SUM(I13:I16)+I19+I20+I21+I23+I22 -> 3070602.7 | J24: =SUM(J13:J16)+J19+J20+J21+J23+J22 -> 23931093 | K24: 1
A25: 总流出的 其中：投资活动流出 | B25: 项目内容 | C25: 3月 | D25: 4月 | E25: 5月 | F25: 6月 | G25: 7月 | H25: 8月 | I25: 9月 | J25: 合计
B26: 项目内容 | C26: 0 | D26: 0 | E26: 900000 | F26: 1200000 | G26: 0 | H26: 0 | I26: 0 | J26: =SUM(C26:I26) -> 2100000 | K26: =J26/J24 -> 0.087751946
A27: 资金净流量 | C27: =C11-C24 -> 354260.81 | D27: =D11-D24 -> -2395567.5 | E27: =E11-E24 -> -194699.02 | F27: =F11-F24 -> 2524480.7 | G27: =G11-G24 -> -637687.06 | H27: =H11-H24 -> -1866583.6 | I27: =I11-I24 -> -3179071 | J27: =J11-J24 -> -5394866.7

Sheet 待完工项目
A1: 合同名称 | B1: 合同编号 | C1: 创建时间 | D1: 施工状态 | E1: 甲方 | F1: 完工日期（产值上报） | G1: 乙方 | H1: 含税合同额(元) | I1: 税率(%) | J1: 结算应收款(元) | K1: 结算未开票 | L1: 累计开票 | M1: 开票应收款(元) | N1: 项目收款金额 | O1: 质保金(元) | P1: 保证金支付金额 | Q1: 保证金退还金额 | R1: 待退保证金 | S1: 验收日期 | T1: 合同工 期 | U1: 预计完工日期 | V1: 3-9月份回款比例
A2: 湘潭瑞通球团2026 年 2 月回转窑带托轮车削及调整项目26-009 | B2: KMX2026227-009 | C2: 2026-02-27 15:17 | D2: 施工中 | E2: 湘潭瑞通球团有限公司 | G2: 武汉开明 | H2: 163850 | I2: 13% | J2: 0 | K2: 0 | L2: 0 | M2: 0 | N2: 0 | P2: 5000 | Q2: 0 | R2: 5000 | T2: 189天 | V2: =H2*0.7 -> 114695
A3: 江西福丰新材料科技有限公司反应炉托轮、轮带维修及调整项目26-008 | B3: KMX2026127-008 | C3: 2026-01-27 15:01 | D3: 施工中 | E3: 江西福丰新材料科技有限公司 | G3: 武汉开明高新科技有限公司 | H3: 300000 | I3: 9% | J3: 0 | K3: 0 | L3: 0 | M3: 0 | N3: 0 | O3: 15000 | P3: 0 | Q3: 0 | R3: 0 | V3: 0
A4: 青海盐湖镁业纯碱厂6#压缩机委外维护保养项目26-007 | B4: KMX2026122-007 | C4: 2026-01-22 10:56 | D4: 待入场 | E4: 青海盐湖镁业有限公司 | G4: 武汉开明高新科技有限公司 | H4: 608000 | I4: 13% | J4: 0 | K4: 0 | L4: 0 | M4: 0 | N4: 0 | O4: 60800 | P4: 0 | Q4: 0 | R4: 0 | T4: 30天
A5: 盐湖海纳甘河水泥厂波纹膨胀节、管道更换项目 | B5: KMX2026122-006 | C5: 2026-01-22 09:41 | D5: 施工中 | E5: 青海盐湖海纳化工有限公司 | G5: 武汉开明高新科技有限公司 | H5: 320000 | I5: 9% | J5: 0 | K5: 0 | L5: 0 | M5: 0 | N5: 0 | O5: 32000 | P5: 0 | Q5: 0 | R5: 0 | T5: 20天
A6: 设备更新改造-甘河水泥厂4600T/D回转窑维修合同 | B6: KMX2026121-005 | C6: 2026-01-21 15:16 | D6: 施工中 | E6: 青海盐湖海纳化工有限公司 | G6: 武汉开明高新科技有限公司 | H6: 415000 | I6: 9% | J6: 0 | K6: 0 | L6: 0 | M6: 0 | N6: 0 | O6: 41500 | P6: 0 | Q6: 0 | R6: 0 | T6: 天
A7: 回转窑外委检测施工项目 | B7: KMX2026120-004 | C7: 2026-01-20 09:10 | D7: 施工中 | E7: 贵州凯里瑞安建材有限公司 | G7: 武汉开明高新科技有限公司 | H7: 98368 | I7: 6% | J7: 0 | K7: 0 | L7: 0 | M7: 0 | N7: 0 | P7: 0 | Q7: 0 | R7: 0 | T7: 天
A8: 福建鼎信托轮轮带剥落掉块焊补维修 | B8: KMX2026116-003 | C8: 2026-01-16 10:03 | D8: 待入场 | E8: 福建鼎信实业有限公司 | G8: 武汉开明高新科技有限公司 | H8: 40000 | I8: 13% | J8: 0 | K8: 0 | L8: 0 | M8: 0 | N8: 0 | O8: 2000 | P8: 0 | Q8: 0 | R8: 0 | T8: 25天
A9: 青海盐湖镁业有限公司纯碱厂轻灰煅烧炉炉头滚圈更换委外维修合同25-083 | B9: KMX20251217 -083 | C9: 2025-12-17 20:02 | D9: 待入场 | E9: 青海盐湖镁业有限公司 | G9: 武汉开明高新科技有限公司 | H9: 346000 | I9: 13% | J9: 0 | K9: 0 | L9: 0 | M9: 0 | N9: 0 | O9: 34600 | P9: 0 | Q9: 0 | R9: 0 | T9: 维修周期为15天/台
A10: 青海盐湖镁业纯碱厂细粉回用重新结晶提质项目设备安装 | B10: KMX20251210 - 082 | C10: 2025-12-10 09:06 | D10: 施工中 | E10: 青海盐湖镁业有限公司 | G10: 武汉开明高新科技有限公司 | H10: 460000 | I10: 9% | J10: 0 | K10: 0 | L10: 0 | M10: 0 | N10: 0 | P10: 0 | Q10: 0 | R10: 0 | T10: 天
A11: 山东圣川-武汉开明-回转窑检修合同25-081 | B11: KMX2025125-081 | C11: 2025-12-05 15:55 | D11: 部分施工 | E11: 山东圣川新材料科技股份有限公司 | G11: 武汉开明高新科技有限公司 | H11: 60000 | I11: 9% | J11: 0 | K11: 0 | L11: 0 | M11: 0 | N11: 0 | P11: 0 | Q11: 0 | R11: 0 | T11: 10天
A12: 新疆宜化4#5#电石炉技改项目安装工程 | B12: KMX2025121-080 | C12: 2025-12-01 09:04 | D12: 施工中 | E12: 新疆宜化化工有限公司 | G12: 武汉开明高新科技有限公司 | H12: 3808371.2 | I12: 9% | J12: -95300 | K12: -112800 | L12: 112800 | M12: 17500 | N12: 95300 | O12: 114251.14 | P12: 0 | Q12: 0 | R12: 0 | T12: 天 | V12: =H12*0.8*0.5*0.8 -> 1218678.8
A13: 广安台泥回转窑调整及拖轮/轮带在线调整合同 | B13: KMX20251119-079 | C13: 2025-11-19 16:02 | D13: 施工中 | E13: 广安昌兴水泥有限公司 | G13: 武汉开明高新科技有限公司 | H13: 228900 | I13: 9% | J13: 0 | K13: 0 | L13: 0 | M13: 0 | N13: 0 | O13: 11445 | P13: 0 | Q13: 0 | R13: 0 | T13: 天
A14: 江苏金峰水泥设备修复年度合同25-075 | B14: KMX20251017-075 | C14: 2025-10-17 13:29 | D14: 部分施工 | E14: 江苏金峰水泥集团有限公司 | F14: 2025-10-27 | G14: 武汉开明高新科技有限公司 | H14: 87912 | I14: 13% | J14: -65686.5 | K14: -65686.5 | L14: 65686.5 | M14: 0 | N14: 65686.5 | O14: 2637.36 | P14: 0 | Q14: 0 | R14: 0 | S14: 2025-12-20 | T14: 天
A15: 阜阳皖润电力有限公司磨煤机大齿轮安全防护隐患治理项目 | B15: KMX2025101 - 073 | C15: 2025-10-01 09:00 | D15: 部分施工 | E15: 阜阳皖润电力有限公司 | F15: 2025-11-11 | G15: 武汉开明高新科技有限公司 | H15: 454000 | I15: 9% | J15: 42600 | K15: 42600 | L15: 99400 | M15: 0 | N15: 99400 | O15: 0 | P15: 0 | Q15: 0 | R15: 0 | T15: 天
A16: 池州恒鑫材料科技有限公司回转窑托轮、挡轮更换和维修项目 | B16: KMX250721-061 | C16: 2025-07-21 17:15 | D16: 施工中 | E16: 池州恒鑫材料科技有限公司 | F16: 2025-12-01 | G16: 武汉开明高新科技有限公司 | H16: 306000 | I16: 9% | J16: -197800 | K16: 0 | L16: 0 | M16: -197800 | N16: 197800 | P16: 6120 | Q16: 0 | R16: 6120 | S16: 2025-11-09 | T16: 天
A17: 芜湖新兴铸管炼铁部烧结混合机隐患治理项目 | B17: KMX250715-059 | C17: 2025-07-15 16:35 | D17: 部分施工 | E17: 芜湖新兴铸管有限责任公司 | G17: 武汉开明高新科技有限公司 | H17: 155000 | I17: 13% | J17: 0 | K17: 0 | L17: 0 | M17: 0 | N17: 0 | O17: 15500 | P17: 0 | Q17: 0 | R17: 0 | T17: 天
A18: 内蒙古宜化转化器总管更换安装项目 | B18: KMX250711-057 | C18: 2025-07-11 09:03 | D18: 部分施工 | E18: 内蒙古宜化化工有限公司 | F18: 45900 | G18: 湖北岚丹建设工程有限公司 | H18: 850000 | I18: 9% | J18: -325543.2 | K18: -325543.2 | L18: 325543.2 | M18: 0 | N18: 325543.2 | P18: 85000 | Q18: 0 | R18: 85000 | T18: 天
A19: 青海发投碱业有限公司热电车间锅炉喷水减温器更换项目 | B19: KMX250618-050 | C19: 2025-06-18 15:33 | D19: 部分施工 | E19: 青海发投碱业有限公司 | G19: 江苏唐电电力有限公司 | H19: 350000 | I19: 9% | J19: 0 | K19: 0 | L19: 0 | M19: 0 | N19: 0 | O19: 35000 | P19: 500 | Q19: 0 | R19: 500 | T19: 天
A20: 江西玉山万年青回转窑维修项目 | B20: KMX250610-043 | C20: 2025-06-10 09:34 | D20: 部分施工 | E20: 江西玉山万年青水泥有限公司 | G20: 武汉开明高新科技有限公司 | H20: 195000 | I20: 13% | J20: 175000 | K20: 175000 | L20: 0 | M20: 0 | N20: 0 | O20: 19500 | P20: 10000 | Q20: 0 | R20: 10000 | S20: 2025-08-29 | T20: 天
A21: 河南华润电力首阳山有限公司2024 年-2025 年磨煤机大齿轮修理项目 | B21: KMX2503014-018-XF | C21: 2025-03-14 15:40 | D21: 部分施工 | E21: 河南华润电力首阳山有限公司 | F21: 2025-03-28 | G21: 武汉开明高新科技有限公司 | H21: 90000 | I21: 13% | J21: 3000 | K21: 0 | L21: 30000 | M21: 3000 | N21: 27000 | O21: 9000 | P21: 0 | Q21: 0 | R21: 0 | T21: 天
A22: 青海发投碱业有限公司重灰2#、3#、5#重灰炉炉头总成技改项目 | B22: KMX250307-014-XF | C22: 2025-03-07 17:28 | D22: 施工中 | E22: 青海发投碱业有限公司 | G22: 武汉开明高新科技有限公司 | H22: 560000 | I22: 9% | J22: -320499.6 | K22: -534166 | L22: 534166 | M22: 213666.4 | N22: 320499.6 | P22: 84000 | Q22: 84000 | R22: 0 | T22: 天
A23: 萍乡萍钢安源钢铁有限公司08m2烧结混合机、制粒机进出口轮带堆焊修复项目检修承包合同 | B23: KMX250226-012-XF | C23: 2025-02-26 11:28 | D23: 部分施工 | E23: 萍乡萍钢安源钢铁有限公司 | G23: 武汉开明高新科技有限公司 | H23: 86000 | I23: 9% | J23: 0 | K23: 0 | L23: 0 | M23: 0 | N23: 0 | P23: 0 | Q23: 0 | R23: 0 | T23: 天
A24: 日照钢铁控股集团有限公司+长型材制造部压力容器更换项 目 | B24: KMX250210-007-XF | C24: 2025-02-10 10:05 | D24: 待入场 | E24: 日照钢铁有限公司 | G24: 武汉开明高新科技有限公司 | H24: 74000 | I24: 9% | J24: 0 | K24: 0 | L24: 0 | M24: 0 | N24: 0 | O24: 3700 | P24: 0 | Q24: 0 | R24: 0 | T24: 天
G25: 合计金额： | H25: =SUBTOTAL(9,H2:H24) -> 10056401 | I25: =SUBTOTAL(9,I2:I24) -> 0 | J25: =SUBTOTAL(9,J2:J24) -> -784229.3 | K25: =SUBTOTAL(9,K2:K24) -> -820595.7 | L25: =SUBTOTAL(9,L2:L24) -> 1167595.7 | M25: =SUBTOTAL(9,M2:M24) -> 36366.4 | N25: =SUBTOTAL(9,N2:N24) -> 1131229.3 | O25: =SUBTOTAL(9,O2:O24) -> 396933.5 | ... V25: =SUBTOTAL(9,V2:V24) -> 1333373.8
