Workbook

Sheet 保证金登记
C1: 其他应收明细表
A2: 序号 | B2: 编号 | C2: 月份 | D2: 账龄 | E2: 支付日期 | F2: 部门 | G2: 经办人 | H2: 公司名称 | I2: 公司名称2 | J2: 支付金额 | K2: 公司 | L2: 支付方式 | M2: 支付类型 | N2: 退款金额/ 发票冲账 | O2: 未退余额 | P2: 退款时间 | Q2: 退回月份 | R2: 未退原因 | S2: 备注 | T2: 省份 | U2: 业务经理 | V2: 联系人 | W2: 中标结果 | X2: 业务员 | Y2: 支付状态
A3: 182 | B3: BZJ-0001 | C3: 42370 | D3: =IF(TODAY()-E3<60,"2个月内",IF(TODAY()-E3<180,"3-6个月",IF(TODAY()-E3<360,"6个月-1年","一年以上"))) -> 一年以上 | H3: 三门峡腾跃同力水泥有限公司 | I3: 三门峡腾跃同力水泥有限公司 | J3: 1000 | K3: 武汉 | L3: 期初余额 | M3: 投标保证金 | N3: 1000 | O3: =J3-N3 -> 0 | P3: 42826 | Q3: =P3 -> 42826 | R3: 找付款凭证 | T3: 河南省 | U3: =VLOOKUP(T3,[1]区域划分!$A$1:$C$39,3,0) -> 方渊
A4: 183 | B4: BZJ-0002 | C4: 42370 | D4: =IF(TODAY()-E4<60,"2个月内",IF(TODAY()-E4<180,"3-6个月",IF(TODAY()-E4<360,"6个月-1年","一年以上"))) -> 一年以上 | H4: 云南西南水泥有限公司 | I4: 云南西南水泥有限公司 | J4: 50000 | L4: 期初余额 | M4: 投标保证金 | N4: 50000 | O4: =J4-N4 -> 0 | P4: 44155 | Q4: =P4 -> 44155
A5: 184 | B5: BZJ-0003 | C5: 42370 | D5: =IF(TODAY()-E5<60,"2个月内",IF(TODAY()-E5<180,"3-6个月",IF(TODAY()-E5<360,"6个月-1年","一年以上"))) -> 一年以上 | H5: 淮北众城水泥有限责任公司 | I5: 淮北众城水泥有限责任公司 | J5: 3000 | K5: 武汉 | L5: 期初余额 | M5: 投标保证金 | O5: =J5-N5 -> 3000 | Q5: =P5 -> 0 | S5: 已被收购 | T5: 安徽省 | U5: =VLOOKUP(T5,[1]区域划分!$A$1:$C$39,3,0) -> 方渊
A6: 186 | B6: BZJ-0004 | C6: 42370 | D6: =IF(TODAY()-E6<60,"2个月内",IF(TODAY()-E6<180,"3-6个月",IF(TODAY()-E6<360,"6个月-1年","一年以上"))) -> 一年以上 | H6: 吉林亚泰（集团）股份有限公司物资经销分公司 | I6: 吉林亚泰集团物资贸易有限公司 | J6: 3800 | K6: 武汉 | L6: 期初余额 | M6: 投标保证金 | O6: =J6-N6 -> 3800 | Q6: =P6 -> 0 | R6: 预计2023.04或2023.05月退还，熊伟跟进中.客人无此笔,我司资料为期初数据有23800 | S6: 有凭证才可查询 | T6: 吉林省 | U6: =VLOOKUP(T6,[1]区域划分!$A$1:$C$39,3,0) -> 殷坤鹏 | V6: 张玉鹏13634307383
A7: 187 | B7: BZJ-0005 | C7: 42370 | D7: =IF(TODAY()-E7<60,"2个月内",IF(TODAY()-E7<180,"3-6个月",IF(TODAY()-E7<360,"6个月-1年","一年以上"))) -> 一年以上 | H7: 江苏永钢集团物资贸易有限公司 | I7: 江苏永钢集团物资贸易有限公司 | J7: 20000 | K7: 武汉 | L7: 期初余额 | M7: 投标保证金 | O7: =J7-N7 -> 20000 | Q7: =P7 -> 0 | R7: 对方财务查询并无此款 | S7: 对方财务查询并无此款 | T7: 江苏省 | U7: =VLOOKUP(T7,[1]区域划分!$A$1:$C$39,3,0) -> 龚运谱
A8: 188 | B8: BZJ-0006 | C8: 42370 | D8: =IF(TODAY()-E8<60,"2个月内",IF(TODAY()-E8<180,"3-6个月",IF(TODAY()-E8<360,"6个月-1年","一年以上"))) -> 一年以上 | H8: 酒泉钢铁（集团）有限公司 | I8: 酒泉钢铁（集团）有限公司 | J8: 300 | L8: 期初余额 | M8: 投标保证金 | N8: 300 | O8: =J8-N8 -> 0 | P8: 44728 | Q8: =P8 -> 44728 | S8: 可能是标书费
A9: 185 | B9: BZJ-0007 | C9: 42370 | D9: =IF(TODAY()-E9<60,"2个月内",IF(TODAY()-E9<180,"3-6个月",IF(TODAY()-E9<360,"6个月-1年","一年以上"))) -> 一年以上 | E9: 42390 | G9: 吴海波 | H9: 亚泰伊通 | I9: 亚泰集团伊通水泥有限公司 | J9: 20000 | K9: 武汉 | L9: 武汉对公 | M9: 投标保证金 | O9: =J9-N9 -> 20000 | Q9: =P9 -> 0 | R9: 预计2023.04或2023.05月退还，熊伟跟进中.客人无此笔,我司资料为期初数据有23800 | S9: 2016年1月42#凭证 | T9: 吉林省 | U9: =VLOOKUP(T9,[1]区域划分!$A$1:$C$39,3,0) -> 殷坤鹏 | V9: 张玉鹏13634307383
A10: 189 | B10: BZJ-0008 | C10: 42370 | D10: =IF(TODAY()-E10<60,"2个月内",IF(TODAY()-E10<180,"3-6个月",IF(TODAY()-E10<360,"6个月-1年","一年以上"))) -> 一年以上 | E10: 42400 | H10: 江苏沙钢集团有限公司 | I10: 江苏沙钢集团有限公司 | J10: 10000 | K10: 武汉 | L10: 平台上共8万 | M10: 投标保证金 | N10: 10000 | O10: =J10-N10 -> 0 | P10: 45923 | Q10: =P10 -> 45923 | R10: 长期投标不退 | S10: 投标保证金（前期借支2万元 后期借支5万元） 销售部查询系统里面有8万元保证金，长期投标不退 | T10: 江苏省 | U10: =VLOOKUP(T10,[1]区域划分!$A$1:$C$39,3,0) -> 龚运谱
A11: 1 | B11: BZJ-0009 | C11: 42887 | D11: =IF(TODAY()-E11<60,"2个月内",IF(TODAY()-E11<180,"3-6个月",IF(TODAY()-E11<360,"6个月-1年","一年以上"))) -> 一年以上 | E11: 42887 | H11: 江苏沙钢集团有限公司 | I11: 江苏沙钢集团有限公司 | J11: 10000 | K11: 武汉 | L11: 平台上共8万 | M11: 安全保证金 | N11: 10000 | O11: =J11-N11 -> 0 | P11: 45923 | Q11: =P11 -> 45923 | S11: 2025-9-23退回8万元 | T11: 江苏省 | U11: =VLOOKUP(T11,[1]区域划分!$A$1:$C$39,3,0) -> 龚运谱
A12: 190 | B12: BZJ-0010 | C12: 43466 | D12: =IF(TODAY()-E12<60,"2个月内",IF(TODAY()-E12<180,"3-6个月",IF(TODAY()-E12<360,"6个月-1年","一年以上"))) -> 一年以上 | E12: 43475 | G12: 汤勇华 | H12: 江苏沙钢集团有限公司 | I12: 江苏沙钢集团有限公司 | J12: 50000 | K12: 武汉 | L12: 平台上共8万 | M12: 投标保证金 | N12: 50000 | O12: =J12-N12 -> 0 | P12: 45923 | Q12: =P12 -> 45923 | R12: 长期投标不退 | S12: 投标保证金（前期借支2万元 后期借支5万元） 销售部查询系统里面有8万元保证金，长期投标不退 | T12: 江苏省 | U12: =VLOOKUP(T12,[1]区域划分!$A$1:$C$39,3,0) -> 龚运谱
A13: 5 | B13: BZJ-0011 | C13: 43101 | D13: =IF(TODAY()-E13<60,"2个月内",IF(TODAY()-E13<180,"3-6个月",IF(TODAY()-E13<360,"6个月-1年","一年以上"))) -> 一年以上 | E13: 43113 | F13: 生产部 | G13: 姜兵 | H13: 永登祁连山水泥有限公司 | I13: 永登祁连山水泥有限公司 | J13: 2000 | L13: 对公 | M13: 安全保证金 | N13: 2000 | O13: =J13-N13 -> 0 | P13: 44099 | Q13: =P13 -> 44099 | S13: 近期要施工
A14: 2 | B14: BZJ-0012 | C14: 43101 | D14: =IF(TODAY()-E14<60,"2个月内",IF(TODAY()-E14<180,"3-6个月",IF(TODAY()-E14<360,"6个月-1年","一年以上"))) -> 一年以上 | E14: 43124 | G14: 丁俊 | H14: 逸盛大化石化有限公司 | I14: 逸盛大化石化有限公司 | J14: 7000 | K14: 武汉 | M14: 安全保证金 | O14: 7000 | Q14: =P14 -> 0 | R14: 2023.03月殷总说之前做的质量有重大问题暂时不催 | S14: 2019年12月从丁俊个人转公司账7000元 | T14: 辽宁省 | U14: =VLOOKUP(T14,[1]区域划分!$A$1:$C$39,3,0) -> 殷坤鹏
A15: 10 | B15: BZJ-0013 | C15: 43252 | D15: =IF(TODAY()-E15<60,"2个月内",IF(TODAY()-E15<180,"3-6个月",IF(TODAY()-E15<360,"6个月-1年","一年以上"))) -> 一年以上 | E15: 43255 | F15: 生产一部 | G15: 汪勇刚 | H15: 德州中联大坝水泥有限公司 | I15: 德州中联大坝水泥有限公司 | J15: 15000 | K15: 武汉 | L15: 武汉对公 | M15: 安全保证金 | N15: 15000 | O15: =J15-N15 -> 0 | P15: 44936 | Q15: =P15 -> 44936 | S15: 武汉2018.06-40 | T15: 山东省 | U15: 李松林
A16: 15 | B16: BZJ-0014 | C16: 43313 | D16: =IF(TODAY()-E16<60,"2个月内",IF(TODAY()-E16<180,"3-6个月",IF(TODAY()-E16<360,"6个月-1年","一年以上"))) -> 一年以上 | E16: 43330 | F16: 生产部 | G16: 张子仪 | H16: 四川西南水泥有限公司 | I16: 四川西南水泥有限公司 | J16: 2000 | L16: 对公 | M16: 安全保证金 | N16: 2000 | O16: =J16-N16 -> 0 | P16: 43707 | Q16: =P16 -> 43707
A17: 6 | B17: BZJ-0015 | C17: 43374 | D17: =IF(TODAY()-E17<60,"2个月内",IF(TODAY()-E17<180,"3-6个月",IF(TODAY()-E17<360,"6个月-1年","一年以上"))) -> 一年以上 | E17: 43393 | F17: 生产部 | G17: 刘西 | H17: 新安中联万基水泥有限公司 | I17: 新安中联万基水泥有限公司 | J17: 3000 | L17: 对公 | M17: 安全保证金 | N17: 3000 | O17: =J17-N17 -> 0 | P17: 44126 | Q17: =P17 -> 44126 | S17: 施工质量问题无法办理
A18: 19 | B18: BZJ-0016 | C18: 43374 | D18: =IF(TODAY()-E18<60,"2个月内",IF(TODAY()-E18<180,"3-6个月",IF(TODAY()-E18<360,"6个月-1年","一年以上"))) -> 一年以上 | E18: 43404 | F18: 生产部 | G18: 丁俊 | H18: 逸盛大化石化有限公司 | I18: 逸盛大化石化有限公司 | J18: 7000 | L18: 个人 | M18: 安全保证金 | N18: 7000 | O18: =J18-N18 -> 0 | P18: 43480 | Q18: =P18 -> 43480
A19: 3 | B19: BZJ-0017 | C19: 43405 | D19: =IF(TODAY()-E19<60,"2个月内",IF(TODAY()-E19<180,"3-6个月",IF(TODAY()-E19<360,"6个月-1年","一年以上"))) -> 一年以上 | E19: 43414 | F19: 生产部 | G19: 丁俊 | H19: 韩城尧柏阳山庄水泥有限公司 | I19: 韩城尧柏阳山庄水泥有限公司 | J19: =20000 -> 20000 | K19: 武汉 | L19: 对公 | M19: 安全保证金 | N19: 20000 | O19: =J19-N19 -> 0 | P19: 43823 | Q19: =P19 -> 43823 | S19: 2019/12/24退19800
A20: 4 | B20: BZJ-0018 | C20: 43435 | D20: =IF(TODAY()-E20<60,"2个月内",IF(TODAY()-E20<180,"3-6个月",IF(TODAY()-E20<360,"6个月-1年","一年以上"))) -> 一年以上 | E20: 43446 | F20: 生产部 | G20: 冯海雄 | H20: 民和祁连山水泥有限公司 | I20: 民和祁连山水泥有限公司 | J20: 8000 | L20: 对公 | M20: 安全保证金 | N20: 8000 | O20: =J20-N20 -> 0 | P20: 43609 | Q20: =P20 -> 43609
A21: 12 | B21: BZJ-0019 | C21: 43466 | D21: =IF(TODAY()-E21<60,"2个月内",IF(TODAY()-E21<180,"3-6个月",IF(TODAY()-E21<360,"6个月-1年","一年以上"))) -> 一年以上 | E21: 43493 | F21: 生产部 | G21: 吴昌松 | H21: 冀东海天水泥闻喜有限公司 | I21: 冀东海天水泥闻喜有限公司 | J21: 10000 | L21: 对公 | M21: 安全保证金 | N21: 10000 | O21: =J21-N21 -> 0 | P21: 43664 | Q21: =P21 -> 43664
A22: 11 | B22: BZJ-0020 | C22: 43497 | D22: =IF(TODAY()-E22<60,"2个月内",IF(TODAY()-E22<180,"3-6个月",IF(TODAY()-E22<360,"6个月-1年","一年以上"))) -> 一年以上 | E22: 43511 | F22: 生产部 | G22: 汪勇刚 | H22: 贵州中诚水泥有限公司 | I22: 贵州中诚水泥有限公司 | J22: 3000 | L22: 对公 | M22: 安全保证金 | N22: 3000 | O22: =J22-N22 -> 0 | P22: 43646 | Q22: =P22 -> 43646
A23: 8 | B23: BZJ-0021 | C23: 43497 | D23: =IF(TODAY()-E23<60,"2个月内",IF(TODAY()-E23<180,"3-6个月",IF(TODAY()-E23<360,"6个月-1年","一年以上"))) -> 一年以上 | E23: 43516 | F23: 生产部 | G23: 覃延吉 | H23: 云南丽江西南水泥有限公司 | I23: 云南丽江西南水泥有限公司 | J23: 1000 | L23: 对公 | M23: 安全保证金 | N23: 1000 | O23: =J23-N23 -> 0 | P23: 43692 | Q23: =P23 -> 43692
A24: 14 | B24: BZJ-0022 | C24: 43525 | D24: =IF(TODAY()-E24<60,"2个月内",IF(TODAY()-E24<180,"3-6个月",IF(TODAY()-E24<360,"6个月-1年","一年以上"))) -> 一年以上 | E24: 43526 | F24: 生产部 | G24: 詹年喜 | H24: 邯郸涉县金隅水泥有限公司 | I24: 邯郸涉县金隅水泥有限公司 | J24: 2000 | L24: 对公 | M24: 安全保证金 | N24: 2000 | O24: =J24-N24 -> 0 | P24: 43698 | Q24: =P24 -> 43698
A25: 13 | B25: BZJ-0023 | C25: 43525 | D25: =IF(TODAY()-E25<60,"2个月内",IF(TODAY()-E25<180,"3-6个月",IF(TODAY()-E25<360,"6个月-1年","一年以上"))) -> 一年以上 | E25: 43530 | F25: 生产部 | G25: 詹年喜 | H25: 阳泉冀东水泥有限责任公司 | I25: 阳泉冀东水泥有限责任公司 | J25: 3000 | L25: 对公 | M25: 安全保证金 | N25: 3000 | O25: =J25-N25 -> 0 | P25: 43700 | Q25: =P25 -> 43700
A26: 9 | B26: BZJ-0024 | C26: 43525 | D26: =IF(TODAY()-E26<60,"2个月内",IF(TODAY()-E26<180,"3-6个月",IF(TODAY()-E26<360,"6个月-1年","一年以上"))) -> 一年以上 | E26: 43539 | F26: 生产部 | G26: 覃延吉 | H26: 河钢股份有限公司邯郸分公司 | I26: 河钢股份有限公司邯郸分公司 | J26: 10000 | L26: 对公 | M26: 安全保证金 | N26: 10000 | O26: =J26-N26 -> 0 | P26: 43613 | Q26: =P26 -> 43613
A27: 7 | B27: BZJ-0025 | C27: 43556 | D27: =IF(TODAY()-E27<60,"2个月内",IF(TODAY()-E27<180,"3-6个月",IF(TODAY()-E27<360,"6个月-1年","一年以上"))) -> 一年以上 | E27: 43557 | F27: 生产部 | G27: 石靖 | H27: 达州利森水泥有限公司 | I27: 达州利森水泥有限公司 | J27: 5000 | L27: 对公 | M27: 安全保证金 | N27: 5000 | O27: =J27-N27 -> 0 | P27: 43633 | Q27: =P27 -> 43633
A28: 16 | B28: BZJ-0026 | C28: 43556 | D28: =IF(TODAY()-E28<60,"2个月内",IF(TODAY()-E28<180,"3-6个月",IF(TODAY()-E28<360,"6个月-1年","一年以上"))) -> 一年以上 | E28: 43560 | F28: 总经办 | G28: 汤勇华 | H28: 张家港宏昌钢板有限公司 | I28: 张家港宏昌钢板有限公司 | J28: 124500 | K28: 武汉 | L28: 武汉对公 | M28: 安全保证金 | N28: 124500 | O28: =J28-N28 -> 0 | P28: 44890 | Q28: =P28 -> 44890 | S28: 武汉2019.4-50 | T28: 江苏省 | U28: 杨春龙 | V28: 预计2022.10月，收完全款后退回
A29: 194 | B29: BZJ-0027 | C29: 43556 | D29: =IF(TODAY()-E29<60,"2个月内",IF(TODAY()-E29<180,"3-6个月",IF(TODAY()-E29<360,"6个月-1年","一年以上"))) -> 一年以上 | E29: 43570 | G29: 夏锋泽 | H29: 四川西南水泥有限公司 | I29: 四川西南水泥有限公司 | J29: 10000 | L29: 对公 | M29: 投标保证金 | N29: 10000 | O29: =J29-N29 -> 0 | P29: 44064 | Q29: =P29 -> 44064 | S29: 长期投标不退
A30: 343 | B30: BZJ-0028 | C30: 43556 | D30: =IF(TODAY()-E30<60,"2个月内",IF(TODAY()-E30<180,"3-6个月",IF(TODAY()-E30<360,"6个月-1年","一年以上"))) -> 一年以上 | E30: 43585 | F30: 销售部 | G30: 李辉 | H30: 葛洲坝钟祥水泥有限公司 | I30: 葛洲坝钟祥水泥有限公司 | J30: 10000 | L30: 对公 | M30: 履约保证金 | N30: 10000 | O30: =J30-N30 -> 0 | P30: 43938 | Q30: =P30 -> 43938 | S30: 履约保证金
A31: 17 | B31: BZJ-0029 | C31: 43586 | D31: =IF(TODAY()-E31<60,"2个月内",IF(TODAY()-E31<180,"3-6个月",IF(TODAY()-E31<360,"6个月-1年","一年以上"))) -> 一年以上 | E31: 43600 | F31: 生产部 | G31: 李文池 | H31: 四川峨眉山西南水泥有限公司 | I31: 四川峨眉山西南水泥有限公司 | J31: 3000 | L31: 对公 | M31: 安全保证金 | N31: 3000 | O31: =J31-N31 -> 0 | P31: 43824 | Q31: =P31 -> 43824
A32: 18 | B32: BZJ-0030 | C32: 43586 | D32: =IF(TODAY()-E32<60,"2个月内",IF(TODAY()-E32<180,"3-6个月",IF(TODAY()-E32<360,"6个月-1年","一年以上"))) -> 一年以上 | E32: 43601 | F32: 生产部 | G32: 吴昌松 | H32: 云南昆钢嘉华水泥建材有限公司 | I32: 云南昆钢嘉华水泥建材有限公司 | J32: 3000 | L32: 对公 | M32: 安全保证金 | N32: 3000 | O32: =J32-N32 -> 0 | P32: 44484 | Q32: =P32 -> 44484
A33: 20 | B33: BZJ-0031 | C33: 43586 | D33: =IF(TODAY()-E33<60,"2个月内",IF(TODAY()-E33<180,"3-6个月",IF(TODAY()-E33<360,"6个月-1年","一年以上"))) -> 一年以上 | E33: 43601 | F33: 生产部 | G33: 余茶林 | H33: 汉中尧柏水泥有限公司 | I33: 汉中尧柏水泥有限公司 | J33: 10000 | L33: 对公 | M33: 安全保证金 | N33: 10000 | O33: =J33-N33 -> 0 | P33: 43973 | Q33: =P33 -> 43973
A34: 21 | B34: BZJ-0032 | C34: 43617 | D34: =IF(TODAY()-E34<60,"2个月内",IF(TODAY()-E34<180,"3-6个月",IF(TODAY()-E34<360,"6个月-1年","一年以上"))) -> 一年以上 | E34: 43621 | F34: 生产部 | G34: 房延云 | H34: 鲁南中联水泥有限公司 | I34: 鲁南中联水泥有限公司 | J34: 2000 | L34: 个人 | M34: 安全保证金 | N34: 2000 | O34: =J34-N34 -> 0 | P34: 43676 | Q34: =P34 -> 43676
A35: 22 | B35: BZJ-0033 | C35: 43617 | D35: =IF(TODAY()-E35<60,"2个月内",IF(TODAY()-E35<180,"3-6个月",IF(TODAY()-E35<360,"6个月-1年","一年以上"))) -> 一年以上 | E35: 43628 | F35: 生产部 | G35: 王小勇 | H35: 莒县中联水泥有限公司 | I35: 莒县中联水泥有限公司 | J35: 5000 | L35: 对公 | M35: 安全保证金 | N35: 5000 | O35: =J35-N35 -> 0 | P35: 43641 | Q35: =P35 -> 43641
A36: 23 | B36: BZJ-0034 | C36: 43617 | D36: =IF(TODAY()-E36<60,"2个月内",IF(TODAY()-E36<180,"3-6个月",IF(TODAY()-E36<360,"6个月-1年","一年以上"))) -> 一年以上 | E36: 43635 | F36: 生产部 | G36: 程时勇 | H36: 贵州沿河西南水泥有限公司 | I36: 贵州沿河西南水泥有限公司 | J36: 2000 | L36: 对公 | M36: 安全保证金 | N36: 2000 | O36: =J36-N36 -> 0 | P36: 43644 | Q36: =P36 -> 43644
A37: 24 | B37: BZJ-0035 | C37: 43617 | D37: =IF(TODAY()-E37<60,"2个月内",IF(TODAY()-E37<180,"3-6个月",IF(TODAY()-E37<360,"6个月-1年","一年以上"))) -> 一年以上 | E37: 43644 | F37: 生产部 | G37: 李文池 | H37: 西安蓝田尧柏水泥有限公司 | I37: 西安蓝田尧柏水泥有限公司 | J37: 10000 | L37: 对公 | M37: 安全保证金 | N37: 10000 | O37: =J37-N37 -> 0 | P37: 43703 | Q37: =P37 -> 43703
A38: 25 | B38: BZJ-0036 | C38: 43647 | D38: =IF(TODAY()-E38<60,"2个月内",IF(TODAY()-E38<180,"3-6个月",IF(TODAY()-E38<360,"6个月-1年","一年以上"))) -> 一年以上 | E38: 43657 | F38: 生产部 | G38: 吴昌松 | H38: 会东利森水泥有限公司 | I38: 会东利森水泥有限公司 | J38: 3000 | L38: 对公 | M38: 安全保证金 | N38: 3000 | O38: =J38-N38 -> 0 | P38: 43703 | Q38: =P38 -> 43703
A39: 27 | B39: BZJ-0037 | C39: 43647 | D39: =IF(TODAY()-E39<60,"2个月内",IF(TODAY()-E39<180,"3-6个月",IF(TODAY()-E39<360,"6个月-1年","一年以上"))) -> 一年以上 | E39: 43657 | F39: 生产部 | G39: 熊军 | H39: 冀东水泥铜川有限公司 | I39: 冀东水泥铜川有限公司 | J39: 1000 | L39: 个人 | M39: 安全保证金 | N39: 1000 | O39: =J39-N39 -> 0 | P39: 43661 | Q39: =P39 -> 43661
A40: 26 | B40: BZJ-0038 | C40: 43647 | D40: =IF(TODAY()-E40<60,"2个月内",IF(TODAY()-E40<180,"3-6个月",IF(TODAY()-E40<360,"6个月-1年","一年以上"))) -> 一年以上 | E40: 43664 | F40: 生产部 | G40: 吴昌松 | H40: 四川省绵竹澳东水泥有限责任公司 | I40: 四川省绵竹澳东水泥有限责任公司 | J40: 3000 | L40: 对公 | M40: 安全保证金 | N40: 3000 | O40: =J40-N40 -> 0 | P40: 43794 | Q40: =P40 -> 43794
A41: 28 | B41: BZJ-0039 | C41: 43678 | D41: =IF(TODAY()-E41<60,"2个月内",IF(TODAY()-E41<180,"3-6个月",IF(TODAY()-E41<360,"6个月-1年","一年以上"))) -> 一年以上 | E41: 43678 | F41: 生产部 | G41: 余茶林 | H41: 嘉华特种水泥股份有限公司嘉华水泥总厂 | I41: 嘉华特种水泥股份有限公司嘉华水泥总厂 | J41: 2000 | L41: 对公 | M41: 安全保证金 | N41: 2000 | O41: =J41-N41 -> 0 | P41: 43700 | Q41: =P41 -> 43700
A42: 29 | B42: BZJ-0040 | C42: 43678 | D42: =IF(TODAY()-E42<60,"2个月内",IF(TODAY()-E42<180,"3-6个月",IF(TODAY()-E42<360,"6个月-1年","一年以上"))) -> 一年以上 | E42: 43685 | F42: 销售部 | G42: 吴海波 | H42: 山东鲁城水泥有限公司 | I42: 山东鲁城水泥有限公司 | J42: 10000 | L42: 对公 | M42: 安全保证金 | N42: 10000 | O42: =J42-N42 -> 0 | P42: 44403 | Q42: =P42 -> 44403
A43: 30 | B43: BZJ-0041 | C43: 43678 | D43: =IF(TODAY()-E43<60,"2个月内",IF(TODAY()-E43<180,"3-6个月",IF(TODAY()-E43<360,"6个月-1年","一年以上"))) -> 一年以上 | E43: 43692 | F43: 生产部 | G43: 熊军、左汉军 | H43: 甘肃永固特种水泥有限公司 | I43: 甘肃永固特种水泥有限公司 | J43: 10000 | L43: 对公 | M43: 安全保证金 | N43: 10000 | O43: =J43-N43 -> 0 | P43: 43701 | Q43: =P43 -> 43701
A44: 31 | B44: BZJ-0042 | C44: 43678 | D44: =IF(TODAY()-E44<60,"2个月内",IF(TODAY()-E44<180,"3-6个月",IF(TODAY()-E44<360,"6个月-1年","一年以上"))) -> 一年以上 | E44: 43696 | F44: 生产部 | G44: 张子仪 | H44: 贵州纳雍隆庆乌江水泥有限公司 | I44: 贵州纳雍隆庆乌江水泥有限公司 | J44: 2000 | K44: 武汉 | L44: 武汉对公 | M44: 安全保证金 | N44: 2000 | O44: =J44-N44 -> 0 | P44: 45012 | Q44: =P44 -> 45012 | S44: 武汉2019.08-102 | T44: 贵州省 | U44: 陈涛
A45: 342 | B45: BZJ-0043 | C45: 43678 | D45: =IF(TODAY()-E45<60,"2个月内",IF(TODAY()-E45<180,"3-6个月",IF(TODAY()-E45<360,"6个月-1年","一年以上"))) -> 一年以上 | E45: 43696 | F45: 销售部 | G45: 吴海波 | H45: 涿鹿金隅水泥有限公司 | I45: 涿鹿金隅水泥有限公司 | J45: 20000 | L45: 对公 | M45: 履约保证金 | N45: 20000 | O45: =J45-N45 -> 0 | P45: 44673 | Q45: =P45 -> 44673 | S45: 是投标保证金转为了履约，履约又 转为了质保，质保刚刚到期。大约9月底回
A46: 32 | B46: BZJ-0044 | C46: 43678 | D46: =IF(TODAY()-E46<60,"2个月内",IF(TODAY()-E46<180,"3-6个月",IF(TODAY()-E46<360,"6个月-1年","一年以上"))) -> 一年以上 | E46: 43698 | F46: 生产部 | G46: 李文池 | H46: 重庆秀山西南水泥有限公司 | I46: 重庆秀山西南水泥有限公司 | J46: 2000 | L46: 对公 | M46: 安全保证金 | N46: 2000 | O46: =J46-N46 -> 0 | P46: 43829 | Q46: =P46 -> 43829
A47: 33 | B47: BZJ-0045 | C47: 43678 | D47: =IF(TODAY()-E47<60,"2个月内",IF(TODAY()-E47<180,"3-6个月",IF(TODAY()-E47<360,"6个月-1年","一年以上"))) -> 一年以上 | E47: 43700 | F47: 生产部 | G47: 程时勇 | H47: 山东泰西水泥有限公司 | I47: 山东泰西水泥有限公司 | J47: 1000 | L47: 个人 | M47: 安全保证金 | N47: 1000 | O47: =J47-N47 -> 0 | P47: 43718 | Q47: =P47 -> 43718
A48: 34 | B48: BZJ-0046 | C48: 43709 | D48: =IF(TODAY()-E48<60,"2个月内",IF(TODAY()-E48<180,"3-6个月",IF(TODAY()-E48<360,"6个月-1年","一年以上"))) -> 一年以上 | E48: 43710 | F48: 销售部 | G48: 吴海波 | H48: 涿鹿金隅水泥有限公司 | I48: 涿鹿金隅水泥有限公司 | J48: 25350 | K48: 武汉 | L48: 武汉对公 | M48: 安全保证金 | N48: 25350 | O48: =J48-N48 -> 0 | P48: 44673 | Q48: =P48 -> 44673 | S48: 武汉2019.9-105 | T48: 河北省 | U48: 杨春龙
A49: 35 | B49: BZJ-0047 | C49: 43709 | D49: =IF(TODAY()-E49<60,"2个月内",IF(TODAY()-E49<180,"3-6个月",IF(TODAY()-E49<360,"6个月-1年","一年以上"))) -> 一年以上 | E49: 43719 | F49: 生产部 | G49: 李文池 | H49: 绥江县永固水泥有限责任公司 | I49: 绥江县永固水泥有限责任公司 | J49: 4000 | L49: 对公 | M49: 安全保证金 | N49: 4000 | O49: =J49-N49 -> 0 | P49: 43723 | Q49: =P49 -> 43723
A50: 36 | B50: BZJ-0048 | C50: 43709 | D50: =IF(TODAY()-E50<60,"2个月内",IF(TODAY()-E50<180,"3-6个月",IF(TODAY()-E50<360,"6个月-1年","一年以上"))) -> 一年以上 | E50: 43727 | F50: 生产部 | G50: 吴昌松 | H50: 华新水泥（房县)有限公司 | I50: 华新水泥（房县)有限公司 | J50: 3000 | L50: 个人 | M50: 安全保证金 | N50: 3000 | O50: =J50-N50 -> 0 | P50: 43761 | Q50: =P50 -> 43761
A51: 37 | B51: BZJ-0049 | C51: 43709 | D51: =IF(TODAY()-E51<60,"2个月内",IF(TODAY()-E51<180,"3-6个月",IF(TODAY()-E51<360,"6个月-1年","一年以上"))) -> 一年以上 | E51: 43731 | F51: 生产部 | G51: 汪勇刚 | H51: 云南普洱西南水泥有限公司 | I51: 云南普洱西南水泥有限公司 | J51: 2000 | L51: 对公 | M51: 安全保证金 | N51: 2000 | O51: =J51-N51 -> 0 | P51: 43829 | Q51: =P51 -> 43829
A52: 38 | B52: BZJ-0050 | C52: 43709 | D52: =IF(TODAY()-E52<60,"2个月内",IF(TODAY()-E52<180,"3-6个月",IF(TODAY()-E52<360,"6个月-1年","一年以上"))) -> 一年以上 | E52: 43731 | F52: 生产部 | G52: 刘思佳 | H52: 冀东水泥重庆江津有限公司 | I52: 冀东水泥重庆江津有限公司 | J52: 7160 | L52: 对公 | M52: 安全保证金 | N52: 7160 | O52: =J52-N52 -> 0 | P52: 43847 | Q52: =P52 -> 43847
A53: 39 | B53: BZJ-0051 | C53: 43709 | D53: =IF(TODAY()-E53<60,"2个月内",IF(TODAY()-E53<180,"3-6个月",IF(TODAY()-E53<360,"6个月-1年","一年以上"))) -> 一年以上 | E53: 43733 | F53: 生产部 | G53: 覃延吉 | H53: 北京金隅琉水环保科技有限公司 | I53: 北京金隅琉水环保科技有限公司 | J53: 2000 | L53: 个人 | M53: 安全保证金 | N53: 2000 | O53: =J53-N53 -> 0 | P53: 43755 | Q53: =P53 -> 43755
A54: 40 | B54: BZJ-0052 | C54: 43739 | D54: =IF(TODAY()-E54<60,"2个月内",IF(TODAY()-E54<180,"3-6个月",IF(TODAY()-E54<360,"6个月-1年","一年以上"))) -> 一年以上 | E54: 43749 | F54: 生产部 | G54: 刘靖 | H54: 淮北众城水泥有限责任公司 | I54: 淮北众城水泥有限责任公司 | J54: 2600 | L54: 对公 | M54: 安全保证金 | N54: 2600 | O54: =J54-N54 -> 0 | P54: 43776 | Q54: =P54 -> 43776
A55: 41 | B55: BZJ-0053 | C55: 43739 | D55: =IF(TODAY()-E55<60,"2个月内",IF(TODAY()-E55<180,"3-6个月",IF(TODAY()-E55<360,"6个月-1年","一年以上"))) -> 一年以上 | E55: 43749 | F55: 生产部 | G55: 刘佳 | H55: 冀东水泥铜川有限公司 | I55: 冀东水泥铜川有限公司 | J55: 1000 | L55: 个人 | M55: 安全保证金 | N55: 1000 | O55: =J55-N55 -> 0 | P55: 43725 | Q55: =P55 -> 43725
A56: 43 | B56: BZJ-0054 | C56: 43739 | D56: =IF(TODAY()-E56<60,"2个月内",IF(TODAY()-E56<180,"3-6个月",IF(TODAY()-E56<360,"6个月-1年","一年以上"))) -> 一年以上 | E56: 43759 | F56: 生产部 | G56: 程时勇 | H56: 贵州清镇西南水泥有限公司 | I56: 贵州清镇西南水泥有限公司 | J56: 3000 | L56: 个人 | M56: 安全保证金 | N56: 3000 | O56: =J56-N56 -> 0 | P56: 43789 | Q56: =P56 -> 43789
A57: 44 | B57: BZJ-0055 | C57: 43739 | D57: =IF(TODAY()-E57<60,"2个月内",IF(TODAY()-E57<180,"3-6个月",IF(TODAY()-E57<360,"6个月-1年","一年以上"))) -> 一年以上 | E57: 43761 | F57: 生产部 | G57: 吴昌松 | H57: 华新水泥（恩施）有限公司 | I57: 华新水泥（恩施）有限公司 | J57: 3000 | L57: 个人 | M57: 安全保证金 | N57: 3000 | O57: =J57-N57 -> 0 | P57: 43768 | Q57: =P57 -> 43768
A58: 42 | B58: BZJ-0056 | C58: 43739 | D58: =IF(TODAY()-E58<60,"2个月内",IF(TODAY()-E58<180,"3-6个月",IF(TODAY()-E58<360,"6个月-1年","一年以上"))) -> 一年以上 | E58: 43766 | F58: 生产部 | G58: 刘西 | H58: 巴彦淖尔中联水泥有限公司 | I58: 巴彦淖尔中联水泥有限公司 | J58: 4000 | L58: 对公 | M58: 安全保证金 | N58: 4000 | O58: =J58-N58 -> 0 | P58: 44465 | Q58: =P58 -> 44465
A59: 45 | B59: BZJ-0057 | C59: 43770 | D59: =IF(TODAY()-E59<60,"2个月内",IF(TODAY()-E59<180,"3-6个月",IF(TODAY()-E59<360,"6个月-1年","一年以上"))) -> 一年以上 | E59: 43774 | F59: 生产部 | G59: 祝威 | H59: 安康市尧柏水泥有限公司 | I59: 安康市尧柏水泥有限公司 | J59: 10000 | L59: 对公 | M59: 安全保证金 | N59: 10000 | O59: =J59-N59 -> 0 | P59: 43976 | Q59: =P59 -> 43976
A60: 191 | B60: BZJ-0058 | C60: 43770 | D60: =IF(TODAY()-E60<60,"2个月内",IF(TODAY()-E60<180,"3-6个月",IF(TODAY()-E60<360,"6个月-1年","一年以上"))) -> 一年以上 | E60: 43774 | G60: 田学军 | H60: 贵州西南水泥有限公司 | I60: 贵州西南水泥有限公司 | J60: 50000 | K60: 武汉 | L60: 对公 | M60: 投标保证金 | N60: 50000 | O60: =J60-N60 -> 0 | P60: 44908 | Q60: =P60 -> 44908 | R60: 2022/12/31前退回，年标，转履约 | S60: 窑磨专业测窑调窑及整形，窑磨裂纹：长期投标不退
A61: 46 | B61: BZJ-0059 | C61: 43770 | D61: =IF(TODAY()-E61<60,"2个月内",IF(TODAY()-E61<180,"3-6个月",IF(TODAY()-E61<360,"6个月-1年","一年以上"))) -> 一年以上 | E61: 43775 | F61: 生产部 | G61: 刘思佳 | H61: 华新水泥（恩施）有限公司 | I61: 华新水泥（恩施）有限公司 | J61: 2000 | L61: 个人 | M61: 安全保证金 | N61: 2000 | O61: =J61-N61 -> 0 | P61: 43787 | Q61: =P61 -> 43787
A62: 47 | B62: BZJ-0060 | C62: 43770 | D62: =IF(TODAY()-E62<60,"2个月内",IF(TODAY()-E62<180,"3-6个月",IF(TODAY()-E62<360,"6个月-1年","一年以上"))) -> 一年以上 | E62: 43796 | F62: 生产部 | G62: 程时勇 | H62: 华新水泥（房县)有限公司 | I62: 华新水泥（房县)有限公司 | J62: 2000 | L62: 个人 | M62: 安全保证金 | N62: 2000 | O62: =J62-N62 -> 0 | P62: 43801 | Q62: =P62 -> 43801
A63: 193 | B63: BZJ-0061 | C63: 43800 | D63: =IF(TODAY()-E63<60,"2个月内",IF(TODAY()-E63<180,"3-6个月",IF(TODAY()-E63<360,"6个月-1年","一年以上"))) -> 一年以上 | E63: 43804 | G63: 杨春龙 | H63: 江苏永钢集团有限公司 | I63: 江苏永钢集团有限公司 | J63: 10000 | L63: 对公 | M63: 投标保证金 | N63: 10000 | O63: =J63-N63 -> 0 | P63: 44018 | Q63: =P63 -> 44018
A64: 48 | B64: BZJ-0062 | C64: 43800 | D64: =IF(TODAY()-E64<60,"2个月内",IF(TODAY()-E64<180,"3-6个月",IF(TODAY()-E64<360,"6个月-1年","一年以上"))) -> 一年以上 | E64: 43805 | F64: 生产部 | G64: 刘思佳 | H64: 阳泉冀东水泥有限责任公司 | I64: 阳泉冀东水泥有限责任公司 | J64: 2700 | L64: 对公 | M64: 安全保证金 | N64: 2700 | O64: =J64-N64 -> 0 | P64: 43985 | Q64: =P64 -> 43985
A65: 50 | B65: BZJ-0063 | C65: 43800 | D65: =IF(TODAY()-E65<60,"2个月内",IF(TODAY()-E65<180,"3-6个月",IF(TODAY()-E65<360,"6个月-1年","一年以上"))) -> 一年以上 | E65: 43808 | F65: 生产部 | G65: 吴昌松 | H65: 山东泰西水泥有限公司 | I65: 山东泰西水泥有限公司 | J65: 2000 | L65: 个人 | M65: 安全保证金 | N65: 2000 | O65: =J65-N65 -> 0 | P65: 43819 | Q65: =P65 -> 43819
A66: 49 | B66: BZJ-0064 | C66: 43800 | D66: =IF(TODAY()-E66<60,"2个月内",IF(TODAY()-E66<180,"3-6个月",IF(TODAY()-E66<360,"6个月-1年","一年以上"))) -> 一年以上 | E66: 43812 | F66: 生产部 | G66: 王延军 | H66: 渤海水泥（葫芦岛）有限公司 | I66: 渤海水泥（葫芦岛）有限公司 | J66: 3000 | L66: 对公 | M66: 安全保证金 | N66: 3000 | O66: =J66-N66 -> 0 | P66: 44189 | Q66: =P66 -> 44189
A67: 51 | B67: BZJ-0065 | C67: 43800 | D67: =IF(TODAY()-E67<60,"2个月内",IF(TODAY()-E67<180,"3-6个月",IF(TODAY()-E67<360,"6个月-1年","一年以上"))) -> 一年以上 | E67: 43823 | F67: 生产部 | G67: 吴昌松 | H67: 天瑞新登郑州水泥有限公司 | I67: 天瑞新登郑州水泥有限公司 | J67: 2000 | L67: 个人 | M67: 安全保证金 | N67: 2000 | O67: =J67-N67 -> 0 | P67: 43834 | Q67: =P67 -> 43834
A68: 52 | B68: BZJ-0066 | C68: 43800 | D68: =IF(TODAY()-E68<60,"2个月内",IF(TODAY()-E68<180,"3-6个月",IF(TODAY()-E68<360,"6个月-1年","一年以上"))) -> 一年以上 | E68: 43825 | F68: 生产部 | G68: 何煜军 | H68: 酒钢（集团）宏达建材有限责任公司 | I68: 酒钢（集团）宏达建材有限责任公司 | J68: 5000 | L68: 对公 | M68: 安全保证金 | N68: 5000 | O68: =J68-N68 -> 0 | P68: 44099 | Q68: =P68 -> 44099
A69: 73 | B69: BZJ-0067 | C69: 43800 | D69: =IF(TODAY()-E69<60,"2个月内",IF(TODAY()-E69<180,"3-6个月",IF(TODAY()-E69<360,"6个月-1年","一年以上"))) -> 一年以上 | E69: 43830 | F69: 销售部 | G69: 杨春龙 | H69: 江苏沙钢集团有限公司 | I69: 江苏沙钢集团有限公司 | J69: 900 | K69: 武汉 | L69: 个人 | M69: 安全保证金 | O69: =J69-N69 -> 900 | Q69: =P69 -> 0 | R69: 门禁卡押金 | S69: 门禁卡 | T69: 江苏省 | U69: =VLOOKUP(T69,[1]区域划分!$A$1:$C$39,3,0) -> 龚运谱
A70: 53 | B70: BZJ-0068 | C70: 43831 | D70: =IF(TODAY()-E70<60,"2个月内",IF(TODAY()-E70<180,"3-6个月",IF(TODAY()-E70<360,"6个月-1年","一年以上"))) -> 一年以上 | E70: 43840 | F70: 生产部 | G70: 祝发权 | H70: 安钢集团信阳钢铁有限责任公司 | I70: 安钢集团信阳钢铁有限责任公司 | J70: 3000 | L70: 个人 | M70: 安全保证金 | N70: 3000 | O70: =J70-N70 -> 0 | P70: 43920 | Q70: =P70 -> 43920
A71: 54 | B71: BZJ-0069 | C71: 43831 | D71: =IF(TODAY()-E71<60,"2个月内",IF(TODAY()-E71<180,"3-6个月",IF(TODAY()-E71<360,"6个月-1年","一年以上"))) -> 一年以上 | E71: 43840 | F71: 生产部 | G71: 黄庭兴 | H71: 承德金隅水泥有限责任公司 | I71: 承德金隅水泥有限责任公司 | J71: 2000 | K71: 武汉 | L71: 武汉对公 | M71: 安全保证金 | N71: 2000 | O71: =J71-N71 -> 0 | P71: 45035 | Q71: =P71 -> 45035 | R71: 预计2023.03月退款 | S71: 武汉2020.1-136 | T71: 河北省 | U71: 杨春龙 | V71: 安环部詹工
A72: 195 | B72: BZJ-0070 | C72: 43831 | D72: =IF(TODAY()-E72<60,"2个月内",IF(TODAY()-E72<180,"3-6个月",IF(TODAY()-E72<360,"6个月-1年","一年以上"))) -> 一年以上 | E72: 43840 | G72: 殷坤鹏 | H72: 鄂尔多斯市君正能源化工有限公司水泥分公司 | I72: 鄂尔多斯市君正能源化工有限公司水泥分公司 | J72: 10000 | L72: 对公 | M72: 投标保证金 | N72: 10000 | O72: =J72-N72 -> 0 | P72: 43913 | Q72: =P72 -> 43913 | S72: 长期投标不退
A73: 55 | B73: BZJ-0071 | C73: 43831 | D73: =IF(TODAY()-E73<60,"2个月内",IF(TODAY()-E73<180,"3-6个月",IF(TODAY()-E73<360,"6个月-1年","一年以上"))) -> 一年以上 | E73: 43843 | F73: 生产部 | G73: 王小勇 | H73: 渤海水泥（葫芦岛）有限公司 | I73: 渤海水泥（葫芦岛）有限公司 | J73: 3000 | K73: 武汉 | L73: 对公 | M73: 安全保证金 | N73: 2900 | O73: =J73-N73-100 -> 0 | P73: 44279 | Q73: =P73 -> 44279 | R73: 2021/3/24实际退款2900元，2025.11.7签署销账明细 | T73: 辽宁省 | U73: =VLOOKUP(T73,[1]区域划分!$A$1:$C$39,3,0) -> 殷坤鹏
A74: 344 | B74: BZJ-0072 | C74: 43831 | D74: =IF(TODAY()-E74<60,"2个月内",IF(TODAY()-E74<180,"3-6个月",IF(TODAY()-E74<360,"6个月-1年","一年以上"))) -> 一年以上 | E74: 43843 | F74: 销售部 | G74: 夏锋泽 | H74: 四川金宏通实业有限公司 | I74: 四川金宏通实业有限公司 | J74: 24000 | L74: 对公 | M74: 履约保证金 | N74: 24000 | O74: =J74-N74 -> 0 | P74: 44193 | Q74: =P74 -> 44193 | S74: 履约保证金
A75: 56 | B75: BZJ-0073 | C75: 43891 | D75: =IF(TODAY()-E75<60,"2个月内",IF(TODAY()-E75<180,"3-6个月",IF(TODAY()-E75<360,"6个月-1年","一年以上"))) -> 一年以上 | E75: 43920 | F75: 生产部 | G75: 雍佳强 | H75: 青海海西化工建材股份有限公司 | I75: 青海海西化工建材股份有限公司 | J75: 5000 | L75: 个人 | M75: 安全保证金 | N75: 5000 | O75: =J75-N75 -> 0 | P75: 44039 | Q75: =P75 -> 44039
A76: 57 | B76: BZJ-0074 | C76: 43922 | D76: =IF(TODAY()-E76<60,"2个月内",IF(TODAY()-E76<180,"3-6个月",IF(TODAY()-E76<360,"6个月-1年","一年以上"))) -> 一年以上 | E76: 43923 | F76: 生产部 | G76: 祝威 | H76: 甘肃永固特种水泥有限公司 | I76: 甘肃永固特种水泥有限公司 | J76: 10000 | K76: 武汉 | L76: 武汉对公 | M76: 安全保证金 | O76: =J76-N76 -> 10000 | Q76: =P76 -> 0 | R76: 已提供对账单，与货款一起请方渊在跟进。起诉调解，第一批25万已支付 | S76: 武汉2020.04-07 | T76: 甘肃省 | U76: =VLOOKUP(T76,[1]区域划分!$A$1:$C$39,3,0) -> 曾江利
A77: 196 | B77: BZJ-0075 | C77: 43922 | D77: =IF(TODAY()-E77<60,"2个月内",IF(TODAY()-E77<180,"3-6个月",IF(TODAY()-E77<360,"6个月-1年","一年以上"))) -> 一年以上 | E77: 43936 | G77: 吴海波 | H77: 河北新金轧材有限公司 | I77: 河北新金轧材有限公司 | J77: 10000 | L77: 对公 | M77: 投标保证金 | N77: 10000 | O77: =J77-N77 -> 0 | P77: 44155 | Q77: =P77 -> 44155 | S77: 投标保证金
A78: 58 | B78: BZJ-0076 | C78: 43952 | D78: =IF(TODAY()-E78<60,"2个月内",IF(TODAY()-E78<180,"3-6个月",IF(TODAY()-E78<360,"6个月-1年","一年以上"))) -> 一年以上 | E78: 43967 | F78: 生产部 | G78: 吕海洲 | H78: 贵州沿河西南水泥有限公司 | I78: 贵州沿河西南水泥有限公司 | J78: 5000 | L78: 对公 | M78: 安全保证金 | N78: 5000 | O78: =J78-N78 -> 0 | P78: 44463 | Q78: =P78 -> 44463
A79: 59 | B79: BZJ-0077 | C79: 43952 | D79: =IF(TODAY()-E79<60,"2个月内",IF(TODAY()-E79<180,"3-6个月",IF(TODAY()-E79<360,"6个月-1年","一年以上"))) -> 一年以上 | E79: 43969 | F79: 生产部 | G79: 汪勇刚 | H79: 四川达州钢铁有限公司 | I79: 四川达州钢铁有限公司 | J79: 2000 | L79: 个人 | M79: 安全保证金 | N79: 2000 | O79: =J79-N79 -> 0 | P79: 44034 | Q79: =P79 -> 44034
A80: 60 | B80: BZJ-0078 | C80: 43952 | D80: =IF(TODAY()-E80<60,"2个月内",IF(TODAY()-E80<180,"3-6个月",IF(TODAY()-E80<360,"6个月-1年","一年以上"))) -> 一年以上 | E80: 43969 | F80: 生产部 | G80: 黄国恩 | H80: 四川峨眉山西南水泥有限公司 | I80: 四川峨眉山西南水泥有限公司 | J80: 3000 | L80: 对公 | M80: 安全保证金 | N80: 3000 | O80: =J80-N80 -> 0 | P80: 44035 | Q80: =P80 -> 44035
A81: 61 | B81: BZJ-0079 | C81: 43952 | D81: =IF(TODAY()-E81<60,"2个月内",IF(TODAY()-E81<180,"3-6个月",IF(TODAY()-E81<360,"6个月-1年","一年以上"))) -> 一年以上 | E81: 43977 | F81: 生产部 | G81: 何煜军 | H81: 冀东海天水泥闻喜有限公司 | I81: 冀东海天水泥闻喜有限公司 | J81: 5000 | L81: 对公 | M81: 安全保证金 | N81: 5000 | O81: =J81-N81 -> 0 | P81: 44491 | Q81: =P81 -> 44491
A82: 62 | B82: BZJ-0080 | C82: 43983 | D82: =IF(TODAY()-E82<60,"2个月内",IF(TODAY()-E82<180,"3-6个月",IF(TODAY()-E82<360,"6个月-1年","一年以上"))) -> 一年以上 | E82: 43992 | F82: 生产部 | G82: 吕海洲 | H82: 阳泉冀东水泥有限责任公司 | I82: 阳泉冀东水泥有限责任公司 | J82: 2000 | L82: 对公 | M82: 安全保证金 | N82: 2000 | O82: =J82-N82 -> 0 | P82: 44083 | Q82: =P82 -> 44083
A83: 63 | B83: BZJ-0081 | C83: 43983 | D83: =IF(TODAY()-E83<60,"2个月内",IF(TODAY()-E83<180,"3-6个月",IF(TODAY()-E83<360,"6个月-1年","一年以上"))) -> 一年以上 | E83: 44010 | F83: 生产部 | G83: 黄庭兴 | H83: 四川华蓥西南水泥有限公司 | I83: 四川华蓥西南水泥有限公司 | J83: 1500 | L83: 对公 | M83: 安全保证金 | N83: 1500 | O83: =J83-N83 -> 0 | P83: 44130 | Q83: =P83 -> 44130
A84: 197 | B84: BZJ-0082 | C84: 43983 | D84: =IF(TODAY()-E84<60,"2个月内",IF(TODAY()-E84<180,"3-6个月",IF(TODAY()-E84<360,"6个月-1年","一年以上"))) -> 一年以上 | E84: 44011 | G84: 夏锋泽 | H84: 四川西南水泥有限公司（川渝西南） | I84: 四川西南水泥有限公司 | J84: 50000 | K84: 武汉 | L84: 对公 | M84: 投标保证金 | N84: 50000 | O84: =J84-N84 -> 0 | P84: 45554 | Q84: =P84 -> 45554 | S84: 测窑及维修，长期投标不退 | T84: 四川省 | U84: =VLOOKUP(T84,[1]区域划分!$A$1:$C$39,3,0) -> 牛国庆
A85: 64 | B85: BZJ-0083 | C85: 43983 | D85: =IF(TODAY()-E85<60,"2个月内",IF(TODAY()-E85<180,"3-6个月",IF(TODAY()-E85<360,"6个月-1年","一年以上"))) -> 一年以上 | E85: 44012 | F85: 销售部 | G85: 杨春龙 | H85: 天瑞集团郑州水泥有限公司 | I85: 天瑞集团郑州水泥有限公司 | J85: 3000 | L85: 个人 | M85: 安全保证金 | N85: 3000 | O85: =J85-N85 -> 0 | P85: 44196 | Q85: =P85 -> 44196
A86: 65 | B86: BZJ-0084 | C86: 44013 | D86: =IF(TODAY()-E86<60,"2个月内",IF(TODAY()-E86<180,"3-6个月",IF(TODAY()-E86<360,"6个月-1年","一年以上"))) -> 一年以上 | E86: 44018 | F86: 生产部 | G86: 祝发权 | H86: 阳泉冀东水泥有限责任公司 | I86: 阳泉冀东水泥有限责任公司 | J86: 2000 | L86: 对公 | M86: 安全保证金 | N86: 2000 | O86: =J86-N86 -> 0 | P86: 44083 | Q86: =P86 -> 44083
A87: 66 | B87: BZJ-0085 | C87: 44013 | D87: =IF(TODAY()-E87<60,"2个月内",IF(TODAY()-E87<180,"3-6个月",IF(TODAY()-E87<360,"6个月-1年","一年以上"))) -> 一年以上 | E87: 44021 | F87: 生产部 | G87: 王小勇 | H87: 贵州松桃高力水泥实业有限公司 | I87: 贵州松桃高力水泥实业有限公司 | J87: 1000 | L87: 对公 | M87: 安全保证金 | N87: 1000 | O87: =J87-N87 -> 0 | P87: 44069 | Q87: =P87 -> 44069 | S87: 对公退款800元和交现金200元
A88: 68 | B88: BZJ-0086 | C88: 44013 | D88: =IF(TODAY()-E88<60,"2个月内",IF(TODAY()-E88<180,"3-6个月",IF(TODAY()-E88<360,"6个月-1年","一年以上"))) -> 一年以上 | E88: 44025 | F88: 生产部 | G88: 程时勇 | H88: 冀东水泥璧山有限公司 | I88: 冀东水泥璧山有限公司 | J88: 2000 | L88: 对公 | M88: 安全保证金 | N88: 2000 | O88: =J88-N88 -> 0 | P88: 44223 | Q88: =P88 -> 44223 | S88: 2021年1月27日收2000冀东水泥璧山有限公司退安全保证金
A89: 67 | B89: BZJ-0087 | C89: 44013 | D89: =IF(TODAY()-E89<60,"2个月内",IF(TODAY()-E89<180,"3-6个月",IF(TODAY()-E89<360,"6个月-1年","一年以上"))) -> 一年以上 | E89: 44027 | F89: 生产部 | G89: 王小勇 | H89: 贵州织金西南水泥有限公司 | I89: 贵州织金西南水泥有限公司 | J89: 1000 | L89: 对公 | M89: 安全保证金 | N89: 1000 | O89: =J89-N89 -> 0 | P89: 44547 | Q89: =P89 -> 44547
A90: 69 | B90: BZJ-0088 | C90: 44013 | D90: =IF(TODAY()-E90<60,"2个月内",IF(TODAY()-E90<180,"3-6个月",IF(TODAY()-E90<360,"6个月-1年","一年以上"))) -> 一年以上 | E90: 44034 | F90: 生产部 | G90: 程时勇 | H90: 达州利森水泥有限公司 | I90: 达州利森水泥有限公司 | J90: 3000 | L90: 对公 | M90: 安全保证金 | N90: 3000 | O90: =J90-N90 -> 0 | P90: 44071 | Q90: =P90 -> 44071 | S90: 2020-8-27程时勇退3000达州利森水泥安全保证金（款打给达州利森水泥有限公司）
A91: 70 | B91: BZJ-0089 | C91: 44013 | D91: =IF(TODAY()-E91<60,"2个月内",IF(TODAY()-E91<180,"3-6个月",IF(TODAY()-E91<360,"6个月-1年","一年以上"))) -> 一年以上 | E91: 44034 | F91: 生产二部 | G91: 黄庭兴 | H91: 赞皇金隅水泥有限公司 | I91: 赞皇金隅水泥有限公司 | J91: 3200 | K91: 武汉 | L91: 武汉对公 | M91: 安全保证金 | N91: 3200 | O91: =J91-N91 -> 0 | P91: 44678 | Q91: =P91 -> 44678 | S91: 安全保证金 | T91: 河北省 | U91: 杨春龙 | V91: 武汉2020.7-147
A92: 71 | B92: BZJ-0090 | C92: 44013 | D92: =IF(TODAY()-E92<60,"2个月内",IF(TODAY()-E92<180,"3-6个月",IF(TODAY()-E92<360,"6个月-1年","一年以上"))) -> 一年以上 | E92: 44034 | F92: 生产部 | G92: 汪勇刚 | H92: 四川德胜集团水泥有限公司 | I92: 四川德胜集团水泥有限公司 | J92: 3000 | L92: 对公 | M92: 安全保证金 | N92: 3000 | O92: =J92-N92 -> 0 | P92: 44221 | Q92: =P92 -> 44221 | S92: 2021年1月25日收四川德胜集团水泥有限公司退安全保证金
A93: 72 | B93: BZJ-0091 | C93: 44013 | D93: =IF(TODAY()-E93<60,"2个月内",IF(TODAY()-E93<180,"3-6个月",IF(TODAY()-E93<360,"6个月-1年","一年以上"))) -> 一年以上 | E93: 44038 | F93: 生产部 | G93: 程时勇 | H93: 韩城尧柏阳山庄水泥有限公司 | I93: 韩城尧柏阳山庄水泥有限公司 | J93: 10000 | L93: 对公 | M93: 安全保证金 | N93: 10000 | O93: =J93-N93 -> 0 | P93: 44073 | Q93: =P93 -> 44073 | S93: 2020-8-31程时勇退10000韩城尧柏水泥安全保证金（款打给韩城尧柏阳山庄水泥有限公司）
A94: 74 | B94: BZJ-0092 | C94: 44044 | D94: =IF(TODAY()-E94<60,"2个月内",IF(TODAY()-E94<180,"3-6个月",IF(TODAY()-E94<360,"6个月-1年","一年以上"))) -> 一年以上 | E94: 44048 | F94: 销售部 | G94: 夏锋泽 | H94: 冀东水泥重庆合川有限责任公司 | I94: 冀东水泥重庆合川有限责任公司 | J94: 2000 | K94: 武汉 | L94: 武汉对公 | M94: 安全保证金 | N94: 2000 | O94: =J94-N94 -> 0 | P94: 44707 | Q94: =P94 -> 44707 | R94: 需要上门办理牛国庆处理，预计5月 | S94: 安全保证金 | T94: 重庆 | U94: 牛国庆 | V94: 武汉2020.08-07
A95: 75 | B95: BZJ-0093 | C95: 44044 | D95: =IF(TODAY()-E95<60,"2个月内",IF(TODAY()-E95<180,"3-6个月",IF(TODAY()-E95<360,"6个月-1年","一年以上"))) -> 一年以上 | E95: 44050 | F95: 销售部 | G95: 陈冲 | H95: 商洛尧柏龙桥水泥有限公司 | I95: 商洛尧柏龙桥水泥有限公司 | J95: 10000 | K95: 武汉 | L95: 对公 | M95: 安全保证金 | N95: 10000 | O95: =J95-N95 -> 0 | P95: 45070 | Q95: =P95 -> 45070 | R95: 3.2023.4月林维现场跟进，退款手续办理中，预计5月退回 | S95: 安全保证金 | T95: 陕西省 | U95: 朱利勇
A96: 76 | B96: BZJ-0094 | C96: 44044 | D96: =IF(TODAY()-E96<60,"2个月内",IF(TODAY()-E96<180,"3-6个月",IF(TODAY()-E96<360,"6个月-1年","一年以上"))) -> 一年以上 | E96: 44053 | F96: 销售部 | G96: 夏锋泽 | H96: 旺苍川煤水泥有限责任公司 | I96: 旺苍川煤水泥有限责任公司 | J96: 3000 | L96: 对公 | M96: 安全保证金 | N96: 3000 | O96: =J96-N96 -> 0 | P96: 44094 | Q96: =P96 -> 44094
A97: 77 | B97: BZJ-0095 | C97: 44044 | D97: =IF(TODAY()-E97<60,"2个月内",IF(TODAY()-E97<180,"3-6个月",IF(TODAY()-E97<360,"6个月-1年","一年以上"))) -> 一年以上 | E97: 44057 | F97: 销售部 | G97: 夏锋泽 | H97: 重庆长寿西南水泥有限公司 | I97: 重庆长寿西南水泥有限公司 | J97: 3000 | L97: 对公 | M97: 安全保证金 | N97: 3000 | O97: =J97-N97 -> 0 | P97: 44335 | Q97: =P97 -> 44335
A98: 78 | B98: BZJ-0096 | C98: 44044 | D98: =IF(TODAY()-E98<60,"2个月内",IF(TODAY()-E98<180,"3-6个月",IF(TODAY()-E98<360,"6个月-1年","一年以上"))) -> 一年以上 | E98: 44063 | F98: 销售部 | G98: 瞿新虎 | H98: 华新水泥（红河）有限公司 | I98: 华新水泥（红河）有限公司 | J98: 5000 | L98: 个人 | M98: 安全保证金 | N98: 5000 | O98: =J98-N98 -> 0 | P98: 44068 | Q98: =P98 -> 44068
A99: 198 | B99: BZJ-0097 | C99: 44075 | D99: =IF(TODAY()-E99<60,"2个月内",IF(TODAY()-E99<180,"3-6个月",IF(TODAY()-E99<360,"6个月-1年","一年以上"))) -> 一年以上 | E99: 44078 | G99: 瞿新虎 | H99: 云南西南水泥有限公司 | I99: 云南西南水泥有限公司 | J99: 50000 | K99: 武汉 | L99: 对公 | M99: 投标保证金 | N99: 50000 | O99: =J99-N99 -> 0 | P99: 45257 | Q99: =P99 -> 45257 | R99: 年标，转履约 | S99: 长期投标不退 | T99: 云南省 | U99: =VLOOKUP(T99,[1]区域划分!$A$1:$C$39,3,0) -> 牛国庆
A100: 199 | B100: BZJ-0098 | C100: 44075 | D100: =IF(TODAY()-E100<60,"2个月内",IF(TODAY()-E100<180,"3-6个月",IF(TODAY()-E100<360,"6个月-1年","一年以上"))) -> 一年以上 | E100: 44085 | G100: 吴海波 | H100: 昌黎冀东水泥有限公司 | I100: 昌黎冀东水泥有限公司 | J100: 2000 | L100: 对公 | M100: 投标保证金 | N100: 2000 | O100: =J100-N100 -> 0 | P100: 44559 | Q100: =P100 -> 44559 | S100: 投标保证金
...

Sheet 退款明细
A1: 保证金回款明细表
A2: 序列 | B2: 日期 | C2: 公司名称 | D2: 合同号 | E2: 回款类型 | F2: 回款金额（元） | G2: 回款方式 | H2: 备注 | I2: 保证金编号 | J2: 退款退还编号
A3: 1 | B3: 46029 | C3: 山东泰山钢铁集团有限公司 | E3: 转账 | F3: 5000 | G3: 林维转款（武汉浦发） | H3: 安全保证金 | K3: =_xlfn.XLOOKUP(I3,保证金登记!B:B,保证金登记!O:O) -> 0
A4: 2 | B4: 46045 | C4: 安徽省优质采科技发展有限责任公司 | E4: 转账 | F4: 20000 | G4: 武汉浦发 | H4: 投标保证金 | I4: BZJSQ-20251118-0158 | J4: BZJTH-20260126-0001 | K4: =_xlfn.XLOOKUP(I4,保证金登记!B:B,保证金登记!O:O) -> 0
A5: 3 | B5: 46049 | C5: 青海发投碱业有限公司 | E5: 转账 | F5: 28000 | G5: 武汉浦发 | H5: 履约保证金 | I5: BZJSQ-20250311-0032 | J5: BZJTH-20260128-0002 | K5: =_xlfn.XLOOKUP(I5,保证金登记!B:B,保证金登记!O:O) -> 0
A6: 4 | B6: 46049 | C6: 青海发投碱业有限公司 | E6: 转账 | F6: 18000 | G6: 武汉浦发 | H6: 安全保证金 | I6: BZJSQ-20250318-0040 | J6: BZJTH-20260128-0003 | K6: =_xlfn.XLOOKUP(I6,保证金登记!B:B,保证金登记!O:O) -> 0
A7: 5 | B7: 46049 | C7: 青海发投碱业有限公司 | E7: 转账 | F7: 17875 | G7: 武汉浦发 | H7: 履约保证金 | I7: BZJSQ-20250319-0045 | J7: BZJTH-20260128-0004 | K7: =_xlfn.XLOOKUP(I7,保证金登记!B:B,保证金登记!O:O) -> 0
A8: 6 | B8: 46049 | C8: 青海发投碱业有限公司 | E8: 转账 | F8: 50000 | G8: 武汉浦发 | H8: 安全保证金 | I8: BZJSQ-20250429-0069 | J8: BZJTH-20260128-0005 | K8: =_xlfn.XLOOKUP(I8,保证金登记!B:B,保证金登记!O:O) -> 0
A9: 7 | B9: 46049 | C9: 青海发投碱业有限公司 | E9: 转账 | F9: 9000 | G9: 武汉浦发 | H9: 安全保证金 | I9: BZJSQ-20250609-0092 | J9: BZJTH-20260128-0006 | K9: =_xlfn.XLOOKUP(I9,保证金登记!B:B,保证金登记!O:O) -> 0
A10: 8 | B10: 46049 | C10: 青海发投碱业有限公司 | E10: 转账 | F10: 7500 | G10: 武汉浦发 | H10: 安全保证金 | I10: BZJSQ-20250609-0095 | J10: BZJTH-20260128-0007 | K10: =_xlfn.XLOOKUP(I10,保证金登记!B:B,保证金登记!O:O) -> 0
A11: 9 | B11: 46049 | C11: 青海发投碱业有限公司 | E11: 转账 | F11: 8500 | G11: 武汉浦发 | H11: 安全保证金 | I11: BZJSQ-20250609-0098 | J11: BZJTH-20260128-0008 | K11: =_xlfn.XLOOKUP(I11,保证金登记!B:B,保证金登记!O:O) -> 0
A12: 10 | B12: 46049 | C12: 青海发投碱业有限公司 | E12: 转账 | F12: 16500 | G12: 武汉浦发 | H12: 安全保证金 | I12: BZJSQ-20250609-0101 | J12: BZJTH-20260128-0009 | K12: =_xlfn.XLOOKUP(I12,保证金登记!B:B,保证金登记!O:O) -> 0
A13: 11 | B13: 46049 | C13: 青海发投碱业有限公司 | E13: 转账 | F13: 500 | G13: 武汉浦发 | H13: 安全保证金 | I13: BZJSQ-20250623-0108 | J13: BZJTH-20260128-0010 | K13: =_xlfn.XLOOKUP(I13,保证金登记!B:B,保证金登记!O:O) -> 0
A14: 12 | B14: 46049 | C14: 青海发投碱业有限公司 | E14: 转账 | F14: 500 | G14: 武汉浦发 | H14: 安全保证金 | I14: BZJSQ-20250623-0109 | J14: BZJTH-20260128-0011 | K14: =_xlfn.XLOOKUP(I14,保证金登记!B:B,保证金登记!O:O) -> 0
A15: 13 | B15: 46049 | C15: 青海发投碱业有限公司 | E15: 转账 | F15: 500 | G15: 武汉浦发 | H15: 安全保证金 | I15: BZJSQ-20250623-0110 | J15: BZJTH-20260128-0012 | K15: =_xlfn.XLOOKUP(I15,保证金登记!B:B,保证金登记!O:O) -> 0
A16: 14 | B16: 46049 | C16: 青海发投碱业有限公司 | E16: 转账 | F16: 37000 | G16: 湖北岚丹中信 | H16: 安全保证金 | I16: BZJSQ-20250318-0038 | J16: BZJTH-20260128-0013 | K16: =_xlfn.XLOOKUP(I16,保证金登记!B:B,保证金登记!O:O) -> 0
A17: 15 | B17: 46049 | C17: 江苏唐电电力安装有限公司 | E17: 转账 | F17: 44000 | H17: 安全保证金 | I17: BZJSQ-20250416-0059 | J17: BZJTH-20260128-0014 | K17: =_xlfn.XLOOKUP(I17,保证金登记!B:B,保证金登记!O:O) -> 0
A18: 16 | B18: 46062 | C18: 新疆伊犁钢铁有限责任公司 | E18: 转账 | F18: 25536.9 | G18: 武汉浦发 | H18: 农民工工资保证金 | I18: BZJSQ-20241026-0115 | J18: BZJTH-20260209-0015 | K18: =_xlfn.XLOOKUP(I18,保证金登记!B:B,保证金登记!O:O) -> 0
A19: 17 | B19: 46062 | C19: 新疆伊犁钢铁有限责任公司 | E19: 转账 | F19: 4644.08 | G19: 武汉浦发 | H19: 农民工工资保证金 | I19: BZJSQ-20241026-0116 | J19: BZJTH-20260209-0016 | K19: =_xlfn.XLOOKUP(I19,保证金登记!B:B,保证金登记!O:O) -> 0
A20: 18 | B20: 46062 | C20: 新疆伊犁钢铁有限责任公司 | E20: 转账 | F20: 20838.39 | G20: 武汉浦发 | H20: 农民工工资保证金 | I20: BZJSQ-20241026-0117 | J20: BZJTH-20260209-0017 | K20: =_xlfn.XLOOKUP(I20,保证金登记!B:B,保证金登记!O:O) -> 0
A21: 19 | B21: 46062 | C21: 新疆伊犁钢铁有限责任公司 | E21: 转账 | F21: 15500 | G21: 武汉浦发 | H21: 履约保证金 | I21: BZJSQ-20241030-0122 | J21: BZJTH-20260209-0018 | K21: =_xlfn.XLOOKUP(I21,保证金登记!B:B,保证金登记!O:O) -> 0
A22: 20 | B22: 46062 | C22: 新疆伊犁钢铁有限责任公司 | E22: 转账 | F22: 69500 | G22: 武汉浦发 | H22: 履约保证金 | I22: BZJSQ-20241030-0123 | J22: BZJTH-20260209-0019 | K22: =_xlfn.XLOOKUP(I22,保证金登记!B:B,保证金登记!O:O) -> 0
A23: 21 | B23: 46062 | C23: 新疆伊犁钢铁有限责任公司 | E23: 转账 | F23: 85100 | G23: 武汉浦发 | H23: 履约保证金 | I23: BZJSQ-20241030-0124 | J23: BZJTH-20260209-0020 | K23: =_xlfn.XLOOKUP(I23,保证金登记!B:B,保证金登记!O:O) -> 0
A24: 22 | B24: 46080 | C24: 青海发投碱业有限公司 | E24: 转账 | F24: 6500 | G24: 湖北岚丹中信 | H24: 安全保证金 | I24: BZJSQ-20241230-0143 | J24: BZJTH-20260227-0021 | K24: =_xlfn.XLOOKUP(I24,保证金登记!B:B,保证金登记!O:O) -> 0
A25: 23 | B25: 46080 | C25: 青海发投碱业有限公司 | E25: 转账 | F25: 50000 | G25: 武汉浦发 | H25: 安全保证金 | I25: BZJSQ-20250114-0006 | J25: BZJTH-20260227-0022 | K25: =_xlfn.XLOOKUP(I25,保证金登记!B:B,保证金登记!O:O) -> 0
A26: 24 | B26: 46080 | C26: 青海发投碱业有限公司 | E26: 转账 | F26: 28000 | G26: 武汉浦发 | H26: 安全保证金 | I26: BZJSQ-20250311-0033 | J26: BZJTH-20260227-0023 | K26: =_xlfn.XLOOKUP(I26,保证金登记!B:B,保证金登记!O:O) -> 0
B27: 46081 | C27: 青海发投碱业有限公司 | E27: 转账 | F27: 11500 | H27: 履约保证金 | I27: BZJSQ-20231208-0777 | J27: BZJTH-20260228-0024 | K27: =_xlfn.XLOOKUP(I27,保证金登记!B:B,保证金登记!O:O) -> 0
B28: 46081 | C28: 青海发投碱业有限公司 | E28: 转账 | F28: 14300 | H28: 履约保证金 | I28: BZJSQ-20240508-0076 | J28: BZJTH-20260228-0025 | K28: =_xlfn.XLOOKUP(I28,保证金登记!B:B,保证金登记!O:O) -> 0
B29: 46081 | C29: 青海发投碱业有限公司 | E29: 转账 | F29: 14300 | H29: 农民工工资保证金 | I29: BZJSQ-20240508-0077 | J29: BZJTH-20260228-0026 | K29: =_xlfn.XLOOKUP(I29,保证金登记!B:B,保证金登记!O:O) -> 0
B30: 46081 | C30: 青海发投碱业有限公司 | E30: 转账 | F30: 50000 | H30: 履约保证金 | I30: BZJSQ-20250114-0005 | J30: BZJTH-20260228-0027 | K30: =_xlfn.XLOOKUP(I30,保证金登记!B:B,保证金登记!O:O) -> 0
B31: 46090 | C31: 安徽省优质采科技发展有限责任公司 | E31: 转账 | F31: 2000 | G31: 武汉浦发 | H31: 保证金 | I31: BZJSQ-20260227-0008 | J31: BZJTH-20260310-0028 | K31: =_xlfn.XLOOKUP(I31,保证金登记!B:B,保证金登记!O:O) -> 0
B32: 46094 | C32: 新疆宜化化工有限公司 | E32: 转账 | F32: 5500 | G32: 武汉浦发 | H32: 保证金 | I32: BZJSQ-20260129-0001 | J32: BZJTH-20260314-0029 | K32: =_xlfn.XLOOKUP(I32,保证金登记!B:B,保证金登记!O:O) -> 0
B33: 46094 | C33: 新疆宜化化工有限公司 | E33: 转账 | F33: 10000 | G33: 武汉浦发 | H33: 保证金 | I33: BZJSQ-20260209-0004 | J33: BZJTH-20260314-0030 | K33: =_xlfn.XLOOKUP(I33,保证金登记!B:B,保证金登记!O:O) -> 0
B34: 46097 | C34: 新疆宜化化工有限公司 | E34: 转账 | F34: 22000 | G34: 武汉浦发 | H34: 保证金 | I34: BZJSQ-20260209-0003 | J34: ZJTH-20260316-0031 | K34: =_xlfn.XLOOKUP(I34,保证金登记!B:B,保证金登记!O:O) -> 0
B35: 46099 | C35: 新疆宜化化工有限公司 | E35: 转账 | F35: 35000 | G35: 武汉浦发 | H35: 保证金 | I35: BZJSQ-20251225-0163 | J35: BZJTH-20260318-0032 | K35: =_xlfn.XLOOKUP(I35,保证金登记!B:B,保证金登记!O:O) -> 0
B36: 46106 | C36: 佛山住商肥料有限公司 | E36: 转账 | F36: 3000 | H36: 保证金 | I36: BZJSQ-20260303-0014 | J36: BZJTH-20260325-0033 | K36: =_xlfn.XLOOKUP(I36,保证金登记!B:B,保证金登记!O:O) -> 0
B37: 46119 | C37: 成都云图控股股份有限公司 | E37: 转账 | F37: 30000 | G37: 湖北岚丹中信 | H37: 投标保证金 | I37: BZJSQ-20260311-0017 | J37: BZJTH-20260407-0034 | K37: =_xlfn.XLOOKUP(I37,保证金登记!B:B,保证金登记!O:O) -> 0
B38: 46119 | C38: 江西省精彩纵横采购咨询有限公司 | E38: 转账 | F38: 2000.26 | G38: 武汉浦发 | H38: 投标保证金 | I38: BZJSQ-20260302-0013 | J38: BZJTH-20260407-0035 | K38: =_xlfn.XLOOKUP(I38,保证金登记!B:B,保证金登记!O:O) -> -0.26
B39: 46121 | C39: 江苏唐电电力安装有限公司 | E39: 转账 | F39: 8000 | G39: 王先梅 | H39: 投标保证金 | I39: BZJSQ-20260224-0007 | J39: BZJTH-20260409-0036 | K39: =_xlfn.XLOOKUP(I39,保证金登记!B:B,保证金登记!O:O) -> 0
B40: 46120 | C40: 江西省精彩纵横采购咨询有限公司 | E40: 转账 | F40: 4000.16 | G40: 武汉浦发 | H40: 保证金 | I40: BZJSQ-20260403-0027 | J40: BZJTH-20260414-0037 | K40: =_xlfn.XLOOKUP(I40,保证金登记!B:B,保证金登记!O:O) -> -0.16
B41: 46122 | C41: 湖北长江运营咨询有限公司 | E41: 转账 | F41: 15000 | G41: 武汉浦发 | H41: 保证金 | I41: BZJSQ-20260317-0019 | J41: BZJTH-20260414-0038 | K41: =_xlfn.XLOOKUP(I41,保证金登记!B:B,保证金登记!O:O) -> 0
B42: 46122 | C42: 湖北长江运营咨询有限公司 | E42: 转账 | F42: 15000 | G42: 武汉浦发 | H42: 保证金 | I42: BZJSQ-20260317-0020 | J42: BZJTH-20260414-0039 | K42: =_xlfn.XLOOKUP(I42,保证金登记!B:B,保证金登记!O:O) -> 0
B43: 46122 | C43: 湖北长江运营咨询有限公司 | E43: 转账 | F43: 15000 | G43: 武汉浦发 | H43: 保证金 | I43: BZJSQ-20260317-0021 | J43: BZJTH-20260414-0040 | K43: =_xlfn.XLOOKUP(I43,保证金登记!B:B,保证金登记!O:O) -> 0
B44: 46122 | C44: 湖北长江运营咨询有限公司 | E44: 转账 | F44: 15000 | G44: 武汉浦发 | H44: 保证金 | I44: BZJSQ-20260317-0022 | J44: BZJTH-20260414-0041 | K44: =_xlfn.XLOOKUP(I44,保证金登记!B:B,保证金登记!O:O) -> 0
B45: 46122 | C45: 湖北长江运营咨询有限公司 | E45: 转账 | F45: 15000 | G45: 武汉浦发 | H45: 保证金 | I45: BZJSQ-20260317-0023 | J45: BZJTH-20260414-0042 | K45: =_xlfn.XLOOKUP(I45,保证金登记!B:B,保证金登记!O:O) -> 0
B46: 46139 | C46: 江西省精彩纵横采购咨询有限公司 | E46: 转账 | F46: 2000.31 | G46: 武汉浦发 | H46: 保证金 | I46: BZJSQ-20260403-0026 | J46: BZJTH-20260420-0043 | K46: =_xlfn.XLOOKUP(I46,保证金登记!B:B,保证金登记!O:O) -> -0.31
B47: 46139 | C47: 湖北双环科技股份有限公司 | E47: 转账 | F47: 20000 | G47: 湖北岚丹中信 | H47: 投标保证金 | I47: BZJSQ-20260410-0028 | J47: BZJTH-20260428-0044 | K47: =_xlfn.XLOOKUP(I47,保证金登记!B:B,保证金登记!O:O) -> 0
B48: 46140 | C48: 青海黎明化工有限责任公司 | E48: 转账 | F48: 10000 | G48: 武汉浦发 | H48: 投标保证金 | I48: BZJSQ-20260401-0025 | J48: BZJTH-20260429-0045 | K48: =_xlfn.XLOOKUP(I48,保证金登记!B:B,保证金登记!O:O) -> 0
... B62: 46202 | C62: 江阴兴澄特种钢铁有限公司 | E62: 转账 | F62: 2000 | G62: 武汉浦发 | H62: 投标保证金 | I62: BZJSQ-20260511-0034 | J62: BZJTH-20260629-0059 | K62: =_xlfn.XLOOKUP(I62,保证金登记!B:B,保证金登记!O:O) -> 0
D142: 合计： | F142: =SUBTOTAL(9,F3:F141) -> 1038695.1

Sheet 标书
C1: 其他应收明细表
A2: 序号 | B2: 编号 | C2: 月份 | D2: 账龄 | E2: 支付日期 | F2: 部门 | G2: 经办人 | H2: 公司名称 | I2: 公司名称2 | J2: 支付金额 | K2: 公司 | L2: 支付方式 | M2: 支付类型 | N2: 退款金额/ 发票冲账 | O2: 未退余额 | P2: 退款时间 | Q2: 退回月份 | R2: 未退原因 | S2: 备注 | T2: 省份 | U2: 业务经理 | V2: 联系人 | W2: 中标结果 | X2: 业务员
A3: 182 | B3: BZJ-0001 | C3: 42370 | D3: =IF(TODAY()-E3<60,"2个月内",IF(TODAY()-E3<180,"3-6个月",IF(TODAY()-E3<360,"6个月-1年","一年以上"))) -> 一年以上 | H3: 三门峡腾跃同力水泥有限公司 | I3: 三门峡腾跃同力水泥有限公司 | J3: 1000 | K3: 武汉 | L3: 期初余额 | M3: 投标保证金 | O3: =J3-N3 -> 1000 | Q3: =P3 -> 0 | R3: 找付款凭证 | T3: 河南省 | U3: =VLOOKUP(T3,[1]区域划分!$A$1:$C$39,3,0) -> 方渊
A4: 183 | B4: BZJ-0002 | C4: 42370 | D4: =IF(TODAY()-E4<60,"2个月内",IF(TODAY()-E4<180,"3-6个月",IF(TODAY()-E4<360,"6个月-1年","一年以上"))) -> 一年以上 | H4: 云南西南水泥有限公司 | I4: 云南西南水泥有限公司 | J4: 50000 | L4: 期初余额 | M4: 投标保证金 | N4: 50000 | O4: =J4-N4 -> 0 | P4: 44155 | Q4: =P4 -> 44155
A5: 184 | B5: BZJ-0003 | C5: 42370 | D5: =IF(TODAY()-E5<60,"2个月内",IF(TODAY()-E5<180,"3-6个月",IF(TODAY()-E5<360,"6个月-1年","一年以上"))) -> 一年以上 | H5: 淮北众城水泥有限责任公司 | I5: 淮北众城水泥有限责任公司 | J5: 3000 | K5: 武汉 | L5: 期初余额 | M5: 投标保证金 | O5: =J5-N5 -> 3000 | Q5: =P5 -> 0 | S5: 已被收购 | T5: 安徽省 | U5: =VLOOKUP(T5,[1]区域划分!$A$1:$C$39,3,0) -> 方渊
A6: 186 | B6: BZJ-0004 | C6: 42370 | D6: =IF(TODAY()-E6<60,"2个月内",IF(TODAY()-E6<180,"3-6个月",IF(TODAY()-E6<360,"6个月-1年","一年以上"))) -> 一年以上 | H6: 吉林亚泰（集团）股份有限公司物资经销分公司 | I6: 吉林亚泰集团物资贸易有限公司 | J6: 3800 | K6: 武汉 | L6: 期初余额 | M6: 投标保证金 | O6: =J6-N6 -> 3800 | Q6: =P6 -> 0 | R6: 预计2023.04或2023.05月退还，熊伟跟进中.客人无此笔,我司资料为期初数据有23800 | S6: 有凭证才可查询 | T6: 吉林省 | U6: =VLOOKUP(T6,[1]区域划分!$A$1:$C$39,3,0) -> 殷坤鹏 | V6: 张玉鹏13634307383
A7: 187 | B7: BZJ-0005 | C7: 42370 | D7: =IF(TODAY()-E7<60,"2个月内",IF(TODAY()-E7<180,"3-6个月",IF(TODAY()-E7<360,"6个月-1年","一年以上"))) -> 一年以上 | H7: 江苏永钢集团物资贸易有限公司 | I7: 江苏永钢集团物资贸易有限公司 | J7: 20000 | K7: 武汉 | L7: 期初余额 | M7: 投标保证金 | O7: =J7-N7 -> 20000 | Q7: =P7 -> 0 | R7: 对方财务查询并无此款 | S7: 对方财务查询并无此款 | T7: 江苏省 | U7: =VLOOKUP(T7,[1]区域划分!$A$1:$C$39,3,0) -> 龚运谱
A8: 188 | B8: BZJ-0006 | C8: 42370 | D8: =IF(TODAY()-E8<60,"2个月内",IF(TODAY()-E8<180,"3-6个月",IF(TODAY()-E8<360,"6个月-1年","一年以上"))) -> 一年以上 | H8: 酒泉钢铁（集团）有限公司 | I8: 酒泉钢铁（集团）有限公司 | J8: 300 | L8: 期初余额 | M8: 投标保证金 | N8: 300 | O8: =J8-N8 -> 0 | P8: 44728 | Q8: =P8 -> 44728 | S8: 可能是标书费
A9: 185 | B9: BZJ-0007 | C9: 42370 | D9: =IF(TODAY()-E9<60,"2个月内",IF(TODAY()-E9<180,"3-6个月",IF(TODAY()-E9<360,"6个月-1年","一年以上"))) -> 一年以上 | E9: 42390 | G9: 吴海波 | H9: 亚泰伊通 | I9: 亚泰集团伊通水泥有限公司 | J9: 20000 | K9: 武汉 | L9: 武汉对公 | M9: 投标保证金 | O9: =J9-N9 -> 20000 | Q9: =P9 -> 0 | R9: 预计2023.04或2023.05月退还，熊伟跟进中.客人无此笔,我司资料为期初数据有23800 | S9: 2016年1月42#凭证 | T9: 吉林省 | U9: =VLOOKUP(T9,[1]区域划分!$A$1:$C$39,3,0) -> 殷坤鹏 | V9: 张玉鹏13634307383
A10: 189 | B10: BZJ-0008 | C10: 42370 | D10: =IF(TODAY()-E10<60,"2个月内",IF(TODAY()-E10<180,"3-6个月",IF(TODAY()-E10<360,"6个月-1年","一年以上"))) -> 一年以上 | E10: 42400 | H10: 江苏沙钢集团有限公司 | I10: 江苏沙钢集团有限公司 | J10: 10000 | K10: 武汉 | L10: 平台上共8万 | M10: 投标保证金 | O10: =J10-N10 -> 10000 | Q10: =P10 -> 0 | R10: 长期投标不退 | S10: 投标保证金（前期借支2万元 后期借支5万元） 销售部查询系统里面有8万元保证金，长期投标不退 | T10: 江苏省 | U10: =VLOOKUP(T10,[1]区域划分!$A$1:$C$39,3,0) -> 龚运谱
A11: 1 | B11: BZJ-0009 | C11: 42887 | D11: =IF(TODAY()-E11<60,"2个月内",IF(TODAY()-E11<180,"3-6个月",IF(TODAY()-E11<360,"6个月-1年","一年以上"))) -> 一年以上 | E11: 42887 | H11: 江苏沙钢集团有限公司 | I11: 江苏沙钢集团有限公司 | J11: 10000 | K11: 武汉 | L11: 平台上共8万 | M11: 安全保证金 | O11: 10000 | Q11: =P11 -> 0 | T11: 江苏省 | U11: =VLOOKUP(T11,[1]区域划分!$A$1:$C$39,3,0) -> 龚运谱
A12: 190 | B12: BZJ-0010 | C12: 43466 | D12: =IF(TODAY()-E12<60,"2个月内",IF(TODAY()-E12<180,"3-6个月",IF(TODAY()-E12<360,"6个月-1年","一年以上"))) -> 一年以上 | E12: 43475 | G12: 汤勇华 | H12: 江苏沙钢集团有限公司 | I12: 江苏沙钢集团有限公司 | J12: 50000 | K12: 武汉 | L12: 平台上共8万 | M12: 投标保证金 | O12: =J12-N12 -> 50000 | Q12: =P12 -> 0 | R12: 长期投标不退 | S12: 投标保证金（前期借支2万元 后期借支5万元） 销售部查询系统里面有8万元保证金，长期投标不退 | T12: 江苏省 | U12: =VLOOKUP(T12,[1]区域划分!$A$1:$C$39,3,0) -> 龚运谱
A13: 5 | B13: BZJ-0011 | C13: 43101 | D13: =IF(TODAY()-E13<60,"2个月内",IF(TODAY()-E13<180,"3-6个月",IF(TODAY()-E13<360,"6个月-1年","一年以上"))) -> 一年以上 | E13: 43113 | F13: 生产部 | G13: 姜兵 | H13: 永登祁连山水泥有限公司 | I13: 永登祁连山水泥有限公司 | J13: 2000 | L13: 对公 | M13: 安全保证金 | N13: 2000 | O13: =J13-N13 -> 0 | P13: 44099 | Q13: =P13 -> 44099 | S13: 近期要施工
A14: 2 | B14: BZJ-0012 | C14: 43101 | D14: =IF(TODAY()-E14<60,"2个月内",IF(TODAY()-E14<180,"3-6个月",IF(TODAY()-E14<360,"6个月-1年","一年以上"))) -> 一年以上 | E14: 43124 | G14: 丁俊 | H14: 逸盛大化石化有限公司 | I14: 逸盛大化石化有限公司 | J14: 7000 | K14: 武汉 | M14: 安全保证金 | O14: 7000 | Q14: =P14 -> 0 | R14: 2023.03月殷总说之前做的质量有重大问题暂时不催 | S14: 2019年12月从丁俊个人转公司账7000元 | T14: 辽宁省 | U14: =VLOOKUP(T14,[1]区域划分!$A$1:$C$39,3,0) -> 殷坤鹏
A15: 10 | B15: BZJ-0013 | C15: 43252 | D15: =IF(TODAY()-E15<60,"2个月内",IF(TODAY()-E15<180,"3-6个月",IF(TODAY()-E15<360,"6个月-1年","一年以上"))) -> 一年以上 | E15: 43255 | F15: 生产一部 | G15: 汪勇刚 | H15: 德州中联大坝水泥有限公司 | I15: 德州中联大坝水泥有限公司 | J15: 15000 | K15: 武汉 | L15: 武汉对公 | M15: 安全保证金 | N15: 15000 | O15: =J15-N15 -> 0 | P15: 44936 | Q15: =P15 -> 44936 | S15: 武汉2018.06-40 | T15: 山东省 | U15: 李松林
A16: 15 | B16: BZJ-0014 | C16: 43313 | D16: =IF(TODAY()-E16<60,"2个月内",IF(TODAY()-E16<180,"3-6个月",IF(TODAY()-E16<360,"6个月-1年","一年以上"))) -> 一年以上 | E16: 43330 | F16: 生产部 | G16: 张子仪 | H16: 四川西南水泥有限公司 | I16: 四川西南水泥有限公司 | J16: 2000 | L16: 对公 | M16: 安全保证金 | N16: 2000 | O16: =J16-N16 -> 0 | P16: 43707 | Q16: =P16 -> 43707
A17: 6 | B17: BZJ-0015 | C17: 43374 | D17: =IF(TODAY()-E17<60,"2个月内",IF(TODAY()-E17<180,"3-6个月",IF(TODAY()-E17<360,"6个月-1年","一年以上"))) -> 一年以上 | E17: 43393 | F17: 生产部 | G17: 刘西 | H17: 新安中联万基水泥有限公司 | I17: 新安中联万基水泥有限公司 | J17: 3000 | L17: 对公 | M17: 安全保证金 | N17: 3000 | O17: =J17-N17 -> 0 | P17: 44126 | Q17: =P17 -> 44126 | S17: 施工质量问题无法办理
A18: 19 | B18: BZJ-0016 | C18: 43374 | D18: =IF(TODAY()-E18<60,"2个月内",IF(TODAY()-E18<180,"3-6个月",IF(TODAY()-E18<360,"6个月-1年","一年以上"))) -> 一年以上 | E18: 43404 | F18: 生产部 | G18: 丁俊 | H18: 逸盛大化石化有限公司 | I18: 逸盛大化石化有限公司 | J18: 7000 | L18: 个人 | M18: 安全保证金 | N18: 7000 | O18: =J18-N18 -> 0 | P18: 43480 | Q18: =P18 -> 43480
A19: 3 | B19: BZJ-0017 | C19: 43405 | D19: =IF(TODAY()-E19<60,"2个月内",IF(TODAY()-E19<180,"3-6个月",IF(TODAY()-E19<360,"6个月-1年","一年以上"))) -> 一年以上 | E19: 43414 | F19: 生产部 | G19: 丁俊 | H19: 韩城尧柏阳山庄水泥有限公司 | I19: 韩城尧柏阳山庄水泥有限公司 | J19: =20000 -> 20000 | K19: 武汉 | L19: 对公 | M19: 安全保证金 | N19: 20000 | O19: =J19-N19 -> 0 | Q19: =P19 -> 0 | S19: 2019/12/24退19800
A20: 4 | B20: BZJ-0018 | C20: 43435 | D20: =IF(TODAY()-E20<60,"2个月内",IF(TODAY()-E20<180,"3-6个月",IF(TODAY()-E20<360,"6个月-1年","一年以上"))) -> 一年以上 | E20: 43446 | F20: 生产部 | G20: 冯海雄 | H20: 民和祁连山水泥有限公司 | I20: 民和祁连山水泥有限公司 | J20: 8000 | L20: 对公 | M20: 安全保证金 | N20: 8000 | O20: =J20-N20 -> 0 | P20: 43609 | Q20: =P20 -> 43609
A21: 12 | B21: BZJ-0019 | C21: 43466 | D21: =IF(TODAY()-E21<60,"2个月内",IF(TODAY()-E21<180,"3-6个月",IF(TODAY()-E21<360,"6个月-1年","一年以上"))) -> 一年以上 | E21: 43493 | F21: 生产部 | G21: 吴昌松 | H21: 冀东海天水泥闻喜有限公司 | I21: 冀东海天水泥闻喜有限公司 | J21: 10000 | L21: 对公 | M21: 安全保证金 | N21: 10000 | O21: =J21-N21 -> 0 | P21: 43664 | Q21: =P21 -> 43664
A22: 11 | B22: BZJ-0020 | C22: 43497 | D22: =IF(TODAY()-E22<60,"2个月内",IF(TODAY()-E22<180,"3-6个月",IF(TODAY()-E22<360,"6个月-1年","一年以上"))) -> 一年以上 | E22: 43511 | F22: 生产部 | G22: 汪勇刚 | H22: 贵州中诚水泥有限公司 | I22: 贵州中诚水泥有限公司 | J22: 3000 | L22: 对公 | M22: 安全保证金 | N22: 3000 | O22: =J22-N22 -> 0 | P22: 43646 | Q22: =P22 -> 43646
A23: 8 | B23: BZJ-0021 | C23: 43497 | D23: =IF(TODAY()-E23<60,"2个月内",IF(TODAY()-E23<180,"3-6个月",IF(TODAY()-E23<360,"6个月-1年","一年以上"))) -> 一年以上 | E23: 43516 | F23: 生产部 | G23: 覃延吉 | H23: 云南丽江西南水泥有限公司 | I23: 云南丽江西南水泥有限公司 | J23: 1000 | L23: 对公 | M23: 安全保证金 | N23: 1000 | O23: =J23-N23 -> 0 | P23: 43692 | Q23: =P23 -> 43692
A24: 14 | B24: BZJ-0022 | C24: 43525 | D24: =IF(TODAY()-E24<60,"2个月内",IF(TODAY()-E24<180,"3-6个月",IF(TODAY()-E24<360,"6个月-1年","一年以上"))) -> 一年以上 | E24: 43526 | F24: 生产部 | G24: 詹年喜 | H24: 邯郸涉县金隅水泥有限公司 | I24: 邯郸涉县金隅水泥有限公司 | J24: 2000 | L24: 对公 | M24: 安全保证金 | N24: 2000 | O24: =J24-N24 -> 0 | P24: 43698 | Q24: =P24 -> 43698
A25: 13 | B25: BZJ-0023 | C25: 43525 | D25: =IF(TODAY()-E25<60,"2个月内",IF(TODAY()-E25<180,"3-6个月",IF(TODAY()-E25<360,"6个月-1年","一年以上"))) -> 一年以上 | E25: 43530 | F25: 生产部 | G25: 詹年喜 | H25: 阳泉冀东水泥有限责任公司 | I25: 阳泉冀东水泥有限责任公司 | J25: 3000 | L25: 对公 | M25: 安全保证金 | N25: 3000 | O25: =J25-N25 -> 0 | P25: 43700 | Q25: =P25 -> 43700
A26: 9 | B26: BZJ-0024 | C26: 43525 | D26: =IF(TODAY()-E26<60,"2个月内",IF(TODAY()-E26<180,"3-6个月",IF(TODAY()-E26<360,"6个月-1年","一年以上"))) -> 一年以上 | E26: 43539 | F26: 生产部 | G26: 覃延吉 | H26: 河钢股份有限公司邯郸分公司 | I26: 河钢股份有限公司邯郸分公司 | J26: 10000 | L26: 对公 | M26: 安全保证金 | N26: 10000 | O26: =J26-N26 -> 0 | P26: 43613 | Q26: =P26 -> 43613
A27: 7 | B27: BZJ-0025 | C27: 43556 | D27: =IF(TODAY()-E27<60,"2个月内",IF(TODAY()-E27<180,"3-6个月",IF(TODAY()-E27<360,"6个月-1年","一年以上"))) -> 一年以上 | E27: 43557 | F27: 生产部 | G27: 石靖 | H27: 达州利森水泥有限公司 | I27: 达州利森水泥有限公司 | J27: 5000 | L27: 对公 | M27: 安全保证金 | N27: 5000 | O27: =J27-N27 -> 0 | P27: 43633 | Q27: =P27 -> 43633
A28: 16 | B28: BZJ-0026 | C28: 43556 | D28: =IF(TODAY()-E28<60,"2个月内",IF(TODAY()-E28<180,"3-6个月",IF(TODAY()-E28<360,"6个月-1年","一年以上"))) -> 一年以上 | E28: 43560 | F28: 总经办 | G28: 汤勇华 | H28: 张家港宏昌钢板有限公司 | I28: 张家港宏昌钢板有限公司 | J28: 124500 | K28: 武汉 | L28: 武汉对公 | M28: 安全保证金 | N28: 124500 | O28: =J28-N28 -> 0 | P28: 44890 | Q28: =P28 -> 44890 | S28: 武汉2019.4-50 | T28: 江苏省 | U28: 杨春龙 | V28: 预计2022.10月，收完全款后退回
A29: 194 | B29: BZJ-0027 | C29: 43556 | D29: =IF(TODAY()-E29<60,"2个月内",IF(TODAY()-E29<180,"3-6个月",IF(TODAY()-E29<360,"6个月-1年","一年以上"))) -> 一年以上 | E29: 43570 | G29: 夏锋泽 | H29: 四川西南水泥有限公司 | I29: 四川西南水泥有限公司 | J29: 10000 | L29: 对公 | M29: 投标保证金 | N29: 10000 | O29: =J29-N29 -> 0 | P29: 44064 | Q29: =P29 -> 44064 | S29: 长期投标不退
A30: 343 | B30: BZJ-0028 | C30: 43556 | D30: =IF(TODAY()-E30<60,"2个月内",IF(TODAY()-E30<180,"3-6个月",IF(TODAY()-E30<360,"6个月-1年","一年以上"))) -> 一年以上 | E30: 43585 | F30: 销售部 | G30: 李辉 | H30: 葛洲坝钟祥水泥有限公司 | I30: 葛洲坝钟祥水泥有限公司 | J30: 10000 | L30: 对公 | M30: 履约保证金 | N30: 10000 | O30: =J30-N30 -> 0 | P30: 43938 | Q30: =P30 -> 43938 | S30: 履约保证金
A31: 17 | B31: BZJ-0029 | C31: 43586 | D31: =IF(TODAY()-E31<60,"2个月内",IF(TODAY()-E31<180,"3-6个月",IF(TODAY()-E31<360,"6个月-1年","一年以上"))) -> 一年以上 | E31: 43600 | F31: 生产部 | G31: 李文池 | H31: 四川峨眉山西南水泥有限公司 | I31: 四川峨眉山西南水泥有限公司 | J31: 3000 | L31: 对公 | M31: 安全保证金 | N31: 3000 | O31: =J31-N31 -> 0 | P31: 43824 | Q31: =P31 -> 43824
A32: 18 | B32: BZJ-0030 | C32: 43586 | D32: =IF(TODAY()-E32<60,"2个月内",IF(TODAY()-E32<180,"3-6个月",IF(TODAY()-E32<360,"6个月-1年","一年以上"))) -> 一年以上 | E32: 43601 | F32: 生产部 | G32: 吴昌松 | H32: 云南昆钢嘉华水泥建材有限公司 | I32: 云南昆钢嘉华水泥建材有限公司 | J32: 3000 | L32: 对公 | M32: 安全保证金 | N32: 3000 | O32: =J32-N32 -> 0 | P32: 44484 | Q32: =P32 -> 44484
A33: 20 | B33: BZJ-0031 | C33: 43586 | D33: =IF(TODAY()-E33<60,"2个月内",IF(TODAY()-E33<180,"3-6个月",IF(TODAY()-E33<360,"6个月-1年","一年以上"))) -> 一年以上 | E33: 43601 | F33: 生产部 | G33: 余茶林 | H33: 汉中尧柏水泥有限公司 | I33: 汉中尧柏水泥有限公司 | J33: 10000 | L33: 对公 | M33: 安全保证金 | N33: 10000 | O33: =J33-N33 -> 0 | P33: 43973 | Q33: =P33 -> 43973
A34: 21 | B34: BZJ-0032 | C34: 43617 | D34: =IF(TODAY()-E34<60,"2个月内",IF(TODAY()-E34<180,"3-6个月",IF(TODAY()-E34<360,"6个月-1年","一年以上"))) -> 一年以上 | E34: 43621 | F34: 生产部 | G34: 房延云 | H34: 鲁南中联水泥有限公司 | I34: 鲁南中联水泥有限公司 | J34: 2000 | L34: 个人 | M34: 安全保证金 | N34: 2000 | O34: =J34-N34 -> 0 | P34: 43676 | Q34: =P34 -> 43676
A35: 22 | B35: BZJ-0033 | C35: 43617 | D35: =IF(TODAY()-E35<60,"2个月内",IF(TODAY()-E35<180,"3-6个月",IF(TODAY()-E35<360,"6个月-1年","一年以上"))) -> 一年以上 | E35: 43628 | F35: 生产部 | G35: 王小勇 | H35: 莒县中联水泥有限公司 | I35: 莒县中联水泥有限公司 | J35: 5000 | L35: 对公 | M35: 安全保证金 | N35: 5000 | O35: =J35-N35 -> 0 | P35: 43641 | Q35: =P35 -> 43641
A36: 23 | B36: BZJ-0034 | C36: 43617 | D36: =IF(TODAY()-E36<60,"2个月内",IF(TODAY()-E36<180,"3-6个月",IF(TODAY()-E36<360,"6个月-1年","一年以上"))) -> 一年以上 | E36: 43635 | F36: 生产部 | G36: 程时勇 | H36: 贵州沿河西南水泥有限公司 | I36: 贵州沿河西南水泥有限公司 | J36: 2000 | L36: 对公 | M36: 安全保证金 | N36: 2000 | O36: =J36-N36 -> 0 | P36: 43644 | Q36: =P36 -> 43644
A37: 24 | B37: BZJ-0035 | C37: 43617 | D37: =IF(TODAY()-E37<60,"2个月内",IF(TODAY()-E37<180,"3-6个月",IF(TODAY()-E37<360,"6个月-1年","一年以上"))) -> 一年以上 | E37: 43644 | F37: 生产部 | G37: 李文池 | H37: 西安蓝田尧柏水泥有限公司 | I37: 西安蓝田尧柏水泥有限公司 | J37: 10000 | L37: 对公 | M37: 安全保证金 | N37: 10000 | O37: =J37-N37 -> 0 | P37: 43703 | Q37: =P37 -> 43703
A38: 25 | B38: BZJ-0036 | C38: 43647 | D38: =IF(TODAY()-E38<60,"2个月内",IF(TODAY()-E38<180,"3-6个月",IF(TODAY()-E38<360,"6个月-1年","一年以上"))) -> 一年以上 | E38: 43657 | F38: 生产部 | G38: 吴昌松 | H38: 会东利森水泥有限公司 | I38: 会东利森水泥有限公司 | J38: 3000 | L38: 对公 | M38: 安全保证金 | N38: 3000 | O38: =J38-N38 -> 0 | P38: 43703 | Q38: =P38 -> 43703
A39: 27 | B39: BZJ-0037 | C39: 43647 | D39: =IF(TODAY()-E39<60,"2个月内",IF(TODAY()-E39<180,"3-6个月",IF(TODAY()-E39<360,"6个月-1年","一年以上"))) -> 一年以上 | E39: 43657 | F39: 生产部 | G39: 熊军 | H39: 冀东水泥铜川有限公司 | I39: 冀东水泥铜川有限公司 | J39: 1000 | L39: 个人 | M39: 安全保证金 | N39: 1000 | O39: =J39-N39 -> 0 | P39: 43661 | Q39: =P39 -> 43661
A40: 26 | B40: BZJ-0038 | C40: 43647 | D40: =IF(TODAY()-E40<60,"2个月内",IF(TODAY()-E40<180,"3-6个月",IF(TODAY()-E40<360,"6个月-1年","一年以上"))) -> 一年以上 | E40: 43664 | F40: 生产部 | G40: 吴昌松 | H40: 四川省绵竹澳东水泥有限责任公司 | I40: 四川省绵竹澳东水泥有限责任公司 | J40: 3000 | L40: 对公 | M40: 安全保证金 | N40: 3000 | O40: =J40-N40 -> 0 | P40: 43794 | Q40: =P40 -> 43794
A41: 28 | B41: BZJ-0039 | C41: 43678 | D41: =IF(TODAY()-E41<60,"2个月内",IF(TODAY()-E41<180,"3-6个月",IF(TODAY()-E41<360,"6个月-1年","一年以上"))) -> 一年以上 | E41: 43678 | F41: 生产部 | G41: 余茶林 | H41: 嘉华特种水泥股份有限公司嘉华水泥总厂 | I41: 嘉华特种水泥股份有限公司嘉华水泥总厂 | J41: 2000 | L41: 对公 | M41: 安全保证金 | N41: 2000 | O41: =J41-N41 -> 0 | P41: 43700 | Q41: =P41 -> 43700
A42: 29 | B42: BZJ-0040 | C42: 43678 | D42: =IF(TODAY()-E42<60,"2个月内",IF(TODAY()-E42<180,"3-6个月",IF(TODAY()-E42<360,"6个月-1年","一年以上"))) -> 一年以上 | E42: 43685 | F42: 销售部 | G42: 吴海波 | H42: 山东鲁城水泥有限公司 | I42: 山东鲁城水泥有限公司 | J42: 10000 | L42: 对公 | M42: 安全保证金 | N42: 10000 | O42: =J42-N42 -> 0 | P42: 44403 | Q42: =P42 -> 44403
A43: 30 | B43: BZJ-0041 | C43: 43678 | D43: =IF(TODAY()-E43<60,"2个月内",IF(TODAY()-E43<180,"3-6个月",IF(TODAY()-E43<360,"6个月-1年","一年以上"))) -> 一年以上 | E43: 43692 | F43: 生产部 | G43: 熊军、左汉军 | H43: 甘肃永固特种水泥有限公司 | I43: 甘肃永固特种水泥有限公司 | J43: 10000 | L43: 对公 | M43: 安全保证金 | N43: 10000 | O43: =J43-N43 -> 0 | P43: 43701 | Q43: =P43 -> 43701
A44: 31 | B44: BZJ-0042 | C44: 43678 | D44: =IF(TODAY()-E44<60,"2个月内",IF(TODAY()-E44<180,"3-6个月",IF(TODAY()-E44<360,"6个月-1年","一年以上"))) -> 一年以上 | E44: 43696 | F44: 生产部 | G44: 张子仪 | H44: 贵州纳雍隆庆乌江水泥有限公司 | I44: 贵州纳雍隆庆乌江水泥有限公司 | J44: 2000 | K44: 武汉 | L44: 武汉对公 | M44: 安全保证金 | N44: 2000 | O44: =J44-N44 -> 0 | P44: 45012 | Q44: =P44 -> 45012 | S44: 武汉2019.08-102 | T44: 贵州省 | U44: 陈涛
A45: 342 | B45: BZJ-0043 | C45: 43678 | D45: =IF(TODAY()-E45<60,"2个月内",IF(TODAY()-E45<180,"3-6个月",IF(TODAY()-E45<360,"6个月-1年","一年以上"))) -> 一年以上 | E45: 43696 | F45: 销售部 | G45: 吴海波 | H45: 涿鹿金隅水泥有限公司 | I45: 涿鹿金隅水泥有限公司 | J45: 20000 | L45: 对公 | M45: 履约保证金 | N45: 20000 | O45: =J45-N45 -> 0 | P45: 44673 | Q45: =P45 -> 44673 | S45: 是投标保证金转为了履约，履约又 转为了质保，质保刚刚到期。大约9月底回
A46: 32 | B46: BZJ-0044 | C46: 43678 | D46: =IF(TODAY()-E46<60,"2个月内",IF(TODAY()-E46<180,"3-6个月",IF(TODAY()-E46<360,"6个月-1年","一年以上"))) -> 一年以上 | E46: 43698 | F46: 生产部 | G46: 李文池 | H46: 重庆秀山西南水泥有限公司 | I46: 重庆秀山西南水泥有限公司 | J46: 2000 | L46: 对公 | M46: 安全保证金 | N46: 2000 | O46: =J46-N46 -> 0 | P46: 43829 | Q46: =P46 -> 43829
A47: 33 | B47: BZJ-0045 | C47: 43678 | D47: =IF(TODAY()-E47<60,"2个月内",IF(TODAY()-E47<180,"3-6个月",IF(TODAY()-E47<360,"6个月-1年","一年以上"))) -> 一年以上 | E47: 43700 | F47: 生产部 | G47: 程时勇 | H47: 山东泰西水泥有限公司 | I47: 山东泰西水泥有限公司 | J47: 1000 | L47: 个人 | M47: 安全保证金 | N47: 1000 | O47: =J47-N47 -> 0 | P47: 43718 | Q47: =P47 -> 43718
A48: 34 | B48: BZJ-0046 | C48: 43709 | D48: =IF(TODAY()-E48<60,"2个月内",IF(TODAY()-E48<180,"3-6个月",IF(TODAY()-E48<360,"6个月-1年","一年以上"))) -> 一年以上 | E48: 43710 | F48: 销售部 | G48: 吴海波 | H48: 涿鹿金隅水泥有限公司 | I48: 涿鹿金隅水泥有限公司 | J48: 25350 | K48: 武汉 | L48: 武汉对公 | M48: 安全保证金 | N48: 25350 | O48: =J48-N48 -> 0 | P48: 44673 | Q48: =P48 -> 44673 | S48: 武汉2019.9-105 | T48: 河北省 | U48: 杨春龙
A49: 35 | B49: BZJ-0047 | C49: 43709 | D49: =IF(TODAY()-E49<60,"2个月内",IF(TODAY()-E49<180,"3-6个月",IF(TODAY()-E49<360,"6个月-1年","一年以上"))) -> 一年以上 | E49: 43719 | F49: 生产部 | G49: 李文池 | H49: 绥江县永固水泥有限责任公司 | I49: 绥江县永固水泥有限责任公司 | J49: 4000 | L49: 对公 | M49: 安全保证金 | N49: 4000 | O49: =J49-N49 -> 0 | P49: 43723 | Q49: =P49 -> 43723
A50: 36 | B50: BZJ-0048 | C50: 43709 | D50: =IF(TODAY()-E50<60,"2个月内",IF(TODAY()-E50<180,"3-6个月",IF(TODAY()-E50<360,"6个月-1年","一年以上"))) -> 一年以上 | E50: 43727 | F50: 生产部 | G50: 吴昌松 | H50: 华新水泥（房县)有限公司 | I50: 华新水泥（房县)有限公司 | J50: 3000 | L50: 个人 | M50: 安全保证金 | N50: 3000 | O50: =J50-N50 -> 0 | P50: 43761 | Q50: =P50 -> 43761
A51: 37 | B51: BZJ-0049 | C51: 43709 | D51: =IF(TODAY()-E51<60,"2个月内",IF(TODAY()-E51<180,"3-6个月",IF(TODAY()-E51<360,"6个月-1年","一年以上"))) -> 一年以上 | E51: 43731 | F51: 生产部 | G51: 汪勇刚 | H51: 云南普洱西南水泥有限公司 | I51: 云南普洱西南水泥有限公司 | J51: 2000 | L51: 对公 | M51: 安全保证金 | N51: 2000 | O51: =J51-N51 -> 0 | P51: 43829 | Q51: =P51 -> 43829
A52: 38 | B52: BZJ-0050 | C52: 43709 | D52: =IF(TODAY()-E52<60,"2个月内",IF(TODAY()-E52<180,"3-6个月",IF(TODAY()-E52<360,"6个月-1年","一年以上"))) -> 一年以上 | E52: 43731 | F52: 生产部 | G52: 刘思佳 | H52: 冀东水泥重庆江津有限公司 | I52: 冀东水泥重庆江津有限公司 | J52: 7160 | L52: 对公 | M52: 安全保证金 | N52: 7160 | O52: =J52-N52 -> 0 | P52: 43847 | Q52: =P52 -> 43847
A53: 39 | B53: BZJ-0051 | C53: 43709 | D53: =IF(TODAY()-E53<60,"2个月内",IF(TODAY()-E53<180,"3-6个月",IF(TODAY()-E53<360,"6个月-1年","一年以上"))) -> 一年以上 | E53: 43733 | F53: 生产部 | G53: 覃延吉 | H53: 北京金隅琉水环保科技有限公司 | I53: 北京金隅琉水环保科技有限公司 | J53: 2000 | L53: 个人 | M53: 安全保证金 | N53: 2000 | O53: =J53-N53 -> 0 | P53: 43755 | Q53: =P53 -> 43755
A54: 40 | B54: BZJ-0052 | C54: 43739 | D54: =IF(TODAY()-E54<60,"2个月内",IF(TODAY()-E54<180,"3-6个月",IF(TODAY()-E54<360,"6个月-1年","一年以上"))) -> 一年以上 | E54: 43749 | F54: 生产部 | G54: 刘靖 | H54: 淮北众城水泥有限责任公司 | I54: 淮北众城水泥有限责任公司 | J54: 2600 | L54: 对公 | M54: 安全保证金 | N54: 2600 | O54: =J54-N54 -> 0 | P54: 43776 | Q54: =P54 -> 43776
A55: 41 | B55: BZJ-0053 | C55: 43739 | D55: =IF(TODAY()-E55<60,"2个月内",IF(TODAY()-E55<180,"3-6个月",IF(TODAY()-E55<360,"6个月-1年","一年以上"))) -> 一年以上 | E55: 43749 | F55: 生产部 | G55: 刘佳 | H55: 冀东水泥铜川有限公司 | I55: 冀东水泥铜川有限公司 | J55: 1000 | L55: 个人 | M55: 安全保证金 | N55: 1000 | O55: =J55-N55 -> 0 | P55: 43725 | Q55: =P55 -> 43725
A56: 43 | B56: BZJ-0054 | C56: 43739 | D56: =IF(TODAY()-E56<60,"2个月内",IF(TODAY()-E56<180,"3-6个月",IF(TODAY()-E56<360,"6个月-1年","一年以上"))) -> 一年以上 | E56: 43759 | F56: 生产部 | G56: 程时勇 | H56: 贵州清镇西南水泥有限公司 | I56: 贵州清镇西南水泥有限公司 | J56: 3000 | L56: 个人 | M56: 安全保证金 | N56: 3000 | O56: =J56-N56 -> 0 | P56: 43789 | Q56: =P56 -> 43789
A57: 44 | B57: BZJ-0055 | C57: 43739 | D57: =IF(TODAY()-E57<60,"2个月内",IF(TODAY()-E57<180,"3-6个月",IF(TODAY()-E57<360,"6个月-1年","一年以上"))) -> 一年以上 | E57: 43761 | F57: 生产部 | G57: 吴昌松 | H57: 华新水泥（恩施）有限公司 | I57: 华新水泥（恩施）有限公司 | J57: 3000 | L57: 个人 | M57: 安全保证金 | N57: 3000 | O57: =J57-N57 -> 0 | P57: 43768 | Q57: =P57 -> 43768
A58: 42 | B58: BZJ-0056 | C58: 43739 | D58: =IF(TODAY()-E58<60,"2个月内",IF(TODAY()-E58<180,"3-6个月",IF(TODAY()-E58<360,"6个月-1年","一年以上"))) -> 一年以上 | E58: 43766 | F58: 生产部 | G58: 刘西 | H58: 巴彦淖尔中联水泥有限公司 | I58: 巴彦淖尔中联水泥有限公司 | J58: 4000 | L58: 对公 | M58: 安全保证金 | N58: 4000 | O58: =J58-N58 -> 0 | P58: 44465 | Q58: =P58 -> 44465
A59: 45 | B59: BZJ-0057 | C59: 43770 | D59: =IF(TODAY()-E59<60,"2个月内",IF(TODAY()-E59<180,"3-6个月",IF(TODAY()-E59<360,"6个月-1年","一年以上"))) -> 一年以上 | E59: 43774 | F59: 生产部 | G59: 祝威 | H59: 安康市尧柏水泥有限公司 | I59: 安康市尧柏水泥有限公司 | J59: 10000 | L59: 对公 | M59: 安全保证金 | N59: 10000 | O59: =J59-N59 -> 0 | P59: 43976 | Q59: =P59 -> 43976
A60: 191 | B60: BZJ-0058 | C60: 43770 | D60: =IF(TODAY()-E60<60,"2个月内",IF(TODAY()-E60<180,"3-6个月",IF(TODAY()-E60<360,"6个月-1年","一年以上"))) -> 一年以上 | E60: 43774 | G60: 田学军 | H60: 贵州西南水泥有限公司 | I60: 贵州西南水泥有限公司 | J60: 50000 | K60: 武汉 | L60: 对公 | M60: 投标保证金 | N60: 50000 | O60: =J60-N60 -> 0 | P60: 44908 | Q60: =P60 -> 44908 | R60: 2022/12/31前退回，年标，转履约 | S60: 窑磨专业测窑调窑及整形，窑磨裂纹：长期投标不退
A61: 46 | B61: BZJ-0059 | C61: 43770 | D61: =IF(TODAY()-E61<60,"2个月内",IF(TODAY()-E61<180,"3-6个月",IF(TODAY()-E61<360,"6个月-1年","一年以上"))) -> 一年以上 | E61: 43775 | F61: 生产部 | G61: 刘思佳 | H61: 华新水泥（恩施）有限公司 | I61: 华新水泥（恩施）有限公司 | J61: 2000 | L61: 个人 | M61: 安全保证金 | N61: 2000 | O61: =J61-N61 -> 0 | P61: 43787 | Q61: =P61 -> 43787
A62: 47 | B62: BZJ-0060 | C62: 43770 | D62: =IF(TODAY()-E62<60,"2个月内",IF(TODAY()-E62<180,"3-6个月",IF(TODAY()-E62<360,"6个月-1年","一年以上"))) -> 一年以上 | E62: 43796 | F62: 生产部 | G62: 程时勇 | H62: 华新水泥（房县)有限公司 | I62: 华新水泥（房县)有限公司 | J62: 2000 | L62: 个人 | M62: 安全保证金 | N62: 2000 | O62: =J62-N62 -> 0 | P62: 43801 | Q62: =P62 -> 43801
A63: 193 | B63: BZJ-0061 | C63: 43800 | D63: =IF(TODAY()-E63<60,"2个月内",IF(TODAY()-E63<180,"3-6个月",IF(TODAY()-E63<360,"6个月-1年","一年以上"))) -> 一年以上 | E63: 43804 | G63: 杨春龙 | H63: 江苏永钢集团有限公司 | I63: 江苏永钢集团有限公司 | J63: 10000 | L63: 对公 | M63: 投标保证金 | N63: 10000 | O63: =J63-N63 -> 0 | P63: 44018 | Q63: =P63 -> 44018
A64: 48 | B64: BZJ-0062 | C64: 43800 | D64: =IF(TODAY()-E64<60,"2个月内",IF(TODAY()-E64<180,"3-6个月",IF(TODAY()-E64<360,"6个月-1年","一年以上"))) -> 一年以上 | E64: 43805 | F64: 生产部 | G64: 刘思佳 | H64: 阳泉冀东水泥有限责任公司 | I64: 阳泉冀东水泥有限责任公司 | J64: 2700 | L64: 对公 | M64: 安全保证金 | N64: 2700 | O64: =J64-N64 -> 0 | P64: 43985 | Q64: =P64 -> 43985
A65: 50 | B65: BZJ-0063 | C65: 43800 | D65: =IF(TODAY()-E65<60,"2个月内",IF(TODAY()-E65<180,"3-6个月",IF(TODAY()-E65<360,"6个月-1年","一年以上"))) -> 一年以上 | E65: 43808 | F65: 生产部 | G65: 吴昌松 | H65: 山东泰西水泥有限公司 | I65: 山东泰西水泥有限公司 | J65: 2000 | L65: 个人 | M65: 安全保证金 | N65: 2000 | O65: =J65-N65 -> 0 | P65: 43819 | Q65: =P65 -> 43819
A66: 49 | B66: BZJ-0064 | C66: 43800 | D66: =IF(TODAY()-E66<60,"2个月内",IF(TODAY()-E66<180,"3-6个月",IF(TODAY()-E66<360,"6个月-1年","一年以上"))) -> 一年以上 | E66: 43812 | F66: 生产部 | G66: 王延军 | H66: 渤海水泥（葫芦岛）有限公司 | I66: 渤海水泥（葫芦岛）有限公司 | J66: 3000 | L66: 对公 | M66: 安全保证金 | N66: 3000 | O66: =J66-N66 -> 0 | P66: 44189 | Q66: =P66 -> 44189
A67: 51 | B67: BZJ-0065 | C67: 43800 | D67: =IF(TODAY()-E67<60,"2个月内",IF(TODAY()-E67<180,"3-6个月",IF(TODAY()-E67<360,"6个月-1年","一年以上"))) -> 一年以上 | E67: 43823 | F67: 生产部 | G67: 吴昌松 | H67: 天瑞新登郑州水泥有限公司 | I67: 天瑞新登郑州水泥有限公司 | J67: 2000 | L67: 个人 | M67: 安全保证金 | N67: 2000 | O67: =J67-N67 -> 0 | P67: 43834 | Q67: =P67 -> 43834
A68: 52 | B68: BZJ-0066 | C68: 43800 | D68: =IF(TODAY()-E68<60,"2个月内",IF(TODAY()-E68<180,"3-6个月",IF(TODAY()-E68<360,"6个月-1年","一年以上"))) -> 一年以上 | E68: 43825 | F68: 生产部 | G68: 何煜军 | H68: 酒钢（集团）宏达建材有限责任公司 | I68: 酒钢（集团）宏达建材有限责任公司 | J68: 5000 | L68: 对公 | M68: 安全保证金 | N68: 5000 | O68: =J68-N68 -> 0 | P68: 44099 | Q68: =P68 -> 44099
A69: 73 | B69: BZJ-0067 | C69: 43800 | D69: =IF(TODAY()-E69<60,"2个月内",IF(TODAY()-E69<180,"3-6个月",IF(TODAY()-E69<360,"6个月-1年","一年以上"))) -> 一年以上 | E69: 43830 | F69: 销售部 | G69: 杨春龙 | H69: 江苏沙钢集团有限公司 | I69: 江苏沙钢集团有限公司 | J69: 900 | K69: 武汉 | L69: 个人 | M69: 安全保证金 | O69: =J69-N69 -> 900 | Q69: =P69 -> 0 | R69: 门禁卡押金 | S69: 门禁卡 | T69: 江苏省 | U69: =VLOOKUP(T69,[1]区域划分!$A$1:$C$39,3,0) -> 龚运谱
A70: 53 | B70: BZJ-0068 | C70: 43831 | D70: =IF(TODAY()-E70<60,"2个月内",IF(TODAY()-E70<180,"3-6个月",IF(TODAY()-E70<360,"6个月-1年","一年以上"))) -> 一年以上 | E70: 43840 | F70: 生产部 | G70: 祝发权 | H70: 安钢集团信阳钢铁有限责任公司 | I70: 安钢集团信阳钢铁有限责任公司 | J70: 3000 | L70: 个人 | M70: 安全保证金 | N70: 3000 | O70: =J70-N70 -> 0 | P70: 43920 | Q70: =P70 -> 43920
A71: 54 | B71: BZJ-0069 | C71: 43831 | D71: =IF(TODAY()-E71<60,"2个月内",IF(TODAY()-E71<180,"3-6个月",IF(TODAY()-E71<360,"6个月-1年","一年以上"))) -> 一年以上 | E71: 43840 | F71: 生产部 | G71: 黄庭兴 | H71: 承德金隅水泥有限责任公司 | I71: 承德金隅水泥有限责任公司 | J71: 2000 | K71: 武汉 | L71: 武汉对公 | M71: 安全保证金 | N71: 2000 | O71: =J71-N71 -> 0 | P71: 45035 | Q71: =P71 -> 45035 | R71: 预计2023.03月退款 | S71: 武汉2020.1-136 | T71: 河北省 | U71: 杨春龙 | V71: 安环部詹工
A72: 195 | B72: BZJ-0070 | C72: 43831 | D72: =IF(TODAY()-E72<60,"2个月内",IF(TODAY()-E72<180,"3-6个月",IF(TODAY()-E72<360,"6个月-1年","一年以上"))) -> 一年以上 | E72: 43840 | G72: 殷坤鹏 | H72: 鄂尔多斯市君正能源化工有限公司水泥分公司 | I72: 鄂尔多斯市君正能源化工有限公司水泥分公司 | J72: 10000 | L72: 对公 | M72: 投标保证金 | N72: 10000 | O72: =J72-N72 -> 0 | P72: 43913 | Q72: =P72 -> 43913 | S72: 长期投标不退
A73: 55 | B73: BZJ-0071 | C73: 43831 | D73: =IF(TODAY()-E73<60,"2个月内",IF(TODAY()-E73<180,"3-6个月",IF(TODAY()-E73<360,"6个月-1年","一年以上"))) -> 一年以上 | E73: 43843 | F73: 生产部 | G73: 王小勇 | H73: 渤海水泥（葫芦岛）有限公司 | I73: 渤海水泥（葫芦岛）有限公司 | J73: 3000 | K73: 武汉 | L73: 对公 | M73: 安全保证金 | N73: 2900 | O73: =J73-N73 -> 100 | Q73: =P73 -> 0 | R73: 2021/3/24实际退款2900元 | T73: 辽宁省 | U73: =VLOOKUP(T73,[1]区域划分!$A$1:$C$39,3,0) -> 殷坤鹏
A74: 344 | B74: BZJ-0072 | C74: 43831 | D74: =IF(TODAY()-E74<60,"2个月内",IF(TODAY()-E74<180,"3-6个月",IF(TODAY()-E74<360,"6个月-1年","一年以上"))) -> 一年以上 | E74: 43843 | F74: 销售部 | G74: 夏锋泽 | H74: 四川金宏通实业有限公司 | I74: 四川金宏通实业有限公司 | J74: 24000 | L74: 对公 | M74: 履约保证金 | N74: 24000 | O74: =J74-N74 -> 0 | P74: 44193 | Q74: =P74 -> 44193 | S74: 履约保证金
A75: 56 | B75: BZJ-0073 | C75: 43891 | D75: =IF(TODAY()-E75<60,"2个月内",IF(TODAY()-E75<180,"3-6个月",IF(TODAY()-E75<360,"6个月-1年","一年以上"))) -> 一年以上 | E75: 43920 | F75: 生产部 | G75: 雍佳强 | H75: 青海海西化工建材股份有限公司 | I75: 青海海西化工建材股份有限公司 | J75: 5000 | L75: 个人 | M75: 安全保证金 | N75: 5000 | O75: =J75-N75 -> 0 | P75: 44039 | Q75: =P75 -> 44039
A76: 57 | B76: BZJ-0074 | C76: 43922 | D76: =IF(TODAY()-E76<60,"2个月内",IF(TODAY()-E76<180,"3-6个月",IF(TODAY()-E76<360,"6个月-1年","一年以上"))) -> 一年以上 | E76: 43923 | F76: 生产部 | G76: 祝威 | H76: 甘肃永固特种水泥有限公司 | I76: 甘肃永固特种水泥有限公司 | J76: 10000 | K76: 武汉 | L76: 武汉对公 | M76: 安全保证金 | O76: =J76-N76 -> 10000 | Q76: =P76 -> 0 | R76: 已提供对账单，与货款一起请方渊在跟进。起诉调解，第一批25万已支付 | S76: 武汉2020.04-07 | T76: 甘肃省 | U76: =VLOOKUP(T76,[1]区域划分!$A$1:$C$39,3,0) -> 曾江利
A77: 196 | B77: BZJ-0075 | C77: 43922 | D77: =IF(TODAY()-E77<60,"2个月内",IF(TODAY()-E77<180,"3-6个月",IF(TODAY()-E77<360,"6个月-1年","一年以上"))) -> 一年以上 | E77: 43936 | G77: 吴海波 | H77: 河北新金轧材有限公司 | I77: 河北新金轧材有限公司 | J77: 10000 | L77: 对公 | M77: 投标保证金 | N77: 10000 | O77: =J77-N77 -> 0 | P77: 44155 | Q77: =P77 -> 44155 | S77: 投标保证金
A78: 58 | B78: BZJ-0076 | C78: 43952 | D78: =IF(TODAY()-E78<60,"2个月内",IF(TODAY()-E78<180,"3-6个月",IF(TODAY()-E78<360,"6个月-1年","一年以上"))) -> 一年以上 | E78: 43967 | F78: 生产部 | G78: 吕海洲 | H78: 贵州沿河西南水泥有限公司 | I78: 贵州沿河西南水泥有限公司 | J78: 5000 | L78: 对公 | M78: 安全保证金 | N78: 5000 | O78: =J78-N78 -> 0 | P78: 44463 | Q78: =P78 -> 44463
A79: 59 | B79: BZJ-0077 | C79: 43952 | D79: =IF(TODAY()-E79<60,"2个月内",IF(TODAY()-E79<180,"3-6个月",IF(TODAY()-E79<360,"6个月-1年","一年以上"))) -> 一年以上 | E79: 43969 | F79: 生产部 | G79: 汪勇刚 | H79: 四川达州钢铁有限公司 | I79: 四川达州钢铁有限公司 | J79: 2000 | L79: 个人 | M79: 安全保证金 | N79: 2000 | O79: =J79-N79 -> 0 | P79: 44034 | Q79: =P79 -> 44034
A80: 60 | B80: BZJ-0078 | C80: 43952 | D80: =IF(TODAY()-E80<60,"2个月内",IF(TODAY()-E80<180,"3-6个月",IF(TODAY()-E80<360,"6个月-1年","一年以上"))) -> 一年以上 | E80: 43969 | F80: 生产部 | G80: 黄国恩 | H80: 四川峨眉山西南水泥有限公司 | I80: 四川峨眉山西南水泥有限公司 | J80: 3000 | L80: 对公 | M80: 安全保证金 | N80: 3000 | O80: =J80-N80 -> 0 | P80: 44035 | Q80: =P80 -> 44035
A81: 61 | B81: BZJ-0079 | C81: 43952 | D81: =IF(TODAY()-E81<60,"2个月内",IF(TODAY()-E81<180,"3-6个月",IF(TODAY()-E81<360,"6个月-1年","一年以上"))) -> 一年以上 | E81: 43977 | F81: 生产部 | G81: 何煜军 | H81: 冀东海天水泥闻喜有限公司 | I81: 冀东海天水泥闻喜有限公司 | J81: 5000 | L81: 对公 | M81: 安全保证金 | N81: 5000 | O81: =J81-N81 -> 0 | P81: 44491 | Q81: =P81 -> 44491
A82: 62 | B82: BZJ-0080 | C82: 43983 | D82: =IF(TODAY()-E82<60,"2个月内",IF(TODAY()-E82<180,"3-6个月",IF(TODAY()-E82<360,"6个月-1年","一年以上"))) -> 一年以上 | E82: 43992 | F82: 生产部 | G82: 吕海洲 | H82: 阳泉冀东水泥有限责任公司 | I82: 阳泉冀东水泥有限责任公司 | J82: 2000 | L82: 对公 | M82: 安全保证金 | N82: 2000 | O82: =J82-N82 -> 0 | P82: 44083 | Q82: =P82 -> 44083
A83: 63 | B83: BZJ-0081 | C83: 43983 | D83: =IF(TODAY()-E83<60,"2个月内",IF(TODAY()-E83<180,"3-6个月",IF(TODAY()-E83<360,"6个月-1年","一年以上"))) -> 一年以上 | E83: 44010 | F83: 生产部 | G83: 黄庭兴 | H83: 四川华蓥西南水泥有限公司 | I83: 四川华蓥西南水泥有限公司 | J83: 1500 | L83: 对公 | M83: 安全保证金 | N83: 1500 | O83: =J83-N83 -> 0 | P83: 44130 | Q83: =P83 -> 44130
A84: 197 | B84: BZJ-0082 | C84: 43983 | D84: =IF(TODAY()-E84<60,"2个月内",IF(TODAY()-E84<180,"3-6个月",IF(TODAY()-E84<360,"6个月-1年","一年以上"))) -> 一年以上 | E84: 44011 | G84: 夏锋泽 | H84: 四川西南水泥有限公司（川渝西南） | I84: 四川西南水泥有限公司 | J84: 50000 | K84: 武汉 | L84: 对公 | M84: 投标保证金 | O84: =J84-N84 -> 50000 | Q84: =P84 -> 0 | R84: 年标，转履约 | S84: 测窑及维修，长期投标不退 | T84: 四川省 | U84: =VLOOKUP(T84,[1]区域划分!$A$1:$C$39,3,0) -> 牛国庆
A85: 64 | B85: BZJ-0083 | C85: 43983 | D85: =IF(TODAY()-E85<60,"2个月内",IF(TODAY()-E85<180,"3-6个月",IF(TODAY()-E85<360,"6个月-1年","一年以上"))) -> 一年以上 | E85: 44012 | F85: 销售部 | G85: 杨春龙 | H85: 天瑞集团郑州水泥有限公司 | I85: 天瑞集团郑州水泥有限公司 | J85: 3000 | L85: 个人 | M85: 安全保证金 | N85: 3000 | O85: =J85-N85 -> 0 | P85: 44196 | Q85: =P85 -> 44196
A86: 65 | B86: BZJ-0084 | C86: 44013 | D86: =IF(TODAY()-E86<60,"2个月内",IF(TODAY()-E86<180,"3-6个月",IF(TODAY()-E86<360,"6个月-1年","一年以上"))) -> 一年以上 | E86: 44018 | F86: 生产部 | G86: 祝发权 | H86: 阳泉冀东水泥有限责任公司 | I86: 阳泉冀东水泥有限责任公司 | J86: 2000 | L86: 对公 | M86: 安全保证金 | N86: 2000 | O86: =J86-N86 -> 0 | P86: 44083 | Q86: =P86 -> 44083
A87: 66 | B87: BZJ-0085 | C87: 44013 | D87: =IF(TODAY()-E87<60,"2个月内",IF(TODAY()-E87<180,"3-6个月",IF(TODAY()-E87<360,"6个月-1年","一年以上"))) -> 一年以上 | E87: 44021 | F87: 生产部 | G87: 王小勇 | H87: 贵州松桃高力水泥实业有限公司 | I87: 贵州松桃高力水泥实业有限公司 | J87: 1000 | L87: 对公 | M87: 安全保证金 | N87: 1000 | O87: =J87-N87 -> 0 | P87: 44069 | Q87: =P87 -> 44069 | S87: 对公退款800元和交现金200元
A88: 68 | B88: BZJ-0086 | C88: 44013 | D88: =IF(TODAY()-E88<60,"2个月内",IF(TODAY()-E88<180,"3-6个月",IF(TODAY()-E88<360,"6个月-1年","一年以上"))) -> 一年以上 | E88: 44025 | F88: 生产部 | G88: 程时勇 | H88: 冀东水泥璧山有限公司 | I88: 冀东水泥璧山有限公司 | J88: 2000 | L88: 对公 | M88: 安全保证金 | N88: 2000 | O88: =J88-N88 -> 0 | P88: 44223 | Q88: =P88 -> 44223 | S88: 2021年1月27日收2000冀东水泥璧山有限公司退安全保证金
A89: 67 | B89: BZJ-0087 | C89: 44013 | D89: =IF(TODAY()-E89<60,"2个月内",IF(TODAY()-E89<180,"3-6个月",IF(TODAY()-E89<360,"6个月-1年","一年以上"))) -> 一年以上 | E89: 44027 | F89: 生产部 | G89: 王小勇 | H89: 贵州织金西南水泥有限公司 | I89: 贵州织金西南水泥有限公司 | J89: 1000 | L89: 对公 | M89: 安全保证金 | N89: 1000 | O89: =J89-N89 -> 0 | P89: 44547 | Q89: =P89 -> 44547
A90: 69 | B90: BZJ-0088 | C90: 44013 | D90: =IF(TODAY()-E90<60,"2个月内",IF(TODAY()-E90<180,"3-6个月",IF(TODAY()-E90<360,"6个月-1年","一年以上"))) -> 一年以上 | E90: 44034 | F90: 生产部 | G90: 程时勇 | H90: 达州利森水泥有限公司 | I90: 达州利森水泥有限公司 | J90: 3000 | L90: 对公 | M90: 安全保证金 | N90: 3000 | O90: =J90-N90 -> 0 | P90: 44071 | Q90: =P90 -> 44071 | S90: 2020-8-27程时勇退3000达州利森水泥安全保证金（款打给达州利森水泥有限公司）
A91: 70 | B91: BZJ-0089 | C91: 44013 | D91: =IF(TODAY()-E91<60,"2个月内",IF(TODAY()-E91<180,"3-6个月",IF(TODAY()-E91<360,"6个月-1年","一年以上"))) -> 一年以上 | E91: 44034 | F91: 生产二部 | G91: 黄庭兴 | H91: 赞皇金隅水泥有限公司 | I91: 赞皇金隅水泥有限公司 | J91: 3200 | K91: 武汉 | L91: 武汉对公 | M91: 安全保证金 | N91: 3200 | O91: =J91-N91 -> 0 | P91: 44678 | Q91: =P91 -> 44678 | S91: 安全保证金 | T91: 河北省 | U91: 杨春龙 | V91: 武汉2020.7-147
A92: 71 | B92: BZJ-0090 | C92: 44013 | D92: =IF(TODAY()-E92<60,"2个月内",IF(TODAY()-E92<180,"3-6个月",IF(TODAY()-E92<360,"6个月-1年","一年以上"))) -> 一年以上 | E92: 44034 | F92: 生产部 | G92: 汪勇刚 | H92: 四川德胜集团水泥有限公司 | I92: 四川德胜集团水泥有限公司 | J92: 3000 | L92: 对公 | M92: 安全保证金 | N92: 3000 | O92: =J92-N92 -> 0 | P92: 44221 | Q92: =P92 -> 44221 | S92: 2021年1月25日收四川德胜集团水泥有限公司退安全保证金
A93: 72 | B93: BZJ-0091 | C93: 44013 | D93: =IF(TODAY()-E93<60,"2个月内",IF(TODAY()-E93<180,"3-6个月",IF(TODAY()-E93<360,"6个月-1年","一年以上"))) -> 一年以上 | E93: 44038 | F93: 生产部 | G93: 程时勇 | H93: 韩城尧柏阳山庄水泥有限公司 | I93: 韩城尧柏阳山庄水泥有限公司 | J93: 10000 | L93: 对公 | M93: 安全保证金 | N93: 10000 | O93: =J93-N93 -> 0 | P93: 44073 | Q93: =P93 -> 44073 | S93: 2020-8-31程时勇退10000韩城尧柏水泥安全保证金（款打给韩城尧柏阳山庄水泥有限公司）
A94: 74 | B94: BZJ-0092 | C94: 44044 | D94: =IF(TODAY()-E94<60,"2个月内",IF(TODAY()-E94<180,"3-6个月",IF(TODAY()-E94<360,"6个月-1年","一年以上"))) -> 一年以上 | E94: 44048 | F94: 销售部 | G94: 夏锋泽 | H94: 冀东水泥重庆合川有限责任公司 | I94: 冀东水泥重庆合川有限责任公司 | J94: 2000 | K94: 武汉 | L94: 武汉对公 | M94: 安全保证金 | N94: 2000 | O94: =J94-N94 -> 0 | P94: 44707 | Q94: =P94 -> 44707 | R94: 需要上门办理牛国庆处理，预计5月 | S94: 安全保证金 | T94: 重庆 | U94: 牛国庆 | V94: 武汉2020.08-07
A95: 75 | B95: BZJ-0093 | C95: 44044 | D95: =IF(TODAY()-E95<60,"2个月内",IF(TODAY()-E95<180,"3-6个月",IF(TODAY()-E95<360,"6个月-1年","一年以上"))) -> 一年以上 | E95: 44050 | F95: 销售部 | G95: 陈冲 | H95: 商洛尧柏龙桥水泥有限公司 | I95: 商洛尧柏龙桥水泥有限公司 | J95: 10000 | K95: 武汉 | L95: 对公 | M95: 安全保证金 | N95: 10000 | O95: =J95-N95 -> 0 | P95: 45070 | Q95: =P95 -> 45070 | R95: 3.2023.4月林维现场跟进，退款手续办理中，预计5月退回 | S95: 安全保证金 | T95: 陕西省 | U95: 朱利勇
A96: 76 | B96: BZJ-0094 | C96: 44044 | D96: =IF(TODAY()-E96<60,"2个月内",IF(TODAY()-E96<180,"3-6个月",IF(TODAY()-E96<360,"6个月-1年","一年以上"))) -> 一年以上 | E96: 44053 | F96: 销售部 | G96: 夏锋泽 | H96: 旺苍川煤水泥有限责任公司 | I96: 旺苍川煤水泥有限责任公司 | J96: 3000 | L96: 对公 | M96: 安全保证金 | N96: 3000 | O96: =J96-N96 -> 0 | P96: 44094 | Q96: =P96 -> 44094
A97: 77 | B97: BZJ-0095 | C97: 44044 | D97: =IF(TODAY()-E97<60,"2个月内",IF(TODAY()-E97<180,"3-6个月",IF(TODAY()-E97<360,"6个月-1年","一年以上"))) -> 一年以上 | E97: 44057 | F97: 销售部 | G97: 夏锋泽 | H97: 重庆长寿西南水泥有限公司 | I97: 重庆长寿西南水泥有限公司 | J97: 3000 | L97: 对公 | M97: 安全保证金 | N97: 3000 | O97: =J97-N97 -> 0 | P97: 44335 | Q97: =P97 -> 44335
A98: 78 | B98: BZJ-0096 | C98: 44044 | D98: =IF(TODAY()-E98<60,"2个月内",IF(TODAY()-E98<180,"3-6个月",IF(TODAY()-E98<360,"6个月-1年","一年以上"))) -> 一年以上 | E98: 44063 | F98: 销售部 | G98: 瞿新虎 | H98: 华新水泥（红河）有限公司 | I98: 华新水泥（红河）有限公司 | J98: 5000 | L98: 个人 | M98: 安全保证金 | N98: 5000 | O98: =J98-N98 -> 0 | P98: 44068 | Q98: =P98 -> 44068
A99: 198 | B99: BZJ-0097 | C99: 44075 | D99: =IF(TODAY()-E99<60,"2个月内",IF(TODAY()-E99<180,"3-6个月",IF(TODAY()-E99<360,"6个月-1年","一年以上"))) -> 一年以上 | E99: 44078 | G99: 瞿新虎 | H99: 云南西南水泥有限公司 | I99: 云南西南水泥有限公司 | J99: 50000 | K99: 武汉 | L99: 对公 | M99: 投标保证金 | N99: 50000 | O99: =J99-N99 -> 0 | P99: 45257 | Q99: =P99 -> 45257 | R99: 年标，转履约 | S99: 长期投标不退 | T99: 云南省 | U99: =VLOOKUP(T99,[1]区域划分!$A$1:$C$39,3,0) -> 牛国庆
A100: 199 | B100: BZJ-0098 | C100: 44075 | D100: =IF(TODAY()-E100<60,"2个月内",IF(TODAY()-E100<180,"3-6个月",IF(TODAY()-E100<360,"6个月-1年","一年以上"))) -> 一年以上 | E100: 44085 | G100: 吴海波 | H100: 昌黎冀东水泥有限公司 | I100: 昌黎冀东水泥有限公司 | J100: 2000 | L100: 对公 | M100: 投标保证金 | N100: 2000 | O100: =J100-N100 -> 0 | P100: 44559 | Q100: =P100 -> 44559 | S100: 投标保证金
...

Sheet Sheet1 (2)
C1: 其他应收明细表
A2: 序号 | B2: 编号 | C2: 月份 | D2: 账龄 | E2: 支付日期 | F2: 部门 | G2: 经办人 | H2: 公司名称 | I2: 公司名称2 | J2: 支付金额 | K2: 公司 | L2: 支付方式 | M2: 支付类型 | N2: 退款金额/ 发票冲账 | O2: 未退余额 | P2: 退款时间 | Q2: 退回月份 | R2: 未退原因 | S2: 备注 | T2: 省份 | U2: 业务经理 | V2: 联系人 | W2: 中标结果 | X2: 业务员
A3: 182 | B3: BZJ-0001 | C3: 42370 | D3: =IF(TODAY()-E3<60,"2个月内",IF(TODAY()-E3<180,"3-6个月",IF(TODAY()-E3<360,"6个月-1年","一年以上"))) -> 一年以上 | H3: 三门峡腾跃同力水泥有限公司 | I3: 三门峡腾跃同力水泥有限公司 | J3: 1000 | K3: 武汉 | L3: 期初余额 | M3: 投标保证金 | O3: =J3-N3 -> 1000 | Q3: =P3 -> 0 | R3: 找付款凭证 | T3: 河南省 | U3: =VLOOKUP(T3,[1]区域划分!$A$1:$C$39,3,0) -> 方渊
A4: 183 | B4: BZJ-0002 | C4: 42370 | D4: =IF(TODAY()-E4<60,"2个月内",IF(TODAY()-E4<180,"3-6个月",IF(TODAY()-E4<360,"6个月-1年","一年以上"))) -> 一年以上 | H4: 云南西南水泥有限公司 | I4: 云南西南水泥有限公司 | J4: 50000 | L4: 期初余额 | M4: 投标保证金 | N4: 50000 | O4: =J4-N4 -> 0 | P4: 44155 | Q4: =P4 -> 44155
A5: 184 | B5: BZJ-0003 | C5: 42370 | D5: =IF(TODAY()-E5<60,"2个月内",IF(TODAY()-E5<180,"3-6个月",IF(TODAY()-E5<360,"6个月-1年","一年以上"))) -> 一年以上 | H5: 淮北众城水泥有限责任公司 | I5: 淮北众城水泥有限责任公司 | J5: 3000 | K5: 武汉 | L5: 期初余额 | M5: 投标保证金 | O5: =J5-N5 -> 3000 | Q5: =P5 -> 0 | S5: 已被收购 | T5: 安徽省 | U5: =VLOOKUP(T5,[1]区域划分!$A$1:$C$39,3,0) -> 方渊
A6: 186 | B6: BZJ-0004 | C6: 42370 | D6: =IF(TODAY()-E6<60,"2个月内",IF(TODAY()-E6<180,"3-6个月",IF(TODAY()-E6<360,"6个月-1年","一年以上"))) -> 一年以上 | H6: 吉林亚泰（集团）股份有限公司物资经销分公司 | I6: 吉林亚泰集团物资贸易有限公司 | J6: 3800 | K6: 武汉 | L6: 期初余额 | M6: 投标保证金 | O6: =J6-N6 -> 3800 | Q6: =P6 -> 0 | R6: 预计2023.04或2023.05月退还，熊伟跟进中.客人无此笔,我司资料为期初数据有23800 | S6: 有凭证才可查询 | T6: 吉林省 | U6: =VLOOKUP(T6,[1]区域划分!$A$1:$C$39,3,0) -> 殷坤鹏 | V6: 张玉鹏13634307383
A7: 187 | B7: BZJ-0005 | C7: 42370 | D7: =IF(TODAY()-E7<60,"2个月内",IF(TODAY()-E7<180,"3-6个月",IF(TODAY()-E7<360,"6个月-1年","一年以上"))) -> 一年以上 | H7: 江苏永钢集团物资贸易有限公司 | I7: 江苏永钢集团物资贸易有限公司 | J7: 20000 | K7: 武汉 | L7: 期初余额 | M7: 投标保证金 | O7: =J7-N7 -> 20000 | Q7: =P7 -> 0 | R7: 对方财务查询并无此款 | S7: 对方财务查询并无此款 | T7: 江苏省 | U7: =VLOOKUP(T7,[1]区域划分!$A$1:$C$39,3,0) -> 龚运谱
A8: 188 | B8: BZJ-0006 | C8: 42370 | D8: =IF(TODAY()-E8<60,"2个月内",IF(TODAY()-E8<180,"3-6个月",IF(TODAY()-E8<360,"6个月-1年","一年以上"))) -> 一年以上 | H8: 酒泉钢铁（集团）有限公司 | I8: 酒泉钢铁（集团）有限公司 | J8: 300 | L8: 期初余额 | M8: 投标保证金 | N8: 300 | O8: =J8-N8 -> 0 | P8: 44728 | Q8: =P8 -> 44728 | S8: 可能是标书费
A9: 185 | B9: BZJ-0007 | C9: 42370 | D9: =IF(TODAY()-E9<60,"2个月内",IF(TODAY()-E9<180,"3-6个月",IF(TODAY()-E9<360,"6个月-1年","一年以上"))) -> 一年以上 | E9: 42390 | G9: 吴海波 | H9: 亚泰伊通 | I9: 亚泰集团伊通水泥有限公司 | J9: 20000 | K9: 武汉 | L9: 武汉对公 | M9: 投标保证金 | O9: =J9-N9 -> 20000 | Q9: =P9 -> 0 | R9: 预计2023.04或2023.05月退还，熊伟跟进中.客人无此笔,我司资料为期初数据有23800 | S9: 2016年1月42#凭证 | T9: 吉林省 | U9: =VLOOKUP(T9,[1]区域划分!$A$1:$C$39,3,0) -> 殷坤鹏 | V9: 张玉鹏13634307383
A10: 189 | B10: BZJ-0008 | C10: 42370 | D10: =IF(TODAY()-E10<60,"2个月内",IF(TODAY()-E10<180,"3-6个月",IF(TODAY()-E10<360,"6个月-1年","一年以上"))) -> 一年以上 | E10: 42400 | H10: 江苏沙钢集团有限公司 | I10: 江苏沙钢集团有限公司 | J10: 10000 | K10: 武汉 | L10: 平台上共8万 | M10: 投标保证金 | O10: =J10-N10 -> 10000 | Q10: =P10 -> 0 | R10: 长期投标不退 | S10: 投标保证金（前期借支2万元 后期借支5万元） 销售部查询系统里面有8万元保证金，长期投标不退 | T10: 江苏省 | U10: =VLOOKUP(T10,[1]区域划分!$A$1:$C$39,3,0) -> 龚运谱
A11: 1 | B11: BZJ-0009 | C11: 42887 | D11: =IF(TODAY()-E11<60,"2个月内",IF(TODAY()-E11<180,"3-6个月",IF(TODAY()-E11<360,"6个月-1年","一年以上"))) -> 一年以上 | E11: 42887 | H11: 江苏沙钢集团有限公司 | I11: 江苏沙钢集团有限公司 | J11: 10000 | K11: 武汉 | L11: 平台上共8万 | M11: 安全保证金 | O11: 10000 | Q11: =P11 -> 0 | T11: 江苏省 | U11: =VLOOKUP(T11,[1]区域划分!$A$1:$C$39,3,0) -> 龚运谱
A12: 190 | B12: BZJ-0010 | C12: 43466 | D12: =IF(TODAY()-E12<60,"2个月内",IF(TODAY()-E12<180,"3-6个月",IF(TODAY()-E12<360,"6个月-1年","一年以上"))) -> 一年以上 | E12: 43475 | G12: 汤勇华 | H12: 江苏沙钢集团有限公司 | I12: 江苏沙钢集团有限公司 | J12: 50000 | K12: 武汉 | L12: 平台上共8万 | M12: 投标保证金 | O12: =J12-N12 -> 50000 | Q12: =P12 -> 0 | R12: 长期投标不退 | S12: 投标保证金（前期借支2万元 后期借支5万元） 销售部查询系统里面有8万元保证金，长期投标不退 | T12: 江苏省 | U12: =VLOOKUP(T12,[1]区域划分!$A$1:$C$39,3,0) -> 龚运谱
A13: 5 | B13: BZJ-0011 | C13: 43101 | D13: =IF(TODAY()-E13<60,"2个月内",IF(TODAY()-E13<180,"3-6个月",IF(TODAY()-E13<360,"6个月-1年","一年以上"))) -> 一年以上 | E13: 43113 | F13: 生产部 | G13: 姜兵 | H13: 永登祁连山水泥有限公司 | I13: 永登祁连山水泥有限公司 | J13: 2000 | L13: 对公 | M13: 安全保证金 | N13: 2000 | O13: =J13-N13 -> 0 | P13: 44099 | Q13: =P13 -> 44099 | S13: 近期要施工
A14: 2 | B14: BZJ-0012 | C14: 43101 | D14: =IF(TODAY()-E14<60,"2个月内",IF(TODAY()-E14<180,"3-6个月",IF(TODAY()-E14<360,"6个月-1年","一年以上"))) -> 一年以上 | E14: 43124 | G14: 丁俊 | H14: 逸盛大化石化有限公司 | I14: 逸盛大化石化有限公司 | J14: 7000 | K14: 武汉 | M14: 安全保证金 | O14: 7000 | Q14: =P14 -> 0 | R14: 2023.03月殷总说之前做的质量有重大问题暂时不催 | S14: 2019年12月从丁俊个人转公司账7000元 | T14: 辽宁省 | U14: =VLOOKUP(T14,[1]区域划分!$A$1:$C$39,3,0) -> 殷坤鹏
A15: 10 | B15: BZJ-0013 | C15: 43252 | D15: =IF(TODAY()-E15<60,"2个月内",IF(TODAY()-E15<180,"3-6个月",IF(TODAY()-E15<360,"6个月-1年","一年以上"))) -> 一年以上 | E15: 43255 | F15: 生产一部 | G15: 汪勇刚 | H15: 德州中联大坝水泥有限公司 | I15: 德州中联大坝水泥有限公司 | J15: 15000 | K15: 武汉 | L15: 武汉对公 | M15: 安全保证金 | N15: 15000 | O15: =J15-N15 -> 0 | P15: 44936 | Q15: =P15 -> 44936 | S15: 武汉2018.06-40 | T15: 山东省 | U15: 李松林
A16: 15 | B16: BZJ-0014 | C16: 43313 | D16: =IF(TODAY()-E16<60,"2个月内",IF(TODAY()-E16<180,"3-6个月",IF(TODAY()-E16<360,"6个月-1年","一年以上"))) -> 一年以上 | E16: 43330 | F16: 生产部 | G16: 张子仪 | H16: 四川西南水泥有限公司 | I16: 四川西南水泥有限公司 | J16: 2000 | L16: 对公 | M16: 安全保证金 | N16: 2000 | O16: =J16-N16 -> 0 | P16: 43707 | Q16: =P16 -> 43707
A17: 6 | B17: BZJ-0015 | C17: 43374 | D17: =IF(TODAY()-E17<60,"2个月内",IF(TODAY()-E17<180,"3-6个月",IF(TODAY()-E17<360,"6个月-1年","一年以上"))) -> 一年以上 | E17: 43393 | F17: 生产部 | G17: 刘西 | H17: 新安中联万基水泥有限公司 | I17: 新安中联万基水泥有限公司 | J17: 3000 | L17: 对公 | M17: 安全保证金 | N17: 3000 | O17: =J17-N17 -> 0 | P17: 44126 | Q17: =P17 -> 44126 | S17: 施工质量问题无法办理
A18: 19 | B18: BZJ-0016 | C18: 43374 | D18: =IF(TODAY()-E18<60,"2个月内",IF(TODAY()-E18<180,"3-6个月",IF(TODAY()-E18<360,"6个月-1年","一年以上"))) -> 一年以上 | E18: 43404 | F18: 生产部 | G18: 丁俊 | H18: 逸盛大化石化有限公司 | I18: 逸盛大化石化有限公司 | J18: 7000 | L18: 个人 | M18: 安全保证金 | N18: 7000 | O18: =J18-N18 -> 0 | P18: 43480 | Q18: =P18 -> 43480
A19: 3 | B19: BZJ-0017 | C19: 43405 | D19: =IF(TODAY()-E19<60,"2个月内",IF(TODAY()-E19<180,"3-6个月",IF(TODAY()-E19<360,"6个月-1年","一年以上"))) -> 一年以上 | E19: 43414 | F19: 生产部 | G19: 丁俊 | H19: 韩城尧柏阳山庄水泥有限公司 | I19: 韩城尧柏阳山庄水泥有限公司 | J19: =20000 -> 20000 | K19: 武汉 | L19: 对公 | M19: 安全保证金 | N19: 20000 | O19: =J19-N19 -> 0 | Q19: =P19 -> 0 | S19: 2019/12/24退19800
A20: 4 | B20: BZJ-0018 | C20: 43435 | D20: =IF(TODAY()-E20<60,"2个月内",IF(TODAY()-E20<180,"3-6个月",IF(TODAY()-E20<360,"6个月-1年","一年以上"))) -> 一年以上 | E20: 43446 | F20: 生产部 | G20: 冯海雄 | H20: 民和祁连山水泥有限公司 | I20: 民和祁连山水泥有限公司 | J20: 8000 | L20: 对公 | M20: 安全保证金 | N20: 8000 | O20: =J20-N20 -> 0 | P20: 43609 | Q20: =P20 -> 43609
A21: 12 | B21: BZJ-0019 | C21: 43466 | D21: =IF(TODAY()-E21<60,"2个月内",IF(TODAY()-E21<180,"3-6个月",IF(TODAY()-E21<360,"6个月-1年","一年以上"))) -> 一年以上 | E21: 43493 | F21: 生产部 | G21: 吴昌松 | H21: 冀东海天水泥闻喜有限公司 | I21: 冀东海天水泥闻喜有限公司 | J21: 10000 | L21: 对公 | M21: 安全保证金 | N21: 10000 | O21: =J21-N21 -> 0 | P21: 43664 | Q21: =P21 -> 43664
A22: 11 | B22: BZJ-0020 | C22: 43497 | D22: =IF(TODAY()-E22<60,"2个月内",IF(TODAY()-E22<180,"3-6个月",IF(TODAY()-E22<360,"6个月-1年","一年以上"))) -> 一年以上 | E22: 43511 | F22: 生产部 | G22: 汪勇刚 | H22: 贵州中诚水泥有限公司 | I22: 贵州中诚水泥有限公司 | J22: 3000 | L22: 对公 | M22: 安全保证金 | N22: 3000 | O22: =J22-N22 -> 0 | P22: 43646 | Q22: =P22 -> 43646
A23: 8 | B23: BZJ-0021 | C23: 43497 | D23: =IF(TODAY()-E23<60,"2个月内",IF(TODAY()-E23<180,"3-6个月",IF(TODAY()-E23<360,"6个月-1年","一年以上"))) -> 一年以上 | E23: 43516 | F23: 生产部 | G23: 覃延吉 | H23: 云南丽江西南水泥有限公司 | I23: 云南丽江西南水泥有限公司 | J23: 1000 | L23: 对公 | M23: 安全保证金 | N23: 1000 | O23: =J23-N23 -> 0 | P23: 43692 | Q23: =P23 -> 43692
A24: 14 | B24: BZJ-0022 | C24: 43525 | D24: =IF(TODAY()-E24<60,"2个月内",IF(TODAY()-E24<180,"3-6个月",IF(TODAY()-E24<360,"6个月-1年","一年以上"))) -> 一年以上 | E24: 43526 | F24: 生产部 | G24: 詹年喜 | H24: 邯郸涉县金隅水泥有限公司 | I24: 邯郸涉县金隅水泥有限公司 | J24: 2000 | L24: 对公 | M24: 安全保证金 | N24: 2000 | O24: =J24-N24 -> 0 | P24: 43698 | Q24: =P24 -> 43698
A25: 13 | B25: BZJ-0023 | C25: 43525 | D25: =IF(TODAY()-E25<60,"2个月内",IF(TODAY()-E25<180,"3-6个月",IF(TODAY()-E25<360,"6个月-1年","一年以上"))) -> 一年以上 | E25: 43530 | F25: 生产部 | G25: 詹年喜 | H25: 阳泉冀东水泥有限责任公司 | I25: 阳泉冀东水泥有限责任公司 | J25: 3000 | L25: 对公 | M25: 安全保证金 | N25: 3000 | O25: =J25-N25 -> 0 | P25: 43700 | Q25: =P25 -> 43700
A26: 9 | B26: BZJ-0024 | C26: 43525 | D26: =IF(TODAY()-E26<60,"2个月内",IF(TODAY()-E26<180,"3-6个月",IF(TODAY()-E26<360,"6个月-1年","一年以上"))) -> 一年以上 | E26: 43539 | F26: 生产部 | G26: 覃延吉 | H26: 河钢股份有限公司邯郸分公司 | I26: 河钢股份有限公司邯郸分公司 | J26: 10000 | L26: 对公 | M26: 安全保证金 | N26: 10000 | O26: =J26-N26 -> 0 | P26: 43613 | Q26: =P26 -> 43613
A27: 7 | B27: BZJ-0025 | C27: 43556 | D27: =IF(TODAY()-E27<60,"2个月内",IF(TODAY()-E27<180,"3-6个月",IF(TODAY()-E27<360,"6个月-1年","一年以上"))) -> 一年以上 | E27: 43557 | F27: 生产部 | G27: 石靖 | H27: 达州利森水泥有限公司 | I27: 达州利森水泥有限公司 | J27: 5000 | L27: 对公 | M27: 安全保证金 | N27: 5000 | O27: =J27-N27 -> 0 | P27: 43633 | Q27: =P27 -> 43633
A28: 16 | B28: BZJ-0026 | C28: 43556 | D28: =IF(TODAY()-E28<60,"2个月内",IF(TODAY()-E28<180,"3-6个月",IF(TODAY()-E28<360,"6个月-1年","一年以上"))) -> 一年以上 | E28: 43560 | F28: 总经办 | G28: 汤勇华 | H28: 张家港宏昌钢板有限公司 | I28: 张家港宏昌钢板有限公司 | J28: 124500 | K28: 武汉 | L28: 武汉对公 | M28: 安全保证金 | N28: 124500 | O28: =J28-N28 -> 0 | P28: 44890 | Q28: =P28 -> 44890 | S28: 武汉2019.4-50 | T28: 江苏省 | U28: 杨春龙 | V28: 预计2022.10月，收完全款后退回
A29: 194 | B29: BZJ-0027 | C29: 43556 | D29: =IF(TODAY()-E29<60,"2个月内",IF(TODAY()-E29<180,"3-6个月",IF(TODAY()-E29<360,"6个月-1年","一年以上"))) -> 一年以上 | E29: 43570 | G29: 夏锋泽 | H29: 四川西南水泥有限公司 | I29: 四川西南水泥有限公司 | J29: 10000 | L29: 对公 | M29: 投标保证金 | N29: 10000 | O29: =J29-N29 -> 0 | P29: 44064 | Q29: =P29 -> 44064 | S29: 长期投标不退
A30: 343 | B30: BZJ-0028 | C30: 43556 | D30: =IF(TODAY()-E30<60,"2个月内",IF(TODAY()-E30<180,"3-6个月",IF(TODAY()-E30<360,"6个月-1年","一年以上"))) -> 一年以上 | E30: 43585 | F30: 销售部 | G30: 李辉 | H30: 葛洲坝钟祥水泥有限公司 | I30: 葛洲坝钟祥水泥有限公司 | J30: 10000 | L30: 对公 | M30: 履约保证金 | N30: 10000 | O30: =J30-N30 -> 0 | P30: 43938 | Q30: =P30 -> 43938 | S30: 履约保证金
A31: 17 | B31: BZJ-0029 | C31: 43586 | D31: =IF(TODAY()-E31<60,"2个月内",IF(TODAY()-E31<180,"3-6个月",IF(TODAY()-E31<360,"6个月-1年","一年以上"))) -> 一年以上 | E31: 43600 | F31: 生产部 | G31: 李文池 | H31: 四川峨眉山西南水泥有限公司 | I31: 四川峨眉山西南水泥有限公司 | J31: 3000 | L31: 对公 | M31: 安全保证金 | N31: 3000 | O31: =J31-N31 -> 0 | P31: 43824 | Q31: =P31 -> 43824
A32: 18 | B32: BZJ-0030 | C32: 43586 | D32: =IF(TODAY()-E32<60,"2个月内",IF(TODAY()-E32<180,"3-6个月",IF(TODAY()-E32<360,"6个月-1年","一年以上"))) -> 一年以上 | E32: 43601 | F32: 生产部 | G32: 吴昌松 | H32: 云南昆钢嘉华水泥建材有限公司 | I32: 云南昆钢嘉华水泥建材有限公司 | J32: 3000 | L32: 对公 | M32: 安全保证金 | N32: 3000 | O32: =J32-N32 -> 0 | P32: 44484 | Q32: =P32 -> 44484
A33: 20 | B33: BZJ-0031 | C33: 43586 | D33: =IF(TODAY()-E33<60,"2个月内",IF(TODAY()-E33<180,"3-6个月",IF(TODAY()-E33<360,"6个月-1年","一年以上"))) -> 一年以上 | E33: 43601 | F33: 生产部 | G33: 余茶林 | H33: 汉中尧柏水泥有限公司 | I33: 汉中尧柏水泥有限公司 | J33: 10000 | L33: 对公 | M33: 安全保证金 | N33: 10000 | O33: =J33-N33 -> 0 | P33: 43973 | Q33: =P33 -> 43973
A34: 21 | B34: BZJ-0032 | C34: 43617 | D34: =IF(TODAY()-E34<60,"2个月内",IF(TODAY()-E34<180,"3-6个月",IF(TODAY()-E34<360,"6个月-1年","一年以上"))) -> 一年以上 | E34: 43621 | F34: 生产部 | G34: 房延云 | H34: 鲁南中联水泥有限公司 | I34: 鲁南中联水泥有限公司 | J34: 2000 | L34: 个人 | M34: 安全保证金 | N34: 2000 | O34: =J34-N34 -> 0 | P34: 43676 | Q34: =P34 -> 43676
A35: 22 | B35: BZJ-0033 | C35: 43617 | D35: =IF(TODAY()-E35<60,"2个月内",IF(TODAY()-E35<180,"3-6个月",IF(TODAY()-E35<360,"6个月-1年","一年以上"))) -> 一年以上 | E35: 43628 | F35: 生产部 | G35: 王小勇 | H35: 莒县中联水泥有限公司 | I35: 莒县中联水泥有限公司 | J35: 5000 | L35: 对公 | M35: 安全保证金 | N35: 5000 | O35: =J35-N35 -> 0 | P35: 43641 | Q35: =P35 -> 43641
A36: 23 | B36: BZJ-0034 | C36: 43617 | D36: =IF(TODAY()-E36<60,"2个月内",IF(TODAY()-E36<180,"3-6个月",IF(TODAY()-E36<360,"6个月-1年","一年以上"))) -> 一年以上 | E36: 43635 | F36: 生产部 | G36: 程时勇 | H36: 贵州沿河西南水泥有限公司 | I36: 贵州沿河西南水泥有限公司 | J36: 2000 | L36: 对公 | M36: 安全保证金 | N36: 2000 | O36: =J36-N36 -> 0 | P36: 43644 | Q36: =P36 -> 43644
A37: 24 | B37: BZJ-0035 | C37: 43617 | D37: =IF(TODAY()-E37<60,"2个月内",IF(TODAY()-E37<180,"3-6个月",IF(TODAY()-E37<360,"6个月-1年","一年以上"))) -> 一年以上 | E37: 43644 | F37: 生产部 | G37: 李文池 | H37: 西安蓝田尧柏水泥有限公司 | I37: 西安蓝田尧柏水泥有限公司 | J37: 10000 | L37: 对公 | M37: 安全保证金 | N37: 10000 | O37: =J37-N37 -> 0 | P37: 43703 | Q37: =P37 -> 43703
A38: 25 | B38: BZJ-0036 | C38: 43647 | D38: =IF(TODAY()-E38<60,"2个月内",IF(TODAY()-E38<180,"3-6个月",IF(TODAY()-E38<360,"6个月-1年","一年以上"))) -> 一年以上 | E38: 43657 | F38: 生产部 | G38: 吴昌松 | H38: 会东利森水泥有限公司 | I38: 会东利森水泥有限公司 | J38: 3000 | L38: 对公 | M38: 安全保证金 | N38: 3000 | O38: =J38-N38 -> 0 | P38: 43703 | Q38: =P38 -> 43703
A39: 27 | B39: BZJ-0037 | C39: 43647 | D39: =IF(TODAY()-E39<60,"2个月内",IF(TODAY()-E39<180,"3-6个月",IF(TODAY()-E39<360,"6个月-1年","一年以上"))) -> 一年以上 | E39: 43657 | F39: 生产部 | G39: 熊军 | H39: 冀东水泥铜川有限公司 | I39: 冀东水泥铜川有限公司 | J39: 1000 | L39: 个人 | M39: 安全保证金 | N39: 1000 | O39: =J39-N39 -> 0 | P39: 43661 | Q39: =P39 -> 43661
A40: 26 | B40: BZJ-0038 | C40: 43647 | D40: =IF(TODAY()-E40<60,"2个月内",IF(TODAY()-E40<180,"3-6个月",IF(TODAY()-E40<360,"6个月-1年","一年以上"))) -> 一年以上 | E40: 43664 | F40: 生产部 | G40: 吴昌松 | H40: 四川省绵竹澳东水泥有限责任公司 | I40: 四川省绵竹澳东水泥有限责任公司 | J40: 3000 | L40: 对公 | M40: 安全保证金 | N40: 3000 | O40: =J40-N40 -> 0 | P40: 43794 | Q40: =P40 -> 43794
A41: 28 | B41: BZJ-0039 | C41: 43678 | D41: =IF(TODAY()-E41<60,"2个月内",IF(TODAY()-E41<180,"3-6个月",IF(TODAY()-E41<360,"6个月-1年","一年以上"))) -> 一年以上 | E41: 43678 | F41: 生产部 | G41: 余茶林 | H41: 嘉华特种水泥股份有限公司嘉华水泥总厂 | I41: 嘉华特种水泥股份有限公司嘉华水泥总厂 | J41: 2000 | L41: 对公 | M41: 安全保证金 | N41: 2000 | O41: =J41-N41 -> 0 | P41: 43700 | Q41: =P41 -> 43700
A42: 29 | B42: BZJ-0040 | C42: 43678 | D42: =IF(TODAY()-E42<60,"2个月内",IF(TODAY()-E42<180,"3-6个月",IF(TODAY()-E42<360,"6个月-1年","一年以上"))) -> 一年以上 | E42: 43685 | F42: 销售部 | G42: 吴海波 | H42: 山东鲁城水泥有限公司 | I42: 山东鲁城水泥有限公司 | J42: 10000 | L42: 对公 | M42: 安全保证金 | N42: 10000 | O42: =J42-N42 -> 0 | P42: 44403 | Q42: =P42 -> 44403
A43: 30 | B43: BZJ-0041 | C43: 43678 | D43: =IF(TODAY()-E43<60,"2个月内",IF(TODAY()-E43<180,"3-6个月",IF(TODAY()-E43<360,"6个月-1年","一年以上"))) -> 一年以上 | E43: 43692 | F43: 生产部 | G43: 熊军、左汉军 | H43: 甘肃永固特种水泥有限公司 | I43: 甘肃永固特种水泥有限公司 | J43: 10000 | L43: 对公 | M43: 安全保证金 | N43: 10000 | O43: =J43-N43 -> 0 | P43: 43701 | Q43: =P43 -> 43701
A44: 31 | B44: BZJ-0042 | C44: 43678 | D44: =IF(TODAY()-E44<60,"2个月内",IF(TODAY()-E44<180,"3-6个月",IF(TODAY()-E44<360,"6个月-1年","一年以上"))) -> 一年以上 | E44: 43696 | F44: 生产部 | G44: 张子仪 | H44: 贵州纳雍隆庆乌江水泥有限公司 | I44: 贵州纳雍隆庆乌江水泥有限公司 | J44: 2000 | K44: 武汉 | L44: 武汉对公 | M44: 安全保证金 | N44: 2000 | O44: =J44-N44 -> 0 | P44: 45012 | Q44: =P44 -> 45012 | S44: 武汉2019.08-102 | T44: 贵州省 | U44: 陈涛
A45: 342 | B45: BZJ-0043 | C45: 43678 | D45: =IF(TODAY()-E45<60,"2个月内",IF(TODAY()-E45<180,"3-6个月",IF(TODAY()-E45<360,"6个月-1年","一年以上"))) -> 一年以上 | E45: 43696 | F45: 销售部 | G45: 吴海波 | H45: 涿鹿金隅水泥有限公司 | I45: 涿鹿金隅水泥有限公司 | J45: 20000 | L45: 对公 | M45: 履约保证金 | N45: 20000 | O45: =J45-N45 -> 0 | P45: 44673 | Q45: =P45 -> 44673 | S45: 是投标保证金转为了履约，履约又 转为了质保，质保刚刚到期。大约9月底回
A46: 32 | B46: BZJ-0044 | C46: 43678 | D46: =IF(TODAY()-E46<60,"2个月内",IF(TODAY()-E46<180,"3-6个月",IF(TODAY()-E46<360,"6个月-1年","一年以上"))) -> 一年以上 | E46: 43698 | F46: 生产部 | G46: 李文池 | H46: 重庆秀山西南水泥有限公司 | I46: 重庆秀山西南水泥有限公司 | J46: 2000 | L46: 对公 | M46: 安全保证金 | N46: 2000 | O46: =J46-N46 -> 0 | P46: 43829 | Q46: =P46 -> 43829
A47: 33 | B47: BZJ-0045 | C47: 43678 | D47: =IF(TODAY()-E47<60,"2个月内",IF(TODAY()-E47<180,"3-6个月",IF(TODAY()-E47<360,"6个月-1年","一年以上"))) -> 一年以上 | E47: 43700 | F47: 生产部 | G47: 程时勇 | H47: 山东泰西水泥有限公司 | I47: 山东泰西水泥有限公司 | J47: 1000 | L47: 个人 | M47: 安全保证金 | N47: 1000 | O47: =J47-N47 -> 0 | P47: 43718 | Q47: =P47 -> 43718
A48: 34 | B48: BZJ-0046 | C48: 43709 | D48: =IF(TODAY()-E48<60,"2个月内",IF(TODAY()-E48<180,"3-6个月",IF(TODAY()-E48<360,"6个月-1年","一年以上"))) -> 一年以上 | E48: 43710 | F48: 销售部 | G48: 吴海波 | H48: 涿鹿金隅水泥有限公司 | I48: 涿鹿金隅水泥有限公司 | J48: 25350 | K48: 武汉 | L48: 武汉对公 | M48: 安全保证金 | N48: 25350 | O48: =J48-N48 -> 0 | P48: 44673 | Q48: =P48 -> 44673 | S48: 武汉2019.9-105 | T48: 河北省 | U48: 杨春龙
A49: 35 | B49: BZJ-0047 | C49: 43709 | D49: =IF(TODAY()-E49<60,"2个月内",IF(TODAY()-E49<180,"3-6个月",IF(TODAY()-E49<360,"6个月-1年","一年以上"))) -> 一年以上 | E49: 43719 | F49: 生产部 | G49: 李文池 | H49: 绥江县永固水泥有限责任公司 | I49: 绥江县永固水泥有限责任公司 | J49: 4000 | L49: 对公 | M49: 安全保证金 | N49: 4000 | O49: =J49-N49 -> 0 | P49: 43723 | Q49: =P49 -> 43723
A50: 36 | B50: BZJ-0048 | C50: 43709 | D50: =IF(TODAY()-E50<60,"2个月内",IF(TODAY()-E50<180,"3-6个月",IF(TODAY()-E50<360,"6个月-1年","一年以上"))) -> 一年以上 | E50: 43727 | F50: 生产部 | G50: 吴昌松 | H50: 华新水泥（房县)有限公司 | I50: 华新水泥（房县)有限公司 | J50: 3000 | L50: 个人 | M50: 安全保证金 | N50: 3000 | O50: =J50-N50 -> 0 | P50: 43761 | Q50: =P50 -> 43761
A51: 37 | B51: BZJ-0049 | C51: 43709 | D51: =IF(TODAY()-E51<60,"2个月内",IF(TODAY()-E51<180,"3-6个月",IF(TODAY()-E51<360,"6个月-1年","一年以上"))) -> 一年以上 | E51: 43731 | F51: 生产部 | G51: 汪勇刚 | H51: 云南普洱西南水泥有限公司 | I51: 云南普洱西南水泥有限公司 | J51: 2000 | L51: 对公 | M51: 安全保证金 | N51: 2000 | O51: =J51-N51 -> 0 | P51: 43829 | Q51: =P51 -> 43829
A52: 38 | B52: BZJ-0050 | C52: 43709 | D52: =IF(TODAY()-E52<60,"2个月内",IF(TODAY()-E52<180,"3-6个月",IF(TODAY()-E52<360,"6个月-1年","一年以上"))) -> 一年以上 | E52: 43731 | F52: 生产部 | G52: 刘思佳 | H52: 冀东水泥重庆江津有限公司 | I52: 冀东水泥重庆江津有限公司 | J52: 7160 | L52: 对公 | M52: 安全保证金 | N52: 7160 | O52: =J52-N52 -> 0 | P52: 43847 | Q52: =P52 -> 43847
A53: 39 | B53: BZJ-0051 | C53: 43709 | D53: =IF(TODAY()-E53<60,"2个月内",IF(TODAY()-E53<180,"3-6个月",IF(TODAY()-E53<360,"6个月-1年","一年以上"))) -> 一年以上 | E53: 43733 | F53: 生产部 | G53: 覃延吉 | H53: 北京金隅琉水环保科技有限公司 | I53: 北京金隅琉水环保科技有限公司 | J53: 2000 | L53: 个人 | M53: 安全保证金 | N53: 2000 | O53: =J53-N53 -> 0 | P53: 43755 | Q53: =P53 -> 43755
A54: 40 | B54: BZJ-0052 | C54: 43739 | D54: =IF(TODAY()-E54<60,"2个月内",IF(TODAY()-E54<180,"3-6个月",IF(TODAY()-E54<360,"6个月-1年","一年以上"))) -> 一年以上 | E54: 43749 | F54: 生产部 | G54: 刘靖 | H54: 淮北众城水泥有限责任公司 | I54: 淮北众城水泥有限责任公司 | J54: 2600 | L54: 对公 | M54: 安全保证金 | N54: 2600 | O54: =J54-N54 -> 0 | P54: 43776 | Q54: =P54 -> 43776
A55: 41 | B55: BZJ-0053 | C55: 43739 | D55: =IF(TODAY()-E55<60,"2个月内",IF(TODAY()-E55<180,"3-6个月",IF(TODAY()-E55<360,"6个月-1年","一年以上"))) -> 一年以上 | E55: 43749 | F55: 生产部 | G55: 刘佳 | H55: 冀东水泥铜川有限公司 | I55: 冀东水泥铜川有限公司 | J55: 1000 | L55: 个人 | M55: 安全保证金 | N55: 1000 | O55: =J55-N55 -> 0 | P55: 43725 | Q55: =P55 -> 43725
A56: 43 | B56: BZJ-0054 | C56: 43739 | D56: =IF(TODAY()-E56<60,"2个月内",IF(TODAY()-E56<180,"3-6个月",IF(TODAY()-E56<360,"6个月-1年","一年以上"))) -> 一年以上 | E56: 43759 | F56: 生产部 | G56: 程时勇 | H56: 贵州清镇西南水泥有限公司 | I56: 贵州清镇西南水泥有限公司 | J56: 3000 | L56: 个人 | M56: 安全保证金 | N56: 3000 | O56: =J56-N56 -> 0 | P56: 43789 | Q56: =P56 -> 43789
A57: 44 | B57: BZJ-0055 | C57: 43739 | D57: =IF(TODAY()-E57<60,"2个月内",IF(TODAY()-E57<180,"3-6个月",IF(TODAY()-E57<360,"6个月-1年","一年以上"))) -> 一年以上 | E57: 43761 | F57: 生产部 | G57: 吴昌松 | H57: 华新水泥（恩施）有限公司 | I57: 华新水泥（恩施）有限公司 | J57: 3000 | L57: 个人 | M57: 安全保证金 | N57: 3000 | O57: =J57-N57 -> 0 | P57: 43768 | Q57: =P57 -> 43768
A58: 42 | B58: BZJ-0056 | C58: 43739 | D58: =IF(TODAY()-E58<60,"2个月内",IF(TODAY()-E58<180,"3-6个月",IF(TODAY()-E58<360,"6个月-1年","一年以上"))) -> 一年以上 | E58: 43766 | F58: 生产部 | G58: 刘西 | H58: 巴彦淖尔中联水泥有限公司 | I58: 巴彦淖尔中联水泥有限公司 | J58: 4000 | L58: 对公 | M58: 安全保证金 | N58: 4000 | O58: =J58-N58 -> 0 | P58: 44465 | Q58: =P58 -> 44465
A59: 45 | B59: BZJ-0057 | C59: 43770 | D59: =IF(TODAY()-E59<60,"2个月内",IF(TODAY()-E59<180,"3-6个月",IF(TODAY()-E59<360,"6个月-1年","一年以上"))) -> 一年以上 | E59: 43774 | F59: 生产部 | G59: 祝威 | H59: 安康市尧柏水泥有限公司 | I59: 安康市尧柏水泥有限公司 | J59: 10000 | L59: 对公 | M59: 安全保证金 | N59: 10000 | O59: =J59-N59 -> 0 | P59: 43976 | Q59: =P59 -> 43976
A60: 191 | B60: BZJ-0058 | C60: 43770 | D60: =IF(TODAY()-E60<60,"2个月内",IF(TODAY()-E60<180,"3-6个月",IF(TODAY()-E60<360,"6个月-1年","一年以上"))) -> 一年以上 | E60: 43774 | G60: 田学军 | H60: 贵州西南水泥有限公司 | I60: 贵州西南水泥有限公司 | J60: 50000 | K60: 武汉 | L60: 对公 | M60: 投标保证金 | N60: 50000 | O60: =J60-N60 -> 0 | P60: 44908 | Q60: =P60 -> 44908 | R60: 2022/12/31前退回，年标，转履约 | S60: 窑磨专业测窑调窑及整形，窑磨裂纹：长期投标不退
A61: 46 | B61: BZJ-0059 | C61: 43770 | D61: =IF(TODAY()-E61<60,"2个月内",IF(TODAY()-E61<180,"3-6个月",IF(TODAY()-E61<360,"6个月-1年","一年以上"))) -> 一年以上 | E61: 43775 | F61: 生产部 | G61: 刘思佳 | H61: 华新水泥（恩施）有限公司 | I61: 华新水泥（恩施）有限公司 | J61: 2000 | L61: 个人 | M61: 安全保证金 | N61: 2000 | O61: =J61-N61 -> 0 | P61: 43787 | Q61: =P61 -> 43787
A62: 47 | B62: BZJ-0060 | C62: 43770 | D62: =IF(TODAY()-E62<60,"2个月内",IF(TODAY()-E62<180,"3-6个月",IF(TODAY()-E62<360,"6个月-1年","一年以上"))) -> 一年以上 | E62: 43796 | F62: 生产部 | G62: 程时勇 | H62: 华新水泥（房县)有限公司 | I62: 华新水泥（房县)有限公司 | J62: 2000 | L62: 个人 | M62: 安全保证金 | N62: 2000 | O62: =J62-N62 -> 0 | P62: 43801 | Q62: =P62 -> 43801
A63: 193 | B63: BZJ-0061 | C63: 43800 | D63: =IF(TODAY()-E63<60,"2个月内",IF(TODAY()-E63<180,"3-6个月",IF(TODAY()-E63<360,"6个月-1年","一年以上"))) -> 一年以上 | E63: 43804 | G63: 杨春龙 | H63: 江苏永钢集团有限公司 | I63: 江苏永钢集团有限公司 | J63: 10000 | L63: 对公 | M63: 投标保证金 | N63: 10000 | O63: =J63-N63 -> 0 | P63: 44018 | Q63: =P63 -> 44018
A64: 48 | B64: BZJ-0062 | C64: 43800 | D64: =IF(TODAY()-E64<60,"2个月内",IF(TODAY()-E64<180,"3-6个月",IF(TODAY()-E64<360,"6个月-1年","一年以上"))) -> 一年以上 | E64: 43805 | F64: 生产部 | G64: 刘思佳 | H64: 阳泉冀东水泥有限责任公司 | I64: 阳泉冀东水泥有限责任公司 | J64: 2700 | L64: 对公 | M64: 安全保证金 | N64: 2700 | O64: =J64-N64 -> 0 | P64: 43985 | Q64: =P64 -> 43985
A65: 50 | B65: BZJ-0063 | C65: 43800 | D65: =IF(TODAY()-E65<60,"2个月内",IF(TODAY()-E65<180,"3-6个月",IF(TODAY()-E65<360,"6个月-1年","一年以上"))) -> 一年以上 | E65: 43808 | F65: 生产部 | G65: 吴昌松 | H65: 山东泰西水泥有限公司 | I65: 山东泰西水泥有限公司 | J65: 2000 | L65: 个人 | M65: 安全保证金 | N65: 2000 | O65: =J65-N65 -> 0 | P65: 43819 | Q65: =P65 -> 43819
A66: 49 | B66: BZJ-0064 | C66: 43800 | D66: =IF(TODAY()-E66<60,"2个月内",IF(TODAY()-E66<180,"3-6个月",IF(TODAY()-E66<360,"6个月-1年","一年以上"))) -> 一年以上 | E66: 43812 | F66: 生产部 | G66: 王延军 | H66: 渤海水泥（葫芦岛）有限公司 | I66: 渤海水泥（葫芦岛）有限公司 | J66: 3000 | L66: 对公 | M66: 安全保证金 | N66: 3000 | O66: =J66-N66 -> 0 | P66: 44189 | Q66: =P66 -> 44189
A67: 51 | B67: BZJ-0065 | C67: 43800 | D67: =IF(TODAY()-E67<60,"2个月内",IF(TODAY()-E67<180,"3-6个月",IF(TODAY()-E67<360,"6个月-1年","一年以上"))) -> 一年以上 | E67: 43823 | F67: 生产部 | G67: 吴昌松 | H67: 天瑞新登郑州水泥有限公司 | I67: 天瑞新登郑州水泥有限公司 | J67: 2000 | L67: 个人 | M67: 安全保证金 | N67: 2000 | O67: =J67-N67 -> 0 | P67: 43834 | Q67: =P67 -> 43834
A68: 52 | B68: BZJ-0066 | C68: 43800 | D68: =IF(TODAY()-E68<60,"2个月内",IF(TODAY()-E68<180,"3-6个月",IF(TODAY()-E68<360,"6个月-1年","一年以上"))) -> 一年以上 | E68: 43825 | F68: 生产部 | G68: 何煜军 | H68: 酒钢（集团）宏达建材有限责任公司 | I68: 酒钢（集团）宏达建材有限责任公司 | J68: 5000 | L68: 对公 | M68: 安全保证金 | N68: 5000 | O68: =J68-N68 -> 0 | P68: 44099 | Q68: =P68 -> 44099
A69: 73 | B69: BZJ-0067 | C69: 43800 | D69: =IF(TODAY()-E69<60,"2个月内",IF(TODAY()-E69<180,"3-6个月",IF(TODAY()-E69<360,"6个月-1年","一年以上"))) -> 一年以上 | E69: 43830 | F69: 销售部 | G69: 杨春龙 | H69: 江苏沙钢集团有限公司 | I69: 江苏沙钢集团有限公司 | J69: 900 | K69: 武汉 | L69: 个人 | M69: 安全保证金 | O69: =J69-N69 -> 900 | Q69: =P69 -> 0 | R69: 门禁卡押金 | S69: 门禁卡 | T69: 江苏省 | U69: =VLOOKUP(T69,[1]区域划分!$A$1:$C$39,3,0) -> 龚运谱
A70: 53 | B70: BZJ-0068 | C70: 43831 | D70: =IF(TODAY()-E70<60,"2个月内",IF(TODAY()-E70<180,"3-6个月",IF(TODAY()-E70<360,"6个月-1年","一年以上"))) -> 一年以上 | E70: 43840 | F70: 生产部 | G70: 祝发权 | H70: 安钢集团信阳钢铁有限责任公司 | I70: 安钢集团信阳钢铁有限责任公司 | J70: 3000 | L70: 个人 | M70: 安全保证金 | N70: 3000 | O70: =J70-N70 -> 0 | P70: 43920 | Q70: =P70 -> 43920
A71: 54 | B71: BZJ-0069 | C71: 43831 | D71: =IF(TODAY()-E71<60,"2个月内",IF(TODAY()-E71<180,"3-6个月",IF(TODAY()-E71<360,"6个月-1年","一年以上"))) -> 一年以上 | E71: 43840 | F71: 生产部 | G71: 黄庭兴 | H71: 承德金隅水泥有限责任公司 | I71: 承德金隅水泥有限责任公司 | J71: 2000 | K71: 武汉 | L71: 武汉对公 | M71: 安全保证金 | N71: 2000 | O71: =J71-N71 -> 0 | P71: 45035 | Q71: =P71 -> 45035 | R71: 预计2023.03月退款 | S71: 武汉2020.1-136 | T71: 河北省 | U71: 杨春龙 | V71: 安环部詹工
A72: 195 | B72: BZJ-0070 | C72: 43831 | D72: =IF(TODAY()-E72<60,"2个月内",IF(TODAY()-E72<180,"3-6个月",IF(TODAY()-E72<360,"6个月-1年","一年以上"))) -> 一年以上 | E72: 43840 | G72: 殷坤鹏 | H72: 鄂尔多斯市君正能源化工有限公司水泥分公司 | I72: 鄂尔多斯市君正能源化工有限公司水泥分公司 | J72: 10000 | L72: 对公 | M72: 投标保证金 | N72: 10000 | O72: =J72-N72 -> 0 | P72: 43913 | Q72: =P72 -> 43913 | S72: 长期投标不退
A73: 55 | B73: BZJ-0071 | C73: 43831 | D73: =IF(TODAY()-E73<60,"2个月内",IF(TODAY()-E73<180,"3-6个月",IF(TODAY()-E73<360,"6个月-1年","一年以上"))) -> 一年以上 | E73: 43843 | F73: 生产部 | G73: 王小勇 | H73: 渤海水泥（葫芦岛）有限公司 | I73: 渤海水泥（葫芦岛）有限公司 | J73: 3000 | K73: 武汉 | L73: 对公 | M73: 安全保证金 | N73: 2900 | O73: =J73-N73 -> 100 | Q73: =P73 -> 0 | R73: 2021/3/24实际退款2900元 | T73: 辽宁省 | U73: =VLOOKUP(T73,[1]区域划分!$A$1:$C$39,3,0) -> 殷坤鹏
A74: 344 | B74: BZJ-0072 | C74: 43831 | D74: =IF(TODAY()-E74<60,"2个月内",IF(TODAY()-E74<180,"3-6个月",IF(TODAY()-E74<360,"6个月-1年","一年以上"))) -> 一年以上 | E74: 43843 | F74: 销售部 | G74: 夏锋泽 | H74: 四川金宏通实业有限公司 | I74: 四川金宏通实业有限公司 | J74: 24000 | L74: 对公 | M74: 履约保证金 | N74: 24000 | O74: =J74-N74 -> 0 | P74: 44193 | Q74: =P74 -> 44193 | S74: 履约保证金
A75: 56 | B75: BZJ-0073 | C75: 43891 | D75: =IF(TODAY()-E75<60,"2个月内",IF(TODAY()-E75<180,"3-6个月",IF(TODAY()-E75<360,"6个月-1年","一年以上"))) -> 一年以上 | E75: 43920 | F75: 生产部 | G75: 雍佳强 | H75: 青海海西化工建材股份有限公司 | I75: 青海海西化工建材股份有限公司 | J75: 5000 | L75: 个人 | M75: 安全保证金 | N75: 5000 | O75: =J75-N75 -> 0 | P75: 44039 | Q75: =P75 -> 44039
A76: 57 | B76: BZJ-0074 | C76: 43922 | D76: =IF(TODAY()-E76<60,"2个月内",IF(TODAY()-E76<180,"3-6个月",IF(TODAY()-E76<360,"6个月-1年","一年以上"))) -> 一年以上 | E76: 43923 | F76: 生产部 | G76: 祝威 | H76: 甘肃永固特种水泥有限公司 | I76: 甘肃永固特种水泥有限公司 | J76: 10000 | K76: 武汉 | L76: 武汉对公 | M76: 安全保证金 | O76: =J76-N76 -> 10000 | Q76: =P76 -> 0 | R76: 已提供对账单，与货款一起请方渊在跟进。起诉调解，第一批25万已支付 | S76: 武汉2020.04-07 | T76: 甘肃省 | U76: =VLOOKUP(T76,[1]区域划分!$A$1:$C$39,3,0) -> 曾江利
A77: 196 | B77: BZJ-0075 | C77: 43922 | D77: =IF(TODAY()-E77<60,"2个月内",IF(TODAY()-E77<180,"3-6个月",IF(TODAY()-E77<360,"6个月-1年","一年以上"))) -> 一年以上 | E77: 43936 | G77: 吴海波 | H77: 河北新金轧材有限公司 | I77: 河北新金轧材有限公司 | J77: 10000 | L77: 对公 | M77: 投标保证金 | N77: 10000 | O77: =J77-N77 -> 0 | P77: 44155 | Q77: =P77 -> 44155 | S77: 投标保证金
A78: 58 | B78: BZJ-0076 | C78: 43952 | D78: =IF(TODAY()-E78<60,"2个月内",IF(TODAY()-E78<180,"3-6个月",IF(TODAY()-E78<360,"6个月-1年","一年以上"))) -> 一年以上 | E78: 43967 | F78: 生产部 | G78: 吕海洲 | H78: 贵州沿河西南水泥有限公司 | I78: 贵州沿河西南水泥有限公司 | J78: 5000 | L78: 对公 | M78: 安全保证金 | N78: 5000 | O78: =J78-N78 -> 0 | P78: 44463 | Q78: =P78 -> 44463
A79: 59 | B79: BZJ-0077 | C79: 43952 | D79: =IF(TODAY()-E79<60,"2个月内",IF(TODAY()-E79<180,"3-6个月",IF(TODAY()-E79<360,"6个月-1年","一年以上"))) -> 一年以上 | E79: 43969 | F79: 生产部 | G79: 汪勇刚 | H79: 四川达州钢铁有限公司 | I79: 四川达州钢铁有限公司 | J79: 2000 | L79: 个人 | M79: 安全保证金 | N79: 2000 | O79: =J79-N79 -> 0 | P79: 44034 | Q79: =P79 -> 44034
A80: 60 | B80: BZJ-0078 | C80: 43952 | D80: =IF(TODAY()-E80<60,"2个月内",IF(TODAY()-E80<180,"3-6个月",IF(TODAY()-E80<360,"6个月-1年","一年以上"))) -> 一年以上 | E80: 43969 | F80: 生产部 | G80: 黄国恩 | H80: 四川峨眉山西南水泥有限公司 | I80: 四川峨眉山西南水泥有限公司 | J80: 3000 | L80: 对公 | M80: 安全保证金 | N80: 3000 | O80: =J80-N80 -> 0 | P80: 44035 | Q80: =P80 -> 44035
A81: 61 | B81: BZJ-0079 | C81: 43952 | D81: =IF(TODAY()-E81<60,"2个月内",IF(TODAY()-E81<180,"3-6个月",IF(TODAY()-E81<360,"6个月-1年","一年以上"))) -> 一年以上 | E81: 43977 | F81: 生产部 | G81: 何煜军 | H81: 冀东海天水泥闻喜有限公司 | I81: 冀东海天水泥闻喜有限公司 | J81: 5000 | L81: 对公 | M81: 安全保证金 | N81: 5000 | O81: =J81-N81 -> 0 | P81: 44491 | Q81: =P81 -> 44491
A82: 62 | B82: BZJ-0080 | C82: 43983 | D82: =IF(TODAY()-E82<60,"2个月内",IF(TODAY()-E82<180,"3-6个月",IF(TODAY()-E82<360,"6个月-1年","一年以上"))) -> 一年以上 | E82: 43992 | F82: 生产部 | G82: 吕海洲 | H82: 阳泉冀东水泥有限责任公司 | I82: 阳泉冀东水泥有限责任公司 | J82: 2000 | L82: 对公 | M82: 安全保证金 | N82: 2000 | O82: =J82-N82 -> 0 | P82: 44083 | Q82: =P82 -> 44083
A83: 63 | B83: BZJ-0081 | C83: 43983 | D83: =IF(TODAY()-E83<60,"2个月内",IF(TODAY()-E83<180,"3-6个月",IF(TODAY()-E83<360,"6个月-1年","一年以上"))) -> 一年以上 | E83: 44010 | F83: 生产部 | G83: 黄庭兴 | H83: 四川华蓥西南水泥有限公司 | I83: 四川华蓥西南水泥有限公司 | J83: 1500 | L83: 对公 | M83: 安全保证金 | N83: 1500 | O83: =J83-N83 -> 0 | P83: 44130 | Q83: =P83 -> 44130
A84: 197 | B84: BZJ-0082 | C84: 43983 | D84: =IF(TODAY()-E84<60,"2个月内",IF(TODAY()-E84<180,"3-6个月",IF(TODAY()-E84<360,"6个月-1年","一年以上"))) -> 一年以上 | E84: 44011 | G84: 夏锋泽 | H84: 四川西南水泥有限公司（川渝西南） | I84: 四川西南水泥有限公司 | J84: 50000 | K84: 武汉 | L84: 对公 | M84: 投标保证金 | O84: =J84-N84 -> 50000 | Q84: =P84 -> 0 | R84: 年标，转履约 | S84: 测窑及维修，长期投标不退 | T84: 四川省 | U84: =VLOOKUP(T84,[1]区域划分!$A$1:$C$39,3,0) -> 牛国庆
A85: 64 | B85: BZJ-0083 | C85: 43983 | D85: =IF(TODAY()-E85<60,"2个月内",IF(TODAY()-E85<180,"3-6个月",IF(TODAY()-E85<360,"6个月-1年","一年以上"))) -> 一年以上 | E85: 44012 | F85: 销售部 | G85: 杨春龙 | H85: 天瑞集团郑州水泥有限公司 | I85: 天瑞集团郑州水泥有限公司 | J85: 3000 | L85: 个人 | M85: 安全保证金 | N85: 3000 | O85: =J85-N85 -> 0 | P85: 44196 | Q85: =P85 -> 44196
A86: 65 | B86: BZJ-0084 | C86: 44013 | D86: =IF(TODAY()-E86<60,"2个月内",IF(TODAY()-E86<180,"3-6个月",IF(TODAY()-E86<360,"6个月-1年","一年以上"))) -> 一年以上 | E86: 44018 | F86: 生产部 | G86: 祝发权 | H86: 阳泉冀东水泥有限责任公司 | I86: 阳泉冀东水泥有限责任公司 | J86: 2000 | L86: 对公 | M86: 安全保证金 | N86: 2000 | O86: =J86-N86 -> 0 | P86: 44083 | Q86: =P86 -> 44083
A87: 66 | B87: BZJ-0085 | C87: 44013 | D87: =IF(TODAY()-E87<60,"2个月内",IF(TODAY()-E87<180,"3-6个月",IF(TODAY()-E87<360,"6个月-1年","一年以上"))) -> 一年以上 | E87: 44021 | F87: 生产部 | G87: 王小勇 | H87: 贵州松桃高力水泥实业有限公司 | I87: 贵州松桃高力水泥实业有限公司 | J87: 1000 | L87: 对公 | M87: 安全保证金 | N87: 1000 | O87: =J87-N87 -> 0 | P87: 44069 | Q87: =P87 -> 44069 | S87: 对公退款800元和交现金200元
A88: 68 | B88: BZJ-0086 | C88: 44013 | D88: =IF(TODAY()-E88<60,"2个月内",IF(TODAY()-E88<180,"3-6个月",IF(TODAY()-E88<360,"6个月-1年","一年以上"))) -> 一年以上 | E88: 44025 | F88: 生产部 | G88: 程时勇 | H88: 冀东水泥璧山有限公司 | I88: 冀东水泥璧山有限公司 | J88: 2000 | L88: 对公 | M88: 安全保证金 | N88: 2000 | O88: =J88-N88 -> 0 | P88: 44223 | Q88: =P88 -> 44223 | S88: 2021年1月27日收2000冀东水泥璧山有限公司退安全保证金
A89: 67 | B89: BZJ-0087 | C89: 44013 | D89: =IF(TODAY()-E89<60,"2个月内",IF(TODAY()-E89<180,"3-6个月",IF(TODAY()-E89<360,"6个月-1年","一年以上"))) -> 一年以上 | E89: 44027 | F89: 生产部 | G89: 王小勇 | H89: 贵州织金西南水泥有限公司 | I89: 贵州织金西南水泥有限公司 | J89: 1000 | L89: 对公 | M89: 安全保证金 | N89: 1000 | O89: =J89-N89 -> 0 | P89: 44547 | Q89: =P89 -> 44547
A90: 69 | B90: BZJ-0088 | C90: 44013 | D90: =IF(TODAY()-E90<60,"2个月内",IF(TODAY()-E90<180,"3-6个月",IF(TODAY()-E90<360,"6个月-1年","一年以上"))) -> 一年以上 | E90: 44034 | F90: 生产部 | G90: 程时勇 | H90: 达州利森水泥有限公司 | I90: 达州利森水泥有限公司 | J90: 3000 | L90: 对公 | M90: 安全保证金 | N90: 3000 | O90: =J90-N90 -> 0 | P90: 44071 | Q90: =P90 -> 44071 | S90: 2020-8-27程时勇退3000达州利森水泥安全保证金（款打给达州利森水泥有限公司）
A91: 70 | B91: BZJ-0089 | C91: 44013 | D91: =IF(TODAY()-E91<60,"2个月内",IF(TODAY()-E91<180,"3-6个月",IF(TODAY()-E91<360,"6个月-1年","一年以上"))) -> 一年以上 | E91: 44034 | F91: 生产二部 | G91: 黄庭兴 | H91: 赞皇金隅水泥有限公司 | I91: 赞皇金隅水泥有限公司 | J91: 3200 | K91: 武汉 | L91: 武汉对公 | M91: 安全保证金 | N91: 3200 | O91: =J91-N91 -> 0 | P91: 44678 | Q91: =P91 -> 44678 | S91: 安全保证金 | T91: 河北省 | U91: 杨春龙 | V91: 武汉2020.7-147
A92: 71 | B92: BZJ-0090 | C92: 44013 | D92: =IF(TODAY()-E92<60,"2个月内",IF(TODAY()-E92<180,"3-6个月",IF(TODAY()-E92<360,"6个月-1年","一年以上"))) -> 一年以上 | E92: 44034 | F92: 生产部 | G92: 汪勇刚 | H92: 四川德胜集团水泥有限公司 | I92: 四川德胜集团水泥有限公司 | J92: 3000 | L92: 对公 | M92: 安全保证金 | N92: 3000 | O92: =J92-N92 -> 0 | P92: 44221 | Q92: =P92 -> 44221 | S92: 2021年1月25日收四川德胜集团水泥有限公司退安全保证金
A93: 72 | B93: BZJ-0091 | C93: 44013 | D93: =IF(TODAY()-E93<60,"2个月内",IF(TODAY()-E93<180,"3-6个月",IF(TODAY()-E93<360,"6个月-1年","一年以上"))) -> 一年以上 | E93: 44038 | F93: 生产部 | G93: 程时勇 | H93: 韩城尧柏阳山庄水泥有限公司 | I93: 韩城尧柏阳山庄水泥有限公司 | J93: 10000 | L93: 对公 | M93: 安全保证金 | N93: 10000 | O93: =J93-N93 -> 0 | P93: 44073 | Q93: =P93 -> 44073 | S93: 2020-8-31程时勇退10000韩城尧柏水泥安全保证金（款打给韩城尧柏阳山庄水泥有限公司）
A94: 74 | B94: BZJ-0092 | C94: 44044 | D94: =IF(TODAY()-E94<60,"2个月内",IF(TODAY()-E94<180,"3-6个月",IF(TODAY()-E94<360,"6个月-1年","一年以上"))) -> 一年以上 | E94: 44048 | F94: 销售部 | G94: 夏锋泽 | H94: 冀东水泥重庆合川有限责任公司 | I94: 冀东水泥重庆合川有限责任公司 | J94: 2000 | K94: 武汉 | L94: 武汉对公 | M94: 安全保证金 | N94: 2000 | O94: =J94-N94 -> 0 | P94: 44707 | Q94: =P94 -> 44707 | R94: 需要上门办理牛国庆处理，预计5月 | S94: 安全保证金 | T94: 重庆 | U94: 牛国庆 | V94: 武汉2020.08-07
A95: 75 | B95: BZJ-0093 | C95: 44044 | D95: =IF(TODAY()-E95<60,"2个月内",IF(TODAY()-E95<180,"3-6个月",IF(TODAY()-E95<360,"6个月-1年","一年以上"))) -> 一年以上 | E95: 44050 | F95: 销售部 | G95: 陈冲 | H95: 商洛尧柏龙桥水泥有限公司 | I95: 商洛尧柏龙桥水泥有限公司 | J95: 10000 | K95: 武汉 | L95: 对公 | M95: 安全保证金 | N95: 10000 | O95: =J95-N95 -> 0 | P95: 45070 | Q95: =P95 -> 45070 | R95: 3.2023.4月林维现场跟进，退款手续办理中，预计5月退回 | S95: 安全保证金 | T95: 陕西省 | U95: 朱利勇
A96: 76 | B96: BZJ-0094 | C96: 44044 | D96: =IF(TODAY()-E96<60,"2个月内",IF(TODAY()-E96<180,"3-6个月",IF(TODAY()-E96<360,"6个月-1年","一年以上"))) -> 一年以上 | E96: 44053 | F96: 销售部 | G96: 夏锋泽 | H96: 旺苍川煤水泥有限责任公司 | I96: 旺苍川煤水泥有限责任公司 | J96: 3000 | L96: 对公 | M96: 安全保证金 | N96: 3000 | O96: =J96-N96 -> 0 | P96: 44094 | Q96: =P96 -> 44094
A97: 77 | B97: BZJ-0095 | C97: 44044 | D97: =IF(TODAY()-E97<60,"2个月内",IF(TODAY()-E97<180,"3-6个月",IF(TODAY()-E97<360,"6个月-1年","一年以上"))) -> 一年以上 | E97: 44057 | F97: 销售部 | G97: 夏锋泽 | H97: 重庆长寿西南水泥有限公司 | I97: 重庆长寿西南水泥有限公司 | J97: 3000 | L97: 对公 | M97: 安全保证金 | N97: 3000 | O97: =J97-N97 -> 0 | P97: 44335 | Q97: =P97 -> 44335
A98: 78 | B98: BZJ-0096 | C98: 44044 | D98: =IF(TODAY()-E98<60,"2个月内",IF(TODAY()-E98<180,"3-6个月",IF(TODAY()-E98<360,"6个月-1年","一年以上"))) -> 一年以上 | E98: 44063 | F98: 销售部 | G98: 瞿新虎 | H98: 华新水泥（红河）有限公司 | I98: 华新水泥（红河）有限公司 | J98: 5000 | L98: 个人 | M98: 安全保证金 | N98: 5000 | O98: =J98-N98 -> 0 | P98: 44068 | Q98: =P98 -> 44068
A99: 198 | B99: BZJ-0097 | C99: 44075 | D99: =IF(TODAY()-E99<60,"2个月内",IF(TODAY()-E99<180,"3-6个月",IF(TODAY()-E99<360,"6个月-1年","一年以上"))) -> 一年以上 | E99: 44078 | G99: 瞿新虎 | H99: 云南西南水泥有限公司 | I99: 云南西南水泥有限公司 | J99: 50000 | K99: 武汉 | L99: 对公 | M99: 投标保证金 | N99: 50000 | O99: =J99-N99 -> 0 | P99: 45257 | Q99: =P99 -> 45257 | R99: 年标，转履约 | S99: 长期投标不退 | T99: 云南省 | U99: =VLOOKUP(T99,[1]区域划分!$A$1:$C$39,3,0) -> 牛国庆
A100: 199 | B100: BZJ-0098 | C100: 44075 | D100: =IF(TODAY()-E100<60,"2个月内",IF(TODAY()-E100<180,"3-6个月",IF(TODAY()-E100<360,"6个月-1年","一年以上"))) -> 一年以上 | E100: 44085 | G100: 吴海波 | H100: 昌黎冀东水泥有限公司 | I100: 昌黎冀东水泥有限公司 | J100: 2000 | L100: 对公 | M100: 投标保证金 | N100: 2000 | O100: =J100-N100 -> 0 | P100: 44559 | Q100: =P100 -> 44559 | S100: 投标保证金
...

Sheet Sheet2
A1: 标书费 | B1: 12668
A2: 投标保证金 | B2: 257775
A3: 安全保证金 | B3: 5000
A4: 平台服务费 | B4: 12500
A5: 中标服务费 | B5: 4160
A6: 履约保证金 | B6: 50000
B8: =SUM(B1:B7) -> 342103

Sheet Sheet3-婷
A1: 支付日期 | B1: 公司名称2 | C1: 支付类型 | D1: 部门 | E1: 经办人 | F1: 求和项:未退余额
A2: 2024-06-25 | B2: 青海发投碱业有限公司 | C2: 履约保证金 | D2: 销售部 | E2: 陈纤 | F2: 6950
A3: 2024-06-26 | B3: 安徽恒泰新材料有限公司 | C3: 投标保证金 | D3: 商务部 | E3: 周奇 | F3: 2000
A4: 2024-06-27 | B4: 青海发投碱业有限公司 | C4: 安全保证金 | D4: 内勤组 | E4: 陈云 | F4: 7000
A5: 2024-06-27 | B5: 青海发投碱业有限公司 | C5: 农民工工资保证金 | D5: 内勤组 | E5: 陈云 | F5: 6950
A6: 2024-07-01 | B6: 新疆宜化化工有限公司 | C6: 投标保证金 | D6: 商务部 | E6: 周奇 | F6: 0
A7: 2024-07-19 | B7: 国家电投集团山西铝业有限公司 | C7: 投标保证金 | D7: 商务部 | E7: 周奇 | F7: 0
A8: 2024-07-24 | B8: 青海发投碱业有限公司 | C8: 投标保证金 | D8: 商务部 | E8: 周奇 | F8: 0
A9: 2024-07-26 | B9: 鞍山冀东水泥有限责任公司 | C9: 投标保证金 | D9: 商务部 | E9: 周奇 | F9: 0
A10: 42390 | B10: 亚泰集团伊通水泥有限公司 | C10: 投标保证金 | D10: (空白) | E10: 吴海波 | F10: 20000
A11: 42400 | B11: 江苏沙钢集团有限公司 | C11: 投标保证金 | D11: (空白) | E11: (空白) | F11: 10000
A12: 42887 | B12: 江苏沙钢集团有限公司 | C12: 安全保证金 | D12: (空白) | E12: (空白) | F12: 10000
A13: 43113 | B13: 永登祁连山水泥有限公司 | C13: 安全保证金 | D13: 生产部 | E13: 姜兵 | F13: 0
A14: 43124 | B14: 逸盛大化石化有限公司 | C14: 安全保证金 | D14: (空白) | E14: 丁俊 | F14: 7000
A15: 43255 | B15: 德州中联大坝水泥有限公司 | C15: 安全保证金 | D15: 生产一部 | E15: 汪勇刚 | F15: 0
A16: 43330 | B16: 四川西南水泥有限公司 | C16: 安全保证金 | D16: 生产部 | E16: 张子仪 | F16: 0
A17: 43393 | B17: 新安中联万基水泥有限公司 | C17: 安全保证金 | D17: 生产部 | E17: 刘西 | F17: 0
A18: 43404 | B18: 逸盛大化石化有限公司 | C18: 安全保证金 | D18: 生产部 | E18: 丁俊 | F18: 0
A19: 43414 | B19: 韩城尧柏阳山庄水泥有限公司 | C19: 安全保证金 | D19: 生产部 | E19: 丁俊 | F19: 0
A20: 43446 | B20: 民和祁连山水泥有限公司 | C20: 安全保证金 | D20: 生产部 | E20: 冯海雄 | F20: 0
A21: 43475 | B21: 江苏沙钢集团有限公司 | C21: 投标保证金 | D21: (空白) | E21: 汤勇华 | F21: 50000
... A318: 44609 | B318: 山东泰山钢铁集团有限公司 | C318: 安全保证金 | D318: 生产部 | E318: 汪勇刚 | F318: 0
A319: 44615 | B319: 0 | C319: 投标保证金 | D319: (空白) | E319: 周奇 | F319: 0
A320: 44615 | B320: 山西省中条山新型建材有限公司 | C320: 投标保证金 | D320: (空白) | E320: 周奇 | F320: 0
A321: 44617 | B321: 河南省兴豫电子商务有限公司 | C321: 投标保证金 | D321: (空白) | E321: 杨江 | F321: 0
A322: 44617 | B322: 河南省豫鹤同力水泥有限公司 | C322: 标书费 | D322: 商务部 | E322: 杨江 | F322: 0
A323: 44617 | B323: 新兴铸管股份有限公司 | C323: 安全保证金 | D323: 销售部 | E323: 陈远志 | F323: 2000
A324: 44617 | B324: 云南远东水泥有限公司 | C324: 安全保证金 | D324: 生产二部 | E324: 吴结 | F324: 0
A325: 44620 | B325: 会东利森水泥有限公司 | C325: 安全保证金 | D325: 生产部 | E325: 程时勇 | F325: 0
A326: 44622 | B326: 河南晋开化工投资控股集团有限责任公司 | C326: 安全保证金 | D326: 生产部 | E326: 肖辉军 | F326: 0
A327: 44623 | B327: 重庆长寿西南水泥有限公司 | C327: 安全保证金 | D327: 生产部 | E327: 程时勇 | F327: 0
A328: 44624 | B328: 江苏磊达股份有限公司 | C328: 投标保证金 | D328: (空白) | E328: 杨江 | F328: 0
A329: 44627 | B329: 仁寿县汪洋建宝水泥有限公司广石分公司 | C329: 投标保证金 | D329: (空白) | E329: 周奇 | F329: 0
A330: 44628 | B330: 江苏磊达股份有限公司 | C330: 标书费 | D330: 商务部 | E330: 杨江 | F330: 0
A331: 44630 | B331: 鹤岗鑫塔水泥有限责任公司 | C331: 标书费 | D331: 销售部 | E331: 殷坤鹏 | F331: 0
... A861: 45716 | B861: 青海发投碱业有限公司 | C861: 投标保证金 | D861: 商务部 | E861: 周奇 | F861: 20000
A862: (空白) | B862: 东方希望重庆水泥有限公司 | C862: 投标保证金 | D862: 商务部 | E862: 周奇 | F862: 0
A863: (空白) | B863: 湖北宜化松滋肥业有限公司 | C863: 投标保证金 | D863: 商务部 | E863: 周奇 | F863: 0
A864: (空白) | B864: 淮北众城水泥有限责任公司 | C864: 投标保证金 | D864: (空白) | E864: (空白) | F864: 3000
A865: (空白) | B865: 吉林亚泰集团物资贸易有限公司 | C865: 投标保证金 | D865: (空白) | E865: (空白) | F865: 3800
A866: (空白) | B866: 江苏永钢集团物资贸易有限公司 | C866: 投标保证金 | D866: (空白) | E866: (空白) | F866: 20000
A867: (空白) | B867: 酒泉钢铁（集团）有限公司 | C867: 投标保证金 | D867: (空白) | E867: (空白) | F867: 0
A868: (空白) | B868: 三门峡腾跃同力水泥有限公司 | C868: 投标保证金 | D868: (空白) | E868: (空白) | F868: 1000
A869: (空白) | B869: 山东泰山钢铁集团有限公司 | C869: 安全保证金 | D869: 生产部 | E869: 陈云 | F869: 0
A870: (空白) | B870: 新疆宜化化工有限公司 | C870: 投标保证金 | D870: 商务部 | E870: 周奇 | F870: 0
A871: (空白) | B871: 云南西南水泥有限公司 | C871: 投标保证金 | D871: (空白) | E871: (空白) | F871: 0
A872: 总计 | F872: 3270188.1

Sheet Sheet4-婷
A1: 支付日期 | B1: 公司名称2 | C1: 支付类型 | D1: 部门 | E1: 经办人 | F1: 求和项:未退余额
A2: 45468 | B2: 青海发投碱业有限公司 | C2: 履约保证金 | D2: 销售部 | E2: 陈纤 | F2: 6950
A3: 45469 | B3: 安徽恒泰新材料有限公司 | C3: 投标保证金 | D3: 商务部 | E3: 周奇 | F3: 2000
A4: 45470 | B4: 青海发投碱业有限公司 | C4: 安全保证金 | D4: 内勤组 | E4: 陈云 | F4: 7000
A5: 45470 | B5: 青海发投碱业有限公司 | C5: 农民工工资保证金 | D5: 内勤组 | E5: 陈云 | F5: 6950
A6: 45474 | B6: 新疆宜化化工有限公司 | C6: 投标保证金 | D6: 商务部 | E6: 周奇 | F6: 0
A7: 45492 | B7: 国家电投集团山西铝业有限公司 | C7: 投标保证金 | D7: 商务部 | E7: 周奇 | F7: 0
A8: 45497 | B8: 青海发投碱业有限公司 | C8: 投标保证金 | D8: 商务部 | E8: 周奇 | F8: 0
A9: 45499 | B9: 鞍山冀东水泥有限责任公司 | C9: 投标保证金 | D9: 商务部 | E9: 周奇 | F9: 0
A10: 42390 | B10: 亚泰集团伊通水泥有限公司 | C10: 投标保证金 | D10: (空白) | E10: 吴海波 | F10: 20000
A11: 42400 | B11: 江苏沙钢集团有限公司 | C11: 投标保证金 | D11: (空白) | E11: (空白) | F11: 10000
A12: 42887 | B12: 江苏沙钢集团有限公司 | C12: 安全保证金 | D12: (空白) | E12: (空白) | F12: 10000
A13: 43113 | B13: 永登祁连山水泥有限公司 | C13: 安全保证金 | D13: 生产部 | E13: 姜兵 | F13: 0
... A318: 44609 | B318: 山东泰山钢铁集团有限公司 | C318: 安全保证金 | D318: 生产部 | E318: 汪勇刚 | F318: 0
A319: 44615 | B319: 0 | C319: 投标保证金 | D319: (空白) | E319: 周奇 | F319: 0
A320: 44615 | B320: 山西省中条山新型建材有限公司 | C320: 投标保证金 | D320: (空白) | E320: 周奇 | F320: 0
A321: 44617 | B321: 河南省兴豫电子商务有限公司 | C321: 投标保证金 | D321: (空白) | E321: 杨江 | F321: 0
A322: 44617 | B322: 河南省豫鹤同力水泥有限公司 | C322: 标书费 | D322: 商务部 | E322: 杨江 | F322: 0
A323: 44617 | B323: 新兴铸管股份有限公司 | C323: 安全保证金 | D323: 销售部 | E323: 陈远志 | F323: 2000
A324: 44617 | B324: 云南远东水泥有限公司 | C324: 安全保证金 | D324: 生产二部 | E324: 吴结 | F324: 0
A325: 44620 | B325: 会东利森水泥有限公司 | C325: 安全保证金 | D325: 生产部 | E325: 程时勇 | F325: 0
A326: 44622 | B326: 河南晋开化工投资控股集团有限责任公司 | C326: 安全保证金 | D326: 生产部 | E326: 肖辉军 | F326: 0
A327: 44623 | B327: 重庆长寿西南水泥有限公司 | C327: 安全保证金 | D327: 生产部 | E327: 程时勇 | F327: 0
A328: 44624 | B328: 江苏磊达股份有限公司 | C328: 投标保证金 | D328: (空白) | E328: 杨江 | F328: 0
A329: 44627 | B329: 仁寿县汪洋建宝水泥有限公司广石分公司 | C329: 投标保证金 | D329: (空白) | E329: 周奇 | F329: 0
A330: 44628 | B330: 江苏磊达股份有限公司 | C330: 标书费 | D330: 商务部 | E330: 杨江 | F330: 0
A331: 44630 | B331: 鹤岗鑫塔水泥有限责任公司 | C331: 标书费 | D331: 销售部 | E331: 殷坤鹏 | F331: 0
... A861: 45716 | B861: 青海发投碱业有限公司 | C861: 投标保证金 | D861: 商务部 | E861: 周奇 | F861: 20000
A862: (空白) | B862: 东方希望重庆水泥有限公司 | C862: 投标保证金 | D862: 商务部 | E862: 周奇 | F862: 0
A863: (空白) | B863: 湖北宜化松滋肥业有限公司 | C863: 投标保证金 | D863: 商务部 | E863: 周奇 | F863: 0
A864: (空白) | B864: 淮北众城水泥有限责任公司 | C864: 投标保证金 | D864: (空白) | E864: (空白) | F864: 3000
A865: (空白) | B865: 吉林亚泰集团物资贸易有限公司 | C865: 投标保证金 | D865: (空白) | E865: (空白) | F865: 3800
A866: (空白) | B866: 江苏永钢集团物资贸易有限公司 | C866: 投标保证金 | D866: (空白) | E866: (空白) | F866: 20000
A867: (空白) | B867: 酒泉钢铁（集团）有限公司 | C867: 投标保证金 | D867: (空白) | E867: (空白) | F867: 0
A868: (空白) | B868: 三门峡腾跃同力水泥有限公司 | C868: 投标保证金 | D868: (空白) | E868: (空白) | F868: 1000
A869: (空白) | B869: 山东泰山钢铁集团有限公司 | C869: 安全保证金 | D869: 生产部 | E869: 陈云 | F869: 0
A870: (空白) | B870: 新疆宜化化工有限公司 | C870: 投标保证金 | D870: 商务部 | E870: 周奇 | F870: 0
A871: (空白) | B871: 云南西南水泥有限公司 | C871: 投标保证金 | D871: (空白) | E871: (空白) | F871: 0

Sheet Sheet5-婷
A3: 支付类型 | B3: 求和项:求和项:未退余额
A4: 安全保证金 | B4: 921725
A5: 标书费 | B5: 16568 | C5: 拿票来抵扣
A6: 履约保证金 | B6: 780430.69
A7: 农民工保证金 | B7: 6950
A8: 农民工工资保证金 | B8: 813179.37
A9: 平台服务费 | B9: 26800 | C9: 拿票来抵扣
A10: 其他 | B10: 14300
A11: 投标保证金 | B11: 681075
A12: 押金 | B12: 5000
A13: 中标服务费 | B13: 4160 | C13: 拿票来抵扣
A14: (空白)
A15: 总计 | B15: 3270188.1
A20: 质保金 | B20: 10%-5% | C20: 工程款里面

Sheet 编号对比
A1: 表格 | B1: 红圈 | C1: 表格 | D1: 红圈 | E1: 表格 | F1: 红圈 | G1: 表格 | H1: 红圈 | I1: 表格 | J1: 红圈 | K1: 表格 | L1: 红圈 | M1: 表格 | N1: 红圈 | O1: 表格
A2: BZJ-0001 | B2: 182 | C2: =_xlfn.XLOOKUP(A2,保证金登记!B:B,保证金登记!E:E) -> 0 | D2: {=_xlfn.XLOOKUP(B2,1*[2]保证金申请!$A:$A,[2]保证金申请!$C:$C)} | E2: =_xlfn.XLOOKUP(A2,保证金登记!B:B,保证金登记!I:I) -> 三门峡腾跃同力水泥有限公司 | F2: {=_xlfn.XLOOKUP(B2,1*[2]保证金申请!$A:$A,[2]保证金申请!$Q:$Q)} -> 三门峡腾跃同力水泥有限公司 | G2: =_xlfn.XLOOKUP(A2,保证金登记!B:B,保证金登记!J:J) -> 1000 | H2: {=_xlfn.XLOOKUP(B2,1*[2]保证金申请!$A:$A,[2]保证金申请!$K:$K)} -> 1000 | I2: =C2-D2 -> #VALUE! | J2: =G2-H2 -> 0 | K2: =EXACT(E2,F2) -> TRUE
A3: BZJ-0002 | B3: 183 | C3: =_xlfn.XLOOKUP(A3,保证金登记!B:B,保证金登记!E:E) -> 0 | D3: {=_xlfn.XLOOKUP(B3,1*[2]保证金申请!$A:$A,[2]保证金申请!$C:$C)} | E3: =_xlfn.XLOOKUP(A3,保证金登记!B:B,保证金登记!I:I) -> 云南西南水泥有限公司 | F3: {=_xlfn.XLOOKUP(B3,1*[2]保证金申请!$A:$A,[2]保证金申请!$Q:$Q)} -> 云南西南水泥有限公司 | G3: =_xlfn.XLOOKUP(A3,保证金登记!B:B,保证金登记!J:J) -> 50000 | H3: {=_xlfn.XLOOKUP(B3,1*[2]保证金申请!$A:$A,[2]保证金申请!$K:$K)} -> 50000 | I3: =C3-D3 -> #VALUE! | J3: =G3-H3 -> 0 | K3: =EXACT(E3,F3) -> TRUE
A4: BZJ-0003 | B4: 184 | C4: =_xlfn.XLOOKUP(A4,保证金登记!B:B,保证金登记!E:E) -> 0 | D4: {=_xlfn.XLOOKUP(B4,1*[2]保证金申请!$A:$A,[2]保证金申请!$C:$C)} | E4: =_xlfn.XLOOKUP(A4,保证金登记!B:B,保证金登记!I:I) -> 淮北众城水泥有限责任公司 | F4: {=_xlfn.XLOOKUP(B4,1*[2]保证金申请!$A:$A,[2]保证金申请!$Q:$Q)} -> 淮北众城水泥有限责任公司 | G4: =_xlfn.XLOOKUP(A4,保证金登记!B:B,保证金登记!J:J) -> 3000 | H4: {=_xlfn.XLOOKUP(B4,1*[2]保证金申请!$A:$A,[2]保证金申请!$K:$K)} -> 3000 | I4: =C4-D4 -> #VALUE! | J4: =G4-H4 -> 0 | K4: =EXACT(E4,F4) -> TRUE
A5: BZJ-0004 | B5: 186 | C5: =_xlfn.XLOOKUP(A5,保证金登记!B:B,保证金登记!E:E) -> 0 | D5: {=_xlfn.XLOOKUP(B5,1*[2]保证金申请!$A:$A,[2]保证金申请!$C:$C)} | E5: =_xlfn.XLOOKUP(A5,保证金登记!B:B,保证金登记!I:I) -> 吉林亚泰集团物资贸易有限公司 | F5: {=_xlfn.XLOOKUP(B5,1*[2]保证金申请!$A:$A,[2]保证金申请!$Q:$Q)} -> 吉林亚泰（集团）股份有限公司物资经销分公司 | G5: =_xlfn.XLOOKUP(A5,保证金登记!B:B,保证金登记!J:J) -> 3800 | H5: {=_xlfn.XLOOKUP(B5,1*[2]保证金申请!$A:$A,[2]保证金申请!$K:$K)} -> 3800 | I5: =C5-D5 -> #VALUE! | J5: =G5-H5 -> 0 | K5: =EXACT(E5,F5) -> FALSE
A6: BZJ-0005 | B6: 187 | C6: =_xlfn.XLOOKUP(A6,保证金登记!B:B,保证金登记!E:E) -> 0 | D6: {=_xlfn.XLOOKUP(B6,1*[2]保证金申请!$A:$A,[2]保证金申请!$C:$C)} | E6: =_xlfn.XLOOKUP(A6,保证金登记!B:B,保证金登记!I:I) -> 江苏永钢集团物资贸易有限公司 | F6: {=_xlfn.XLOOKUP(B6,1*[2]保证金申请!$A:$A,[2]保证金申请!$Q:$Q)} -> 江苏永钢集团物资贸易有限公司 | G6: =_xlfn.XLOOKUP(A6,保证金登记!B:B,保证金登记!J:J) -> 20000 | H6: {=_xlfn.XLOOKUP(B6,1*[2]保证金申请!$A:$A,[2]保证金申请!$K:$K)} -> 20000 | I6: =C6-D6 -> #VALUE! | J6: =G6-H6 -> 0 | K6: =EXACT(E6,F6) -> TRUE
A7: BZJ-0006 | B7: 188 | C7: =_xlfn.XLOOKUP(A7,保证金登记!B:B,保证金登记!E:E) -> 0 | D7: {=_xlfn.XLOOKUP(B7,1*[2]保证金申请!$A:$A,[2]保证金申请!$C:$C)} | E7: =_xlfn.XLOOKUP(A7,保证金登记!B:B,保证金登记!I:I) -> 酒泉钢铁（集团）有限公司 | F7: {=_xlfn.XLOOKUP(B7,1*[2]保证金申请!$A:$A,[2]保证金申请!$Q:$Q)} -> 酒泉钢铁（集团）有限公司 | G7: =_xlfn.XLOOKUP(A7,保证金登记!B:B,保证金登记!J:J) -> 300 | H7: {=_xlfn.XLOOKUP(B7,1*[2]保证金申请!$A:$A,[2]保证金申请!$K:$K)} -> 300 | I7: =C7-D7 -> #VALUE! | J7: =G7-H7 -> 0 | K7: =EXACT(E7,F7) -> TRUE
A8: BZJ-0007 | B8: 185 | C8: =_xlfn.XLOOKUP(A8,保证金登记!B:B,保证金登记!E:E) -> 42390 | D8: {=_xlfn.XLOOKUP(B8,1*[2]保证金申请!$A:$A,[2]保证金申请!$C:$C)} -> 2016-01-21 | E8: =_xlfn.XLOOKUP(A8,保证金登记!B:B,保证金登记!I:I) -> 亚泰集团伊通水泥有限公司 | F8: {=_xlfn.XLOOKUP(B8,1*[2]保证金申请!$A:$A,[2]保证金申请!$Q:$Q)} -> 亚泰伊通 | G8: =_xlfn.XLOOKUP(A8,保证金登记!B:B,保证金登记!J:J) -> 20000 | H8: {=_xlfn.XLOOKUP(B8,1*[2]保证金申请!$A:$A,[2]保证金申请!$K:$K)} -> 20000 | I8: =C8-D8 -> 0 | J8: =G8-H8 -> 0 | K8: =EXACT(E8,F8) -> FALSE
A9: BZJ-0008 | B9: 189 | C9: =_xlfn.XLOOKUP(A9,保证金登记!B:B,保证金登记!E:E) -> 42400 | D9: {=_xlfn.XLOOKUP(B9,1*[2]保证金申请!$A:$A,[2]保证金申请!$C:$C)} -> 2016-01-31 | E9: =_xlfn.XLOOKUP(A9,保证金登记!B:B,保证金登记!I:I) -> 江苏沙钢集团有限公司 | F9: {=_xlfn.XLOOKUP(B9,1*[2]保证金申请!$A:$A,[2]保证金申请!$Q:$Q)} -> 江苏沙钢集团有限公司 | G9: =_xlfn.XLOOKUP(A9,保证金登记!B:B,保证金登记!J:J) -> 10000 | H9: {=_xlfn.XLOOKUP(B9,1*[2]保证金申请!$A:$A,[2]保证金申请!$K:$K)} -> 10000 | I9: =C9-D9 -> 0 | J9: =G9-H9 -> 0 | K9: =EXACT(E9,F9) -> TRUE
A10: BZJ-0009 | B10: 1 | C10: =_xlfn.XLOOKUP(A10,保证金登记!B:B,保证金登记!E:E) -> 42887 | D10: {=_xlfn.XLOOKUP(B10,1*[2]保证金申请!$A:$A,[2]保证金申请!$C:$C)} -> 2017-06-01 | E10: =_xlfn.XLOOKUP(A10,保证金登记!B:B,保证金登记!I:I) -> 江苏沙钢集团有限公司 | F10: {=_xlfn.XLOOKUP(B10,1*[2]保证金申请!$A:$A,[2]保证金申请!$Q:$Q)} -> 江苏沙钢集团有限公司 | G10: =_xlfn.XLOOKUP(A10,保证金登记!B:B,保证金登记!J:J) -> 10000 | H10: {=_xlfn.XLOOKUP(B10,1*[2]保证金申请!$A:$A,[2]保证金申请!$K:$K)} -> 10000 | I10: =C10-D10 -> 0 | J10: =G10-H10 -> 0 | K10: =EXACT(E10,F10) -> TRUE
A11: BZJ-0010 | B11: 190 | C11: =_xlfn.XLOOKUP(A11,保证金登记!B:B,保证金登记!E:E) -> 43475 | D11: {=_xlfn.XLOOKUP(B11,1*[2]保证金申请!$A:$A,[2]保证金申请!$C:$C)} -> 2019-01-10 | E11: =_xlfn.XLOOKUP(A11,保证金登记!B:B,保证金登记!I:I) -> 江苏沙钢集团有限公司 | F11: {=_xlfn.XLOOKUP(B11,1*[2]保证金申请!$A:$A,[2]保证金申请!$Q:$Q)} -> 江苏沙钢集团有限公司 | G11: =_xlfn.XLOOKUP(A11,保证金登记!B:B,保证金登记!J:J) -> 50000 | H11: {=_xlfn.XLOOKUP(B11,1*[2]保证金申请!$A:$A,[2]保证金申请!$K:$K)} -> 50000 | I11: =C11-D11 -> 0 | J11: =G11-H11 -> 0 | K11: =EXACT(E11,F11) -> TRUE
A12: BZJ-0011 | B12: 5 | C12: =_xlfn.XLOOKUP(A12,保证金登记!B:B,保证金登记!E:E) -> 43113 | D12: {=_xlfn.XLOOKUP(B12,1*[2]保证金申请!$A:$A,[2]保证金申请!$C:$C)} -> 2018-01-13 | E12: =_xlfn.XLOOKUP(A12,保证金登记!B:B,保证金登记!I:I) -> 永登祁连山水泥有限公司 | F12: {=_xlfn.XLOOKUP(B12,1*[2]保证金申请!$A:$A,[2]保证金申请!$Q:$Q)} -> 永登祁连山水泥有限公司 | G12: =_xlfn.XLOOKUP(A12,保证金登记!B:B,保证金登记!J:J) -> 2000 | H12: {=_xlfn.XLOOKUP(B12,1*[2]保证金申请!$A:$A,[2]保证金申请!$K:$K)} -> 2000 | I12: =C12-D12 -> 0 | J12: =G12-H12 -> 0 | K12: =EXACT(E12,F12) -> TRUE
A13: BZJ-0012 | B13: 2 | C13: =_xlfn.XLOOKUP(A13,保证金登记!B:B,保证金登记!E:E) -> 43124 | D13: {=_xlfn.XLOOKUP(B13,1*[2]保证金申请!$A:$A,[2]保证金申请!$C:$C)} -> 2018-01-24 | E13: =_xlfn.XLOOKUP(A13,保证金登记!B:B,保证金登记!I:I) -> 逸盛大化石化有限公司 | F13: {=_xlfn.XLOOKUP(B13,1*[2]保证金申请!$A:$A,[2]保证金申请!$Q:$Q)} -> 逸盛大化石化有限公司 | G13: =_xlfn.XLOOKUP(A13,保证金登记!B:B,保证金登记!J:J) -> 7000 | H13: {=_xlfn.XLOOKUP(B13,1*[2]保证金申请!$A:$A,[2]保证金申请!$K:$K)} -> 7000 | I13: =C13-D13 -> 0 | J13: =G13-H13 -> 0 | K13: =EXACT(E13,F13) -> TRUE
... A506: BZJ-0655 | B506: 655 | C506: =_xlfn.XLOOKUP(A506,保证金登记!B:B,保证金登记!E:E) -> 45056 | D506: {=_xlfn.XLOOKUP(B506,1*[2]保证金申请!$A:$A,[2]保证金申请!$C:$C)} -> 2023-05-10 | E506: =_xlfn.XLOOKUP(A506,保证金登记!B:B,保证金登记!I:I) -> 青海发投碱业有限公司 | F506: {=_xlfn.XLOOKUP(B506,1*[2]保证金申请!$A:$A,[2]保证金申请!$Q:$Q)} -> 青海发投碱业有限公司 | G506: =_xlfn.XLOOKUP(A506,保证金登记!B:B,保证金登记!J:J) -> 7800 | H506: {=_xlfn.XLOOKUP(B506,1*[2]保证金申请!$A:$A,[2]保证金申请!$K:$K)} -> 7800 | I506: =C506-D506 -> 0 | J506: =G506-H506 -> 0 | K506: =EXACT(E506,F506) -> TRUE
A507: 657 | B507: 657 | C507: =_xlfn.XLOOKUP(A507,保证金登记!B:B,保证金登记!E:E) -> 45058 | D507: {=_xlfn.XLOOKUP(B507,1*[2]保证金申请!$A:$A,[2]保证金申请!$C:$C)} -> 2023-05-12 | E507: =_xlfn.XLOOKUP(A507,保证金登记!B:B,保证金登记!I:I) -> 新疆八一钢铁股份有限公司 | F507: {=_xlfn.XLOOKUP(B507,1*[2]保证金申请!$A:$A,[2]保证金申请!$Q:$Q)} -> 新疆八一钢铁股份有限公司 | G507: =_xlfn.XLOOKUP(A507,保证金登记!B:B,保证金登记!J:J) -> 32300 | H507: {=_xlfn.XLOOKUP(B507,1*[2]保证金申请!$A:$A,[2]保证金申请!$K:$K)} -> 32300 | I507: =C507-D507 -> 0 | J507: =G507-H507 -> 0 | K507: =EXACT(E507,F507) -> TRUE
A508: BZJ-0658 | B508: 658 | C508: =_xlfn.XLOOKUP(A508,保证金登记!B:B,保证金登记!E:E) -> 45058 | D508: {=_xlfn.XLOOKUP(B508,1*[2]保证金申请!$A:$A,[2]保证金申请!$C:$C)} -> 2023-05-12 | E508: =_xlfn.XLOOKUP(A508,保证金登记!B:B,保证金登记!I:I) -> 新洋丰农业科技股份有限公司 | F508: {=_xlfn.XLOOKUP(B508,1*[2]保证金申请!$A:$A,[2]保证金申请!$Q:$Q)} -> 新洋丰农业科技股份有限公司 | G508: =_xlfn.XLOOKUP(A508,保证金登记!B:B,保证金登记!J:J) -> 2000 | H508: {=_xlfn.XLOOKUP(B508,1*[2]保证金申请!$A:$A,[2]保证金申请!$K:$K)} -> 2000 | I508: =C508-D508 -> 0 | J508: =G508-H508 -> 0 | K508: =EXACT(E508,F508) -> TRUE
A509: BZJ-0659 | B509: 659 | C509: =_xlfn.XLOOKUP(A509,保证金登记!B:B,保证金登记!E:E) -> 45062 | D509: {=_xlfn.XLOOKUP(B509,1*[2]保证金申请!$A:$A,[2]保证金申请!$C:$C)} -> 2023-05-16 | E509: =_xlfn.XLOOKUP(A509,保证金登记!B:B,保证金登记!I:I) -> 黑龙江建龙钢铁有限公司 | F509: {=_xlfn.XLOOKUP(B509,1*[2]保证金申请!$A:$A,[2]保证金申请!$Q:$Q)} -> 黑龙江建龙钢铁有限公司 | G509: =_xlfn.XLOOKUP(A509,保证金登记!B:B,保证金登记!J:J) -> 20000 | H509: {=_xlfn.XLOOKUP(B509,1*[2]保证金申请!$A:$A,[2]保证金申请!$K:$K)} -> 20000 | I509: =C509-D509 -> 0 | J509: =G509-H509 -> 0 | K509: =EXACT(E509,F509) -> TRUE
A510: BZJ-0669 | B510: BZJSQ-20230614-0699 | C510: =_xlfn.XLOOKUP(A510,保证金登记!B:B,保证金登记!E:E) -> 45092 | D510: =_xlfn.XLOOKUP(B510,[2]保证金申请!$A:$A,[2]保证金申请!$C:$C) -> 2023-06-14 | E510: =_xlfn.XLOOKUP(A510,保证金登记!B:B,保证金登记!I:I) -> 鞍山冀东水泥有限责任公司 | F510: =_xlfn.XLOOKUP(B510,[2]保证金申请!$A:$A,[2]保证金申请!$Q:$Q) -> 鞍山冀东水泥有限责任公司 | G510: =_xlfn.XLOOKUP(A510,保证金登记!B:B,保证金登记!J:J) -> 1000 | H510: =_xlfn.XLOOKUP(B510,[2]保证金申请!$A:$A,[2]保证金申请!$K:$K) -> 1000 | I510: =C510-D510 -> 1 | J510: =G510-H510 -> 0 | K510: =EXACT(E510,F510) -> TRUE
A511: BZJ-0674 | B511: BZJSQ-20230620-0706 | C511: =_xlfn.XLOOKUP(A511,保证金登记!B:B,保证金登记!E:E) -> 45098 | D511: =_xlfn.XLOOKUP(B511,[2]保证金申请!$A:$A,[2]保证金申请!$C:$C) -> 2023-06-20 | E511: =_xlfn.XLOOKUP(A511,保证金登记!B:B,保证金登记!I:I) -> 叶城天山水泥有限责任公司 | F511: =_xlfn.XLOOKUP(B511,[2]保证金申请!$A:$A,[2]保证金申请!$Q:$Q) | G511: =_xlfn.XLOOKUP(A511,保证金登记!B:B,保证金登记!J:J) -> 10000 | H511: =_xlfn.XLOOKUP(B511,[2]保证金申请!$A:$A,[2]保证金申请!$K:$K) -> 10000 | I511: =C511-D511 -> 1 | J511: =G511-H511 -> 0 | K511: =EXACT(E511,F511) -> FALSE
A512: BZJ-0682 | B512: BZJSQ-20230707-0716 | C512: =_xlfn.XLOOKUP(A512,保证金登记!B:B,保证金登记!E:E) -> 45114 | D512: =_xlfn.XLOOKUP(B512,[2]保证金申请!$A:$A,[2]保证金申请!$C:$C) -> 2023-07-07 | E512: =_xlfn.XLOOKUP(A512,保证金登记!B:B,保证金登记!I:I) -> 天瑞集团汝州水泥有限公司 | F512: =_xlfn.XLOOKUP(B512,[2]保证金申请!$A:$A,[2]保证金申请!$Q:$Q) | G512: =_xlfn.XLOOKUP(A512,保证金登记!B:B,保证金登记!J:J) -> 5000 | H512: =_xlfn.XLOOKUP(B512,[2]保证金申请!$A:$A,[2]保证金申请!$K:$K) -> 5000 | I512: =C512-D512 -> 0 | J512: =G512-H512 -> 0 | K512: =EXACT(E512,F512) -> FALSE
A513: BZJ-0685 | B513: BZJSQ-20230705-0714 | C513: =_xlfn.XLOOKUP(A513,保证金登记!B:B,保证金登记!E:E) -> 45126 | D513: =_xlfn.XLOOKUP(B513,[2]保证金申请!$A:$A,[2]保证金申请!$C:$C) -> 2023-07-05 | E513: =_xlfn.XLOOKUP(A513,保证金登记!B:B,保证金登记!I:I) -> 临沂中联水泥有限公司 | F513: =_xlfn.XLOOKUP(B513,[2]保证金申请!$A:$A,[2]保证金申请!$Q:$Q) -> 临沂中联水泥有限公司 | G513: =_xlfn.XLOOKUP(A513,保证金登记!B:B,保证金登记!J:J) -> 1000 | H513: =_xlfn.XLOOKUP(B513,[2]保证金申请!$A:$A,[2]保证金申请!$K:$K) -> 1000 | I513: =C513-D513 -> 14 | J513: =G513-H513 -> 0 | K513: =EXACT(E513,F513) -> TRUE
A514: BZJ-0691 | B514: BZJSQ-20230804-0725 | C514: =_xlfn.XLOOKUP(A514,保证金登记!B:B,保证金登记!E:E) -> 45145 | D514: =_xlfn.XLOOKUP(B514,[2]保证金申请!$A:$A,[2]保证金申请!$C:$C) -> 2023-08-04 | E514: =_xlfn.XLOOKUP(A514,保证金登记!B:B,保证金登记!I:I) -> 包头冀东水泥有限公司 | F514: =_xlfn.XLOOKUP(B514,[2]保证金申请!$A:$A,[2]保证金申请!$Q:$Q) -> 包头冀东水泥有限公司 | G514: =_xlfn.XLOOKUP(A514,保证金登记!B:B,保证金登记!J:J) -> 4000 | H514: =_xlfn.XLOOKUP(B514,[2]保证金申请!$A:$A,[2]保证金申请!$K:$K) -> 4000 | I514: =C514-D514 -> 3 | J514: =G514-H514 -> 0 | K514: =EXACT(E514,F514) -> TRUE
A515: BZJ-0693 | B515: BZJSQ-20230815-0729 | C515: =_xlfn.XLOOKUP(A515,保证金登记!B:B,保证金登记!E:E) -> 45153 | D515: =_xlfn.XLOOKUP(B515,[2]保证金申请!$A:$A,[2]保证金申请!$C:$C) -> 2023-08-15 | E515: =_xlfn.XLOOKUP(A515,保证金登记!B:B,保证金登记!I:I) -> 青海发投碱业有限公司 | F515: =_xlfn.XLOOKUP(B515,[2]保证金申请!$A:$A,[2]保证金申请!$Q:$Q) -> 青海发投碱业有限公司 | G515: =_xlfn.XLOOKUP(A515,保证金登记!B:B,保证金登记!J:J) -> 14000 | H515: =_xlfn.XLOOKUP(B515,[2]保证金申请!$A:$A,[2]保证金申请!$K:$K) -> 14000 | I515: =C515-D515 -> 0 | J515: =G515-H515 -> 0 | K515: =EXACT(E515,F515) -> TRUE
A516: BZJ-0704 | B516: BZJSQ-20230912-0738 | C516: =_xlfn.XLOOKUP(A516,保证金登记!B:B,保证金登记!E:E) -> 45186 | D516: =_xlfn.XLOOKUP(B516,[2]保证金申请!$A:$A,[2]保证金申请!$C:$C) -> 2023-09-17 | E516: =_xlfn.XLOOKUP(A516,保证金登记!B:B,保证金登记!I:I) -> 内蒙古晟雄科技有限责任公司 | F516: =_xlfn.XLOOKUP(B516,[2]保证金申请!$A:$A,[2]保证金申请!$Q:$Q) -> 内蒙古晟雄科技有限责任公司 | G516: =_xlfn.XLOOKUP(A516,保证金登记!B:B,保证金登记!J:J) -> 4000 | H516: =_xlfn.XLOOKUP(B516,[2]保证金申请!$A:$A,[2]保证金申请!$K:$K) -> 4000 | I516: =C516-D516 -> 0 | J516: =G516-H516 -> 0 | K516: =EXACT(E516,F516) -> TRUE
A517: BZJ-0706 | B517: BZJSQ-20230809-0726 | C517: =_xlfn.XLOOKUP(A517,保证金登记!B:B,保证金登记!E:E) -> 45189 | D517: =_xlfn.XLOOKUP(B517,[2]保证金申请!$A:$A,[2]保证金申请!$C:$C) -> 2023-08-09 | E517: =_xlfn.XLOOKUP(A517,保证金登记!B:B,保证金登记!I:I) -> 江西玉山万年青水泥有限公司 | F517: =_xlfn.XLOOKUP(B517,[2]保证金申请!$A:$A,[2]保证金申请!$Q:$Q) -> 江西玉山万年青水泥有限公司 | G517: =_xlfn.XLOOKUP(A517,保证金登记!B:B,保证金登记!J:J) -> 10000 | H517: =_xlfn.XLOOKUP(B517,[2]保证金申请!$A:$A,[2]保证金申请!$K:$K) -> 10000 | I517: =C517-D517 -> 42 | J517: =G517-H517 -> 0 | K517: =EXACT(E517,F517) -> TRUE
A518: BZJ-0709 | B518: BZJSQ-20230925-0742 | C518: =_xlfn.XLOOKUP(A518,保证金登记!B:B,保证金登记!E:E) -> 45194 | D518: =_xlfn.XLOOKUP(B518,[2]保证金申请!$A:$A,[2]保证金申请!$C:$C) -> 2023-09-25 | E518: =_xlfn.XLOOKUP(A518,保证金登记!B:B,保证金登记!I:I) -> 青海发投碱业有限公司 | F518: =_xlfn.XLOOKUP(B518,[2]保证金申请!$A:$A,[2]保证金申请!$Q:$Q) -> 青海发投碱业有限公司 | G518: =_xlfn.XLOOKUP(A518,保证金登记!B:B,保证金登记!J:J) -> 70000 | H518: =_xlfn.XLOOKUP(B518,[2]保证金申请!$A:$A,[2]保证金申请!$K:$K) -> 70000 | I518: =C518-D518 -> 0 | J518: =G518-H518 -> 0 | K518: =EXACT(E518,F518) -> TRUE
A519: BZJ-0713 | B519: BZJSQ-20231012-0746 | C519: =_xlfn.XLOOKUP(A519,保证金登记!B:B,保证金登记!E:E) -> 45211 | D519: =_xlfn.XLOOKUP(B519,[2]保证金申请!$A:$A,[2]保证金申请!$C:$C) -> 2023-10-12 | E519: =_xlfn.XLOOKUP(A519,保证金登记!B:B,保证金登记!I:I) -> 江苏徐州中联水泥有限公司 | F519: =_xlfn.XLOOKUP(B519,[2]保证金申请!$A:$A,[2]保证金申请!$Q:$Q) -> 徐州中联水泥有限公司 | G519: =_xlfn.XLOOKUP(A519,保证金登记!B:B,保证金登记!J:J) -> 10000 | H519: =_xlfn.XLOOKUP(B519,[2]保证金申请!$A:$A,[2]保证金申请!$K:$K) -> 10000 | I519: =C519-D519 -> 0 | J519: =G519-H519 -> 0 | K519: =EXACT(E519,F519) -> FALSE
A520: BZJ-0715 | B520: BZJSQ-20231016-0747 | C520: =_xlfn.XLOOKUP(A520,保证金登记!B:B,保证金登记!E:E) -> 45217 | D520: =_xlfn.XLOOKUP(B520,[2]保证金申请!$A:$A,[2]保证金申请!$C:$C) -> 2023-10-16 | E520: =_xlfn.XLOOKUP(A520,保证金登记!B:B,保证金登记!I:I) -> 徐州中联水泥有限公司 | F520: =_xlfn.XLOOKUP(B520,[2]保证金申请!$A:$A,[2]保证金申请!$Q:$Q) -> 徐州中联水泥有限公司 | G520: =_xlfn.XLOOKUP(A520,保证金登记!B:B,保证金登记!J:J) -> 10000 | H520: =_xlfn.XLOOKUP(B520,[2]保证金申请!$A:$A,[2]保证金申请!$K:$K) -> 10000 | I520: =C520-D520 -> 2 | J520: =G520-H520 -> 0 | K520: =EXACT(E520,F520) -> TRUE
A521: BZJ-0719 | B521: BZJSQ-20231107-0753 | C521: =_xlfn.XLOOKUP(A521,保证金登记!B:B,保证金登记!E:E) -> 45238 | D521: =_xlfn.XLOOKUP(B521,[2]保证金申请!$A:$A,[2]保证金申请!$C:$C) -> 2023-11-07 | E521: =_xlfn.XLOOKUP(A521,保证金登记!B:B,保证金登记!I:I) -> 山西强伟纸业有限公司 | F521: =_xlfn.XLOOKUP(B521,[2]保证金申请!$A:$A,[2]保证金申请!$Q:$Q) -> 山西强伟纸业有限公司 | G521: =_xlfn.XLOOKUP(A521,保证金登记!B:B,保证金登记!J:J) -> 5000 | H521: =_xlfn.XLOOKUP(B521,[2]保证金申请!$A:$A,[2]保证金申请!$K:$K) -> 5000 | I521: =C521-D521 -> 1 | J521: =G521-H521 -> 0 | K521: =EXACT(E521,F521) -> TRUE
... A539: BZJSQ-20240130-0027 | B539: BZJSQ-20240204-0027 | C539: =_xlfn.XLOOKUP(A539,保证金登记!B:B,保证金登记!E:E) -> 45327 | D539: =_xlfn.XLOOKUP(B539,[2]保证金申请!$A:$A,[2]保证金申请!$C:$C) -> 2024-02-04 | E539: =_xlfn.XLOOKUP(A539,保证金登记!B:B,保证金登记!I:I) -> 青海发投碱业有限公司（周琦转河南祥光） | F539: =_xlfn.XLOOKUP(B539,[2]保证金申请!$A:$A,[2]保证金申请!$Q:$Q) | G539: =_xlfn.XLOOKUP(A539,保证金登记!B:B,保证金登记!J:J) -> 20000 | H539: =_xlfn.XLOOKUP(B539,[2]保证金申请!$A:$A,[2]保证金申请!$K:$K) -> 20000 | I539: =C539-D539 -> 1 | J539: =G539-H539 -> 0 | K539: =EXACT(E539,F539) -> FALSE
A540: 212 | B540: 212 | C540: =_xlfn.XLOOKUP(A540,保证金登记!B:B,保证金登记!E:E) -> 44216 | D540: =_xlfn.XLOOKUP(B540,[2]保证金申请!$A:$A,[2]保证金申请!$C:$C) -> 2021-01-20 | E540: =_xlfn.XLOOKUP(A540,保证金登记!B:B,保证金登记!I:I) -> 内蒙古鄂尔多斯电力冶金集团股份有限公司资源综合利用分公司 | F540: =_xlfn.XLOOKUP(B540,[2]保证金申请!$A:$A,[2]保证金申请!$Q:$Q) -> 内蒙古鄂尔多斯电力冶金集团股份有限公司 | G540: =_xlfn.XLOOKUP(A540,保证金登记!B:B,保证金登记!J:J) -> 5000 | H540: =_xlfn.XLOOKUP(B540,[2]保证金申请!$A:$A,[2]保证金申请!$K:$K) -> 5000 | I540: =C540-D540 -> 0 | J540: =G540-H540 -> 0 | K540: =EXACT(E540,F540) -> FALSE
A541: BZJSQ-20231221-0785 | B541: BZJSQ-20231221-0785 | C541: =_xlfn.XLOOKUP(A541,保证金登记!B:B,保证金登记!E:E) -> 45282 | D541: =_xlfn.XLOOKUP(B541,[2]保证金申请!$A:$A,[2]保证金申请!$C:$C) -> 2023-12-21 | E541: =_xlfn.XLOOKUP(A541,保证金登记!B:B,保证金登记!I:I) -> 新疆伊犁钢铁有限责任公司 | F541: =_xlfn.XLOOKUP(B541,[2]保证金申请!$A:$A,[2]保证金申请!$Q:$Q) | G541: =_xlfn.XLOOKUP(A541,保证金登记!B:B,保证金登记!J:J) -> 39390 | H541: =_xlfn.XLOOKUP(B541,[2]保证金申请!$A:$A,[2]保证金申请!$K:$K) -> 39390 | I541: =C541-D541 -> 1 | J541: =G541-H541 -> 0 | K541: =EXACT(E541,F541) -> FALSE
A542: BZJSQ-20231222-0786 | B542: BZJSQ-20231222-0786 | C542: =_xlfn.XLOOKUP(A542,保证金登记!B:B,保证金登记!E:E) -> 45282 | D542: =_xlfn.XLOOKUP(B542,[2]保证金申请!$A:$A,[2]保证金申请!$C:$C) -> 2023-12-22 | E542: =_xlfn.XLOOKUP(A542,保证金登记!B:B,保证金登记!I:I) -> 青海发投碱业有限公司 | F542: =_xlfn.XLOOKUP(B542,[2]保证金申请!$A:$A,[2]保证金申请!$Q:$Q) -> 青海发投碱业有限公司 | G542: =_xlfn.XLOOKUP(A542,保证金登记!B:B,保证金登记!J:J) -> 10000 | H542: =_xlfn.XLOOKUP(B542,[2]保证金申请!$A:$A,[2]保证金申请!$K:$K) -> 10000 | I542: =C542-D542 -> 0 | J542: =G542-H542 -> 0 | K542: =EXACT(E542,F542) -> TRUE
A543: BZJSQ-20231222-0787 | B543: BZJSQ-20231222-0787 | C543: =_xlfn.XLOOKUP(A543,保证金登记!B:B,保证金登记!E:E) -> 45282 | D543: =_xlfn.XLOOKUP(B543,[2]保证金申请!$A:$A,[2]保证金申请!$C:$C) -> 2023-12-22 | E543: =_xlfn.XLOOKUP(A543,保证金登记!B:B,保证金登记!I:I) -> 青海发投碱业有限公司 | F543: =_xlfn.XLOOKUP(B543,[2]保证金申请!$A:$A,[2]保证金申请!$Q:$Q) -> 青海发投碱业有限公司 | G543: =_xlfn.XLOOKUP(A543,保证金登记!B:B,保证金登记!J:J) -> 10000 | H543: =_xlfn.XLOOKUP(B543,[2]保证金申请!$A:$A,[2]保证金申请!$K:$K) -> 10000 | I543: =C543-D543 -> 0 | J543: =G543-H543 -> 0 | K543: =EXACT(E543,F543) -> TRUE
A544: BZJSQ-20231222-0788 | B544: BZJSQ-20231222-0788 | C544: =_xlfn.XLOOKUP(A544,保证金登记!B:B,保证金登记!E:E) -> 45282 | D544: =_xlfn.XLOOKUP(B544,[2]保证金申请!$A:$A,[2]保证金申请!$C:$C) -> 2023-12-22 | E544: =_xlfn.XLOOKUP(A544,保证金登记!B:B,保证金登记!I:I) -> 青海发投碱业有限公司 | F544: =_xlfn.XLOOKUP(B544,[2]保证金申请!$A:$A,[2]保证金申请!$Q:$Q) -> 青海发投碱业有限公司 | G544: =_xlfn.XLOOKUP(A544,保证金登记!B:B,保证金登记!J:J) -> 10000 | H544: =_xlfn.XLOOKUP(B544,[2]保证金申请!$A:$A,[2]保证金申请!$K:$K) -> 10000 | I544: =C544-D544 -> 0 | J544: =G544-H544 -> 0 | K544: =EXACT(E544,F544) -> TRUE
A545: BZJSQ-20231225-0789 | B545: BZJSQ-20231225-0789 | C545: =_xlfn.XLOOKUP(A545,保证金登记!B:B,保证金登记!E:E) -> 45285 | D545: =_xlfn.XLOOKUP(B545,[2]保证金申请!$A:$A,[2]保证金申请!$C:$C) -> 2023-12-25 | E545: =_xlfn.XLOOKUP(A545,保证金登记!B:B,保证金登记!I:I) -> 青海发投碱业有限公司 | F545: =_xlfn.XLOOKUP(B545,[2]保证金申请!$A:$A,[2]保证金申请!$Q:$Q) -> 青海发投碱业有限公司 | G545: =_xlfn.XLOOKUP(A545,保证金登记!B:B,保证金登记!J:J) -> 10000 | H545: =_xlfn.XLOOKUP(B545,[2]保证金申请!$A:$A,[2]保证金申请!$K:$K) -> 10000 | I545: =C545-D545 -> 0 | J545: =G545-H545 -> 0 | K545: =EXACT(E545,F545) -> TRUE
A546: BZJSQ-20240102-0001 | B546: BZJSQ-20240102-0001 | C546: =_xlfn.XLOOKUP(A546,保证金登记!B:B,保证金登记!E:E) -> 45300 | D546: =_xlfn.XLOOKUP(B546,[2]保证金申请!$A:$A,[2]保证金申请!$C:$C) -> 2024-01-02 | E546: =_xlfn.XLOOKUP(A546,保证金登记!B:B,保证金登记!I:I) -> 青海发投碱业有限公司 | F546: =_xlfn.XLOOKUP(B546,[2]保证金申请!$A:$A,[2]保证金申请!$Q:$Q) -> 青海发投碱业有限公司 | G546: =_xlfn.XLOOKUP(A546,保证金登记!B:B,保证金登记!J:J) -> 20000 | H546: =_xlfn.XLOOKUP(B546,[2]保证金申请!$A:$A,[2]保证金申请!$K:$K) -> 20000 | I546: =C546-D546 -> 7 | J546: =G546-H546 -> 0 | K546: =EXACT(E546,F546) -> TRUE
A547: BZJSQ-20240103-0002 | B547: BZJSQ-20240103-0002 | C547: =_xlfn.XLOOKUP(A547,保证金登记!B:B,保证金登记!E:E) -> 45295 | D547: =_xlfn.XLOOKUP(B547,[2]保证金申请!$A:$A,[2]保证金申请!$C:$C) -> 2024-01-04 | E547: =_xlfn.XLOOKUP(A547,保证金登记!B:B,保证金登记!I:I) -> 青海发投碱业有限公司 | F547: =_xlfn.XLOOKUP(B547,[2]保证金申请!$A:$A,[2]保证金申请!$Q:$Q) -> 青海发投碱业有限公司 | G547: =_xlfn.XLOOKUP(A547,保证金登记!B:B,保证金登记!J:J) -> 27999 | H547: =_xlfn.XLOOKUP(B547,[2]保证金申请!$A:$A,[2]保证金申请!$K:$K) -> 27999 | I547: =C547-D547 -> 0 | J547: =G547-H547 -> 0 | K547: =EXACT(E547,F547) -> TRUE
A548: BZJSQ-20240105-0003 | B548: BZJSQ-20240105-0003 | C548: =_xlfn.XLOOKUP(A548,保证金登记!B:B,保证金登记!E:E) -> 45296 | D548: =_xlfn.XLOOKUP(B548,[2]保证金申请!$A:$A,[2]保证金申请!$C:$C) -> 2024-01-05 | E548: =_xlfn.XLOOKUP(A548,保证金登记!B:B,保证金登记!I:I) -> 青海发投碱业有限公司 | F548: =_xlfn.XLOOKUP(B548,[2]保证金申请!$A:$A,[2]保证金申请!$Q:$Q) -> 青海发投碱业有限公司 | G548: =_xlfn.XLOOKUP(A548,保证金登记!B:B,保证金登记!J:J) -> 27999 | H548: =_xlfn.XLOOKUP(B548,[2]保证金申请!$A:$A,[2]保证金申请!$K:$K) -> 27999 | I548: =C548-D548 -> 0 | J548: =G548-H548 -> 0 | K548: =EXACT(E548,F548) -> TRUE
A549: BZJSQ-20240108-0004 | B549: BZJSQ-20240108-0004 | C549: =_xlfn.XLOOKUP(A549,保证金登记!B:B,保证金登记!E:E) -> 45299 | D549: =_xlfn.XLOOKUP(B549,[2]保证金申请!$A:$A,[2]保证金申请!$C:$C) -> 2024-01-08 | E549: =_xlfn.XLOOKUP(A549,保证金登记!B:B,保证金登记!I:I) -> 青海发投碱业有限公司 | F549: =_xlfn.XLOOKUP(B549,[2]保证金申请!$A:$A,[2]保证金申请!$Q:$Q) -> 青海发投碱业有限公司 | G549: =_xlfn.XLOOKUP(A549,保证金登记!B:B,保证金登记!J:J) -> 28000 | H549: =_xlfn.XLOOKUP(B549,[2]保证金申请!$A:$A,[2]保证金申请!$K:$K) -> 28000 | I549: =C549-D549 -> 0 | J549: =G549-H549 -> 0 | K549: =EXACT(E549,F549) -> TRUE
A550: BZJSQ-20240109-0005 | B550: BZJSQ-20240109-0005 | C550: =_xlfn.XLOOKUP(A550,保证金登记!B:B,保证金登记!E:E) -> 0 | D550: =_xlfn.XLOOKUP(B550,[2]保证金申请!$A:$A,[2]保证金申请!$C:$C) -> 2024-01-09 | E550: =_xlfn.XLOOKUP(A550,保证金登记!B:B,保证金登记!I:I) -> 东方希望重庆水泥有限公司 | F550: =_xlfn.XLOOKUP(B550,[2]保证金申请!$A:$A,[2]保证金申请!$Q:$Q) -> 东方希望重庆水泥有限公司 | G550: =_xlfn.XLOOKUP(A550,保证金登记!B:B,保证金登记!J:J) -> 0 | H550: =_xlfn.XLOOKUP(B550,[2]保证金申请!$A:$A,[2]保证金申请!$K:$K) -> 0 | I550: =C550-D550 -> -45300 | J550: =G550-H550 -> 0 | K550: =EXACT(E550,F550) -> TRUE
A551: BZJSQ-20240109-0006 | B551: BZJSQ-20240109-0006 | C551: =_xlfn.XLOOKUP(A551,保证金登记!B:B,保证金登记!E:E) -> 45302 | D551: =_xlfn.XLOOKUP(B551,[2]保证金申请!$A:$A,[2]保证金申请!$C:$C) -> 2024-01-09 | E551: =_xlfn.XLOOKUP(A551,保证金登记!B:B,保证金登记!I:I) -> 日钢营口中板有限公司 | F551: =_xlfn.XLOOKUP(B551,[2]保证金申请!$A:$A,[2]保证金申请!$Q:$Q) -> 日钢营口中板有限公司 | G551: =_xlfn.XLOOKUP(A551,保证金登记!B:B,保证金登记!J:J) -> 30000 | H551: =_xlfn.XLOOKUP(B551,[2]保证金申请!$A:$A,[2]保证金申请!$K:$K) -> 30000 | I551: =C551-D551 -> 2 | J551: =G551-H551 -> 0 | K551: =EXACT(E551,F551) -> TRUE
A552: BZJSQ-20240109-0007 | B552: BZJSQ-20240109-0007 | C552: =_xlfn.XLOOKUP(A552,保证金登记!B:B,保证金登记!E:E) -> 45300 | D552: =_xlfn.XLOOKUP(B552,[2]保证金申请!$A:$A,[2]保证金申请!$C:$C) -> 2024-01-09 | E552: =_xlfn.XLOOKUP(A552,保证金登记!B:B,保证金登记!I:I) -> 青海发投碱业有限公司 | F552: =_xlfn.XLOOKUP(B552,[2]保证金申请!$A:$A,[2]保证金申请!$Q:$Q) -> 青海发投碱业有限公司 | G552: =_xlfn.XLOOKUP(A552,保证金登记!B:B,保证金登记!J:J) -> 47850 | H552: =_xlfn.XLOOKUP(B552,[2]保证金申请!$A:$A,[2]保证金申请!$K:$K) -> 47850 | I552: =C552-D552 -> 0 | J552: =G552-H552 -> 0 | K552: =EXACT(E552,F552) -> TRUE
... A716: BZJSQ-20250319-0045 | B716: BZJSQ-20250319-0045 | C716: =_xlfn.XLOOKUP(A716,保证金登记!B:B,保证金登记!E:E) -> 45735 | D716: =_xlfn.XLOOKUP(B716,[2]保证金申请!$A:$A,[2]保证金申请!$C:$C) -> 2025-03-19 | E716: =_xlfn.XLOOKUP(A716,保证金登记!B:B,保证金登记!I:I) -> 青海发投碱业有限公司 | F716: =_xlfn.XLOOKUP(B716,[2]保证金申请!$A:$A,[2]保证金申请!$Q:$Q) -> 青海发投碱业有限公司 | G716: =_xlfn.XLOOKUP(A716,保证金登记!B:B,保证金登记!J:J) -> 17875 | H716: =_xlfn.XLOOKUP(B716,[2]保证金申请!$A:$A,[2]保证金申请!$K:$K) -> 17875 | I716: =C716-D716 -> 0 | J716: =G716-H716 -> 0 | K716: =EXACT(E716,F716) -> TRUE
A717: BZJSQ-20250321-0046 | B717: BZJSQ-20250321-0046 | C717: =_xlfn.XLOOKUP(A717,保证金登记!B:B,保证金登记!E:E) -> 45737 | D717: =_xlfn.XLOOKUP(B717,[2]保证金申请!$A:$A,[2]保证金申请!$C:$C) -> 2025-03-21 | E717: =_xlfn.XLOOKUP(A717,保证金登记!B:B,保证金登记!I:I) -> 青海发投碱业有限公司 | F717: =_xlfn.XLOOKUP(B717,[2]保证金申请!$A:$A,[2]保证金申请!$Q:$Q) -> 湖北岚丹建设工程有限公司离心机节能增效农民工工资保证金专户
A718: BZJSQ-20250322-0047 | B718: BZJSQ-20250322-0047 | C718: =_xlfn.XLOOKUP(A718,保证金登记!B:B,保证金登记!E:E) -> 45738 | D718: =_xlfn.XLOOKUP(B718,[2]保证金申请!$A:$A,[2]保证金申请!$C:$C) -> 2025-03-22 | E718: =_xlfn.XLOOKUP(A718,保证金登记!B:B,保证金登记!I:I) -> 江苏永钢集团有限公司 | F718: =_xlfn.XLOOKUP(B718,[2]保证金申请!$A:$A,[2]保证金申请!$Q:$Q) -> 江苏永钢集团有限公司
A719: BZJSQ-20250324-0048 | B719: BZJSQ-20250324-0048 | C719: =_xlfn.XLOOKUP(A719,保证金登记!B:B,保证金登记!E:E) -> 45740 | D719: =_xlfn.XLOOKUP(B719,[2]保证金申请!$A:$A,[2]保证金申请!$C:$C) -> 2025-03-24 | E719: =_xlfn.XLOOKUP(A719,保证金登记!B:B,保证金登记!I:I) -> 江苏唐电电力安装有限公司 | F719: =_xlfn.XLOOKUP(B719,[2]保证金申请!$A:$A,[2]保证金申请!$Q:$Q) -> 中机国际招标有限公司
A720: BZJSQ-20250326-0049 | B720: BZJSQ-20250326-0049 | C720: =_xlfn.XLOOKUP(A720,保证金登记!B:B,保证金登记!E:E) -> 45742 | D720: =_xlfn.XLOOKUP(B720,[2]保证金申请!$A:$A,[2]保证金申请!$C:$C) -> 2025-03-26 | E720: =_xlfn.XLOOKUP(A720,保证金登记!B:B,保证金登记!I:I) -> 江苏唐电电力安装有限公司 | F720: =_xlfn.XLOOKUP(B720,[2]保证金申请!$A:$A,[2]保证金申请!$Q:$Q) -> 江苏唐电电力安装有限公司
