Workbook

Sheet 参数
A1: 分析参数
A3: 分析截止日 | B3: 46024
A8: 口径说明
A9: 1) 开工后开票间隔：开票日期 - 开工日期（若开工日期缺失则不统计）。
A10: 2) 开票后回款间隔：开票日期到该客户“最早一笔回款日期(>=开票日)”的间隔（客户维度匹配，未按发票金额逐张销账）。
A11: 3) 客户账龄：来自【账龄明细】的未回款金额（优先“按照合同未回款”，缺失则用“按照验收未回款”），账龄基准日=开票日(有则用)否则完工日否则合同日。

Sheet 结论_应收_穿透图
A3: 账龄分析 | B3: Sum of 未回款 | C3: Count of 客户
A4: 0-30 | B4: 911000 | C4: 4
A5: 山东圣川新材料科技股份有限公司 | B5: 60000 | C5: 1
A6: 池州恒鑫材料科技有限公司 | B6: 45000 | C6: 1
A7: 青海盐湖镁业有限公司 | B7: 806000 | C7: 2
A8: 181-365 | B8: 8660299.8 | C8: 34
A9: 31-60 | B9: 4265271.2 | C9: 4
A10: 兆山集团诸暨水泥有限公司 | B10: 28000 | C10: 1
A11: 富蕴天山水泥有限责任公司 | B11: 200000 | C11: 1
A12: 广安昌兴水泥有限公司 | B12: 228900 | C12: 1
A13: 新疆宜化化工有限公司 | B13: 3808371.2 | C13: 1
A14: 365+ | B14: 18158405 | C14: 400
A15: 61-90 | B15: 1462000 | C15: 5
... A21: Grand Total | B21: 39783585 | C21: 472

Sheet 账龄桶分析明细
A1: 客户 | B1: 应收余额 | C1: 0-30 | D1: 31-60 | E1: 61-90 | F1: 91-180 | G1: 181-365 | H1: 365+ | I1: 发票数 | J1: 有开工日期发票数 | K1: 开工后开票_自然日_平均 | L1: 开票后回款_自然日_平均
A2: 新疆宜化化工有限公司 | B2: 5036771.2 | D2: 3808371.2 | F2: 1180000 | H2: 48400 | I2: 18 | L2: 95.888889
A3: 青海发投碱业有限公司 | B3: 4667646.7 | F3: 739594.4 | G3: 2735061.5 | H3: 1192990.8 | I3: 109 | L3: 39.889908
A4: 日照钢铁有限公司 | B4: 4223441 | F4: 1263546 | G4: 673605 | H4: 2286290 | I4: 24 | J4: 1 | K4: 119 | L4: 248.82353
A5: 日照京华新型建材有限公司 | B5: 2934000 | E5: 1234000 | G5: 1700000 | I5: 10 | J5: 1 | K5: 299
A6: 新疆伊犁钢铁有限责任公司 | B6: 1391271.7 | G6: 477506.16 | H6: 913765.56 | I6: 44 | J6: 7 | K6: 156.85714 | L6: 78.454545
A7: 内蒙古君正能源化工集团股份有限公司 | B7: 1285166.1 | F7: 828400 | G7: 456766.11
A8: 内蒙古宜化化工有限公司 | B8: 1222456.8 | F8: 524456.8 | G8: 698000 | I8: 2 | L8: 18
A9: 贵州黔西中水发电有限公司 | B9: 1092150 | H9: 1092150 | I9: 8 | L9: 485
A10: 青海盐湖镁业有限公司 | B10: 925792 | C10: 806000 | H10: 119792 | I10: 9 | J10: 4 | K10: 92.5 | L10: 60
A11: 青海海西化工建材股份有限公司 | B11: 651283.2 | H11: 651283.2 | I11: 1 | L11: 455
A12: 莱芜钢铁集团银山型钢有限公司 | B12: 617999.99 | G12: 617999.99 | I12: 1
A13: 内蒙古松塔水泥有限责任公司 | B13: 580000 | H13: 580000
A14: 江西赣锋锂业集团股份有限公司（马洪分公司） | B14: 532730 | H14: 532730
A15: 富蕴天山水泥有限责任公司 | B15: 520000 | D15: 200000 | H15: 320000 | I15: 9 | L15: 216.22222
A16: 湖北京兰水泥集团有限公司（钱场分公司） | B16: 475848.19 | H16: 475848.19
A17: 安钢集团信阳钢铁有限责任公司 | B17: 390784.45 | H17: 390784.45 | I17: 4 | L17: 157.5
A18: 尼勒克县瑞祥焦化有限责任公司（属伊伊犁钢铁分公司） | B18: 374223.11 | H18: 374223.11
A19: 阜阳皖润电力有限公司 | B19: 354600 | F19: 354600 | I19: 1 | L19: 18
A20: 江西亚东水泥有限公司 | B20: 313725.2 | E20: 120000 | H20: 193725.2 | I20: 27 | J20: 4 | K20: 41 | L20: 127.03704
A21: 四川川威集团成渝钒钛科技有限公司 | B21: 305200 | F21: 305200
A22: 山东泰山钢铁集团有限公司 | B22: 300000 | H22: 300000 | I22: 1
A23: 逸盛大化石化有限公司 | B23: 297850 | H23: 297850
A24: 唐山中厚板材有限公司 | B24: 293800 | H24: 293800
A25: 新兴铸管股份有限公司 | B25: 292000 | G25: 292000
A26: 池州恒鑫材料科技有限公司 | B26: 259200 | C26: 45000 | F26: 214200
A27: 新洋丰农业科技股份有限公司 | B27: 245200 | F27: 175000 | G27: 70000 | H27: 200 | I27: 1 | L27: 458
A28: 华润水泥（永定）有限公司 | B28: 239693 | H28: 239693 | I28: 2
A29: 联峰钢铁（张家港）有限公司（江苏永钢） | B29: 230601 | G29: 190001 | H29: 40600 | I29: 1 | J29: 1 | K29: 169
A30: 江苏永钢集团物资贸易有限公司 | B30: 230000 | G30: 230000
A31: 广安昌兴水泥有限公司 | B31: 228900 | D31: 228900 | I31: 1 | L31: 45
A32: 包头冀东水泥有限公司 | B32: 214501.77 | H32: 214501.77 | I32: 28 | J32: 1 | K32: 104 | L32: 213.46429
A33: 贵州金久水泥有限公司 | B33: 201263.29 | H33: 201263.29
A34: 湖南金山环保建材有限公司 | B34: 199757.85 | H34: 199757.85 | I34: 2 | J34: 1 | K34: 75 | L34: 289
A35: 河源市金杰环保建材有限公司 | B35: 196213.49 | H35: 196213.49
A36: 江西玉山万年青水泥有限公司 | B36: 195000 | F36: 195000 | I36: 7 | J36: 2 | K36: 139 | L36: 109
A37: 河钢股份有限公司邯郸分公司 | B37: 194330 | H37: 194330 | I37: 1 | L37: 335
A38: 宁都县赣锋锂业有限公司 | B38: 188000 | H38: 188000 | I38: 1
A39: 湖南韶峰南方水泥有限公司 | B39: 172800 | H39: 172800
A40: 芜湖新兴铸管有限责任公司 | B40: 170600 | F40: 155000 | H40: 15600 | I40: 2 | L40: 309.5
A41: 天瑞集团汝州水泥有限公司 | B41: 163673.95 | G41: 48000 | H41: 115673.95 | I41: 5 | L41: 336
A42: 铜陵上峰水泥股份有限公司 | B42: 160538.28 | H42: 160538.28 | I42: 5 | J42: 4 | K42: 245.75 | L42: 625
A43: 兆山集团诸暨水泥有限公司 | B43: 157100 | D43: 28000 | F43: 120000 | H43: 9100 | I43: 16 | J43: 1 | K43: 99 | L43: 83.8125
A44: 山西恒达能源集团有限公司 | B44: 155196 | H44: 155196
A45: 中材安徽水泥有限公司 | B45: 154767.6 | H45: 154767.6
A46: 四川省广安腾飞华峰水泥有限公司（合同签定：广安腾飞集团有限公司） | B46: 152125 | H46: 152125
A47: 甘肃永固特种水泥有限公司 | B47: 145939 | H47: 145939
A48: 信阳豫信轧钢实业有限公司(安钢集团信阳钢铁) | B48: 144800 | H48: 144800
A49: 福建青拓实业有限公司(合同签订单位：福建鼎信实业有限公司） | B49: 142103.2 | F49: 40000 | H49: 102103.2 | I49: 11 | J49: 2 | K49: 60.5 | L49: 166.85714
A50: 东方希望重庆水泥有限公司 | B50: 140320 | F50: 60260 | G50: 14200 | H50: 65860 | I50: 16 | J50: 5 | K50: 308.8 | L50: 195.125
A51: 宿州泉兴相山水泥有限公司 | B51: 137376 | H51: 137376
A52: 张家港市联泰科技有限公司（江苏永钢） | B52: 130000 | H52: 130000
A53: 中盐内蒙古建材有限公司 | B53: 128000 | G53: 128000 | I53: 1 | L53: 47
A54: 湖南骏泰新材料科技有限责任公司 | B54: 120000 | H54: 120000 | I54: 2 | L54: 337
A55: 焦作坚固水泥有限公司 | B55: 120000 | H55: 120000 | I55: 2 | J55: 1 | K55: 274
A56: 辽宁银盛水泥集团有限公司 | B56: 120000 | G56: 120000
A57: 宜州广驰水泥有限责任公司 | B57: 117570 | H57: 117570 | I57: 1
A58: 洛阳黄河同力水泥有限责任公司 | B58: 111586.6 | H58: 111586.6 | I58: 8 | J58: 1 | K58: 134 | L58: 352.875
A59: 玉溪新平永发新型建材有限公司（元江县永发水泥有限公司） | B59: 109186.98 | H59: 109186.98
A60: 四川泸定山盛水泥有限公司 | B60: 100000 | H60: 100000
A61: 锦州三鸽水泥制造有限公司 | B61: 100000 | H61: 100000
A62: 甘肃三易水泥有限责任公司 | B62: 97621 | H62: 97621
A63: 湖北双环科技股份有限公司 | B63: 96658.73 | E63: 96000 | F63: 658.73 | I63: 7 | J63: 1 | K63: 31 | L63: 357.71429
A64: 彭水县茂田能源开发有限公司 | B64: 94500 | H64: 94500
A65: 华润水泥（上思）有限公司 | B65: 92000 | H65: 92000
A66: 贵州水晶有机化工（集团）有限公司苗岭建材分公司 | B66: 89000 | H66: 89000
A67: 绥江县永固水泥有限责任公司 | B67: 86540 | H67: 86540
A68: 萍乡萍钢安源钢铁有限公司 | B68: 86000 | G68: 86000 | I68: 1 | L68: 64
A69: 拉法基瑞安（红河）水泥有限公司（云南国资水泥红河有限公司）变更华新水泥（红河）有限公司 | B69: 85000 | H69: 85000
A70: 山西强伟纸业有限公司 | B70: 84000 | H70: 84000
A71: 海南逸盛石化有限公司 | B71: 76600 | H71: 76600 | I71: 9 | J71: 3 | K71: 74 | L71: 410.33333
A72: 山东泰西水泥有限公司 | B72: 75573 | H72: 75573 | I72: 3 | J72: 2 | K72: 38 | L72: 230
A73: 河南省安阳湖波水泥有限责任公司 | B73: 73800 | H73: 73800
A74: 湖南张家界南方水泥有限公司 | B74: 73530 | H74: 73530 | I74: 2 | J74: 1 | K74: 208 | L74: 457
A75: 河源市金杰环保建材有限公司（合同签订单位：河南阿尔法工程材料有限公司） | B75: 72000 | H75: 72000
A76: 登电集团水泥有限公司 | B76: 71916 | H76: 71916
A77: 重庆九鑫水泥（集团）有限公司 | B77: 70865 | H77: 70865 | I77: 3 | J77: 1 | K77: 43
A78: 北京金隅琉水环保科技有限公司 | B78: 70800 | H78: 70800 | I78: 3 | J78: 1 | K78: 115 | L78: 424
A79: 内蒙古兴发科技有限公司 | B79: 70000 | F79: 70000
A80: 青海盐湖海纳化工有限公司 | B80: 70000 | H80: 70000
A81: 昭通昆钢嘉华水泥建材有限公司 | B81: 69800 | H81: 69800
A82: 四川峨胜水泥集团股份有限公司 | B82: 65260 | G82: 17260 | H82: 48000 | I82: 18 | J82: 5 | K82: 98.4 | L82: 212.77778
A83: 酒钢（集团）宏达建材有限责任公司（更名：嘉峪关祁连山水泥有限公司） | B83: 65156 | H83: 65156
A84: 吉林省天茂特种水泥有限公司 | B84: 64765 | H84: 64765
A85: 河南华润电力首阳山有限公司 | B85: 63000 | G85: 63000 | I85: 2 | J85: 1 | K85: 62 | L85: 19
A86: 甘肃京兰水泥有限公司 | B86: 62272.81 | H86: 62272.81
A87: 华新水泥重庆涪陵有限公司 | B87: 62000 | H87: 62000
A88: 葛洲坝石门特种水泥有限公司 | B88: 61750 | H88: 61750 | I88: 2 | L88: 486
A89: 成县祁连山水泥有限公司 | B89: 60000 | H89: 60000 | I89: 9 | J89: 3 | K89: 95.666667 | L89: 195.33333
A90: 山东圣川新材料科技股份有限公司 | B90: 60000 | C90: 60000 | I90: 6 | J90: 3 | K90: 25.333333 | L90: 530.66667
A91: 河南隆鑫水泥有限责任公司 | B91: 60000 | H91: 60000
A92: 青海众信建筑安装有限公司 | B92: 60000 | H92: 60000
A93: 内乡县万基水泥有限公司 | B93: 58000 | H93: 58000
A94: 朝阳兰凌水泥有限公司 | B94: 57700 | H94: 57700
A95: 河北承大建材有限公司 | B95: 55000 | H95: 55000
A96: 喀什红旗水泥有限责任公司 | B96: 50000 | H96: 50000 | I96: 1 | L96: 113
A97: 白山山水水泥有限责任公司（合同签订单位：山东昌运机械有限公司） | B97: 50000 | H97: 50000
A98: 黄石成美建材有限公司 | B98: 48000 | H98: 48000 | I98: 1
A99: 大同市云中水泥有限责任公司 | B99: 45500 | F99: 45500 | I99: 2 | L99: 9.5
A100: 河南锦荣水泥有限公司 | B100: 43000 | H100: 43000
...

Sheet 明细_开票
A1: 客户 | B1: 销售合同号 | C1: 公司 | D1: 开工日期 | E1: 完工日期 | F1: 开票日期 | G1: 含税合计 | H1: 金额 | I1: 税额 | J1: 首次回款日期 | K1: 工期 | L1: 完工后开票_自然日 | M1: 开票后回款_自然日 | N1: 异常标记
A2: 华润水泥（永定）有限公司 | B2: KMX200807-180-XF | C2: 武汉 | F2: 44931 | G2: 23693 | H2: 20967.26 | I2: 2725.74 | K2: =IF(OR($D2="", $F2=""),"", $E2-$D2) | L2: =IF(OR($D2="", $F2=""),"", $F2-$E2) | M2: =IF(OR($F2="", $J2=""),"", $J2-$F2) | N2: 无回款匹配
A3: 北京堂海科技有限公司 | B3: KMX221228-450-XF | C3: 武汉 | F3: 44931 | G3: 53000 | H3: 50000 | I3: 3000 | K3: =IF(OR($D3="", $F3=""),"", $E3-$D3) | L3: =IF(OR($D3="", $F3=""),"", $F3-$E3) | M3: =IF(OR($F3="", $J3=""),"", $J3-$F3) | N3: 无回款匹配
A4: 青州中联水泥有限公司 | B4: KMX220305-128-XF | C4: 武汉 | D4: 44635 | E4: 44660 | F4: 44932 | G4: 76000 | H4: 67256.64 | I4: 8743.36 | J4: 45524 | K4: =IF(OR($D4="", $F4=""),"", $E4-$D4) -> 25 | L4: =IF(OR($D4="", $F4=""),"", $F4-$E4) -> 272 | M4: =IF(OR($F4="", $J4=""),"", $J4-$F4) -> 592
A5: 青州中联水泥有限公司 | B5: KMX220305-128-XF | C5: 武汉 | D5: 44635 | E5: 44660 | F5: 44932 | G5: 76000 | H5: 67256.64 | I5: 8743.36 | J5: 45524 | K5: =IF(OR($D5="", $F5=""),"", $E5-$D5) -> 25 | L5: =IF(OR($D5="", $F5=""),"", $F5-$E5) -> 272 | M5: =IF(OR($F5="", $J5=""),"", $J5-$F5) -> 592
A6: 湖南浏阳南方水泥有限公司 | B6: KMX220426-180-XF | C6: 武汉 | F6: 44932 | G6: 40000 | H6: 35398.23 | I6: 4601.77 | J6: 45322 | K6: =IF(OR($D6="", $F6=""),"", $E6-$D6) | L6: =IF(OR($D6="", $F6=""),"", $F6-$E6) | M6: =IF(OR($F6="", $J6=""),"", $J6-$F6) -> 390
A7: 四川峨胜水泥集团股份有限公司 | B7: KMX220930-364-XF | C7: 武汉 | D7: 44843 | E7: 44867 | F7: 44932 | G7: 8000 | H7: 7079.65 | I7: 920.35 | J7: 45365 | K7: =IF(OR($D7="", $F7=""),"", $E7-$D7) -> 24 | L7: =IF(OR($D7="", $F7=""),"", $F7-$E7) -> 65 | M7: =IF(OR($F7="", $J7=""),"", $J7-$F7) -> 433
A8: 四川峨胜水泥集团股份有限公司 | B8: KMX220930-364-XF | C8: 武汉 | D8: 44843 | E8: 44867 | F8: 44932 | G8: 22000 | H8: 19469.03 | I8: 2530.97 | J8: 45365 | K8: =IF(OR($D8="", $F8=""),"", $E8-$D8) -> 24 | L8: =IF(OR($D8="", $F8=""),"", $F8-$E8) -> 65 | M8: =IF(OR($F8="", $J8=""),"", $J8-$F8) -> 433
A9: 四川峨胜水泥集团股份有限公司 | B9: KMX220930-364-XF | C9: 武汉 | D9: 44843 | E9: 44867 | F9: 44932 | G9: 38000 | H9: 33628.32 | I9: 4371.68 | J9: 45365 | K9: =IF(OR($D9="", $F9=""),"", $E9-$D9) -> 24 | L9: =IF(OR($D9="", $F9=""),"", $F9-$E9) -> 65 | M9: =IF(OR($F9="", $J9=""),"", $J9-$F9) -> 433
A10: 卫辉市天瑞水泥有限公司 | B10: KMX221130-420-XF | C10: 湖北 | D10: 44915 | E10: 44922 | F10: 44933 | G10: 3.86 | H10: 3.42 | I10: 0.44 | J10: 45593 | K10: =IF(OR($D10="", $F10=""),"", $E10-$D10) -> 7 | L10: =IF(OR($D10="", $F10=""),"", $F10-$E10) -> 11 | M10: =IF(OR($F10="", $J10=""),"", $J10-$F10) -> 660
A11: 昌江华盛天涯水泥有限公司 | B11: KMX221028-388-XF | C11: 武汉 | D11: 44866 | E11: 44868 | F11: 44935 | G11: 68000 | H11: 64150.94 | I11: 3849.06 | K11: =IF(OR($D11="", $F11=""),"", $E11-$D11) -> 2 | L11: =IF(OR($D11="", $F11=""),"", $F11-$E11) -> 67 | M11: =IF(OR($F11="", $J11=""),"", $J11-$F11) | N11: 无回款匹配
A12: 湖南华菱湘潭钢铁有限公司 | B12: KMX200424-073-XF | C12: 武汉 | F12: 44935 | G12: 101700 | H12: 90000 | I12: 11700 | J12: 45315 | K12: =IF(OR($D12="", $F12=""),"", $E12-$D12) | L12: =IF(OR($D12="", $F12=""),"", $F12-$E12) | M12: =IF(OR($F12="", $J12=""),"", $J12-$F12) -> 380
A13: 北京堂海科技有限公司 | B13: KMX221228-450-XF | C13: 武汉 | F13: 44936 | G13: 53000 | H13: 50000 | I13: 3000 | K13: =IF(OR($D13="", $F13=""),"", $E13-$D13) | L13: =IF(OR($D13="", $F13=""),"", $F13-$E13) | M13: =IF(OR($F13="", $J13=""),"", $J13-$F13) | N13: 无回款匹配
A14: 北京金隅琉水环保科技有限公司 | B14: KMX220510-190-XF | C14: 湖北 | D14: 44822 | E14: 44839 | F14: 44937 | G14: -108000 | H14: -95575.22 | I14: -12424.78 | J14: 45564 | K14: =IF(OR($D14="", $F14=""),"", $E14-$D14) -> 17 | L14: =IF(OR($D14="", $F14=""),"", $F14-$E14) -> 98 | M14: =IF(OR($F14="", $J14=""),"", $J14-$F14) -> 627
A15: 北京金隅琉水环保科技有限公司 | B15: KMX220510-190-XF | C15: 湖北 | F15: 44937 | G15: -108000 | H15: -95575.22 | I15: -12424.78 | J15: 45564 | K15: =IF(OR($D15="", $F15=""),"", $E15-$D15) | L15: =IF(OR($D15="", $F15=""),"", $F15-$E15) | M15: =IF(OR($F15="", $J15=""),"", $J15-$F15) -> 627
A16: 联峰钢铁（张家港）有限公司（江苏永钢） | B16: KMX220720-289-XF | C16: 武汉 | D16: 44773 | E16: 44779 | F16: 44942 | G16: 65000 | H16: 59633.03 | I16: 5366.97 | K16: =IF(OR($D16="", $F16=""),"", $E16-$D16) -> 6 | L16: =IF(OR($D16="", $F16=""),"", $F16-$E16) -> 163 | M16: =IF(OR($F16="", $J16=""),"", $J16-$F16) | N16: 无回款匹配
A17: 海南逸盛石化有限公司 | B17: KMX221208-431-XF | C17: 武汉 | D17: 44905 | E17: 44910 | F17: 44954 | G17: 100000 | H17: 88495.58 | I17: 11504.42 | J17: 45461 | K17: =IF(OR($D17="", $F17=""),"", $E17-$D17) -> 5 | L17: =IF(OR($D17="", $F17=""),"", $F17-$E17) -> 44 | M17: =IF(OR($F17="", $J17=""),"", $J17-$F17) -> 507
A18: 海南逸盛石化有限公司 | B18: KMX221127-418-XF | C18: 武汉 | D18: 44891 | E18: 44895 | F18: 44954 | G18: 65000 | H18: 57522.12 | I18: 7477.88 | J18: 45461 | K18: =IF(OR($D18="", $F18=""),"", $E18-$D18) -> 4 | L18: =IF(OR($D18="", $F18=""),"", $F18-$E18) -> 59 | M18: =IF(OR($F18="", $J18=""),"", $J18-$F18) -> 507
A19: 广西北港新材料有限公司 | B19: KMX220516-206-XF | C19: 武汉 | F19: 44956 | G19: 82720 | H19: 75889.91 | I19: 6830.09 | J19: 45320 | K19: =IF(OR($D19="", $F19=""),"", $E19-$D19) | L19: =IF(OR($D19="", $F19=""),"", $F19-$E19) | M19: =IF(OR($F19="", $J19=""),"", $J19-$F19) -> 364
A20: 广西北港新材料有限公司 | B20: KMX220516-206-XF | C20: 武汉 | F20: 44956 | G20: 82720 | H20: 75889.91 | I20: 6830.09 | J20: 45320 | K20: =IF(OR($D20="", $F20=""),"", $E20-$D20) | L20: =IF(OR($D20="", $F20=""),"", $F20-$E20) | M20: =IF(OR($F20="", $J20=""),"", $J20-$F20) -> 364
A21: 新疆伊犁钢铁有限责任公司 | B21: KMX211021-394-XF | C21: 武汉 | D21: 44529 | E21: 44575 | F21: 44957 | G21: 90754.31 | H21: 83260.83 | I21: 7493.48 | J21: 45314 | K21: =IF(OR($D21="", $F21=""),"", $E21-$D21) -> 46 | L21: =IF(OR($D21="", $F21=""),"", $F21-$E21) -> 382 | M21: =IF(OR($F21="", $J21=""),"", $J21-$F21) -> 357
A22: 新疆伊犁钢铁有限责任公司 | B22: KMX211021-394-XF | C22: 武汉 | D22: 44529 | E22: 44575 | F22: 44957 | G22: 38894.7 | H22: 35683.21 | I22: 3211.49 | J22: 45314 | K22: =IF(OR($D22="", $F22=""),"", $E22-$D22) -> 46 | L22: =IF(OR($D22="", $F22=""),"", $F22-$E22) -> 382 | M22: =IF(OR($F22="", $J22=""),"", $J22-$F22) -> 357
A23: 崇阳县昌华实业有限公司 | B23: KMX230101-001-XF | C23: 武汉 | F23: 44959 | G23: 97 | H23: 85.84 | I23: 11.16 | J23: 45679 | K23: =IF(OR($D23="", $F23=""),"", $E23-$D23) | L23: =IF(OR($D23="", $F23=""),"", $F23-$E23) | M23: =IF(OR($F23="", $J23=""),"", $J23-$F23) -> 720
A24: 崇阳县昌华实业有限公司 | B24: KMX230104-009-XF | C24: 武汉 | F24: 44959 | G24: 12000 | H24: 10619.47 | I24: 1380.53 | J24: 45679 | K24: =IF(OR($D24="", $F24=""),"", $E24-$D24) | L24: =IF(OR($D24="", $F24=""),"", $F24-$E24) | M24: =IF(OR($F24="", $J24=""),"", $J24-$F24) -> 720
A25: 赞皇金隅水泥有限公司 | B25: KMX221111-404-XF | C25: 湖北 | F25: 44966 | G25: 110000 | H25: 97345.13 | I25: 12654.87 | J25: 45593 | K25: =IF(OR($D25="", $F25=""),"", $E25-$D25) | L25: =IF(OR($D25="", $F25=""),"", $F25-$E25) | M25: =IF(OR($F25="", $J25=""),"", $J25-$F25) -> 627
A26: 日照京华新型建材有限公司 | B26: KMX220329-153-XF | C26: 武汉 | D26: 44668 | E26: 44675 | F26: 44967 | G26: 117809.74 | H26: 110619.47 | I26: 7190.27 | K26: =IF(OR($D26="", $F26=""),"", $E26-$D26) -> 7 | L26: =IF(OR($D26="", $F26=""),"", $F26-$E26) -> 292 | M26: =IF(OR($F26="", $J26=""),"", $J26-$F26) | N26: 无回款匹配
A27: 日照京华新型建材有限公司 | B27: KMX220329-153-XF | C27: 武汉 | F27: 44967 | G27: 117809.74 | H27: 110619.47 | I27: 7190.27 | K27: =IF(OR($D27="", $F27=""),"", $E27-$D27) | L27: =IF(OR($D27="", $F27=""),"", $F27-$E27) | M27: =IF(OR($F27="", $J27=""),"", $J27-$F27) | N27: 无回款匹配
A28: 宁波钢铁有限公司 | B28: KMX221121-411-XF | C28: 武汉 | D28: 44885 | E28: 44887 | F28: 44971 | G28: 55700 | H28: 49292.04 | I28: 6407.96 | J28: 45371 | K28: =IF(OR($D28="", $F28=""),"", $E28-$D28) -> 2 | L28: =IF(OR($D28="", $F28=""),"", $F28-$E28) -> 84 | M28: =IF(OR($F28="", $J28=""),"", $J28-$F28) -> 400
A29: 宁波钢铁有限公司 | B29: KMX220601-228-XF | C29: 武汉 | D29: 44882 | E29: 44884 | F29: 44971 | G29: 64000 | H29: 56637.17 | I29: 7362.83 | J29: 45371 | K29: =IF(OR($D29="", $F29=""),"", $E29-$D29) -> 2 | L29: =IF(OR($D29="", $F29=""),"", $F29-$E29) -> 87 | M29: =IF(OR($F29="", $J29=""),"", $J29-$F29) -> 400
A30: 铜陵上峰水泥股份有限公司 | B30: KMX220218-100-XF | C30: 武汉 | F30: 44971 | G30: 105000 | H30: 92920.35 | I30: 12079.65 | J30: 45596 | K30: =IF(OR($D30="", $F30=""),"", $E30-$D30) | L30: =IF(OR($D30="", $F30=""),"", $F30-$E30) | M30: =IF(OR($F30="", $J30=""),"", $J30-$F30) -> 625
A31: 铜陵上峰水泥股份有限公司 | B31: KMX220218-100-XF | C31: 武汉 | D31: 44695 | E31: 44701 | F31: 44971 | G31: 47000 | H31: 41592.92 | I31: 5407.08 | J31: 45596 | K31: =IF(OR($D31="", $F31=""),"", $E31-$D31) -> 6 | L31: =IF(OR($D31="", $F31=""),"", $F31-$E31) -> 270 | M31: =IF(OR($F31="", $J31=""),"", $J31-$F31) -> 625
A32: 铜陵上峰水泥股份有限公司 | B32: KMX220218-100-XF | C32: 武汉 | D32: 44724 | E32: 44862 | F32: 44971 | G32: 18000 | H32: 15929.2 | I32: 2070.8 | J32: 45596 | K32: =IF(OR($D32="", $F32=""),"", $E32-$D32) -> 138 | L32: =IF(OR($D32="", $F32=""),"", $F32-$E32) -> 109 | M32: =IF(OR($F32="", $J32=""),"", $J32-$F32) -> 625
A33: 铜陵上峰水泥股份有限公司 | B33: KMX220218-100-XF | C33: 武汉 | D33: 44724 | E33: 44862 | F33: 44971 | G33: 4900 | H33: 4336.28 | I33: 563.72 | J33: 45596 | K33: =IF(OR($D33="", $F33=""),"", $E33-$D33) -> 138 | L33: =IF(OR($D33="", $F33=""),"", $F33-$E33) -> 109 | M33: =IF(OR($F33="", $J33=""),"", $J33-$F33) -> 625
A34: 铜陵上峰水泥股份有限公司 | B34: KMX220218-100-XF | C34: 武汉 | D34: 44758 | E34: 44772 | F34: 44971 | G34: 40000 | H34: 35398.23 | I34: 4601.77 | J34: 45596 | K34: =IF(OR($D34="", $F34=""),"", $E34-$D34) -> 14 | L34: =IF(OR($D34="", $F34=""),"", $F34-$E34) -> 199 | M34: =IF(OR($F34="", $J34=""),"", $J34-$F34) -> 625
A35: 涞水金隅冀东环保科技有限公司 | B35: KMX221127-419-XF | C35: 湖北 | D35: 44912 | E35: 44924 | F35: 44972 | G35: 58000 | H35: 51327.43 | I35: 6672.57 | J35: 45586 | K35: =IF(OR($D35="", $F35=""),"", $E35-$D35) -> 12 | L35: =IF(OR($D35="", $F35=""),"", $F35-$E35) -> 48 | M35: =IF(OR($F35="", $J35=""),"", $J35-$F35) -> 614
A36: 重庆九鑫水泥（集团）有限公司 | B36: KMX230103-008-XF | C36: 武汉 | F36: 44973 | G36: 52920 | H36: 46831.86 | I36: 6088.14 | K36: =IF(OR($D36="", $F36=""),"", $E36-$D36) | L36: =IF(OR($D36="", $F36=""),"", $F36-$E36) | M36: =IF(OR($F36="", $J36=""),"", $J36-$F36) | N36: 无回款匹配
A37: 江油嘉鸿机电工程有限公司 | B37: KMX230215-052-XF | C37: 武汉 | D37: 44943 | E37: 44943 | F37: 44975 | G37: 14000 | H37: 13207.55 | I37: 792.45 | K37: =IF(OR($D37="", $F37=""),"", $E37-$D37) -> 0 | L37: =IF(OR($D37="", $F37=""),"", $F37-$E37) -> 32 | M37: =IF(OR($F37="", $J37=""),"", $J37-$F37) | N37: 无回款匹配
A38: 北京金隅北水环保科技有限公司 | B38: KMX211221-506-XF | C38: 湖北 | D38: 44648 | E38: 44660 | F38: 44975 | G38: 112892 | H38: 99904.42 | I38: 12987.58 | K38: =IF(OR($D38="", $F38=""),"", $E38-$D38) -> 12 | L38: =IF(OR($D38="", $F38=""),"", $F38-$E38) -> 315 | M38: =IF(OR($F38="", $J38=""),"", $J38-$F38) | N38: 无回款匹配
A39: 北京金隅北水环保科技有限公司 | B39: KMX211221-506-XF | C39: 湖北 | D39: 44648 | E39: 44660 | F39: 44975 | G39: 112554 | H39: 99605.31 | I39: 12948.69 | K39: =IF(OR($D39="", $F39=""),"", $E39-$D39) -> 12 | L39: =IF(OR($D39="", $F39=""),"", $F39-$E39) -> 315 | M39: =IF(OR($F39="", $J39=""),"", $J39-$F39) | N39: 无回款匹配
A40: 北京金隅北水环保科技有限公司 | B40: KMX211221-506-XF | C40: 湖北 | D40: 44648 | E40: 44660 | F40: 44975 | G40: 112554 | H40: 99605.31 | I40: 12948.69 | K40: =IF(OR($D40="", $F40=""),"", $E40-$D40) -> 12 | L40: =IF(OR($D40="", $F40=""),"", $F40-$E40) -> 315 | M40: =IF(OR($F40="", $J40=""),"", $J40-$F40) | N40: 无回款匹配
A41: 湘潭县亿鑫锌业有限公司 | B41: KMX230113-021-XF | C41: 武汉 | D41: 44943 | E41: 44944 | F41: 44979 | G41: 38250 | H41: 33849.56 | I41: 4400.44 | J41: 45553 | K41: =IF(OR($D41="", $F41=""),"", $E41-$D41) -> 1 | L41: =IF(OR($D41="", $F41=""),"", $F41-$E41) -> 35 | M41: =IF(OR($F41="", $J41=""),"", $J41-$F41) -> 574
A42: 湖北京兰水泥集团有限公司 | B42: KMX221126-415-XF | C42: 武汉 | D42: 44892 | E42: 44893 | F42: 44979 | G42: 40000 | H42: 35398.23 | I42: 4601.77 | J42: 45345 | K42: =IF(OR($D42="", $F42=""),"", $E42-$D42) -> 1 | L42: =IF(OR($D42="", $F42=""),"", $F42-$E42) -> 86 | M42: =IF(OR($F42="", $J42=""),"", $J42-$F42) -> 366
A43: 湖州丰盛新材料有限公司 | B43: KMX230112-020-XF | C43: 武汉 | D43: 44953 | E43: 44955 | F43: 44979 | G43: 48000 | H43: 42477.88 | I43: 5522.12 | K43: =IF(OR($D43="", $F43=""),"", $E43-$D43) -> 2 | L43: =IF(OR($D43="", $F43=""),"", $F43-$E43) -> 24 | M43: =IF(OR($F43="", $J43=""),"", $J43-$F43) | N43: 无回款匹配
A44: 江西宝丰生物科技有限公司 | B44: KMX220917-354-XF | C44: 武汉 | D44: 44852 | E44: 44854 | F44: 44981 | G44: 61600 | H44: 56513.76 | I44: 5086.24 | J44: 45315 | K44: =IF(OR($D44="", $F44=""),"", $E44-$D44) -> 2 | L44: =IF(OR($D44="", $F44=""),"", $F44-$E44) -> 127 | M44: =IF(OR($F44="", $J44=""),"", $J44-$F44) -> 334
A45: 重庆市富丰水泥集团特种水泥有限公司 | B45: KMX220810-316-XF | C45: 武汉 | D45: 44785 | E45: 44788 | F45: 44981 | G45: 26204 | H45: 23189.38 | I45: 3014.62 | J45: 45504 | K45: =IF(OR($D45="", $F45=""),"", $E45-$D45) -> 3 | L45: =IF(OR($D45="", $F45=""),"", $F45-$E45) -> 193 | M45: =IF(OR($F45="", $J45=""),"", $J45-$F45) -> 523
A46: 重庆市富丰水泥集团特种水泥有限公司 | B46: KMX220728-293-XF | C46: 武汉 | D46: 44774 | E46: 44784 | F46: 44981 | G46: 82000 | H46: 72566.37 | I46: 9433.63 | J46: 45504 | K46: =IF(OR($D46="", $F46=""),"", $E46-$D46) -> 10 | L46: =IF(OR($D46="", $F46=""),"", $F46-$E46) -> 197 | M46: =IF(OR($F46="", $J46=""),"", $J46-$F46) -> 523
A47: 重庆市富丰水泥集团特种水泥有限公司 | B47: KMX220728-293-XF | C47: 武汉 | F47: 44981 | G47: 104584 | H47: 92552.21 | I47: 12031.79 | J47: 45504 | K47: =IF(OR($D47="", $F47=""),"", $E47-$D47) | L47: =IF(OR($D47="", $F47=""),"", $F47-$E47) | M47: =IF(OR($F47="", $J47=""),"", $J47-$F47) -> 523
A48: 重庆市富丰水泥集团特种水泥有限公司 | B48: KMX220729-296-XF | C48: 武汉 | F48: 44981 | G48: 100000 | H48: 91743.12 | I48: 8256.88 | J48: 45504 | K48: =IF(OR($D48="", $F48=""),"", $E48-$D48) | L48: =IF(OR($D48="", $F48=""),"", $F48-$E48) | M48: =IF(OR($F48="", $J48=""),"", $J48-$F48) -> 523
A49: 贵州黔西中水发电有限公司 | B49: KMX220401-157-XF | C49: 武汉 | F49: 44981 | G49: 64000 | H49: 56637.17 | I49: 7362.83 | J49: 45624 | K49: =IF(OR($D49="", $F49=""),"", $E49-$D49) | L49: =IF(OR($D49="", $F49=""),"", $F49-$E49) | M49: =IF(OR($F49="", $J49=""),"", $J49-$F49) -> 643
A50: 贵州黔西中水发电有限公司 | B50: KMX220401-157-XF | C50: 武汉 | F50: 44981 | G50: 96000 | H50: 84955.75 | I50: 11044.25 | J50: 45624 | K50: =IF(OR($D50="", $F50=""),"", $E50-$D50) | L50: =IF(OR($D50="", $F50=""),"", $F50-$E50) | M50: =IF(OR($F50="", $J50=""),"", $J50-$F50) -> 643
A51: 贵州黔西中水发电有限公司 | B51: KMX220401-157-XF | C51: 武汉 | F51: 44981 | G51: 96000 | H51: 84955.75 | I51: 11044.25 | J51: 45624 | K51: =IF(OR($D51="", $F51=""),"", $E51-$D51) | L51: =IF(OR($D51="", $F51=""),"", $F51-$E51) | M51: =IF(OR($F51="", $J51=""),"", $J51-$F51) -> 643
A52: 贵州黔西中水发电有限公司 | B52: KMX220401-157-XF | C52: 武汉 | F52: 44981 | G52: -96000 | H52: -84955.75 | I52: -11044.25 | J52: 45624 | K52: =IF(OR($D52="", $F52=""),"", $E52-$D52) | L52: =IF(OR($D52="", $F52=""),"", $F52-$E52) | M52: =IF(OR($F52="", $J52=""),"", $J52-$F52) -> 643
A53: 贵州黔西中水发电有限公司 | B53: KMX220401-157-XF | C53: 武汉 | F53: 44981 | G53: -96000 | H53: -84955.75 | I53: -11044.25 | J53: 45624 | K53: =IF(OR($D53="", $F53=""),"", $E53-$D53) | L53: =IF(OR($D53="", $F53=""),"", $F53-$E53) | M53: =IF(OR($F53="", $J53=""),"", $J53-$F53) -> 643
A54: 贵州黔西中水发电有限公司 | B54: KMX220401-157-XF | C54: 武汉 | F54: 44981 | G54: -64000 | H54: -56637.17 | I54: -7362.83 | J54: 45624 | K54: =IF(OR($D54="", $F54=""),"", $E54-$D54) | L54: =IF(OR($D54="", $F54=""),"", $F54-$E54) | M54: =IF(OR($F54="", $J54=""),"", $J54-$F54) -> 643
A55: 廉江市丰诚水泥有限公司 | B55: KMX220708-275-XF | C55: 武汉 | F55: 44985 | G55: 95000 | H55: 84070.8 | I55: 10929.2 | K55: =IF(OR($D55="", $F55=""),"", $E55-$D55) | L55: =IF(OR($D55="", $F55=""),"", $F55-$E55) | M55: =IF(OR($F55="", $J55=""),"", $J55-$F55) | N55: 无回款匹配
A56: 福建春驰集团国产实业水泥有限公司 | B56: KMX230105-010-XF | C56: 彤烨 | F56: 44985 | G56: 73000 | H56: 64601.77 | I56: 8398.23 | J56: 45330 | K56: =IF(OR($D56="", $F56=""),"", $E56-$D56) | L56: =IF(OR($D56="", $F56=""),"", $F56-$E56) | M56: =IF(OR($F56="", $J56=""),"", $J56-$F56) -> 345
A57: 吉林亚泰明城水泥有限公司 | B57: KMX150320-073-XF | C57: 彤烨 | F57: 44985 | G57: 110000 | H57: 97345.13 | I57: 12654.87 | J57: 45477 | K57: =IF(OR($D57="", $F57=""),"", $E57-$D57) | L57: =IF(OR($D57="", $F57=""),"", $F57-$E57) | M57: =IF(OR($F57="", $J57=""),"", $J57-$F57) -> 492
A58: 芜湖新兴铸管有限责任公司 | B58: KMX210515-202-XF | C58: 武汉 | F58: 44991 | G58: 31200 | H58: 27610.62 | I58: 3589.38 | J58: 45372 | K58: =IF(OR($D58="", $F58=""),"", $E58-$D58) | L58: =IF(OR($D58="", $F58=""),"", $F58-$E58) | M58: =IF(OR($F58="", $J58=""),"", $J58-$F58) -> 381
A59: 吉林金隅冀东环保科技有限公司 | B59: KMX220722-290-XF | C59: 湖北 | F59: 44991 | G59: 67600 | H59: 59823.01 | I59: 7776.99 | J59: 45909 | K59: =IF(OR($D59="", $F59=""),"", $E59-$D59) | L59: =IF(OR($D59="", $F59=""),"", $F59-$E59) | M59: =IF(OR($F59="", $J59=""),"", $J59-$F59) -> 918
A60: 吉林金隅冀东环保科技有限公司 | B60: KMX220722-290-XF | C60: 湖北 | F60: 44991 | G60: 95200 | H60: 84247.79 | I60: 10952.21 | J60: 45909 | K60: =IF(OR($D60="", $F60=""),"", $E60-$D60) | L60: =IF(OR($D60="", $F60=""),"", $F60-$E60) | M60: =IF(OR($F60="", $J60=""),"", $J60-$F60) -> 918
A61: 吉林金隅冀东环保科技有限公司 | B61: KMX220722-290-XF | C61: 湖北 | F61: 44991 | G61: 95200 | H61: 84247.79 | I61: 10952.21 | J61: 45909 | K61: =IF(OR($D61="", $F61=""),"", $E61-$D61) | L61: =IF(OR($D61="", $F61=""),"", $F61-$E61) | M61: =IF(OR($F61="", $J61=""),"", $J61-$F61) -> 918
A62: 山西吉港冠宇水泥有限公司 | B62: KMX230302-065-XF | C62: 武汉 | D62: 44988 | E62: 44992 | F62: 44993 | G62: 29142 | H62: 25789.38 | I62: 3352.62 | J62: 45482 | K62: =IF(OR($D62="", $F62=""),"", $E62-$D62) -> 4 | L62: =IF(OR($D62="", $F62=""),"", $F62-$E62) -> 1 | M62: =IF(OR($F62="", $J62=""),"", $J62-$F62) -> 489
A63: 武汉鑫缘绿色冶金渣技术开发有限公司 | B63: KMX221027-385-XF | C63: 武汉 | D63: 44861 | E63: 44868 | F63: 44993 | G63: 89000 | H63: 78761.07 | I63: 10238.93 | J63: 45329 | K63: =IF(OR($D63="", $F63=""),"", $E63-$D63) -> 7 | L63: =IF(OR($D63="", $F63=""),"", $F63-$E63) -> 125 | M63: =IF(OR($F63="", $J63=""),"", $J63-$F63) -> 336
A64: 葛洲坝钟祥水泥有限公司 | B64: KMX230128-034-XF | C64: 武汉 | F64: 44994 | G64: 100940 | H64: 89327.43 | I64: 11612.57 | K64: =IF(OR($D64="", $F64=""),"", $E64-$D64) | L64: =IF(OR($D64="", $F64=""),"", $F64-$E64) | M64: =IF(OR($F64="", $J64=""),"", $J64-$F64) | N64: 无回款匹配
A65: 葛洲坝钟祥水泥有限公司 | B65: KMX230128-034-XF | C65: 武汉 | F65: 44994 | G65: 100940 | H65: 89327.43 | I65: 11612.57 | K65: =IF(OR($D65="", $F65=""),"", $E65-$D65) | L65: =IF(OR($D65="", $F65=""),"", $F65-$E65) | M65: =IF(OR($F65="", $J65=""),"", $J65-$F65) | N65: 无回款匹配
A66: 葛洲坝钟祥水泥有限公司 | B66: KMX230128-034-XF | C66: 武汉 | F66: 44994 | G66: 101920 | H66: 90194.69 | I66: 11725.31 | K66: =IF(OR($D66="", $F66=""),"", $E66-$D66) | L66: =IF(OR($D66="", $F66=""),"", $F66-$E66) | M66: =IF(OR($F66="", $J66=""),"", $J66-$F66) | N66: 无回款匹配
A67: 广西北港不锈钢有限公司 | B67: KMX220822-330-XF | C67: 武汉 | F67: 44998 | G67: 247644 | H67: 227196.33 | I67: 20447.67 | J67: 45715 | K67: =IF(OR($D67="", $F67=""),"", $E67-$D67) | L67: =IF(OR($D67="", $F67=""),"", $F67-$E67) | M67: =IF(OR($F67="", $J67=""),"", $J67-$F67) -> 717
A68: 广西北港不锈钢有限公司 | B68: KMX220822-330-XF | C68: 武汉 | F68: 44998 | G68: 247644 | H68: 227196.33 | I68: 20447.67 | J68: 45715 | K68: =IF(OR($D68="", $F68=""),"", $E68-$D68) | L68: =IF(OR($D68="", $F68=""),"", $F68-$E68) | M68: =IF(OR($F68="", $J68=""),"", $J68-$F68) -> 717
A69: 广西北港不锈钢有限公司 | B69: KMX220822-330-XF | C69: 武汉 | F69: 44998 | G69: 247644 | H69: 227196.33 | I69: 20447.67 | J69: 45715 | K69: =IF(OR($D69="", $F69=""),"", $E69-$D69) | L69: =IF(OR($D69="", $F69=""),"", $F69-$E69) | M69: =IF(OR($F69="", $J69=""),"", $J69-$F69) -> 717
A70: 新疆伊犁钢铁有限责任公司 | B70: KMX221019-379-XF | C70: 武汉 | D70: 44911 | E70: 44964 | F70: 44999 | G70: 570000 | H70: 522935.78 | I70: 47064.22 | J70: 45314 | K70: =IF(OR($D70="", $F70=""),"", $E70-$D70) -> 53 | L70: =IF(OR($D70="", $F70=""),"", $F70-$E70) -> 35 | M70: =IF(OR($F70="", $J70=""),"", $J70-$F70) -> 315
A71: 新疆伊犁钢铁有限责任公司 | B71: KMX221019-379-XF | C71: 武汉 | F71: 44999 | G71: 570000 | H71: 522935.78 | I71: 47064.22 | J71: 45314 | K71: =IF(OR($D71="", $F71=""),"", $E71-$D71) | L71: =IF(OR($D71="", $F71=""),"", $F71-$E71) | M71: =IF(OR($F71="", $J71=""),"", $J71-$F71) -> 315
A72: 新疆伊犁钢铁有限责任公司 | B72: KMX221019-379-XF | C72: 武汉 | F72: 44999 | G72: 570000 | H72: 522935.78 | I72: 47064.22 | J72: 45314 | K72: =IF(OR($D72="", $F72=""),"", $E72-$D72) | L72: =IF(OR($D72="", $F72=""),"", $F72-$E72) | M72: =IF(OR($F72="", $J72=""),"", $J72-$F72) -> 315
A73: 新疆伊犁钢铁有限责任公司 | B73: KMX221019-379-XF | C73: 武汉 | F73: 44999 | G73: 570000 | H73: 522935.78 | I73: 47064.22 | J73: 45314 | K73: =IF(OR($D73="", $F73=""),"", $E73-$D73) | L73: =IF(OR($D73="", $F73=""),"", $F73-$E73) | M73: =IF(OR($F73="", $J73=""),"", $J73-$F73) -> 315
A74: 新疆伊犁钢铁有限责任公司 | B74: KMX221019-379-XF | C74: 武汉 | F74: 44999 | G74: 570000 | H74: 522935.78 | I74: 47064.22 | J74: 45314 | K74: =IF(OR($D74="", $F74=""),"", $E74-$D74) | L74: =IF(OR($D74="", $F74=""),"", $F74-$E74) | M74: =IF(OR($F74="", $J74=""),"", $J74-$F74) -> 315
A75: 新疆伊犁钢铁有限责任公司 | B75: KMX221019-379-XF | C75: 武汉 | F75: 44999 | G75: 570000 | H75: 522935.78 | I75: 47064.22 | J75: 45314 | K75: =IF(OR($D75="", $F75=""),"", $E75-$D75) | L75: =IF(OR($D75="", $F75=""),"", $F75-$E75) | M75: =IF(OR($F75="", $J75=""),"", $J75-$F75) -> 315
A76: 唐山冀东发展机械设备制造有限公司 | B76: KMX221228-449-XF | C76: 武汉 | F76: 45000 | G76: 99000 | H76: 87610.62 | I76: 11389.38 | J76: 45657 | K76: =IF(OR($D76="", $F76=""),"", $E76-$D76) | L76: =IF(OR($D76="", $F76=""),"", $F76-$E76) | M76: =IF(OR($F76="", $J76=""),"", $J76-$F76) -> 657
A77: 宁夏滨河海利建材有限公司 | B77: KMX230302-066-XF | C77: 武汉 | D77: 44990 | E77: 44995 | F77: 45000 | G77: 33000 | H77: 30275.23 | I77: 2724.77 | K77: =IF(OR($D77="", $F77=""),"", $E77-$D77) -> 5 | L77: =IF(OR($D77="", $F77=""),"", $F77-$E77) -> 5 | M77: =IF(OR($F77="", $J77=""),"", $J77-$F77) | N77: 无回款匹配
A78: 合肥南方水泥有限公司 | B78: KMX220601-229-XF | C78: 武汉 | D78: 44714 | E78: 44715 | F78: 45000 | G78: 49000 | H78: 43362.83 | I78: 5637.17 | J78: 45306 | K78: =IF(OR($D78="", $F78=""),"", $E78-$D78) -> 1 | L78: =IF(OR($D78="", $F78=""),"", $F78-$E78) -> 285 | M78: =IF(OR($F78="", $J78=""),"", $J78-$F78) -> 306
A79: 合肥南方水泥有限公司 | B79: KMX220601-229-XF | C79: 武汉 | F79: 45001 | G79: 49000 | H79: 43362.83 | I79: 5637.17 | J79: 45306 | K79: =IF(OR($D79="", $F79=""),"", $E79-$D79) | L79: =IF(OR($D79="", $F79=""),"", $F79-$E79) | M79: =IF(OR($F79="", $J79=""),"", $J79-$F79) -> 305
A80: 江西亚东水泥有限公司 | B80: KMX211227-515-XF | C80: 武汉 | F80: 45001 | G80: 146900 | H80: 130000 | I80: 16900 | J80: 45294 | K80: =IF(OR($D80="", $F80=""),"", $E80-$D80) | L80: =IF(OR($D80="", $F80=""),"", $F80-$E80) | M80: =IF(OR($F80="", $J80=""),"", $J80-$F80) -> 293
A81: 江西亚东水泥有限公司 | B81: KMX211227-515-XF | C81: 武汉 | F81: 45001 | G81: 146900 | H81: 130000 | I81: 16900 | J81: 45294 | K81: =IF(OR($D81="", $F81=""),"", $E81-$D81) | L81: =IF(OR($D81="", $F81=""),"", $F81-$E81) | M81: =IF(OR($F81="", $J81=""),"", $J81-$F81) -> 293
A82: 吉林亚泰水泥有限公司 | B82: KMX230128-035-XF | C82: 彤烨 | F82: 45001 | G82: 11452.76 | H82: 1.26 | I82: 11451.5 | J82: 45471 | K82: =IF(OR($D82="", $F82=""),"", $E82-$D82) | L82: =IF(OR($D82="", $F82=""),"", $F82-$E82) | M82: =IF(OR($F82="", $J82=""),"", $J82-$F82) -> 470
A83: 吉林亚泰水泥有限公司 | B83: KMX230128-035-XF | C83: 彤烨 | F83: 45001 | G83: 1.42 | H83: 1.26 | I83: 0.16 | J83: 45471 | K83: =IF(OR($D83="", $F83=""),"", $E83-$D83) | L83: =IF(OR($D83="", $F83=""),"", $F83-$E83) | M83: =IF(OR($F83="", $J83=""),"", $J83-$F83) -> 470
A84: 廉江市丰诚水泥有限公司 | B84: KMX220708-275-XF | C84: 武汉 | F84: 45003 | G84: 89115.04 | H84: 84070.79 | I84: 5044.25 | K84: =IF(OR($D84="", $F84=""),"", $E84-$D84) | L84: =IF(OR($D84="", $F84=""),"", $F84-$E84) | M84: =IF(OR($F84="", $J84=""),"", $J84-$F84) | N84: 无回款匹配
A85: 廉江市丰诚水泥有限公司 | B85: KMX220708-275-XF | C85: 武汉 | F85: 45003 | G85: -95000 | H85: -84070.8 | I85: -10929.2 | K85: =IF(OR($D85="", $F85=""),"", $E85-$D85) | L85: =IF(OR($D85="", $F85=""),"", $F85-$E85) | M85: =IF(OR($F85="", $J85=""),"", $J85-$F85) | N85: 无回款匹配
A86: 海拉尔蒙西水泥有限公司 | B86: KMX230304-069-XF | C86: 武汉 | D86: 44997 | E86: 45002 | F86: 45007 | G86: 30000 | H86: 28301.89 | I86: 1698.11 | J86: 45919 | K86: =IF(OR($D86="", $F86=""),"", $E86-$D86) -> 5 | L86: =IF(OR($D86="", $F86=""),"", $F86-$E86) -> 5 | M86: =IF(OR($F86="", $J86=""),"", $J86-$F86) -> 912
A87: 四川省星船城水泥股份有限公司 | B87: KMX230113-022-XF | C87: 武汉 | D87: 44955 | E87: 44977 | F87: 45007 | G87: 27000.01 | H87: 23893.81 | I87: 3106.2 | J87: 45436 | K87: =IF(OR($D87="", $F87=""),"", $E87-$D87) -> 22 | L87: =IF(OR($D87="", $F87=""),"", $F87-$E87) -> 30 | M87: =IF(OR($F87="", $J87=""),"", $J87-$F87) -> 429
A88: 四川省星船城水泥股份有限公司 | B88: KMX230113-022-XF | C88: 武汉 | F88: 45007 | G88: 27000.01 | H88: 23893.81 | I88: 3106.2 | J88: 45436 | K88: =IF(OR($D88="", $F88=""),"", $E88-$D88) | L88: =IF(OR($D88="", $F88=""),"", $F88-$E88) | M88: =IF(OR($F88="", $J88=""),"", $J88-$F88) -> 429
A89: 四川省星船城水泥股份有限公司 | B89: KMX230113-022-XF | C89: 武汉 | F89: 45007 | G89: 102000 | H89: 90265.48 | I89: 11734.52 | J89: 45436 | K89: =IF(OR($D89="", $F89=""),"", $E89-$D89) | L89: =IF(OR($D89="", $F89=""),"", $F89-$E89) | M89: =IF(OR($F89="", $J89=""),"", $J89-$F89) -> 429
A90: 四川省星船城水泥股份有限公司 | B90: KMX230113-022-XF | C90: 武汉 | F90: 45007 | G90: 23800 | H90: 21061.95 | I90: 2738.05 | J90: 45436 | K90: =IF(OR($D90="", $F90=""),"", $E90-$D90) | L90: =IF(OR($D90="", $F90=""),"", $F90-$E90) | M90: =IF(OR($F90="", $J90=""),"", $J90-$F90) -> 429
A91: 四川省星船城水泥股份有限公司 | B91: KMX230113-022-XF | C91: 武汉 | F91: 45007 | G91: 23800 | H91: 21061.95 | I91: 2738.05 | J91: 45436 | K91: =IF(OR($D91="", $F91=""),"", $E91-$D91) | L91: =IF(OR($D91="", $F91=""),"", $F91-$E91) | M91: =IF(OR($F91="", $J91=""),"", $J91-$F91) -> 429
A92: 四川省星船城水泥股份有限公司 | B92: KMX230130-037-XF | C92: 武汉 | F92: 45007 | G92: 23800 | H92: 21061.95 | I92: 2738.05 | J92: 45436 | K92: =IF(OR($D92="", $F92=""),"", $E92-$D92) | L92: =IF(OR($D92="", $F92=""),"", $F92-$E92) | M92: =IF(OR($F92="", $J92=""),"", $J92-$F92) -> 429
A93: 山西金隅冀东环保科技有限公司 | B93: KMX220829-339-XF | C93: 武汉 | D93: 44813 | F93: 45007 | G93: 33800 | H93: 31886.8 | I93: 1913.2 | K93: =IF(OR($D93="", $F93=""),"", $E93-$D93) -> -44813 | L93: =IF(OR($D93="", $F93=""),"", $F93-$E93) -> 45007 | M93: =IF(OR($F93="", $J93=""),"", $J93-$F93) | N93: 无回款匹配
A94: 达州利森水泥有限公司 | B94: KMX230118-029-XF | C94: 武汉 | D94: 44982 | F94: 45007 | G94: 2.09 | H94: 1.85 | I94: 0.24 | J94: 45866 | K94: =IF(OR($D94="", $F94=""),"", $E94-$D94) -> -44982 | L94: =IF(OR($D94="", $F94=""),"", $F94-$E94) -> 45007 | M94: =IF(OR($F94="", $J94=""),"", $J94-$F94) -> 859
A95: 山东泰西水泥有限公司 | B95: KMX221116-409-XF | C95: 武汉 | D95: 44964 | F95: 45007 | G95: 70500 | H95: 62389.38 | I95: 8110.62 | J95: 45315 | K95: =IF(OR($D95="", $F95=""),"", $E95-$D95) -> -44964 | L95: =IF(OR($D95="", $F95=""),"", $F95-$E95) -> 45007 | M95: =IF(OR($F95="", $J95=""),"", $J95-$F95) -> 308
A96: 山东泰西水泥有限公司 | B96: KMX230212-049-XF | C96: 武汉 | D96: 44974 | F96: 45007 | G96: 100000 | H96: 91743.12 | I96: 8256.88 | J96: 45315 | K96: =IF(OR($D96="", $F96=""),"", $E96-$D96) -> -44974 | L96: =IF(OR($D96="", $F96=""),"", $F96-$E96) -> 45007 | M96: =IF(OR($F96="", $J96=""),"", $J96-$F96) -> 308
A97: 内蒙古天皓水泥集团有限公司 | B97: KMX220301-122-XF | C97: 武汉 | F97: 45008 | G97: 17680 | H97: 15646.018 | I97: 2033.9823 | J97: 45330 | K97: =IF(OR($D97="", $F97=""),"", $E97-$D97) | L97: =IF(OR($D97="", $F97=""),"", $F97-$E97) | M97: =IF(OR($F97="", $J97=""),"", $J97-$F97) -> 322
A98: 内蒙古天皓水泥集团有限公司 | B98: KMX230204-043-XF | C98: 武汉 | F98: 45008 | G98: 80320 | H98: 71079.646 | I98: 9240.354 | J98: 45330 | K98: =IF(OR($D98="", $F98=""),"", $E98-$D98) | L98: =IF(OR($D98="", $F98=""),"", $F98-$E98) | M98: =IF(OR($F98="", $J98=""),"", $J98-$F98) -> 322
A99: 内蒙古天皓水泥集团有限公司 | B99: KMX230116-026-XF | C99: 武汉 | F99: 45008 | G99: 76320 | H99: 67539.82 | I99: 8780.18 | J99: 45330 | K99: =IF(OR($D99="", $F99=""),"", $E99-$D99) | L99: =IF(OR($D99="", $F99=""),"", $F99-$E99) | M99: =IF(OR($F99="", $J99=""),"", $J99-$F99) -> 322
A100: 山东鲁泰环保建材有限公司 | B100: KMX221210-434-XF | C100: 武汉 | F100: 45008 | G100: 28000 | H100: 24778.76 | I100: 3221.24 | J100: 45322 | K100: =IF(OR($D100="", $F100=""),"", $E100-$D100) | L100: =IF(OR($D100="", $F100=""),"", $F100-$E100) | M100: =IF(OR($F100="", $J100=""),"", $J100-$F100) -> 314
...

Sheet 明细_应收
A1: 合同号 | B1: 客户 | C1: 合同日期 | D1: 完工日期 | E1: 工期 | F1: 开票日期 | G1: 完工后开票 | H1: 账龄基准日 | I1: 账龄天数 | J1: 账龄桶 | K1: 未回款 | L1: 未开票金额
A2: KMX071008-197 | B2: 新疆阿克苏青松建化公司 | C2: 39363 | D2: 39453 | E2: =IF(OR($C2="", $D2=""),"", $D2-$C2) -> 90 | G2: =IF(OR($C2="", $D2="",$F2=""),"", $F2-$D2) | H2: 39453 | I2: =IF($H2="", "", 参数!$B$3-$H2) -> 6571 | J2: 365+ | K2: 35460
A3: KMX080909-077 | B3: 四会市骏马水泥有限公司 | C3: 39700 | D3: 39717 | E3: =IF(OR($C3="", $D3=""),"", $D3-$C3) -> 17 | F3: 39717 | G3: =IF(OR($C3="", $D3="",$F3=""),"", $F3-$D3) -> 0 | H3: 39717 | I3: =IF($H3="", "", 参数!$B$3-$H3) -> 6307 | J3: 365+ | K3: 5900
A4: KMX081010-085 | B4: 山东康达水泥有限公司 | C4: 39731 | D4: 39749 | E4: =IF(OR($C4="", $D4=""),"", $D4-$C4) -> 18 | F4: 39749 | G4: =IF(OR($C4="", $D4="",$F4=""),"", $F4-$D4) -> 0 | H4: 39749 | I4: =IF($H4="", "", 参数!$B$3-$H4) -> 6275 | J4: 365+ | K4: 7500
A5: KMX080807-176 | B5: 湖北金龙新材料股份有限公司 | C5: 40032 | D5: 40122 | E5: =IF(OR($C5="", $D5=""),"", $D5-$C5) -> 90 | G5: =IF(OR($C5="", $D5="",$F5=""),"", $F5-$D5) | H5: 40122 | I5: =IF($H5="", "", 参数!$B$3-$H5) -> 5902 | J5: 365+ | K5: 26400
A6: KMX091120-177 | B6: 哈尔滨金山实业集团有限公司 | C6: 40137 | D6: 40227 | E6: =IF(OR($C6="", $D6=""),"", $D6-$C6) -> 90 | G6: =IF(OR($C6="", $D6="",$F6=""),"", $F6-$D6) | H6: 40227 | I6: =IF($H6="", "", 参数!$B$3-$H6) -> 5797 | J6: 365+ | K6: 27000
A7: KMX091123-151 | B7: 南阳市天泰水泥有限公司 | C7: 40140 | D7: 40170 | E7: =IF(OR($C7="", $D7=""),"", $D7-$C7) -> 30 | F7: 40170 | G7: =IF(OR($C7="", $D7="",$F7=""),"", $F7-$D7) -> 0 | H7: 40170 | I7: =IF($H7="", "", 参数!$B$3-$H7) -> 5854 | J7: 365+ | K7: 18000
A8: KMX100612-029 | B8: 四会市骏马水泥有限公司 | C8: 40341 | D8: 40431 | E8: =IF(OR($C8="", $D8=""),"", $D8-$C8) -> 90 | G8: =IF(OR($C8="", $D8="",$F8=""),"", $F8-$D8) | H8: 40431 | I8: =IF($H8="", "", 参数!$B$3-$H8) -> 5593 | J8: 365+ | K8: 2400
A9: KMX101027-079 | B9: 山东金塔王股份有限公司 | C9: 40478 | D9: 40479 | E9: =IF(OR($C9="", $D9=""),"", $D9-$C9) -> 1 | F9: 40479 | G9: =IF(OR($C9="", $D9="",$F9=""),"", $F9-$D9) -> 0 | H9: 40479 | I9: =IF($H9="", "", 参数!$B$3-$H9) -> 5545 | J9: 365+ | K9: 6000
A10: KMX101223-006 | B10: 普定明达水泥有限公司 | C10: 40535 | D10: 40549 | E10: =IF(OR($C10="", $D10=""),"", $D10-$C10) -> 14 | F10: 40549 | G10: =IF(OR($C10="", $D10="",$F10=""),"", $F10-$D10) -> 0 | H10: 40549 | I10: =IF($H10="", "", 参数!$B$3-$H10) -> 5475 | J10: 365+ | K10: 740
A11: KMX110106-090 | B11: 江西玉山南方水泥有限公司 | C11: 40549 | D11: 40563 | E11: =IF(OR($C11="", $D11=""),"", $D11-$C11) -> 14 | F11: 40563 | G11: =IF(OR($C11="", $D11="",$F11=""),"", $F11-$D11) -> 0 | H11: 40563 | I11: =IF($H11="", "", 参数!$B$3-$H11) -> 5461 | J11: 365+ | K11: 7800
A12: KMX110209-162 | B12: 天瑞集团汝州水泥有限公司 | C12: 40583 | D12: 40732 | E12: =IF(OR($C12="", $D12=""),"", $D12-$C12) -> 149 | F12: 40732 | G12: =IF(OR($C12="", $D12="",$F12=""),"", $F12-$D12) -> 0 | H12: 40732 | I12: =IF($H12="", "", 参数!$B$3-$H12) -> 5292 | J12: 365+ | K12: 19000
A13: KMX110530-153 | B13: 南阳市天泰水泥有限公司 | C13: 40693 | D13: 40792 | E13: =IF(OR($C13="", $D13=""),"", $D13-$C13) -> 99 | F13: 40792 | G13: =IF(OR($C13="", $D13="",$F13=""),"", $F13-$D13) -> 0 | H13: 40792 | I13: =IF($H13="", "", 参数!$B$3-$H13) -> 5232 | J13: 365+ | K13: 18000
A14: KMX110818-258 | B14: 河南省安阳湖波水泥有限责任公司 | C14: 40773 | D14: 41234 | E14: =IF(OR($C14="", $D14=""),"", $D14-$C14) -> 461 | G14: =IF(OR($C14="", $D14="",$F14=""),"", $F14-$D14) | H14: 41234 | I14: =IF($H14="", "", 参数!$B$3-$H14) -> 4790 | J14: 365+ | K14: 46000
A15: KMX110905-069 | B15: 大唐华银金竹山火力发电分公司 | C15: 40791 | D15: 40881 | E15: =IF(OR($C15="", $D15=""),"", $D15-$C15) -> 90 | G15: =IF(OR($C15="", $D15="",$F15=""),"", $F15-$D15) | H15: 40881 | I15: =IF($H15="", "", 参数!$B$3-$H15) -> 5143 | J15: 365+ | K15: 5100
A16: KMX110922-076 | B16: 江西泰和南方水泥有限公司 | C16: 40808 | D16: 40898 | E16: =IF(OR($C16="", $D16=""),"", $D16-$C16) -> 90 | G16: =IF(OR($C16="", $D16="",$F16=""),"", $F16-$D16) | H16: 40898 | I16: =IF($H16="", "", 参数!$B$3-$H16) -> 5126 | J16: 365+ | K16: 5800
A17: KMX111025-047 | B17: 益阳市东方水泥有限公司 | C17: 40841 | D17: 40931 | E17: =IF(OR($C17="", $D17=""),"", $D17-$C17) -> 90 | G17: =IF(OR($C17="", $D17="",$F17=""),"", $F17-$D17) | H17: 40931 | I17: =IF($H17="", "", 参数!$B$3-$H17) -> 5093 | J17: 365+ | K17: 3400
A18: KMX111025-244 | B18: 云南红塔滇西水泥股份有限公司 | C18: 40841 | D18: 40931 | E18: =IF(OR($C18="", $D18=""),"", $D18-$C18) -> 90 | G18: =IF(OR($C18="", $D18="",$F18=""),"", $F18-$D18) | H18: 40931 | I18: =IF($H18="", "", 参数!$B$3-$H18) -> 5093 | J18: 365+ | K18: 37600
A19: KMX111101-237-《1》 | B19: 朝阳兰凌水泥有限公司 | C19: 40877 | D19: 40967 | E19: =IF(OR($C19="", $D19=""),"", $D19-$C19) -> 90 | G19: =IF(OR($C19="", $D19="",$F19=""),"", $F19-$D19) | H19: 40967 | I19: =IF($H19="", "", 参数!$B$3-$H19) -> 5057 | J19: 365+ | K19: 10000
A20: KMX120116-022 | B20: 南阳市天泰水泥有限公司 | C20: 40922 | D20: 40963 | E20: =IF(OR($C20="", $D20=""),"", $D20-$C20) -> 41 | F20: 40963 | G20: =IF(OR($C20="", $D20="",$F20=""),"", $F20-$D20) -> 0 | H20: 40963 | I20: =IF($H20="", "", 参数!$B$3-$H20) -> 5061 | J20: 365+ | K20: 2800
A21: KMX120408-061 | B21: 朝阳兰凌水泥有限公司 | C21: 41008 | D21: 41098 | E21: =IF(OR($C21="", $D21=""),"", $D21-$C21) -> 90 | G21: =IF(OR($C21="", $D21="",$F21=""),"", $F21-$D21) | H21: 41098 | I21: =IF($H21="", "", 参数!$B$3-$H21) -> 4926 | J21: 365+ | K21: 800
A22: KMX120429-071 | B22: 大同市云中有水泥限责任公司 | C22: 41028 | D22: 41118 | E22: =IF(OR($C22="", $D22=""),"", $D22-$C22) -> 90 | G22: =IF(OR($C22="", $D22="",$F22=""),"", $F22-$D22) | H22: 41118 | I22: =IF($H22="", "", 参数!$B$3-$H22) -> 4906 | J22: 365+ | K22: 36000
A23: KMX120512-085 | B23: 普定明达水泥有限公司 | C23: 41041 | D23: 41047 | E23: =IF(OR($C23="", $D23=""),"", $D23-$C23) -> 6 | F23: 41047 | G23: =IF(OR($C23="", $D23="",$F23=""),"", $F23-$D23) -> 0 | H23: 41047 | I23: =IF($H23="", "", 参数!$B$3-$H23) -> 4977 | J23: 365+ | K23: 2000
A24: KMX120621-118 | B24: 河南省安阳湖波水泥有限责任公司 | C24: 41094 | D24: 41184 | E24: =IF(OR($C24="", $D24=""),"", $D24-$C24) -> 90 | G24: =IF(OR($C24="", $D24="",$F24=""),"", $F24-$D24) | H24: 41184 | I24: =IF($H24="", "", 参数!$B$3-$H24) -> 4840 | J24: 365+ | K24: 27800
A25: KMX130224-048 | B25: 库车天山水泥有限责任公司 | C25: 41331 | D25: 41411 | E25: =IF(OR($C25="", $D25=""),"", $D25-$C25) -> 80 | F25: 41411 | G25: =IF(OR($C25="", $D25="",$F25=""),"", $F25-$D25) -> 0 | H25: 41411 | I25: =IF($H25="", "", 参数!$B$3-$H25) -> 4613 | J25: 365+ | K25: 20000
A26: KMX130224-050 | B26: 天瑞集团汝州水泥有限公司 | C26: 41335 | D26: 41591 | E26: =IF(OR($C26="", $D26=""),"", $D26-$C26) -> 256 | F26: 41591 | G26: =IF(OR($C26="", $D26="",$F26=""),"", $F26-$D26) -> 0 | H26: 41591 | I26: =IF($H26="", "", 参数!$B$3-$H26) -> 4433 | J26: 365+ | K26: 6500
A27: KMX130305-056 | B27: 湖北宜化集团楚星化工股份有限公司（更名为：湖北大江化工集团有限公司） | C27: 41338 | D27: 41410 | E27: =IF(OR($C27="", $D27=""),"", $D27-$C27) -> 72 | F27: 41410 | G27: =IF(OR($C27="", $D27="",$F27=""),"", $F27-$D27) -> 0 | H27: 41410 | I27: =IF($H27="", "", 参数!$B$3-$H27) -> 4614 | J27: 365+ | K27: 6160
A28: KMX131205-255 | B28: 重庆拉法基水泥有限公司 | C28: 41613 | D28: 41764 | E28: =IF(OR($C28="", $D28=""),"", $D28-$C28) -> 151 | F28: 41764 | G28: =IF(OR($C28="", $D28="",$F28=""),"", $F28-$D28) -> 0 | H28: 41764 | I28: =IF($H28="", "", 参数!$B$3-$H28) -> 4260 | J28: 365+ | K28: 15800
A29: KMX140111-011 | B29: 四川泸定山盛水泥有限公司 | C29: 41650 | D29: 41774 | E29: =IF(OR($C29="", $D29=""),"", $D29-$C29) -> 124 | F29: 41774 | G29: =IF(OR($C29="", $D29="",$F29=""),"", $F29-$D29) -> 0 | H29: 41774 | I29: =IF($H29="", "", 参数!$B$3-$H29) -> 4250 | J29: 365+ | K29: 6514
A30: KMX140122-028 | B30: 河南隆鑫水泥有限责任公司 | C30: 41678 | D30: 41837 | E30: =IF(OR($C30="", $D30=""),"", $D30-$C30) -> 159 | F30: 41837 | G30: =IF(OR($C30="", $D30="",$F30=""),"", $F30-$D30) -> 0 | H30: 41837 | I30: =IF($H30="", "", 参数!$B$3-$H30) -> 4187 | J30: 365+ | K30: 60000
A31: KMX140327-066 | B31: 宁波科环新型建材股份有限公司 | C31: 41725 | D31: 41801 | E31: =IF(OR($C31="", $D31=""),"", $D31-$C31) -> 76 | F31: 41801 | G31: =IF(OR($C31="", $D31="",$F31=""),"", $F31-$D31) -> 0 | H31: 41801 | I31: =IF($H31="", "", 参数!$B$3-$H31) -> 4223 | J31: 365+ | K31: 6000
A32: KMX140422-084 | B32: 登电集团水泥有限公司 | C32: 41754 | D32: 41844 | E32: =IF(OR($C32="", $D32=""),"", $D32-$C32) -> 90 | G32: =IF(OR($C32="", $D32="",$F32=""),"", $F32-$D32) | H32: 41844 | I32: =IF($H32="", "", 参数!$B$3-$H32) -> 4180 | J32: 365+ | K32: 100
A33: KMX140518-098 | B33: 四川泸定山盛水泥有限公司 | C33: 41777 | D33: 41867 | E33: =IF(OR($C33="", $D33=""),"", $D33-$C33) -> 90 | G33: =IF(OR($C33="", $D33="",$F33=""),"", $F33-$D33) | H33: 41867 | I33: =IF($H33="", "", 参数!$B$3-$H33) -> 4157 | J33: 365+ | K33: 600
A34: KMX140815-169 | B34: 四川洪雅西南水泥有限公司 | C34: 41866 | D34: 41936 | E34: =IF(OR($C34="", $D34=""),"", $D34-$C34) -> 70 | F34: 41936 | G34: =IF(OR($C34="", $D34="",$F34=""),"", $F34-$D34) -> 0 | H34: 41936 | I34: =IF($H34="", "", 参数!$B$3-$H34) -> 4088 | J34: 365+ | K34: 3660
A35: KMX141117-220 | B35: 四川泸定山盛水泥有限公司 | C35: 41960 | D35: 41961 | E35: =IF(OR($C35="", $D35=""),"", $D35-$C35) -> 1 | F35: 41961 | G35: =IF(OR($C35="", $D35="",$F35=""),"", $F35-$D35) -> 0 | H35: 41961 | I35: =IF($H35="", "", 参数!$B$3-$H35) -> 4063 | J35: 365+ | K35: 1280
A36: KMX150127-030 | B36: 台泥(怀化)水泥有限公司（原名湖南金大地材料股份有限公司） | C36: 42031 | D36: 42031 | E36: =IF(OR($C36="", $D36=""),"", $D36-$C36) -> 0 | F36: 42031 | G36: =IF(OR($C36="", $D36="",$F36=""),"", $F36-$D36) -> 0 | H36: 42031 | I36: =IF($H36="", "", 参数!$B$3-$H36) -> 3993 | J36: 365+ | K36: 4000
A37: KMX150202-034 | B37: 芒市西南水泥有限公司 | C37: 42037 | D37: 42063 | E37: =IF(OR($C37="", $D37=""),"", $D37-$C37) -> 26 | F37: 42074 | G37: =IF(OR($C37="", $D37="",$F37=""),"", $F37-$D37) -> 11 | H37: 42074 | I37: =IF($H37="", "", 参数!$B$3-$H37) -> 3950 | J37: 365+ | K37: 4800
A38: KMX150321-076-XF | B38: 湖南印山实业集团印山台水泥有限公司 | C38: 42084 | D38: 42137 | E38: =IF(OR($C38="", $D38=""),"", $D38-$C38) -> 53 | F38: 42137 | G38: =IF(OR($C38="", $D38="",$F38=""),"", $F38-$D38) -> 0 | H38: 42137 | I38: =IF($H38="", "", 参数!$B$3-$H38) -> 3887 | J38: 365+ | K38: 14800
A39: KMX150602-118-CL | B39: 莱芜市双盛机械制造有限公司 | C39: 42157 | D39: 42242 | E39: =IF(OR($C39="", $D39=""),"", $D39-$C39) -> 85 | F39: 42235 | G39: =IF(OR($C39="", $D39="",$F39=""),"", $F39-$D39) -> -7 | H39: 42235 | I39: =IF($H39="", "", 参数!$B$3-$H39) -> 3789 | J39: 365+ | K39: 16000
A40: KMX150901-167-XF | B40: 锦州三鸽水泥制造有限公司 | C40: 42248 | D40: 42260 | E40: =IF(OR($C40="", $D40=""),"", $D40-$C40) -> 12 | F40: 42390 | G40: =IF(OR($C40="", $D40="",$F40=""),"", $F40-$D40) -> 130 | H40: 42390 | I40: =IF($H40="", "", 参数!$B$3-$H40) -> 3634 | J40: 365+ | K40: 100000
A41: KMX160128-24-XF | B41: 安钢集团信阳钢铁有限责任公司 | C41: 42397 | D41: 42487 | E41: =IF(OR($C41="", $D41=""),"", $D41-$C41) -> 90 | G41: =IF(OR($C41="", $D41="",$F41=""),"", $F41-$D41) | H41: 42487 | I41: =IF($H41="", "", 参数!$B$3-$H41) -> 3537 | J41: 365+ | K41: 120000 | L41: 120000
A42: KMX160222-50-XF | B42: 四川泸定山盛水泥有限公司 | C42: 42422 | D42: 42798 | E42: =IF(OR($C42="", $D42=""),"", $D42-$C42) -> 376 | F42: 42831 | G42: =IF(OR($C42="", $D42="",$F42=""),"", $F42-$D42) -> 33 | H42: 42831 | I42: =IF($H42="", "", 参数!$B$3-$H42) -> 3193 | J42: 365+ | K42: 22748.16
A43: KMX160226-57-NM | B43: 安钢集团信阳钢铁有限责任公司 | C43: 42426 | D43: 42563 | E43: =IF(OR($C43="", $D43=""),"", $D43-$C43) -> 137 | F43: 42563 | G43: =IF(OR($C43="", $D43="",$F43=""),"", $F43-$D43) -> 0 | H43: 42563 | I43: =IF($H43="", "", 参数!$B$3-$H43) -> 3461 | J43: 365+ | K43: 92000.45
A44: KMX160507-91-XF | B44: 信阳豫信轧钢实业有限公司(安钢集团信阳钢铁) | C44: 42497 | D44: 42748 | E44: =IF(OR($C44="", $D44=""),"", $D44-$C44) -> 251 | F44: 42563 | G44: =IF(OR($C44="", $D44="",$F44=""),"", $F44-$D44) -> -185 | H44: 42563 | I44: =IF($H44="", "", 参数!$B$3-$H44) -> 3461 | J44: 365+ | K44: 10800
A45: KMX160719-142-CL | B45: 张家港恒乐新型建筑材料有限公司（江苏沙钢） | C45: 42570 | D45: 42991 | E45: =IF(OR($C45="", $D45=""),"", $D45-$C45) -> 421 | F45: 42991 | G45: =IF(OR($C45="", $D45="",$F45=""),"", $F45-$D45) -> 0 | H45: 42991 | I45: =IF($H45="", "", 参数!$B$3-$H45) -> 3033 | J45: 365+ | K45: 5000
A46: KMX160824-171-XF | B46: 信阳豫信轧钢实业有限公司(安钢集团信阳钢铁) | C46: 42606 | D46: 42618 | E46: =IF(OR($C46="", $D46=""),"", $D46-$C46) -> 12 | F46: 42710 | G46: =IF(OR($C46="", $D46="",$F46=""),"", $F46-$D46) -> 92 | H46: 42710 | I46: =IF($H46="", "", 参数!$B$3-$H46) -> 3314 | J46: 365+ | K46: 39800
A47: KMX160928-199-NM | B47: 安钢集团信阳钢铁有限责任公司 | C47: 42641 | D47: 42694 | E47: =IF(OR($C47="", $D47=""),"", $D47-$C47) -> 53 | F47: 42790 | G47: =IF(OR($C47="", $D47="",$F47=""),"", $F47-$D47) -> 96 | H47: 42790 | I47: =IF($H47="", "", 参数!$B$3-$H47) -> 3234 | J47: 365+ | K47: 8000
A48: KMX161103-218-NM | B48: 安钢集团信阳钢铁有限责任公司 | C48: 42677 | D48: 42724 | E48: =IF(OR($C48="", $D48=""),"", $D48-$C48) -> 47 | F48: 42803 | G48: =IF(OR($C48="", $D48="",$F48=""),"", $F48-$D48) -> 79 | H48: 42803 | I48: =IF($H48="", "", 参数!$B$3-$H48) -> 3221 | J48: 365+ | K48: 28000
A49: KMX161107-222-XF | B49: 铜陵上峰水泥股份有限公司 | C49: 42681 | D49: 42683 | E49: =IF(OR($C49="", $D49=""),"", $D49-$C49) -> 2 | F49: 42842 | G49: =IF(OR($C49="", $D49="",$F49=""),"", $F49-$D49) -> 159 | H49: 42842 | I49: =IF($H49="", "", 参数!$B$3-$H49) -> 3182 | J49: 365+ | K49: 3200
A50: KMX161201-232-JX | B50: 信阳豫信轧钢实业有限公司(安钢集团信阳钢铁) | C50: 42705 | D50: 43024 | E50: =IF(OR($C50="", $D50=""),"", $D50-$C50) -> 319 | F50: 43066 | G50: =IF(OR($C50="", $D50="",$F50=""),"", $F50-$D50) -> 42 | H50: 43066 | I50: =IF($H50="", "", 参数!$B$3-$H50) -> 2958 | J50: 365+ | K50: 80000
A51: KMX161214-238-XF | B51: 天瑞集团南召水泥有限公司 | C51: 42718 | D51: 42899 | E51: =IF(OR($C51="", $D51=""),"", $D51-$C51) -> 181 | F51: 42943 | G51: =IF(OR($C51="", $D51="",$F51=""),"", $F51-$D51) -> 44 | H51: 42943 | I51: =IF($H51="", "", 参数!$B$3-$H51) -> 3081 | J51: 365+ | K51: 9000
A52: KMX170109-002-XF | B52: 山西恒达能源集团有限公司 | C52: 42744 | D52: 42740 | E52: =IF(OR($C52="", $D52=""),"", $D52-$C52) -> -4 | F52: 42831 | G52: =IF(OR($C52="", $D52="",$F52=""),"", $F52-$D52) -> 91 | H52: 42831 | I52: =IF($H52="", "", 参数!$B$3-$H52) -> 3193 | J52: 365+ | K52: 4460
A53: KMX170124-024-XF | B53: 会东利森水泥有限公司 | C53: 42759 | D53: 42778 | E53: =IF(OR($C53="", $D53=""),"", $D53-$C53) -> 19 | F53: 42809 | G53: =IF(OR($C53="", $D53="",$F53=""),"", $F53-$D53) -> 31 | H53: 42809 | I53: =IF($H53="", "", 参数!$B$3-$H53) -> 3215 | J53: 365+ | K53: 4993.14
... A55: KMX170304-061-XF | B55: 四川泸定山盛水泥有限公司 | C55: 42798 | D55: 42798 | E55: =IF(OR($C55="", $D55=""),"", $D55-$C55) -> 0 | F55: 42831 | G55: =IF(OR($C55="", $D55="",$F55=""),"", $F55-$D55) -> 33 | H55: 42831 | I55: =IF($H55="", "", 参数!$B$3-$H55) -> 3193 | J55: 365+ | K55: 43369.84
A56: KMX170331-073-XF | B56: 铜陵上峰水泥股份有限公司 | C56: 42825 | D56: 42832 | E56: =IF(OR($C56="", $D56=""),"", $D56-$C56) -> 7 | G56: =IF(OR($C56="", $D56="",$F56=""),"", $F56-$D56) | H56: 42832 | I56: =IF($H56="", "", 参数!$B$3-$H56) -> 3192 | J56: 365+ | K56: 43463.28 | L56: 43463.28
A57: KMX170410-080-XF | B57: 云南祥云飞龙再生科技股份有限公司 | C57: 42835 | D57: 42865 | E57: =IF(OR($C57="", $D57=""),"", $D57-$C57) -> 30 | F57: 42894 | G57: =IF(OR($C57="", $D57="",$F57=""),"", $F57-$D57) -> 29 | H57: 42894 | I57: =IF($H57="", "", 参数!$B$3-$H57) -> 3130 | J57: 365+ | K57: 10000
A58: KMX170507-100-XF | B58: 辽宁富山水泥有限公司 | C58: 42863 | D58: 42877 | E58: =IF(OR($C58="", $D58=""),"", $D58-$C58) -> 14 | F58: 42922 | G58: =IF(OR($C58="", $D58="",$F58=""),"", $F58-$D58) -> 45 | H58: 42922 | I58: =IF($H58="", "", 参数!$B$3-$H58) -> 3102 | J58: 365+ | K58: 3000
A59: KMX170619-136-XF | B59: 信阳豫信轧钢实业有限公司(安钢集团信阳钢铁) | C59: 42905 | D59: 42917 | E59: =IF(OR($C59="", $D59=""),"", $D59-$C59) -> 12 | F59: 43066 | G59: =IF(OR($C59="", $D59="",$F59=""),"", $F59-$D59) -> 149 | H59: 43066 | I59: =IF($H59="", "", 参数!$B$3-$H59) -> 2958 | J59: 365+ | K59: 9700
A60: KMX170626-143-XF | B60: 朝阳兰凌水泥有限公司 | C60: 42912 | D60: 42919 | E60: =IF(OR($C60="", $D60=""),"", $D60-$C60) -> 7 | F60: 42936 | G60: =IF(OR($C60="", $D60="",$F60=""),"", $F60-$D60) -> 17 | H60: 42936 | I60: =IF($H60="", "", 参数!$B$3-$H60) -> 3088 | J60: 365+ | K60: 46900
A61: KMX170722-165-XF | B61: 扎兰屯市龙北水泥有限公司 | C61: 42938 | D61: 42952 | E61: =IF(OR($C61="", $D61=""),"", $D61-$C61) -> 14 | F61: 42977 | G61: =IF(OR($C61="", $D61="",$F61=""),"", $F61-$D61) -> 25 | H61: 42977 | I61: =IF($H61="", "", 参数!$B$3-$H61) -> 3047 | J61: 365+ | K61: 20000
A62: KMX170726-169-XF | B62: 四川泸定山盛水泥有限公司 | C62: 42942 | D62: 42948 | E62: =IF(OR($C62="", $D62=""),"", $D62-$C62) -> 6 | F62: 42956 | G62: =IF(OR($C62="", $D62="",$F62=""),"", $F62-$D62) -> 8 | H62: 42956 | I62: =IF($H62="", "", 参数!$B$3-$H62) -> 3068 | J62: 365+ | K62: 25488
A63: KMX170829-201-XF | B63: 昭通昆钢嘉华水泥建材有限公司 | C63: 42976 | D63: 42991 | E63: =IF(OR($C63="", $D63=""),"", $D63-$C63) -> 15 | F63: 43057 | G63: =IF(OR($C63="", $D63="",$F63=""),"", $F63-$D63) -> 66 | H63: 43057 | I63: =IF($H63="", "", 参数!$B$3-$H63) -> 2967 | J63: 365+ | K63: 69800 | L63: 50000
A64: KMX170919-221-XF | B64: 河北承大建材有限公司 | C64: 42998 | D64: 43005 | E64: =IF(OR($C64="", $D64=""),"", $D64-$C64) -> 7 | F64: 43209 | G64: =IF(OR($C64="", $D64="",$F64=""),"", $F64-$D64) -> 204 | H64: 43209 | I64: =IF($H64="", "", 参数!$B$3-$H64) -> 2815 | J64: 365+ | K64: 55000
A65: KMX171120-261-XF | B65: 泰山中联水泥有限公司 | C65: 43059 | D65: 43111 | E65: =IF(OR($C65="", $D65=""),"", $D65-$C65) -> 52 | F65: 43373 | G65: =IF(OR($C65="", $D65="",$F65=""),"", $F65-$D65) -> 262 | H65: 43373 | I65: =IF($H65="", "", 参数!$B$3-$H65) -> 2651 | J65: 365+ | K65: 18251.2
A66: KMX180117-018-XF | B66: 西安柏通建筑安装工程有限公司（原名西安蓝田尧柏水泥有限公司) | C66: 43117 | D66: 43121 | E66: =IF(OR($C66="", $D66=""),"", $D66-$C66) -> 4 | F66: 43213 | G66: =IF(OR($C66="", $D66="",$F66=""),"", $F66-$D66) -> 92 | H66: 43213 | I66: =IF($H66="", "", 参数!$B$3-$H66) -> 2811 | J66: 365+ | K66: 1614
A67: KMX180207-050-XF | B67: 信阳豫信轧钢实业有限公司(安钢集团信阳钢铁) | C67: 43138 | D67: 43166 | E67: =IF(OR($C67="", $D67=""),"", $D67-$C67) -> 28 | F67: 43211 | G67: =IF(OR($C67="", $D67="",$F67=""),"", $F67-$D67) -> 45 | H67: 43211 | I67: =IF($H67="", "", 参数!$B$3-$H67) -> 2813 | J67: 365+ | K67: 4500
A68: KMX180224-077-XF | B68: 天瑞集团南召水泥有限公司 | C68: 43155 | D68: 43163 | E68: =IF(OR($C68="", $D68=""),"", $D68-$C68) -> 8 | F68: 43207 | G68: =IF(OR($C68="", $D68="",$F68=""),"", $F68-$D68) -> 44 | H68: 43207 | I68: =IF($H68="", "", 参数!$B$3-$H68) -> 2817 | J68: 365+ | K68: 4500
A69: KMX180227-081-XF | B69: 云南永保特种水泥有限责任公司 | C69: 43158 | D69: 43178 | E69: =IF(OR($C69="", $D69=""),"", $D69-$C69) -> 20 | F69: 43207 | G69: =IF(OR($C69="", $D69="",$F69=""),"", $F69-$D69) -> 29 | H69: 43207 | I69: =IF($H69="", "", 参数!$B$3-$H69) -> 2817 | J69: 365+ | K69: 1005.2467
A70: KMX180305-085-XF | B70: 福建省永安万年水泥有限公司 | C70: 43164 | D70: 43181 | E70: =IF(OR($C70="", $D70=""),"", $D70-$C70) -> 17 | F70: 43206 | G70: =IF(OR($C70="", $D70="",$F70=""),"", $F70-$D70) -> 25 | H70: 43206 | I70: =IF($H70="", "", 参数!$B$3-$H70) -> 2818 | J70: 365+ | K70: 40425
A71: KMX180419-126-XF | B71: 福建春驰集团国产实业水泥有限公司 | C71: 43209 | D71: 43319 | E71: =IF(OR($C71="", $D71=""),"", $D71-$C71) -> 110 | F71: 43322 | G71: =IF(OR($C71="", $D71="",$F71=""),"", $F71-$D71) -> 3 | H71: 43322 | I71: =IF($H71="", "", 参数!$B$3-$H71) -> 2702 | J71: 365+ | K71: 12175
A72: KMX180515-150-XF | B72: 逸盛大化石化有限公司 | C72: 43235 | D72: 43255 | E72: =IF(OR($C72="", $D72=""),"", $D72-$C72) -> 20 | F72: 43273 | G72: =IF(OR($C72="", $D72="",$F72=""),"", $F72-$D72) -> 18 | H72: 43273 | I72: =IF($H72="", "", 参数!$B$3-$H72) -> 2751 | J72: 365+ | K72: 54000
A73: KMX180525-163-XF | B73: 安钢集团信阳钢铁有限责任公司 | C73: 43245 | D73: 43256 | E73: =IF(OR($C73="", $D73=""),"", $D73-$C73) -> 11 | F73: 43299 | G73: =IF(OR($C73="", $D73="",$F73=""),"", $F73-$D73) -> 43 | H73: 43299 | I73: =IF($H73="", "", 参数!$B$3-$H73) -> 2725 | J73: 365+ | K73: 18000
A74: KMX180607-171-XF | B74: 铜陵上峰水泥股份有限公司 | C74: 43258 | D74: 43263 | E74: =IF(OR($C74="", $D74=""),"", $D74-$C74) -> 5 | G74: =IF(OR($C74="", $D74="",$F74=""),"", $F74-$D74) | H74: 43263 | I74: =IF($H74="", "", 参数!$B$3-$H74) -> 2761 | J74: 365+ | K74: 14800 | L74: 14800
A75: KMX180626-197-XF | B75: 铜陵上峰水泥股份有限公司 | C75: 43277 | D75: 43286 | E75: =IF(OR($C75="", $D75=""),"", $D75-$C75) -> 9 | G75: =IF(OR($C75="", $D75="",$F75=""),"", $F75-$D75) | H75: 43286 | I75: =IF($H75="", "", 参数!$B$3-$H75) -> 2738 | J75: 365+ | K75: 30000 | L75: 30000
A76: KMX180803-239-XF | B76: 四川省二郎山喇叭河水泥有限公司 | C76: 43315 | D76: 43479 | E76: =IF(OR($C76="", $D76=""),"", $D76-$C76) -> 164 | F76: 43557 | G76: =IF(OR($C76="", $D76="",$F76=""),"", $F76-$D76) -> 78 | H76: 43557 | I76: =IF($H76="", "", 参数!$B$3-$H76) -> 2467 | J76: 365+ | K76: 27
A77: KMX180807-247-XF | B77: 北京金隅琉水环保科技有限公司 | C77: 43320 | D77: 43324 | E77: =IF(OR($C77="", $D77=""),"", $D77-$C77) -> 4 | F77: 43369 | G77: =IF(OR($C77="", $D77="",$F77=""),"", $F77-$D77) -> 45 | H77: 43369 | I77: =IF($H77="", "", 参数!$B$3-$H77) -> 2655 | J77: 365+ | K77: 6600
A78: KMX180815-256-XF | B78: 江苏沙钢集团有限公司 | C78: 43327 | D78: 43405 | E78: =IF(OR($C78="", $D78=""),"", $D78-$C78) -> 78 | F78: 43517 | G78: =IF(OR($C78="", $D78="",$F78=""),"", $F78-$D78) -> 112 | H78: 43517 | I78: =IF($H78="", "", 参数!$B$3-$H78) -> 2507 | J78: 365+ | K78: 5000
A79: KMX180819-261-XF | B79: 河北新金轧材有限公司 | C79: 43331 | D79: 43371 | E79: =IF(OR($C79="", $D79=""),"", $D79-$C79) -> 40 | F79: 43546 | G79: =IF(OR($C79="", $D79="",$F79=""),"", $F79-$D79) -> 175 | H79: 43546 | I79: =IF($H79="", "", 参数!$B$3-$H79) -> 2478 | J79: 365+ | K79: 27090
A80: KMX180827-271-XF | B80: 昭通得云建材有限责任公司 | C80: 43339 | D80: 43343 | E80: =IF(OR($C80="", $D80=""),"", $D80-$C80) -> 4 | F80: 43396 | G80: =IF(OR($C80="", $D80="",$F80=""),"", $F80-$D80) -> 53 | H80: 43396 | I80: =IF($H80="", "", 参数!$B$3-$H80) -> 2628 | J80: 365+ | K80: 10125
A81: KMX181101-320-XF | B81: 逸盛大化石化有限公司 | C81: 43405 | D81: 43454 | E81: =IF(OR($C81="", $D81=""),"", $D81-$C81) -> 49 | F81: 43546 | G81: =IF(OR($C81="", $D81="",$F81=""),"", $F81-$D81) -> 92 | H81: 43546 | I81: =IF($H81="", "", 参数!$B$3-$H81) -> 2478 | J81: 365+ | K81: 33000
A82: KMX181112-325-XF | B82: 北京金隅琉水环保科技有限公司 | C82: 43416 | D82: 43421 | E82: =IF(OR($C82="", $D82=""),"", $D82-$C82) -> 5 | F82: 43452 | G82: =IF(OR($C82="", $D82="",$F82=""),"", $F82-$D82) -> 31 | H82: 43452 | I82: =IF($H82="", "", 参数!$B$3-$H82) -> 2572 | J82: 365+ | K82: 3200
A83: KMX181127-343-XF | B83: 将乐金牛水泥有限公司 | C83: 43431 | D83: 43437 | E83: =IF(OR($C83="", $D83=""),"", $D83-$C83) -> 6 | F83: 43440 | G83: =IF(OR($C83="", $D83="",$F83=""),"", $F83-$D83) -> 3 | H83: 43440 | I83: =IF($H83="", "", 参数!$B$3-$H83) -> 2584 | J83: 365+ | K83: 1176
A84: KMX181207-356-XF | B84: 安钢集团信阳钢铁有限责任公司 | C84: 43441 | D84: 43481 | E84: =IF(OR($C84="", $D84=""),"", $D84-$C84) -> 40 | F84: 43484 | G84: =IF(OR($C84="", $D84="",$F84=""),"", $F84-$D84) -> 3 | H84: 43484 | I84: =IF($H84="", "", 参数!$B$3-$H84) -> 2540 | J84: 365+ | K84: 5444
A85: KMX181216-373-XF | B85: 北京金隅琉水环保科技有限公司 | C85: 43450 | D85: 43451 | E85: =IF(OR($C85="", $D85=""),"", $D85-$C85) -> 1 | F85: 43517 | G85: =IF(OR($C85="", $D85="",$F85=""),"", $F85-$D85) -> 66 | H85: 43517 | I85: =IF($H85="", "", 参数!$B$3-$H85) -> 2507 | J85: 365+ | K85: 28000
A86: KMX190103-004-XF | B86: 江西永丰南方水泥有限公司 | C86: 43468 | D86: 43513 | E86: =IF(OR($C86="", $D86=""),"", $D86-$C86) -> 45 | F86: 43518 | G86: =IF(OR($C86="", $D86="",$F86=""),"", $F86-$D86) -> 5 | H86: 43518 | I86: =IF($H86="", "", 参数!$B$3-$H86) -> 2506 | J86: 365+ | K86: 1750 | L86: 0
A87: KMX190104-008-XF | B87: 安钢集团信阳钢铁有限责任公司 | C87: 43469 | D87: 43676 | E87: =IF(OR($C87="", $D87=""),"", $D87-$C87) -> 207 | F87: 43797 | G87: =IF(OR($C87="", $D87="",$F87=""),"", $F87-$D87) -> 121 | H87: 43797 | I87: =IF($H87="", "", 参数!$B$3-$H87) -> 2227 | J87: 365+ | K87: 26190 | L87: 0
A88: KMX190108-015-XF | B88: 湖南省嘉禾县南岭水泥有限公司 | C88: 43473 | D88: 43480 | E88: =IF(OR($C88="", $D88=""),"", $D88-$C88) -> 7 | F88: 43487 | G88: =IF(OR($C88="", $D88="",$F88=""),"", $F88-$D88) -> 7 | H88: 43487 | I88: =IF($H88="", "", 参数!$B$3-$H88) -> 2537 | J88: 365+ | K88: 6084 | L88: 0
A89: KMX190119-037-XF | B89: 智海企业集团榆次水泥有限公司 | C89: 43484 | D89: 43520 | E89: =IF(OR($C89="", $D89=""),"", $D89-$C89) -> 36 | F89: 43512 | G89: =IF(OR($C89="", $D89="",$F89=""),"", $F89-$D89) -> -8 | H89: 43512 | I89: =IF($H89="", "", 参数!$B$3-$H89) -> 2512 | J89: 365+ | K89: 4500 | L89: 0
A90: KMX190130-058-XF | B90: 山西恒达能源集团有限公司 | C90: 43495 | D90: 43515 | E90: =IF(OR($C90="", $D90=""),"", $D90-$C90) -> 20 | F90: 43523 | G90: =IF(OR($C90="", $D90="",$F90=""),"", $F90-$D90) -> 8 | H90: 43523 | I90: =IF($H90="", "", 参数!$B$3-$H90) -> 2501 | J90: 365+ | K90: 9736 | L90: 0
A91: KMX190201-076-XF | B91: 拉法基瑞安（红河）水泥有限公司（云南国资水泥红河有限公司）变更华新水泥（红河）有限公司 | C91: 43497 | D91: 43490 | E91: =IF(OR($C91="", $D91=""),"", $D91-$C91) -> -7 | F91: 44520 | G91: =IF(OR($C91="", $D91="",$F91=""),"", $F91-$D91) -> 1030 | H91: 44520 | I91: =IF($H91="", "", 参数!$B$3-$H91) -> 1504 | J91: 365+ | K91: 70000 | L91: 70000
A92: KMX190220-096-XF | B92: 华润水泥（贵港）有限公司 | C92: 43516 | D92: 43586 | E92: =IF(OR($C92="", $D92=""),"", $D92-$C92) -> 70 | F92: 43615 | G92: =IF(OR($C92="", $D92="",$F92=""),"", $F92-$D92) -> 29 | H92: 43615 | I92: =IF($H92="", "", 参数!$B$3-$H92) -> 2409 | J92: 365+ | K92: 2800.0178 | L92: 0
A93: KMX190223-099-XF | B93: 长治县三元王庄华泰水泥有限公司 | C93: 43519 | D93: 43524 | E93: =IF(OR($C93="", $D93=""),"", $D93-$C93) -> 5 | F93: 43546 | G93: =IF(OR($C93="", $D93="",$F93=""),"", $F93-$D93) -> 22 | H93: 43546 | I93: =IF($H93="", "", 参数!$B$3-$H93) -> 2478 | J93: 365+ | K93: 2572.92 | L93: 0
A94: KMX190227-107-XF | B94: 敬业钢铁有限公司 | C94: 43523 | D94: 43633 | E94: =IF(OR($C94="", $D94=""),"", $D94-$C94) -> 110 | F94: 43633 | G94: =IF(OR($C94="", $D94="",$F94=""),"", $F94-$D94) -> 0 | H94: 43633 | I94: =IF($H94="", "", 参数!$B$3-$H94) -> 2391 | J94: 365+ | K94: 2318.97 | L94: 0
A95: KMX190311-120-XF | B95: 天瑞集团南召水泥有限公司 | C95: 43535 | D95: 43542 | E95: =IF(OR($C95="", $D95=""),"", $D95-$C95) -> 7 | F95: 43543 | G95: =IF(OR($C95="", $D95="",$F95=""),"", $F95-$D95) -> 1 | H95: 43543 | I95: =IF($H95="", "", 参数!$B$3-$H95) -> 2481 | J95: 365+ | K95: 1150 | L95: 0
A96: KMX190312-122-XF | B96: 侯马市汇丰建材有限责任公司 | C96: 43536 | D96: 43541 | E96: =IF(OR($C96="", $D96=""),"", $D96-$C96) -> 5 | F96: 43545 | G96: =IF(OR($C96="", $D96="",$F96=""),"", $F96-$D96) -> 4 | H96: 43545 | I96: =IF($H96="", "", 参数!$B$3-$H96) -> 2479 | J96: 365+ | K96: 1040 | L96: 0
A97: KMX190321-137-XF | B97: 河钢股份有限公司邯郸分公司 | C97: 43545 | D97: 43543 | E97: =IF(OR($C97="", $D97=""),"", $D97-$C97) -> -2 | F97: 43851 | G97: =IF(OR($C97="", $D97="",$F97=""),"", $F97-$D97) -> 308 | H97: 43851 | I97: =IF($H97="", "", 参数!$B$3-$H97) -> 2173 | J97: 365+ | K97: 23740 | L97: 0
... A114: KMX191018-377-XF | B114: 山西恒达能源集团有限公司 | C114: 43756 | D114: 43763 | E114: =IF(OR($C114="", $D114=""),"", $D114-$C114) -> 7 | F114: 43767 | G114: =IF(OR($C114="", $D114="",$F114=""),"", $F114-$D114) -> 4 | H114: 43767 | I114: =IF($H114="", "", 参数!$B$3-$H114) -> 2257 | J114: 365+ | K114: 4864 | L114: 0
A115: KMX200109-011-XF | B115: 承德金隅水泥有限责任公司 | C115: 43839 | D115: 43845 | E115: =IF(OR($C115="", $D115=""),"", $D115-$C115) -> 6 | G115: =IF(OR($C115="", $D115="",$F115=""),"", $F115-$D115) | H115: 43845 | I115: =IF($H115="", "", 参数!$B$3-$H115) -> 2179 | J115: 365+ | K115: 38000 | L115: 38000
A116: KMX200120-036-XF | B116: 湖南常德南方水泥有限公司 | C116: 43850 | D116: 44275 | E116: =IF(OR($C116="", $D116=""),"", $D116-$C116) -> 425 | F116: 44274 | G116: =IF(OR($C116="", $D116="",$F116=""),"", $F116-$D116) -> -1 | H116: 44274 | I116: =IF($H116="", "", 参数!$B$3-$H116) -> 1750 | J116: 365+ | K116: 28600 | L116: 0
A117: KMX200318-052-XF | B117: 青海海西化工建材股份有限公司 | C117: 43908 | D117: 43977 | E117: =IF(OR($C117="", $D117=""),"", $D117-$C117) -> 69 | F117: 44007 | G117: =IF(OR($C117="", $D117="",$F117=""),"", $F117-$D117) -> 30 | H117: 44007 | I117: =IF($H117="", "", 参数!$B$3-$H117) -> 2017 | J117: 365+ | K117: 153000 | L117: 0
...
